Workbook
Name _Hlk24031923: Sheet2!$C$10
Name Cost_drivers: '[1]2_Cost drivers & standard cost'!$C$5:$C$40
Name Cost_reference_table: '[1]2_Cost drivers & standard cost'!$C$4:$U$40
Name Country_Name: '[1]1_Stratgies and interventions'!$L$9:$L$25
Name CPI: [1]CPI!$A$4:$M$269
Name Exchange_rate: [2]Basic_Inputs!$D$23
Name Official_exchange_rate: '[1]Official Xch rate'!$A$1:$I$19
Name OLE_LINK1: AFRO!$C$8
Name OLE_LINK1: 'ESA_Int$ PPP'!$C$8
Name OLE_LINK1: ESA_USD!$C$8
Name PPP_conversion_factor: '[1]Price PPP Conversion'!$A$2:$N$18
Name Strategic_Direction: '[1]1_Stratgies and interventions'!$D$9:$D$13
Name Threshohod_Low_density: '[3]Need and Supply'!$D$44
Name Zero_reduction: '[1]3_Main_Costing the Plan'!$M$4

Sheet Population 7 Sept 2021
A1: Data Source | B1: World Development Indicators
A2: Last Updated Date | B2: 44407
A4: Country Name | B4: Country Code | C4: Indicator Name | D4: Indicator Code | E4: 1960 | F4: 1961 | G4: 1962 | H4: 1963 | I4: 1964 | J4: 1965 | K4: 1966 | L4: 1967 | M4: 1968 | N4: 1969 | O4: 1970 | P4: 1971 | Q4: 1972 | R4: 1973 | S4: 1974 | T4: 1975 | U4: 1976 | V4: 1977 | W4: 1978 | X4: 1979 | Y4: 1980 | Z4: 1981 | AA4: 1982 | AB4: 1983 | AC4: 1984 | AD4: 1985 | AE4: 1986 | AF4: 1987 | AG4: 1988 | AH4: 1989 | AI4: 1990 | AJ4: 1991 | AK4: 1992 | AL4: 1993 | AM4: 1994 | AN4: 1995 | AO4: 1996 | AP4: 1997 | AQ4: 1998 | AR4: 1999 | AS4: 2000 | AT4: 2001 | AU4: 2002 | AV4: 2003 | AW4: 2004 | AX4: 2005 | AY4: 2006 | AZ4: 2007 | BA4: 2008 | BB4: 2009 | BC4: 2010 | BD4: 2011 | BE4: 2012 | BF4: 2013 | BG4: 2014 | BH4: 2015 | BI4: 2016 | BJ4: 2017 | BK4: 2018 | BL4: 2019 | BM4: 2020
A5: Aruba | B5: ABW | C5: Population, total | D5: SP.POP.TOTL | E5: 54208 | F5: 55434 | G5: 56234 | H5: 56699 | I5: 57029 | J5: 57357 | K5: 57702 | L5: 58044 | M5: 58377 | N5: 58734 | O5: 59070 | P5: 59442 | Q5: 59849 | R5: 60236 | S5: 60527 | T5: 60653 | U5: 60586 | V5: 60366 | W5: 60102 | X5: 59972 | Y5: 60097 | Z5: 60561 | AA5: 61341 | AB5: 62213 | AC5: 62826 | AD5: 63024 | AE5: 62645 | AF5: 61838 | AG5: 61072 | AH5: 61033 | AI5: 62152 | AJ5: 64623 | AK5: 68240 | AL5: 72495 | AM5: 76705 | AN5: 80324 | AO5: 83211 | AP5: 85450 | AQ5: 87280 | AR5: 89009 | AS5: 90866 | AT5: 92892 | AU5: 94992 | AV5: 97016 | AW5: 98744 | AX5: 100028 | AY5: 100830 | AZ5: 101226 | BA5: 101362 | BB5: 101452 | BC5: 101665 | BD5: 102050 | BE5: 102565 | BF5: 103165 | BG5: 103776 | BH5: 104339 | BI5: 104865 | BJ5: 105361 | BK5: 105846 | BL5: 106310 | BM5: 106766
A6: Africa Eastern and Southern | B6: AFE | C6: Population, total | D6: SP.POP.TOTL | E6: 130836765 | F6: 134159786 | G6: 137614644 | H6: 141202036 | I6: 144920186 | J6: 148769974 | K6: 152752671 | L6: 156876454 | M6: 161156430 | N6: 165611760 | O6: 170257189 | P6: 175100167 | Q6: 180141148 | R6: 185376550 | S6: 190800796 | T6: 196409937 | U6: 202205766 | V6: 208193045 | W6: 214368393 | X6: 220740384 | Y6: 227305945 | Z6: 234058404 | AA6: 240999134 | AB6: 248146290 | AC6: 255530063 | AD6: 263161451 | AE6: 271050065 | AF6: 279184536 | AG6: 287524258 | AH6: 296024639 | AI6: 304648010 | AJ6: 313394693 | AK6: 322270073 | AL6: 331265579 | AM6: 340379934 | AN6: 349605660 | AO6: 358953595 | AP6: 368440591 | AQ6: 378098393 | AR6: 387977990 | AS6: 398113044 | AT6: 408522129 | AU6: 419223717 | AV6: 430246635 | AW6: 441630149 | AX6: 453404076 | AY6: 465581372 | AZ6: 478166911 | BA6: 491173160 | BB6: 504604672 | BC6: 518468229 | BD6: 532760424 | BE6: 547482863 | BF6: 562601578 | BG6: 578075373 | BH6: 593871847 | BI6: 609978946 | BJ6: 626392880 | BK6: 643090131 | BL6: 660046272 | BM6: 677243299
A7: Afghanistan | B7: AFG | C7: Population, total | D7: SP.POP.TOTL | E7: 8996967 | F7: 9169406 | G7: 9351442 | H7: 9543200 | I7: 9744772 | J7: 9956318 | K7: 10174840 | L7: 10399936 | M7: 10637064 | N7: 10893772 | O7: 11173654 | P7: 11475450 | Q7: 11791222 | R7: 12108963 | S7: 12412960 | T7: 12689164 | U7: 12943093 | V7: 13171294 | W7: 13341199 | X7: 13411060 | Y7: 13356500 | Z7: 13171679 | AA7: 12882518 | AB7: 12537732 | AC7: 12204306 | AD7: 11938204 | AE7: 11736177 | AF7: 11604538 | AG7: 11618008 | AH7: 11868873 | AI7: 12412311 | AJ7: 13299016 | AK7: 14485543 | AL7: 15816601 | AM7: 17075728 | AN7: 18110662 | AO7: 18853444 | AP7: 19357126 | AQ7: 19737770 | AR7: 20170847 | AS7: 20779957 | AT7: 21606992 | AU7: 22600774 | AV7: 23680871 | AW7: 24726689 | AX7: 25654274 | AY7: 26433058 | AZ7: 27100542 | BA7: 27722281 | BB7: 28394806 | BC7: 29185511 | BD7: 30117411 | BE7: 31161378 | BF7: 32269592 | BG7: 33370804 | BH7: 34413603 | BI7: 35383028 | BJ7: 36296111 | BK7: 37171922 | BL7: 38041757 | BM7: 38928341
A8: Africa Western and Central | B8: AFW | C8: Population, total | D8: SP.POP.TOTL | E8: 96396419 | F8: 98407221 | G8: 100506960 | H8: 102691339 | I8: 104953470 | J8: 107289875 | K8: 109701811 | L8: 112195950 | M8: 114781116 | N8: 117468741 | O8: 120269044 | P8: 123184308 | Q8: 126218502 | R8: 129384954 | S8: 132699537 | T8: 136173544 | U8: 139813171 | V8: 143615715 | W8: 147571063 | X8: 151663853 | Y8: 155882270 | Z8: 160223588 | AA8: 164689764 | AB8: 169279422 | AC8: 173991851 | AD8: 178826553 | AE8: 183785612 | AF8: 188868567 | AG8: 194070079 | AH8: 199382783 | AI8: 204803865 | AJ8: 210332267 | AK8: 215976366 | AL8: 221754806 | AM8: 227692136 | AN8: 233807627 | AO8: 240114179 | AP8: 246613750 | AQ8: 253302310 | AR8: 260170348 | AS8: 267214544 | AT8: 274433894 | AU8: 281842480 | AV8: 289469530 | AW8: 297353098 | AX8: 305520588 | AY8: 313985474 | AZ8: 322741656 | BA8: 331772330 | BB8: 341050537 | BC8: 350556886 | BD8: 360285439 | BE8: 370243017 | BF8: 380437896 | BG8: 390882979 | BH8: 401586651 | BI8: 412551299 | BJ8: 423769930 | BK8: 435229381 | BL8: 446911598 | BM8: 458803476
A9: Angola | B9: AGO | C9: Population, total | D9: SP.POP.TOTL | E9: 5454938 | F9: 5531451 | G9: 5608499 | H9: 5679409 | I9: 5734995 | J9: 5770573 | K9: 5781305 | L9: 5774440 | M9: 5771973 | N9: 5803677 | O9: 5890360 | P9: 6041239 | Q9: 6248965 | R9: 6497283 | S9: 6761623 | T9: 7023994 | U9: 7279630 | V9: 7533814 | W9: 7790774 | X9: 8058112 | Y9: 8341290 | Z9: 8640478 | AA9: 8952971 | AB9: 9278104 | AC9: 9614756 | AD9: 9961993 | AE9: 10320116 | AF9: 10689247 | AG9: 11068051 | AH9: 11454784 | AI9: 11848385 | AJ9: 12248901 | AK9: 12657361 | AL9: 13075044 | AM9: 13503753 | AN9: 13945205 | AO9: 14400722 | AP9: 14871572 | AQ9: 15359600 | AR9: 15866871 | AS9: 16395477 | AT9: 16945753 | AU9: 17519418 | AV9: 18121477 | AW9: 18758138 | AX9: 19433604 | AY9: 20149905 | AZ9: 20905360 | BA9: 21695636 | BB9: 22514275 | BC9: 23356247 | BD9: 24220660 | BE9: 25107925 | BF9: 26015786 | BG9: 26941773 | BH9: 27884380 | BI9: 28842482 | BJ9: 29816769 | BK9: 30809787 | BL9: 31825299 | BM9: 32866268
A10: Albania | B10: ALB | C10: Population, total | D10: SP.POP.TOTL | E10: 1608800 | F10: 1659800 | G10: 1711319 | H10: 1762621 | I10: 1814135 | J10: 1864791 | K10: 1914573 | L10: 1965598 | M10: 2022272 | N10: 2081695 | O10: 2135479 | P10: 2187853 | Q10: 2243126 | R10: 2296752 | S10: 2350124 | T10: 2404831 | U10: 2458526 | V10: 2513546 | W10: 2566266 | X10: 2617832 | Y10: 2671997 | Z10: 2726056 | AA10: 2784278 | AB10: 2843960 | AC10: 2904429 | AD10: 2964762 | AE10: 3022635 | AF10: 3083605 | AG10: 3142336 | AH10: 3227943 | AI10: 3286542 | AJ10: 3266790 | AK10: 3247039 | AL10: 3227287 | AM10: 3207536 | AN10: 3187784 | AO10: 3168033 | AP10: 3148281 | AQ10: 3128530 | AR10: 3108778 | AS10: 3089027 | AT10: 3060173 | AU10: 3051010 | AV10: 3039616 | AW10: 3026939 | AX10: 3011487 | AY10: 2992547 | AZ10: 2970017 | BA10: 2947314 | BB10: 2927519 | BC10: 2913021 | BD10: 2905195 | BE10: 2900401 | BF10: 2895092 | BG10: 2889104 | BH10: 2880703 | BI10: 2876101 | BJ10: 2873457 | BK10: 2866376 | BL10: 2854191 | BM10: 2837743
A11: Andorra | B11: AND | C11: Population, total | D11: SP.POP.TOTL | E11: 13410 | F11: 14378 | G11: 15379 | H11: 16407 | I11: 17466 | J11: 18542 | K11: 19646 | L11: 20760 | M11: 21886 | N11: 23053 | O11: 24275 | P11: 25571 | Q11: 26885 | R11: 28232 | S11: 29515 | T11: 30705 | U11: 31782 | V11: 32769 | W11: 33744 | X11: 34825 | Y11: 36063 | Z11: 37498 | AA11: 39115 | AB11: 40854 | AC11: 42706 | AD11: 44593 | AE11: 46520 | AF11: 48459 | AG11: 50433 | AH11: 52452 | AI11: 54508 | AJ11: 56666 | AK11: 58882 | AL11: 60974 | AM11: 62676 | AN11: 63860 | AO11: 64363 | AP11: 64318 | AQ11: 64140 | AR11: 64368 | AS11: 65390 | AT11: 67344 | AU11: 70048 | AV11: 73180 | AW11: 76250 | AX11: 78871 | AY11: 80995 | AZ11: 82682 | BA11: 83860 | BB11: 84461 | BC11: 84454 | BD11: 83748 | BE11: 82427 | BF11: 80770 | BG11: 79213 | BH11: 77993 | BI11: 77295 | BJ11: 76997 | BK11: 77008 | BL11: 77146 | BM11: 77265
A12: Arab World | B12: ARB | C12: Population, total | D12: SP.POP.TOTL | E12: 92197715 | F12: 94724540 | G12: 97334438 | H12: 100034191 | I12: 102832792 | J12: 105736428 | K12: 108758634 | L12: 111899335 | M12: 115136161 | N12: 118437193 | O12: 121785630 | P12: 125164720 | Q12: 128598743 | R12: 132161302 | S12: 135952270 | T12: 140040580 | U12: 144453278 | V12: 149161836 | W12: 154111160 | X12: 159218539 | Y12: 164420771 | Z12: 169698978 | AA12: 175061794 | AB12: 180505967 | AC12: 186035280 | AD12: 191650328 | AE12: 197338140 | AF12: 203084958 | AG12: 208889669 | AH12: 214753965 | AI12: 222653371 | AJ12: 228731671 | AK12: 232956364 | AL12: 239243294 | AM12: 245449429 | AN12: 253107302 | AO12: 259000937 | AP12: 264822167 | AQ12: 270575777 | AR12: 276393809 | AS12: 282344141 | AT12: 288432153 | AU12: 294665202 | AV12: 301113869 | AW12: 307862846 | AX12: 314965776 | AY12: 322452764 | AZ12: 330290752 | BA12: 338395936 | BB12: 346629179 | BC12: 354890097 | BD12: 363156846 | BE12: 371437642 | BF12: 379696477 | BG12: 387899835 | BH12: 396028301 | BI12: 404042892 | BJ12: 411942825 | BK12: 419851989 | BL12: 427870273 | BM12: 436080728
A13: United Arab Emirates | B13: ARE | C13: Population, total | D13: SP.POP.TOTL | E13: 92417 | F13: 100801 | G13: 112112 | H13: 125130 | I13: 138049 | J13: 149855 | K13: 159979 | L13: 169768 | M13: 182620 | N13: 203103 | O13: 234512 | P13: 277463 | Q13: 330968 | R13: 394625 | S13: 467457 | T13: 548295 | U13: 637926 | V13: 735347 | W13: 835498 | X13: 931752 | Y13: 1019507 | Z13: 1096602 | AA13: 1164816 | AB13: 1228457 | AC13: 1293970 | AD13: 1366165 | AE13: 1446386 | AF13: 1533526 | AG13: 1627068 | AH13: 1725676 | AI13: 1828437 | AJ13: 1937159 | AK13: 2052892 | AL13: 2173135 | AM13: 2294377 | AN13: 2415099 | AO13: 2539121 | AP13: 2671361 | AQ13: 2813214 | AR13: 2966029 | AS13: 3134067 | AT13: 3302722 | AU13: 3478769 | AV13: 3711931 | AW13: 4068577 | AX13: 4588222 | AY13: 5300172 | AZ13: 6168846 | BA13: 7089486 | BB13: 7917368 | BC13: 8549998 | BD13: 8946778 | BE13: 9141598 | BF13: 9197908 | BG13: 9214182 | BH13: 9262896 | BI13: 9360975 | BJ13: 9487206 | BK13: 9630966 | BL13: 9770526 | BM13: 9890400
A14: Argentina | B14: ARG | C14: Population, total | D14: SP.POP.TOTL | E14: 20481781 | F14: 20817270 | G14: 21153042 | H14: 21488916 | I14: 21824427 | J14: 22159644 | K14: 22494031 | L14: 22828872 | M14: 23168268 | N14: 23517613 | O14: 23880564 | P14: 24259564 | Q14: 24653172 | R14: 25056475 | S14: 25462305 | T14: 25865775 | U14: 26264681 | V14: 26661397 | W14: 27061041 | X14: 27471046 | Y14: 27896532 | Z14: 28338514 | AA14: 28794550 | AB14: 29262049 | AC14: 29737097 | AD14: 30216284 | AE14: 30698964 | AF14: 31184411 | AG14: 31668939 | AH14: 32148137 | AI14: 32618648 | AJ14: 33079002 | AK14: 33529320 | AL14: 33970103 | AM14: 34402669 | AN14: 34828168 | AO14: 35246376 | AP14: 35657438 | AQ14: 36063451 | AR14: 36467218 | AS14: 36870796 | AT14: 37275644 | AU14: 37681743 | AV14: 38087866 | AW14: 38491970 | AX14: 38892924 | AY14: 39289876 | AZ14: 39684303 | BA14: 40080159 | BB14: 40482786 | BC14: 40788453 | BD14: 41261490 | BE14: 41733271 | BF14: 42202935 | BG14: 42669500 | BH14: 43131966 | BI14: 43590368 | BJ14: 44044811 | BK14: 44494502 | BL14: 44938712 | BM14: 45376763
A15: Armenia | B15: ARM | C15: Population, total | D15: SP.POP.TOTL | E15: 1874119 | F15: 1941498 | G15: 2009524 | H15: 2077584 | I15: 2145004 | J15: 2211316 | K15: 2276038 | L15: 2339133 | M15: 2401142 | N15: 2462938 | O15: 2525067 | P15: 2587716 | Q15: 2650484 | R15: 2712780 | S15: 2773750 | T15: 2832752 | U15: 2889583 | V15: 2944375 | W15: 2997419 | X15: 3049107 | Y15: 3099759 | Z15: 3148096 | AA15: 3193696 | AB15: 3238592 | AC15: 3285593 | AD15: 3335935 | AE15: 3392264 | AF15: 3451947 | AG15: 3504667 | AH15: 3536473 | AI15: 3538164 | AJ15: 3505249 | AK15: 3442820 | AL15: 3363111 | AM15: 3283664 | AN15: 3217349 | AO15: 3168213 | AP15: 3133081 | AQ15: 3108691 | AR15: 3089020 | AS15: 3069597 | AT15: 3050686 | AU15: 3033976 | AV15: 3017938 | AW15: 3000715 | AX15: 2981262 | AY15: 2958301 | AZ15: 2932615 | BA15: 2907615 | BB15: 2888094 | BC15: 2877314 | BD15: 2876536 | BE15: 2884239 | BF15: 2897593 | BG15: 2912403 | BH15: 2925559 | BI15: 2936147 | BJ15: 2944789 | BK15: 2951741 | BL15: 2957728 | BM15: 2963234
A16: American Samoa | B16: ASM | C16: Population, total | D16: SP.POP.TOTL | E16: 20127 | F16: 20605 | G16: 21246 | H16: 22029 | I16: 22850 | J16: 23675 | K16: 24473 | L16: 25235 | M16: 25980 | N16: 26698 | O16: 27362 | P16: 27982 | Q16: 28564 | R16: 29103 | S16: 29595 | T16: 30045 | U16: 30455 | V16: 30834 | W16: 31262 | X16: 31842 | Y16: 32648 | Z16: 33697 | AA16: 34969 | AB16: 36413 | AC16: 37946 | AD16: 39521 | AE16: 41114 | AF16: 42741 | AG16: 44346 | AH16: 45894 | AI16: 47351 | AJ16: 48682 | AK16: 49900 | AL16: 51025 | AM16: 52099 | AN16: 53158 | AO16: 54209 | AP16: 55227 | AQ16: 56180 | AR16: 57049 | AS16: 57816 | AT16: 58496 | AU16: 59077 | AV16: 59495 | AW16: 59684 | AX16: 59557 | AY16: 59109 | AZ16: 58367 | BA16: 57490 | BB16: 56675 | BC16: 56084 | BD16: 55755 | BE16: 55669 | BF16: 55717 | BG16: 55791 | BH16: 55806 | BI16: 55739 | BJ16: 55617 | BK16: 55461 | BL16: 55312 | BM16: 55197
... A73: Euro area | B73: EMU | C73: Population, total | D73: SP.POP.TOTL | E73: 265203956 | F73: 267621091 | G73: 270110063 | H73: 272655396 | I73: 275163380 | J73: 277650954 | K73: 279969050 | L73: 281974870 | M73: 283866408 | N73: 285778639 | O73: 287338854 | P73: 288923399 | Q73: 290874612 | R73: 292728242 | S73: 294399217 | T73: 295923529 | U73: 297251532 | V73: 298441848 | W73: 299652841 | X73: 300886487 | Y73: 302184216 | Z73: 303343114 | AA73: 304174261 | AB73: 304787497 | AC73: 305299144 | AD73: 305877743 | AE73: 306640636 | AF73: 307488377 | AG73: 308516476 | AH73: 309837575 | AI73: 311262608 | AJ73: 312708132 | AK73: 314162056 | AL73: 315449093 | AM73: 316366781 | AN73: 317181461 | AO73: 318003013 | AP73: 318761752 | AQ73: 319433985 | AR73: 320258891 | AS73: 321310789 | AT73: 322547874 | AU73: 324125339 | AV73: 325885957 | AW73: 327682513 | AX73: 329380417 | AY73: 330922785 | AZ73: 332645162 | BA73: 334274725 | BB73: 335360891 | BC73: 336151482 | BD73: 335419656 | BE73: 336159199 | BF73: 337302111 | BG73: 338462234 | BH73: 339488382 | BI73: 340481755 | BJ73: 341217243 | BK73: 341979171 | BL73: 342282081 | BM73: 342949773
A74: Eritrea | B74: ERI | C74: Population, total | D74: SP.POP.TOTL | E74: 1007586 | F74: 1033320 | G74: 1060489 | H74: 1088859 | I74: 1118152 | J74: 1148188 | K74: 1178875 | L74: 1210304 | M74: 1242633 | N74: 1276122 | O74: 1310947 | P74: 1347180 | Q74: 1384789 | R74: 1423749 | S74: 1463986 | T74: 1505438 | U74: 1547978 | V74: 1591622 | W74: 1636771 | X74: 1683932 | Y74: 1733423 | Z74: 1784557 | AA74: 1836825 | AB74: 1890556 | AC74: 1946299 | AD74: 2003942 | AE74: 2064803 | AF74: 2127421 | AG74: 2185607 | AH74: 2231144 | AI74: 2258649 | AJ74: 2266356 | AK74: 2257593 | AL74: 2238631 | AM74: 2218436 | AN74: 2204227 | AO74: 2196467 | AP74: 2195192 | AQ74: 2206439 | AR74: 2237412 | AS74: 2292413 | AT74: 2374721 | AU74: 2481059 | AV74: 2600972 | AW74: 2719809 | AX74: 2826653 | AY74: 2918209 | AZ74: 2996540 | BA74: 3062782 | BB74: 3119920 | BC74: 3170437 | BD74: 3213969
A75: Spain | B75: ESP | C75: Population, total | D75: SP.POP.TOTL | E75: 30455000 | F75: 30739250 | G75: 31023366 | H75: 31296651 | I75: 31609195 | J75: 31954292 | K75: 32283194 | L75: 32682947 | M75: 33113134 | N75: 33441054 | O75: 33814531 | P75: 34224490 | Q75: 34604469 | R75: 34988947 | S75: 35373335 | T75: 35757900 | U75: 36137812 | V75: 36511638 | W75: 36864898 | X75: 37191330 | Y75: 37491165 | Z75: 37758631 | AA75: 37986012 | AB75: 38171525 | AC75: 38330364 | AD75: 38469512 | AE75: 38584624 | AF75: 38684815 | AG75: 38766939 | AH75: 38827764 | AI75: 38867322 | AJ75: 38966376 | AK75: 39157685 | AL75: 39361262 | AM75: 39549108 | AN75: 39724050 | AO75: 39889852 | AP75: 40057389 | AQ75: 40223509 | AR75: 40386875 | AS75: 40567864 | AT75: 40850412 | AU75: 41431558 | AV75: 42187645 | AW75: 42921895 | AX75: 43653155 | AY75: 44397319 | AZ75: 45226803 | BA75: 45954106 | BB75: 46362946 | BC75: 46576897 | BD75: 46742697 | BE75: 46773055 | BF75: 46620045 | BG75: 46480882 | BH75: 46444832 | BI75: 46484062 | BJ75: 46593236 | BK75: 46797754 | BL75: 47133521 | BM75: 47351567
A76: Estonia | B76: EST | C76: Population, total | D76: SP.POP.TOTL | E76: 1211537 | F76: 1225077 | G76: 1241623 | H76: 1258857 | I76: 1277086 | J76: 1294566 | K76: 1308597 | L76: 1318946 | M76: 1331214 | N76: 1345249 | O76: 1360076 | P76: 1376955 | Q76: 1392518 | R76: 1405951 | S76: 1418169 | T76: 1429352 | U76: 1439576 | V76: 1450211 | W76: 1460188 | X76: 1468333 | Y76: 1477219 | Z76: 1487666 | AA76: 1498414 | AB76: 1508745 | AC76: 1518617 | AD76: 1528781 | AE76: 1540190 | AF76: 1552221 | AG76: 1561900 | AH76: 1568131 | AI76: 1569174 | AJ76: 1561314 | AK76: 1533091 | AL76: 1494128 | AM76: 1462514 | AN76: 1436634 | AO76: 1415594 | AP76: 1399535 | AQ76: 1386156 | AR76: 1390244 | AS76: 1396985 | AT76: 1388115 | AU76: 1379350 | AV76: 1370720 | AW76: 1362550 | AX76: 1354775 | AY76: 1346810 | AZ76: 1340680 | BA76: 1337090 | BB76: 1334515 | BC76: 1331475 | BD76: 1327439 | BE76: 1322696 | BF76: 1317997 | BG76: 1314545 | BH76: 1315407 | BI76: 1315790 | BJ76: 1317384 | BK76: 1321977 | BL76: 1326898 | BM76: 1331057
A77: Ethiopia | B77: ETH | C77: Population, total | D77: SP.POP.TOTL | E77: 22151284 | F77: 22671193 | G77: 23221385 | H77: 23798418 | I77: 24397010 | J77: 25013634 | K77: 25641040 | L77: 26280135 | M77: 26944386 | N77: 27652715 | O77: 28415080 | P77: 29248650 | Q77: 30140799 | R77: 31036670 | S77: 31861353 | T77: 32566855 | U77: 33128151 | V77: 33577240 | W77: 33993301 | X77: 34487806 | Y77: 35141703 | Z77: 35984531 | AA77: 36995246 | AB77: 38142679 | AC77: 39374346 | AD77: 40652146 | AE77: 41965696 | AF77: 43329238 | AG77: 44757205 | AH77: 46272308 | AI77: 47887864 | AJ77: 49609976 | AK77: 51423591 | AL77: 53295556 | AM77: 55180993 | AN77: 57047906 | AO77: 58883531 | AP77: 60697443 | AQ77: 62507724 | AR77: 64343008 | AS77: 66224809 | AT77: 68159422 | AU77: 70142090 | AV77: 72170581 | AW77: 74239508 | AX77: 76346310 | AY77: 78489205 | AZ77: 80674343 | BA77: 82916236 | BB77: 85233923 | BC77: 87639962 | BD77: 90139928 | BE77: 92726982 | BF77: 95385793 | BG77: 98094264 | BH77: 100835453 | BI77: 103603461 | BJ77: 106399926 | BK77: 109224410 | BL77: 112078727 | BM77: 114963583
A78: European Union | B78: EUU | C78: Population, total | D78: SP.POP.TOTL | E78: 356906098 | F78: 359998408 | G78: 363200480 | H78: 366516509 | I78: 369850237 | J78: 373032729 | K78: 376039129 | L78: 378917964 | M78: 381605442 | N78: 384216977 | O78: 386322917 | P78: 388391948 | Q78: 390995000 | R78: 393524745 | S78: 395949381 | T78: 398316579 | U78: 400473497 | V78: 402425493 | W78: 404271789 | X78: 406051882 | Y78: 407875838 | Z78: 409551911 | AA78: 410895608 | AB78: 411974424 | AC78: 412931321 | AD78: 413924499 | AE78: 415076367 | AF78: 416301843 | AG78: 417653046 | AH78: 419073139 | AI78: 420477999 | AJ78: 421730520 | AK78: 422963890 | AL78: 424341124 | AM78: 425399126 | AN78: 426203356 | AO78: 426896861 | AP78: 427538048 | AQ78: 428109867 | AR78: 428815486 | AS78: 429328622 | AT78: 429895628 | AU78: 430881947 | AV78: 432415932 | AW78: 434040244 | AX78: 435581949 | AY78: 436998045 | AZ78: 438468397 | BA78: 439876674 | BB78: 440917801 | BC78: 441532415 | BD78: 440746989 | BE78: 441395937 | BF78: 442469469 | BG78: 443576675 | BH78: 444543761 | BI78: 445487730 | BJ78: 446186344 | BK78: 446915113 | BL78: 447196538 | BM78: 447794691
A79: Fragile and conflict affected situations | B79: FCS | C79: Population, total | D79: SP.POP.TOTL | E79: 208280083 | F79: 213082100 | G79: 218087139 | H79: 223284589 | I79: 228670583 | J79: 234243249 | K79: 240005133 | L79: 245962230 | M79: 252116419 | N79: 258473157 | O79: 265037231 | P79: 271800288 | Q79: 278767597 | R79: 285961194 | S79: 293417700 | T79: 301154406 | U79: 309196463 | V79: 317520801 | W79: 326050578 | X79: 334679714 | Y79: 343334222 | Z79: 352006783 | AA79: 360736356 | AB79: 369569548 | AC79: 378570396 | AD79: 387802210 | AE79: 397235010 | AF79: 406892515 | AG79: 416947257 | AH79: 427617018 | AI79: 440937023 | AJ79: 453319269 | AK79: 466482751 | AL79: 480128168 | AM79: 493815711 | AN79: 507247502 | AO79: 520303326 | AP79: 533112558 | AQ79: 545728172 | AR79: 558627550 | AS79: 572303917 | AT79: 586760366 | AU79: 601848734 | AV79: 617468591 | AW79: 633460044 | AX79: 649704454 | AY79: 666174377 | AZ79: 682901570 | BA79: 700030438 | BB79: 717553793 | BC79: 735448194 | BD79: 753858934 | BE79: 772742559 | BF79: 791943328 | BG79: 811249811 | BH79: 830536041 | BI79: 849739853 | BJ79: 868954263 | BK79: 888488369 | BL79: 908739462 | BM79: 930006546
A80: Finland | B80: FIN | C80: Population, total | D80: SP.POP.TOTL | E80: 4429634 | F80: 4461005 | G80: 4491443 | H80: 4523309 | I80: 4548543 | J80: 4563732 | K80: 4580869 | L80: 4605744 | M80: 4626469 | N80: 4623785 | O80: 4606307 | P80: 4612124 | Q80: 4639657 | R80: 4666081 | S80: 4690574 | T80: 4711440 | U80: 4725664 | V80: 4738902 | W80: 4752528 | X80: 4764690 | Y80: 4779535 | Z80: 4799964 | AA80: 4826933 | AB80: 4855787 | AC80: 4881803 | AD80: 4902206 | AE80: 4918154 | AF80: 4932123 | AG80: 4946481 | AH80: 4964371 | AI80: 4986431 | AJ80: 5013740 | AK80: 5041992 | AL80: 5066447 | AM80: 5088333 | AN80: 5107790 | AO80: 5124573 | AP80: 5139835 | AQ80: 5153498 | AR80: 5165474 | AS80: 5176209 | AT80: 5188008 | AU80: 5200598 | AV80: 5213014 | AW80: 5228172 | AX80: 5246096 | AY80: 5266268 | AZ80: 5288720 | BA80: 5313399 | BB80: 5338871 | BC80: 5363352 | BD80: 5388272 | BE80: 5413971 | BF80: 5438972 | BG80: 5461512 | BH80: 5479531 | BI80: 5495303 | BJ80: 5508214 | BK80: 5515525 | BL80: 5521606 | BM80: 5530719
A81: Fiji | B81: FJI | C81: Population, total | D81: SP.POP.TOTL | E81: 393480 | F81: 407244 | G81: 421673 | H81: 436303 | I81: 450538 | J81: 463960 | K81: 476399 | L81: 487973 | M81: 498944 | N81: 509708 | O81: 520561 | P81: 531622 | Q81: 542843 | R81: 554143 | S81: 565418 | T81: 576626 | U81: 587561 | V81: 598299 | W81: 609383 | X81: 621584 | Y81: 635312 | Z81: 651032 | AA81: 668281 | AB81: 685497 | AC81: 700478 | AD81: 711770 | AE81: 718642 | AF81: 721776 | AG81: 722924 | AH81: 724602 | AI81: 728575 | AJ81: 735398 | AK81: 744470 | AL81: 754962 | AM81: 765607 | AN81: 775428 | AO81: 784389 | AP81: 792736 | AQ81: 800148 | AR81: 806302 | AS81: 811011 | AT81: 813923 | AU81: 815257 | AV81: 816078 | AW81: 817864 | AX81: 821606 | AY81: 827869 | AZ81: 836185 | BA81: 845356 | BB81: 853636 | BC81: 859816 | BD81: 863451 | BE81: 865065 | BF81: 865602 | BG81: 866447 | BH81: 868632 | BI81: 872406 | BJ81: 877460 | BK81: 883490 | BL81: 889955 | BM81: 896444
A82: France | B82: FRA | C82: Population, total | D82: SP.POP.TOTL | E82: 46621688 | F82: 47240526 | G82: 47904879 | H82: 48582624 | I82: 49230585 | J82: 49818019 | K82: 50330268 | L82: 50775788 | M82: 51175507 | N82: 51561833 | O82: 51957747 | P82: 52371320 | Q82: 52793151 | R82: 53207744 | S82: 53592235 | T82: 53931390 | U82: 54220033 | V82: 54467709 | W82: 54691866 | X82: 54917110 | Y82: 55161510 | Z82: 55430278 | AA82: 55718940 | AB82: 56023775 | AC82: 56337675 | AD82: 56654703 | AE82: 56976126 | AF82: 57302642 | AG82: 57627106 | AH82: 57940199 | AI82: 58235716 | AJ82: 58559309 | AK82: 58851216 | AL82: 59106758 | AM82: 59327200 | AN82: 59541904 | AO82: 59753095 | AP82: 59964841 | AQ82: 60186284 | AR82: 60496708 | AS82: 60912500 | AT82: 61357432 | AU82: 61805266 | AV82: 62244880 | AW82: 62704901 | AX82: 63179356 | AY82: 63621376 | AZ82: 64016227 | BA82: 64374979 | BB82: 64707035 | BC82: 65027505 | BD82: 65342789 | BE82: 65659814 | BF82: 65998685 | BG82: 66312067 | BH82: 66548272 | BI82: 66724104 | BJ82: 66918020 | BK82: 67101930 | BL82: 67248926 | BM82: 67391582
A83: Faroe Islands | B83: FRO | C83: Population, total | D83: SP.POP.TOTL | E83: 34624 | F83: 35074 | G83: 35521 | H83: 35965 | I83: 36409 | J83: 36843 | K83: 37283 | L83: 37705 | M83: 38131 | N83: 38560 | O83: 39008 | P83: 39456 | Q83: 39915 | R83: 40395 | S83: 40847 | T83: 41292 | U83: 41724 | V83: 42133 | W83: 42539 | X83: 42941 | Y83: 43339 | Z83: 43725 | AA83: 44101 | AB83: 44483 | AC83: 44895 | AD83: 45328 | AE83: 45812 | AF83: 46340 | AG83: 46833 | AH83: 47159 | AI83: 47276 | AJ83: 47123 | AK83: 46746 | AL83: 46277 | AM83: 45848 | AN83: 45625 | AO83: 45624 | AP83: 45789 | AQ83: 46094 | AR83: 46428 | AS83: 46738 | AT83: 46999 | AU83: 47235 | AV83: 47439 | AW83: 47600 | AX83: 47731 | AY83: 47793 | AZ83: 47825 | BA83: 47822 | BB83: 47814 | BC83: 47803 | BD83: 47815 | BE83: 47843 | BF83: 47901 | BG83: 47965 | BH83: 48055 | BI83: 48173 | BJ83: 48326 | BK83: 48497 | BL83: 48677 | BM83: 48865
A84: Micronesia, Fed. Sts. | B84: FSM | C84: Population, total | D84: SP.POP.TOTL | E84: 44510 | F84: 45939 | G84: 47372 | H84: 48856 | I84: 50476 | J84: 52224 | K84: 54192 | L84: 56308 | M84: 58386 | N84: 60146 | O84: 61415 | P84: 62089 | Q84: 62275 | R84: 62268 | S84: 62456 | T84: 63122 | U84: 64360 | V84: 66079 | W84: 68196 | X84: 70515 | Y84: 72936 | Z84: 75422 | AA84: 78015 | AB84: 80630 | AC84: 83192 | AD84: 85641 | AE84: 87904 | AF84: 89985 | AG84: 91984 | AH84: 94062 | AI84: 96304 | AJ84: 98779 | AK84: 101386 | AL84: 103901 | AM84: 106030 | AN84: 107535 | AO84: 108311 | AP84: 108473 | AQ84: 108206 | AR84: 107769 | AS84: 107405 | AT84: 107170 | AU84: 107027 | AV84: 106902 | AW84: 106624 | AX84: 106135 | AY84: 105374 | AZ84: 104442 | BA84: 103549 | BB84: 102971 | BC84: 102916 | BD84: 103448 | BE84: 104506 | BF84: 105922 | BG84: 107444 | BH84: 108886 | BI84: 110215 | BJ84: 111461 | BK84: 112640 | BL84: 113811 | BM84: 115021
A85: Gabon | B85: GAB | C85: Population, total | D85: SP.POP.TOTL | E85: 500922 | F85: 505793 | G85: 511285 | H85: 517573 | I85: 524891 | J85: 533357 | K85: 543119 | L85: 554054 | M85: 565763 | N85: 577644 | O85: 589317 | P85: 600608 | Q85: 611705 | R85: 622914 | S85: 634739 | T85: 647538 | U85: 661398 | V85: 676264 | W85: 692078 | X85: 708788 | Y85: 726335 | Z85: 744695 | AA85: 763932 | AB85: 784056 | AC85: 805117 | AD85: 827107 | AE85: 850052 | AF85: 873871 | AG85: 898472 | AH85: 923714 | AI85: 949493 | AJ85: 975785 | AK85: 1002573 | AL85: 1029769 | AM85: 1057252 | AN85: 1084951 | AO85: 1112944 | AP85: 1141332 | AQ85: 1170061 | AR85: 1199058 | AS85: 1228359 | AT85: 1258008 | AU85: 1288310 | AV85: 1319946 | AW85: 1353788 | AX85: 1390550 | AY85: 1430144 | AZ85: 1472565 | BA85: 1518538 | BB85: 1568925 | BC85: 1624146 | BD85: 1684629 | BE85: 1749677 | BF85: 1817070 | BG85: 1883801 | BH85: 1947690 | BI85: 2007882 | BJ85: 2064812 | BK85: 2119275 | BL85: 2172578 | BM85: 2225728
A86: United Kingdom | B86: GBR | C86: Population, total | D86: SP.POP.TOTL | E86: 52400000 | F86: 52800000 | G86: 53250000 | H86: 53650000 | I86: 54000000 | J86: 54348050 | K86: 54648500 | L86: 54943600 | M86: 55211700 | N86: 55441750 | O86: 55663250 | P86: 55896223 | Q86: 56086065 | R86: 56194527 | S86: 56229974 | T86: 56225800 | U86: 56211968 | V86: 56193492 | W86: 56196504 | X86: 56246951 | Y86: 56314216 | Z86: 56333829 | AA86: 56313641 | AB86: 56332848 | AC86: 56422072 | AD86: 56550268 | AE86: 56681396 | AF86: 56802050 | AG86: 56928327 | AH86: 57076711 | AI86: 57247586 | AJ86: 57424897 | AK86: 57580402 | AL86: 57718614 | AM86: 57865745 | AN86: 58019030 | AO86: 58166950 | AP86: 58316954 | AQ86: 58487141 | AR86: 58682466 | AS86: 58892514 | AT86: 59119673 | AU86: 59370479 | AV86: 59647577 | AW86: 59987905 | AX86: 60401206 | AY86: 60846820 | AZ86: 61322463 | BA86: 61806995 | BB86: 62276270 | BC86: 62766365 | BD86: 63258810 | BE86: 63700215 | BF86: 64128273 | BG86: 64602298 | BH86: 65116219 | BI86: 65611593 | BJ86: 66058859 | BK86: 66460344 | BL86: 66836327 | BM86: 67215293
... A114: India | B114: IND | C114: Population, total | D114: SP.POP.TOTL | E114: 450547675 | F114: 459642166 | G114: 469077191 | H114: 478825602 | I114: 488848139 | J114: 499123328 | K114: 509631509 | L114: 520400577 | M114: 531513834 | N114: 543084333 | O114: 555189797 | P114: 567868021 | Q114: 581087255 | R114: 594770136 | S114: 608802595 | T114: 623102900 | U114: 637630085 | V114: 652408766 | W114: 667499815 | X114: 682995348 | Y114: 698952837 | Z114: 715384997 | AA114: 732239498 | AB114: 749428958 | AC114: 766833411 | AD114: 784360012 | AE114: 801975250 | AF114: 819682095 | AG114: 837468938 | AH114: 855334675 | AI114: 873277799 | AJ114: 891273202 | AK114: 909307018 | AL114: 927403866 | AM114: 945601828 | AN114: 963922586 | AO114: 982365248 | AP114: 1000900028 | AQ114: 1019483586 | AR114: 1038058154 | AS114: 1056575548 | AT114: 1075000094 | AU114: 1093317187 | AV114: 1111523146 | AW114: 1129623466 | AX114: 1147609924 | AY114: 1165486291 | AZ114: 1183209471 | BA114: 1200669762 | BB114: 1217726217 | BC114: 1234281163 | BD114: 1250287939 | BE114: 1265780243 | BF114: 1280842119 | BG114: 1295600768 | BH114: 1310152392 | BI114: 1324517250 | BJ114: 1338676779 | BK114: 1352642283 | BL114: 1366417756 | BM114: 1380004385
A115: Not classified | B115: INX | C115: Population, total | D115: SP.POP.TOTL
A116: Ireland | B116: IRL | C116: Population, total | D116: SP.POP.TOTL | E116: 2828600 | F116: 2824400 | G116: 2836050 | H116: 2852650 | I116: 2866550 | J116: 2877300 | K116: 2888800 | L116: 2902450 | M116: 2915550 | N116: 2932650 | O116: 2957250 | P116: 2992050 | Q116: 3036850 | R116: 3085950 | S116: 3137500 | T116: 3189550 | U116: 3238050 | V116: 3282200 | W116: 3329100 | X116: 3373750 | Y116: 3412800 | Z116: 3453000 | AA116: 3485800 | AB116: 3510600 | AC116: 3532423 | AD116: 3538082 | AE116: 3539690 | AF116: 3540057 | AG116: 3524949 | AH116: 3511009 | AI116: 3513974 | AJ116: 3534235 | AK116: 3558430 | AL116: 3576261 | AM116: 3590386 | AN116: 3608841 | AO116: 3637510 | AP116: 3674171 | AQ116: 3712696 | AR116: 3754786 | AS116: 3805174 | AT116: 3866243 | AU116: 3931947 | AV116: 3996521 | AW116: 4070262 | AX116: 4159914 | AY116: 4273591 | AZ116: 4398942 | BA116: 4489544 | BB116: 4535375 | BC116: 4560155 | BD116: 4580084 | BE116: 4599533 | BF116: 4623816 | BG116: 4657740 | BH116: 4701957 | BI116: 4755335 | BJ116: 4807388 | BK116: 4867316 | BL116: 4934340 | BM116: 4994724
A117: Iran, Islamic Rep. | B117: IRN | C117: Population, total | D117: SP.POP.TOTL | E117: 21906909 | F117: 22480371 | G117: 23071309 | H117: 23680246 | I117: 24307855 | J117: 24954865 | K117: 25624380 | L117: 26317776 | M117: 27032576 | N117: 27764928 | O117: 28513872 | P117: 29281583 | Q117: 30075295 | R117: 30905721 | S117: 31786481 | T117: 32729772 | U117: 33733975 | V117: 34803041 | W117: 35960811 | X117: 37237145 | Y117: 38650244 | Z117: 40199911 | AA117: 41869231 | AB117: 43636838 | AC117: 45472792 | AD117: 47347197 | AE117: 49260263 | AF117: 51193782 | AG117: 53077312 | AH117: 54822005 | AI117: 56366212 | AJ117: 57679025 | AK117: 58780376 | AL117: 59723761 | AM117: 60590608 | AN117: 61442658 | AO117: 62294919 | AP117: 63136309 | AQ117: 63971836 | AR117: 64800875 | AS117: 65623397 | AT117: 66449111 | AU117: 67284801 | AV117: 68122947 | AW117: 68951279 | AX117: 69762345 | AY117: 70554756 | AZ117: 71336476 | BA117: 72120608 | BB117: 72924833 | BC117: 73762519 | BD117: 74634959 | BE117: 75539881 | BF117: 76481963 | BG117: 77465769 | BH117: 78492208 | BI117: 79563991 | BJ117: 80673888 | BK117: 81800204 | BL117: 82913893 | BM117: 83992953
A118: Iraq | B118: IRQ | C118: Population, total | D118: SP.POP.TOTL | E118: 7289753 | F118: 7475349 | G118: 7674217 | H118: 7888910 | I118: 8122199 | J118: 8375795 | K118: 8651162 | L118: 8947397 | M118: 9260687 | N118: 9585585 | O118: 9917978 | P118: 10255853 | Q118: 10599661 | R118: 10950888 | S118: 11312062 | T118: 11684579 | U118: 12068675 | V118: 12462059 | W118: 12860678 | X118: 13259107 | Y118: 13653348 | Z118: 14044115 | AA118: 14432466 | AB118: 14815653 | AC118: 15190396 | AD118: 15555807 | AE118: 15909764 | AF118: 16257072 | AG118: 16612319 | AH118: 16994942 | AI118: 17419113 | AJ118: 17889457 | AK118: 18402740 | AL118: 18955087 | AM118: 19539348 | AN118: 20149342 | AO118: 20783073 | AP118: 21439579 | AQ118: 22114330 | AR118: 22802061 | AS118: 23497589 | AT118: 24208178 | AU118: 24931922 | AV118: 25644503 | AW118: 26313838 | AX118: 26922279 | AY118: 27448124 | AZ118: 27911242 | BA118: 28385739 | BB118: 28973157 | BC118: 29741977 | BD118: 30725305 | BE118: 31890012 | BF118: 33157061 | BG118: 34411949 | BH118: 35572269 | BI118: 36610632 | BJ118: 37552789 | BK118: 38433604 | BL118: 39309789 | BM118: 40222503
A119: Iceland | B119: ISL | C119: Population, total | D119: SP.POP.TOTL | E119: 175574 | F119: 179029 | G119: 182378 | H119: 185653 | I119: 188983 | J119: 192286 | K119: 195570 | L119: 198751 | M119: 201488 | N119: 203369 | O119: 204438 | P119: 206098 | Q119: 209137 | R119: 212317 | S119: 215209 | T119: 217979 | U119: 220154 | V119: 221799 | W119: 223537 | X119: 225735 | Y119: 228138 | Z119: 230755 | AA119: 233860 | AB119: 236977 | AC119: 239511 | AD119: 241405 | AE119: 243180 | AF119: 245859 | AG119: 249740 | AH119: 252852 | AI119: 254826 | AJ119: 257797 | AK119: 261057 | AL119: 263725 | AM119: 266021 | AN119: 267468 | AO119: 268916 | AP119: 271128 | AQ119: 274047 | AR119: 277381 | AS119: 281205 | AT119: 284968 | AU119: 287523 | AV119: 289521 | AW119: 292074 | AX119: 296734 | AY119: 303782 | AZ119: 311566 | BA119: 317414 | BB119: 318499 | BC119: 318041 | BD119: 319014 | BE119: 320716 | BF119: 323764 | BG119: 327386 | BH119: 330815 | BI119: 335439 | BJ119: 343400 | BK119: 352721 | BL119: 360563 | BM119: 366425
A120: Israel | B120: ISR | C120: Population, total | D120: SP.POP.TOTL | E120: 2114020 | F120: 2185000 | G120: 2293000 | H120: 2379000 | I120: 2475000 | J120: 2563000 | K120: 2629000 | L120: 2745000 | M120: 2803000 | N120: 2877000 | O120: 2974000 | P120: 3069000 | Q120: 3148000 | R120: 3278000 | S120: 3377000 | T120: 3455000 | U120: 3533000 | V120: 3613000 | W120: 3690000 | X120: 3786000 | Y120: 3878000 | Z120: 3956000 | AA120: 4031000 | AB120: 4105000 | AC120: 4159000 | AD120: 4233000 | AE120: 4299000 | AF120: 4369000 | AG120: 4442000 | AH120: 4518000 | AI120: 4660000 | AJ120: 4949000 | AK120: 5123000 | AL120: 5261000 | AM120: 5399000 | AN120: 5545000 | AO120: 5692000 | AP120: 5836000 | AQ120: 5971000 | AR120: 6125000 | AS120: 6289000 | AT120: 6439000 | AU120: 6570000 | AV120: 6689700 | AW120: 6809000 | AX120: 6930100 | AY120: 7053700 | AZ120: 7180100 | BA120: 7308800 | BB120: 7485600 | BC120: 7623600 | BD120: 7765800 | BE120: 7910500 | BF120: 8059500 | BG120: 8215700 | BH120: 8380100 | BI120: 8546000 | BJ120: 8713300 | BK120: 8882800 | BL120: 9054000 | BM120: 9216900
A121: Italy | B121: ITA | C121: Population, total | D121: SP.POP.TOTL | E121: 50199700 | F121: 50536350 | G121: 50879450 | H121: 51252000 | I121: 51675350 | J121: 52112350 | K121: 52519000 | L121: 52900500 | M121: 53235750 | N121: 53537950 | O121: 53821850 | P121: 54073490 | Q121: 54381345 | R121: 54751406 | S121: 55110868 | T121: 55441001 | U121: 55718260 | V121: 55955411 | W121: 56155143 | X121: 56317749 | Y121: 56433883 | Z121: 56501675 | AA121: 56543548 | AB121: 56564074 | AC121: 56576718 | AD121: 56593071 | AE121: 56596155 | AF121: 56601931 | AG121: 56629288 | AH121: 56671781 | AI121: 56719240 | AJ121: 56758521 | AK121: 56797087 | AL121: 56831821 | AM121: 56843400 | AN121: 56844303 | AO121: 56860281 | AP121: 56890372 | AQ121: 56906744 | AR121: 56916317 | AS121: 56942108 | AT121: 56974100 | AU121: 57059007 | AV121: 57313203 | AW121: 57685327 | AX121: 57969484 | AY121: 58143979 | AZ121: 58438310 | BA121: 58826731 | BB121: 59095365 | BC121: 59277417 | BD121: 59379449 | BE121: 59539717 | BF121: 60233948 | BG121: 60789140 | BH121: 60730582 | BI121: 60627498 | BJ121: 60536709 | BK121: 60421760 | BL121: 59729081 | BM121: 59554023
A122: Jamaica | B122: JAM | C122: Population, total | D122: SP.POP.TOTL | E122: 1628524 | F122: 1651067 | G122: 1676500 | H122: 1703660 | I122: 1730739 | J122: 1756508 | K122: 1780522 | L122: 1803324 | M122: 1825873 | N122: 1849658 | O122: 1875637 | P122: 1904281 | Q122: 1935089 | R122: 1966978 | S122: 1998313 | T122: 2028019 | U122: 2055371 | V122: 2080824 | W122: 2105903 | X122: 2132784 | Y122: 2162839 | Z122: 2196921 | AA122: 2234062 | AB122: 2271735 | AC122: 2306367 | AD122: 2335510 | AE122: 2358165 | AF122: 2375400 | AG122: 2389415 | AH122: 2403464 | AI122: 2419901 | AJ122: 2439329 | AK122: 2461047 | AL122: 2484583 | AM122: 2509042 | AN122: 2533705 | AO122: 2558631 | AP122: 2583914 | AQ122: 2608874 | AR122: 2632677 | AS122: 2654698 | AT122: 2674706 | AU122: 2692843 | AV122: 2709438 | AW122: 2725017 | AX122: 2740000 | AY122: 2754414 | AZ122: 2768229 | BA122: 2781869 | BB122: 2795839 | BC122: 2810464 | BD122: 2825932 | BE122: 2842128 | BF122: 2858710 | BG122: 2875137 | BH122: 2891024 | BI122: 2906242 | BJ122: 2920848 | BK122: 2934853 | BL122: 2948277 | BM122: 2961161
A123: Jordan | B123: JOR | C123: Population, total | D123: SP.POP.TOTL | E123: 933102 | F123: 973983 | G123: 1010647 | H123: 1050212 | I123: 1102404 | J123: 1173603 | K123: 1267063 | L123: 1378995 | M123: 1500168 | N123: 1617427 | O123: 1721315 | P123: 1809193 | Q123: 1883923 | R123: 1948443 | S123: 2007735 | T123: 2065916 | U123: 2123180 | V123: 2179361 | W123: 2237936 | X123: 2303116 | Y123: 2377997 | Z123: 2464870 | AA123: 2563525 | AB123: 2671413 | AC123: 2784457 | AD123: 2900055 | AE123: 3015294 | AF123: 3131800 | AG123: 3256552 | AH123: 3399333 | AI123: 3565888 | AJ123: 3760493 | AK123: 3977667 | AL123: 4201559 | AM123: 4410357 | AN123: 4588842 | AO123: 4732848 | AP123: 4848536 | AQ123: 4943975 | AR123: 5031754 | AS123: 5122495 | AT123: 5217328 | AU123: 5317514 | AV123: 5434036 | AW123: 5580241 | AX123: 5765639 | AY123: 5991547 | AZ123: 6255290 | BA123: 6556473 | BB123: 6893258 | BC123: 7261541 | BD123: 7662858 | BE123: 8089963 | BF123: 8518992 | BG123: 8918822 | BH123: 9266573 | BI123: 9554286 | BJ123: 9785840 | BK123: 9965322 | BL123: 10101697 | BM123: 10203140
A124: Japan | B124: JPN | C124: Population, total | D124: SP.POP.TOTL | E124: 93216000 | F124: 94055000 | G124: 94933000 | H124: 95900000 | I124: 96903000 | J124: 97952000 | K124: 98851000 | L124: 99879000 | M124: 101011000 | N124: 102219000 | O124: 103403000 | P124: 105697000 | Q124: 107188000 | R124: 108707000 | S124: 110162000 | T124: 111573000 | U124: 112775000 | V124: 113872000 | W124: 114913000 | X124: 115890000 | Y124: 116807000 | Z124: 117661000 | AA124: 118480000 | AB124: 119307000 | AC124: 120083000 | AD124: 120837000 | AE124: 121482000 | AF124: 122069000 | AG124: 122578000 | AH124: 123069000 | AI124: 123478000 | AJ124: 123964000 | AK124: 124425000 | AL124: 124829000 | AM124: 125178000 | AN124: 125472000 | AO124: 125757000 | AP124: 126057000 | AQ124: 126400000 | AR124: 126631000 | AS124: 126843000 | AT124: 127149000 | AU124: 127445000 | AV124: 127718000 | AW124: 127761000 | AX124: 127773000 | AY124: 127854000 | AZ124: 128001000 | BA124: 128063000 | BB124: 128047000 | BC124: 128070000 | BD124: 127833000 | BE124: 127629000 | BF124: 127445000 | BG124: 127276000 | BH124: 127141000 | BI124: 126994511 | BJ124: 126785797 | BK124: 126529100 | BL124: 126264931 | BM124: 125836021
A125: Kazakhstan | B125: KAZ | C125: Population, total | D125: SP.POP.TOTL | E125: 9934564 | F125: 10349422 | G125: 10756931 | H125: 11147860 | I125: 11511856 | J125: 11841926 | K125: 12132560 | L125: 12385706 | M125: 12611432 | N125: 12824614 | O125: 13036140 | P125: 13250211 | Q125: 13463985 | R125: 13673014 | S125: 13869975 | T125: 14050227 | U125: 14212145 | V125: 14359629 | W125: 14499957 | X125: 14643133 | Y125: 14796175 | Z125: 14958897 | AA125: 15128090 | AB125: 15303316 | AC125: 15483411 | AD125: 15665594 | AE125: 15852524 | AF125: 16039253 | AG125: 16205998 | AH125: 16249500 | AI125: 16348000 | AJ125: 16451711 | AK125: 16439095 | AL125: 16380672 | AM125: 16145766 | AN125: 15816243 | AO125: 15578227 | AP125: 15334405 | AQ125: 15071640 | AR125: 14928374 | AS125: 14883626 | AT125: 14858335 | AU125: 14858948 | AV125: 14909019 | AW125: 15012984 | AX125: 15147029 | AY125: 15308085 | AZ125: 15484192 | BA125: 15776938 | BB125: 16092822 | BC125: 16321872 | BD125: 16557202 | BE125: 16792090 | BF125: 17035551 | BG125: 17288285 | BH125: 17542806 | BI125: 17794055 | BJ125: 18037776 | BK125: 18276452 | BL125: 18513673 | BM125: 18754440
A126: Kenya | B126: KEN | C126: Population, total | D126: SP.POP.TOTL | E126: 8120082 | F126: 8377693 | G126: 8647002 | H126: 8928510 | I126: 9222692 | J126: 9530163 | K126: 9851453 | L126: 10187487 | M126: 10539909 | N126: 10910677 | O126: 11301394 | P126: 11713046 | Q126: 12146070 | R126: 12600799 | S126: 13077341 | T126: 13575898 | U126: 14096258 | V126: 14638887 | W126: 15205381 | X126: 15797771 | Y126: 16417203 | Z126: 17063870 | AA126: 17736326 | AB126: 18431760 | AC126: 19146403 | AD126: 19877078 | AE126: 20622560 | AF126: 21382111 | AG126: 22153685 | AH126: 22935088 | AI126: 23724574 | AJ126: 24521714 | AK126: 25326080 | AL126: 26136217 | AM126: 26950508 | AN126: 27768297 | AO126: 28589456 | AP126: 29415660 | AQ126: 30250488 | AR126: 31098763 | AS126: 31964557 | AT126: 32848569 | AU126: 33751746 | AV126: 34678781 | AW126: 35635267 | AX126: 36624897 | AY126: 37649039 | AZ126: 38705934 | BA126: 39791984 | BB126: 40901798 | BC126: 42030684 | BD126: 43178270 | BE126: 44343469 | BF126: 45519986 | BG126: 46700063 | BH126: 47878339 | BI126: 49051531 | BJ126: 50221146 | BK126: 51392570 | BL126: 52573967 | BM126: 53771300
A127: Kyrgyz Republic | B127: KGZ | C127: Population, total | D127: SP.POP.TOTL | E127: 2172300 | F127: 2255900 | G127: 2333400 | H127: 2413700 | I127: 2495300 | J127: 2573300 | K127: 2655300 | L127: 2736500 | M127: 2818300 | N127: 2894800 | O127: 2959900 | P127: 3022300 | Q127: 3088200 | R127: 3153800 | S127: 3223900 | T127: 3292400 | U127: 3358700 | V127: 3423900 | W127: 3487100 | X127: 3552000 | Y127: 3617400 | Z127: 3685800 | AA127: 3759300 | AB127: 3838300 | AC127: 3916400 | AD127: 3990300 | AE127: 4066500 | AF127: 4144600 | AG127: 4218400 | AH127: 4307500 | AI127: 4391200 | AJ127: 4463600 | AK127: 4515400 | AL127: 4516700 | AM127: 4515100 | AN127: 4560400 | AO127: 4628400 | AP127: 4696400 | AQ127: 4769000 | AR127: 4840400 | AS127: 4898400 | AT127: 4945100 | AU127: 4990700 | AV127: 5043300 | AW127: 5104700 | AX127: 5162600 | AY127: 5218400 | AZ127: 5268400 | BA127: 5318700 | BB127: 5383300 | BC127: 5447900 | BD127: 5514600 | BE127: 5607200 | BF127: 5719600 | BG127: 5835500 | BH127: 5956900 | BI127: 6079500 | BJ127: 6198200 | BK127: 6322800 | BL127: 6456200 | BM127: 6591600
... A131: Korea, Rep. | B131: KOR | C131: Population, total | D131: SP.POP.TOTL | E131: 25012374 | F131: 25765673 | G131: 26513030 | H131: 27261747 | I131: 27984155 | J131: 28704674 | K131: 29435571 | L131: 30130983 | M131: 30838302 | N131: 31544266 | O131: 32240827 | P131: 32882704 | Q131: 33505406 | R131: 34103149 | S131: 34692266 | T131: 35280725 | U131: 35848523 | V131: 36411795 | W131: 36969185 | X131: 37534236 | Y131: 38123775 | Z131: 38723248 | AA131: 39326352 | AB131: 39910403 | AC131: 40405956 | AD131: 40805744 | AE131: 41213674 | AF131: 41621690 | AG131: 42031247 | AH131: 42449038 | AI131: 42869283 | AJ131: 43295704 | AK131: 43747962 | AL131: 44194628 | AM131: 44641540 | AN131: 45092991 | AO131: 45524681 | AP131: 45953580 | AQ131: 46286503 | AR131: 46616677 | AS131: 47008111 | AT131: 47370164 | AU131: 47644736 | AV131: 47892330 | AW131: 48082519 | AX131: 48184561 | AY131: 48438292 | AZ131: 48683638 | BA131: 49054708 | BB131: 49307835 | BC131: 49554112 | BD131: 49936638 | BE131: 50199853 | BF131: 50428893 | BG131: 50746659 | BH131: 51014947 | BI131: 51217803 | BJ131: 51361911 | BK131: 51606633 | BL131: 51709098 | BM131: 51780579
A132: Kuwait | B132: KWT | C132: Population, total | D132: SP.POP.TOTL | E132: 269026 | F132: 300581 | G132: 337346 | H132: 378756 | I132: 423900 | J132: 472032 | K132: 523169 | L132: 577164 | M132: 632911 | N132: 688972 | O132: 744444 | P132: 798639 | Q132: 851918 | R132: 905639 | S132: 961773 | T132: 1021725 | U132: 1085866 | V132: 1153573 | W132: 1224063 | X132: 1296077 | Y132: 1368680 | Z132: 1439334 | AA132: 1507636 | AB132: 1576975 | AC132: 1652150 | AD132: 1735278 | AE132: 1832302 | AF132: 1938916 | AG132: 2034850 | AH132: 2092786 | AI132: 2095350 | AJ132: 2031297 | AN132: 1605907 | AO132: 1626858 | AP132: 1710257 | AQ132: 1831121 | AR132: 1951642 | AS132: 2045123 | AT132: 2103273 | AU132: 2136991 | AV132: 2161626 | AW132: 2200498 | AX132: 2270196 | AY132: 2373661 | AZ132: 2504026 | BA132: 2656010 | BB132: 2821041 | BC132: 2991884 | BD132: 3168054 | BE132: 3348852 | BF132: 3526382 | BG132: 3690939 | BH132: 3835588 | BI132: 3956862 | BJ132: 4056102 | BK132: 4137314 | BL132: 4207077 | BM132: 4270563
A133: Latin America & Caribbean (excluding high income) | B133: LAC | C133: Population, total | D133: SP.POP.TOTL | E133: 197123485 | F133: 202635411 | G133: 208319980 | H133: 214152054 | I133: 220096687 | J133: 226126959 | K133: 232233929 | L133: 238418074 | M133: 244674060 | N133: 250999444 | O133: 257392749 | P133: 263849485 | Q133: 270368419 | R133: 276956213 | S133: 283622634 | T133: 290374325 | U133: 297207329 | V133: 304120290 | W133: 311125944 | X133: 318240296 | Y133: 325470475 | Z133: 332819629 | AA133: 340272476 | AB133: 347792200 | AC133: 355331567 | AD133: 362854776 | AE133: 370346031 | AF133: 377806267 | AG133: 385236744 | AH133: 392644850 | AI133: 400034081 | AJ133: 407394108 | AK133: 414713589 | AL133: 421995092 | AM133: 429246145 | AN133: 436470219 | AO133: 443669730 | AP133: 450833590 | AQ133: 457935268 | AR133: 464933468 | AS133: 471805920 | AT133: 478530627 | AU133: 485108963 | AV133: 491558169 | AW133: 497915775 | AX133: 504205968 | AY133: 510437972 | AZ133: 516611312 | BA133: 522729313 | BB133: 528793175 | BC133: 534699518 | BD133: 540699864 | BE133: 546631449 | BF133: 552552130 | BG133: 558534202 | BH133: 564618410 | BI133: 570838477 | BJ133: 577151682 | BK133: 583432088 | BL133: 589503742 | BM133: 595242966
A134: Lao PDR | B134: LAO | C134: Population, total | D134: SP.POP.TOTL | E134: 2120892 | F134: 2170340 | G134: 2221123 | H134: 2273352 | I134: 2327137 | J134: 2382586 | K134: 2439197 | L134: 2496927 | M134: 2556845 | N134: 2620448 | O134: 2688429 | P134: 2762264 | Q134: 2840842 | R134: 2919288 | S134: 2990963 | T134: 3051583 | U134: 3098962 | V134: 3135839 | W134: 3168838 | X134: 3207331 | Y134: 3258149 | Z134: 3323353 | AA134: 3401193 | AB134: 3489910 | AC134: 3586315 | AD134: 3687889 | AE134: 3794204 | AF134: 3905530 | AG134: 4020817 | AH134: 4138845 | AI134: 4258471 | AJ134: 4379234 | AK134: 4500346 | AL134: 4619946 | AM134: 4735837 | AN134: 4846477 | AO134: 4951189 | AP134: 5050308 | AQ134: 5144601 | AR134: 5235339 | AS134: 5323701 | AT134: 5409584 | AU134: 5493247 | AV134: 5576640 | AW134: 5662199 | AX134: 5751675 | AY134: 5846075 | AZ134: 5944950 | BA134: 6046630 | BB134: 6148621 | BC134: 6249168 | BD134: 6347564 | BE134: 6444527 | BF134: 6541302 | BG134: 6639763 | BH134: 6741160 | BI134: 6845848 | BJ134: 6953031 | BK134: 7061498 | BL134: 7169456 | BM134: 7275556
A135: Lebanon | B135: LBN | C135: Population, total | D135: SP.POP.TOTL | E135: 1804935 | F135: 1864613 | G135: 1925295 | H135: 1984999 | I135: 2041231 | J135: 2092374 | K135: 2136617 | L135: 2174732 | M135: 2210769 | N135: 2250454 | O135: 2297436 | P135: 2354046 | Q135: 2417837 | R135: 2481943 | S135: 2536772 | T135: 2575746 | U135: 2596409 | V135: 2601734 | W135: 2597202 | X135: 2590911 | Y135: 2588928 | Z135: 2594299 | AA135: 2606148 | AB135: 2622072 | AC135: 2638056 | AD135: 2651992 | AE135: 2660873 | AF135: 2667957 | AG135: 2684682 | AH135: 2726438 | AI135: 2803032 | AJ135: 2921700 | AK135: 3076133 | AL135: 3246129 | AM135: 3403359 | AN135: 3528379 | AO135: 3610663 | AP135: 3658425 | AQ135: 3693514 | AR135: 3747762 | AS135: 3842774 | AT135: 3990999 | AU135: 4182205 | AV135: 4388378 | AW135: 4569377 | AX135: 4698761 | AY135: 4759760 | AZ135: 4767347 | BA135: 4764745 | BB135: 4813026 | BC135: 4953064 | BD135: 5202022 | BE135: 5537620 | BF135: 5913016 | BG135: 6261046 | BH135: 6532681 | BI135: 6714281 | BJ135: 6819373 | BK135: 6859408 | BL135: 6855709 | BM135: 6825442
A136: Liberia | B136: LBR | C136: Population, total | D136: SP.POP.TOTL | E136: 1118655 | F136: 1142304 | G136: 1166651 | H136: 1191796 | I136: 1217905 | J136: 1245104 | K136: 1273458 | L136: 1303032 | M136: 1333980 | N136: 1366500 | O136: 1400730 | P136: 1436740 | Q136: 1474567 | R136: 1514364 | S136: 1556288 | T136: 1600454 | U136: 1645833 | V136: 1692155 | W136: 1740919 | X136: 1794251 | Y136: 1852991 | Z136: 1918832 | AA136: 1989477 | AB136: 2057232 | AC136: 2111667 | AD136: 2145756 | AE136: 2158434 | AF136: 2153312 | AG136: 2134105 | AH136: 2106429 | AI136: 2075917 | AJ136: 2040141 | AK136: 2001612 | AL136: 1976701 | AM136: 1986491 | AN136: 2044657 | AO136: 2160480 | AP136: 2326210 | AQ136: 2517472 | AR136: 2699708 | AS136: 2848447 | AT136: 2953928 | AU136: 3024727 | AV136: 3077055 | AW136: 3135654 | AX136: 3218114 | AY136: 3329211 | AZ136: 3461911 | BA136: 3607863 | BB136: 3754129 | BC136: 3891357 | BD136: 4017446 | BE136: 4135662 | BF136: 4248337 | BG136: 4359508 | BH136: 4472229 | BI136: 4586788 | BJ136: 4702224 | BK136: 4818976 | BL136: 4937374 | BM136: 5057677
A137: Libya | B137: LBY | C137: Population, total | D137: SP.POP.TOTL | E137: 1448416 | F137: 1498076 | G137: 1550815 | H137: 1607168 | I137: 1667822 | J137: 1733307 | K137: 1803689 | L137: 1878869 | M137: 1958909 | N137: 2043820 | O137: 2133527 | P137: 2228142 | Q137: 2327487 | R137: 2430754 | S137: 2536895 | T137: 2645136 | U137: 2754698 | V137: 2865639 | W137: 2979102 | X137: 3096724 | Y137: 3219462 | Z137: 3347779 | AA137: 3480443 | AB137: 3614682 | AC137: 3746712 | AD137: 3873781 | AE137: 3994601 | AF137: 4109717 | AG137: 4220451 | AH137: 4328935 | AI137: 4436663 | AJ137: 4544245 | AK137: 4650896 | AL137: 4755134 | AM137: 4854871 | AN137: 4948796 | AO137: 5036173 | AP137: 5118008 | AQ137: 5196774 | AR137: 5275921 | AS137: 5357893 | AT137: 5443249 | AU137: 5531097 | AV137: 5620545 | AW137: 5710163 | AX137: 5798615 | AY137: 5886874 | AZ137: 5974786 | BA137: 6058740 | BB137: 6133987 | BC137: 6197667 | BD137: 6247438 | BE137: 6285751 | BF137: 6320350 | BG137: 6362039 | BH137: 6418315 | BI137: 6492160 | BJ137: 6580723 | BK137: 6678565 | BL137: 6777453 | BM137: 6871287
A138: St. Lucia | B138: LCA | C138: Population, total | D138: SP.POP.TOTL | E138: 89698 | F138: 90718 | G138: 91892 | H138: 93214 | I138: 94637 | J138: 96138 | K138: 97721 | L138: 99370 | M138: 101028 | N138: 102599 | O138: 104016 | P138: 105244 | Q138: 106303 | R138: 107311 | S138: 108389 | T138: 109634 | U138: 111074 | V138: 112685 | W138: 114398 | X138: 116148 | Y138: 117828 | Z138: 119435 | AA138: 120987 | AB138: 122571 | AC138: 124296 | AD138: 126246 | AE138: 128448 | AF138: 130868 | AG138: 133364 | AH138: 135787 | AI138: 138019 | AJ138: 140001 | AK138: 141758 | AL138: 143402 | AM138: 145080 | AN138: 146871 | AO138: 148837 | AP138: 150920 | AQ138: 153023 | AR138: 154988 | AS138: 156737 | AT138: 158184 | AU138: 159392 | AV138: 160530 | AW138: 161821 | AX138: 163408 | AY138: 165378 | AZ138: 167644 | BA138: 170011 | BB138: 172223 | BC138: 174092 | BD138: 175538 | BE138: 176654 | BF138: 177505 | BG138: 178307 | BH138: 179131 | BI138: 180028 | BJ138: 180955 | BK138: 181890 | BL138: 182795 | BM138: 183629
A139: Latin America & Caribbean | B139: LCN | C139: Population, total | D139: SP.POP.TOTL | E139: 219828794 | F139: 225912719 | G139: 232183258 | H139: 238612680 | I139: 245147710 | J139: 251760583 | K139: 258440584 | L139: 265187879 | M139: 272006857 | N139: 278898334 | O139: 285867424 | P139: 292913867 | Q139: 300028905 | R139: 307224818 | S139: 314508488 | T139: 321883714 | U139: 329348136 | V139: 336897935 | W139: 344553109 | X139: 352320721 | Y139: 360211832 | Z139: 368220724 | AA139: 376337306 | AB139: 384527729 | AC139: 392750803 | AD139: 400974913 | AE139: 409183996 | AF139: 417376183 | AG139: 425549887 | AH139: 433708712 | AI139: 441855797 | AJ139: 449968703 | AK139: 458041493 | AL139: 466082322 | AM139: 474089591 | AN139: 482060085 | AO139: 490002410 | AP139: 497889881 | AQ139: 505687097 | AR139: 513366691 | AS139: 520903474 | AT139: 528283130 | AU139: 535509387 | AV139: 542599527 | AW139: 549590680 | AX139: 556504216 | AY139: 563337657 | AZ139: 570091479 | BA139: 576783743 | BB139: 583430021 | BC139: 589932530 | BD139: 596538052 | BE139: 603094656 | BF139: 609595811 | BG139: 615999056 | BH139: 622301041 | BI139: 628493594 | BJ139: 634566052 | BK139: 640483586 | BL139: 646430786 | BM139: 652276325
A140: Least developed countries: UN classification | B140: LDC | C140: Population, total | D140: SP.POP.TOTL | E140: 240518397 | F140: 246113624 | G140: 251900655 | H140: 257908038 | I140: 264174076 | J140: 270720935 | K140: 277573103 | L140: 284708606 | M140: 292046003 | N140: 299473694 | O140: 306916898 | P140: 314345051 | Q140: 321797948 | R140: 329357734 | S140: 337142875 | T140: 345242741 | U140: 353691447 | V140: 362475157 | W140: 371577357 | X140: 380963357 | Y140: 390612544 | Z140: 400528973 | AA140: 410740623 | AB140: 421279177 | AC140: 432185306 | AD140: 443491299 | AE140: 455193679 | AF140: 467290486 | AG140: 479814027 | AH140: 492803041 | AI140: 506275626 | AJ140: 520262436 | AK140: 534731004 | AL140: 549559275 | AM140: 564581120 | AN140: 579681702 | AO140: 594801271 | AP140: 609983284 | AQ140: 625342129 | AR140: 641046832 | AS140: 657215854 | AT140: 673903088 | AU140: 691061433 | AV140: 708587940 | AW140: 726331171 | AX140: 744190509 | AY140: 762132501 | AZ140: 780219573 | BA140: 798563425 | BB140: 817322615 | BC140: 836614841 | BD140: 856471437 | BE140: 876867234 | BF140: 897793439 | BG140: 919222955 | BH140: 941131317 | BI140: 963519718 | BJ140: 986385402 | BK140: 1009691252 | BL140: 1033388868 | BM140: 1057438163
A141: Low income | B141: LIC | C141: Population, total | D141: SP.POP.TOTL | E141: 137782356 | F141: 140848427 | G141: 143991035 | H141: 147246689 | I141: 150668279 | J141: 154292515 | K141: 158131724 | L141: 162169520 | M141: 166378127 | N141: 170716523 | O141: 175154298 | P141: 179681941 | Q141: 184306845 | R141: 189035415 | S141: 193880021 | T141: 198849250 | U141: 203955515 | V141: 209195581 | W141: 214544342 | X141: 219966776 | Y141: 225445124 | Z141: 230976727 | AA141: 236593189 | AB141: 242355131 | AC141: 248343146 | AD141: 254622410 | AE141: 261201749 | AF141: 268084615 | AG141: 275322077 | AH141: 282972202 | AI141: 291068697 | AJ141: 299656373 | AK141: 308709029 | AL141: 318101755 | AM141: 327660123 | AN141: 337265010 | AO141: 346863261 | AP141: 356508832 | AQ141: 366320517 | AR141: 376471932 | AS141: 387088076 | AT141: 398196096 | AU141: 409752737 | AV141: 421725011 | AW141: 434055590 | AX141: 446695034 | AY141: 459659653 | AZ141: 472947450 | BA141: 486468200 | BB141: 500104939 | BC141: 513783318 | BD141: 527467149 | BE141: 541205688 | BF141: 555116804 | BG141: 569367413 | BH141: 584084928 | BI141: 599290280 | BJ141: 614965124 | BK141: 631147232 | BL141: 647870823 | BM141: 665149035
A142: Liechtenstein | B142: LIE | C142: Population, total | D142: SP.POP.TOTL | E142: 16501 | F142: 16894 | G142: 17300 | H142: 17724 | I142: 18170 | J142: 18642 | K142: 19160 | L142: 19688 | M142: 20237 | N142: 20766 | O142: 21268 | P142: 21729 | Q142: 22161 | R142: 22560 | S142: 22985 | T142: 23436 | U142: 23933 | V142: 24451 | W142: 24968 | X142: 25463 | Y142: 25881 | Z142: 26229 | AA142: 26533 | AB142: 26790 | AC142: 27028 | AD142: 27286 | AE142: 27552 | AF142: 27835 | AG142: 28135 | AH142: 28449 | AI142: 28790 | AJ142: 29166 | AK142: 29552 | AL142: 29987 | AM142: 30415 | AN142: 30884 | AO142: 31354 | AP142: 31830 | AQ142: 32306 | AR142: 32765 | AS142: 33184 | AT142: 33543 | AU142: 33885 | AV142: 34172 | AW142: 34444 | AX142: 34718 | AY142: 34975 | AZ142: 35217 | BA142: 35469 | BB142: 35723 | BC142: 35996 | BD142: 36299 | BE142: 36615 | BF142: 36940 | BG142: 37219 | BH142: 37465 | BI142: 37655 | BJ142: 37805 | BK142: 37918 | BL142: 38020 | BM142: 38137
A143: Sri Lanka | B143: LKA | C143: Population, total | D143: SP.POP.TOTL | E143: 9874476 | F143: 10111639 | G143: 10352180 | H143: 10597516 | I143: 10849977 | J143: 11110825 | K143: 11380665 | L143: 11657650 | M143: 11937607 | N143: 12214948 | O143: 12485736 | P143: 12747831 | Q143: 13002234 | R143: 13252033 | S143: 13501931 | T143: 13755141 | U143: 14012894 | V143: 14273495 | W143: 14533691 | X143: 14788866 | Y143: 15035840 | Z143: 15272822 | AA143: 15501210 | AB143: 15724641 | AC143: 15948501 | AD143: 16176282 | AE143: 16408861 | AF143: 16643956 | AG143: 16878186 | AH143: 17106752 | AI143: 17325769 | AJ143: 17535732 | AK143: 17736827 | AL143: 17924827 | AM143: 18094474 | AN143: 18242917 | AO143: 18367290 | AP143: 18470897 | AQ143: 18564595 | AR143: 18663293 | AS143: 18777606 | AT143: 18911727 | AU143: 19062476 | AV143: 19224036 | AW143: 19387153 | AX143: 19544988 | AY143: 19695977 | AZ143: 19842044 | BA143: 19983984 | BB143: 20123508 | BC143: 20261738 | BD143: 20398496 | BE143: 20425000 | BF143: 20585000 | BG143: 20778000 | BH143: 20970000 | BI143: 21203000 | BJ143: 21444000 | BK143: 21670000 | BL143: 21803000 | BM143: 21919000
A144: Lower middle income | B144: LMC | C144: Population, total | D144: SP.POP.TOTL | E144: 989984004 | F144: 1012695283 | G144: 1036174880 | H144: 1060393357 | I144: 1085299211 | J144: 1110852757 | K144: 1137057458 | L144: 1163922580 | M144: 1191458095 | N144: 1219673698 | O144: 1248583279 | P144: 1278208964 | Q144: 1308581612 | R144: 1339744791 | S144: 1371761160 | T144: 1404677295 | U144: 1438471529 | V144: 1473161514 | W144: 1508876331 | X144: 1545785670 | Y144: 1583984211 | Z144: 1623540865 | AA144: 1664223803 | AB144: 1705941229 | AC144: 1748404026 | AD144: 1791342151 | AE144: 1834732208 | AF144: 1878529520 | AG144: 1922581048 | AH144: 1966720233 | AI144: 2012725416 | AJ144: 2056479735 | AK144: 2100111594 | AL144: 2143451976 | AM144: 2186469992 | AN144: 2229481699 | AO144: 2272648448 | AP144: 2315905969 | AQ144: 2359112024 | AR144: 2402132069 | AS144: 2445096607 | AT144: 2487900839 | AU144: 2530679514 | AV144: 2573512638 | AW144: 2616457516 | AX144: 2659559236 | AY144: 2702862046 | AZ144: 2746406133 | BA144: 2790205950 | BB144: 2834272715 | BC144: 2878875404 | BD144: 2923659939 | BE144: 2968243908 | BF144: 3013187396 | BG144: 3058248975 | BH144: 3103569257 | BI144: 3149022555 | BJ144: 3194517542 | BK144: 3240031866 | BL144: 3285416867 | BM144: 3330652547
... A200: Paraguay | B200: PRY | C200: Population, total | D200: SP.POP.TOTL | E200: 1903990 | F200: 1954552 | G200: 2006675 | H200: 2060340 | I200: 2115573 | J200: 2172309 | K200: 2230733 | L200: 2290797 | M200: 2351926 | N200: 2413396 | O200: 2474757 | P200: 2535877 | Q200: 2597149 | R200: 2659418 | S200: 2723816 | T200: 2791236 | U200: 2861868 | V200: 2935710 | W200: 3013281 | X200: 3095151 | Y200: 3181627 | Z200: 3272922 | AA200: 3368763 | AB200: 3468533 | AC200: 3571275 | AD200: 3676206 | AE200: 3783074 | AF200: 3891725 | AG200: 4001678 | AH200: 4112396 | AI200: 4223413 | AJ200: 4334348 | AK200: 4445019 | AL200: 4555518 | AM200: 4666096 | AN200: 4776838 | AO200: 4887638 | AP200: 4998096 | AQ200: 5107840 | AR200: 5216346 | AS200: 5323202 | AT200: 5428442 | AU200: 5531958 | AV200: 5632983 | AW200: 5730556 | AX200: 5824095 | AY200: 5913212 | AZ200: 5998430 | BA200: 6081296 | BB200: 6163970 | BC200: 6248017 | BD200: 6333981 | BE200: 6421510 | BF200: 6510273 | BG200: 6599524 | BH200: 6688746 | BI200: 6777878 | BJ200: 6867058 | BK200: 6956069 | BL200: 7044639 | BM200: 7132530
A201: West Bank and Gaza | B201: PSE | C201: Population, total | D201: SP.POP.TOTL | AI201: 1978248 | AJ201: 2068845 | AK201: 2163591 | AL201: 2262676 | AM201: 2366298 | AN201: 2474666 | AO201: 2587997 | AP201: 2706518 | AQ201: 2776568 | AR201: 2848431 | AS201: 2922153 | AT201: 2997784 | AU201: 3075373 | AV201: 3154969 | AW201: 3236626 | AX201: 3320396 | AY201: 3406334 | AZ201: 3494496 | BA201: 3591977 | BB201: 3689099 | BC201: 3786161 | BD201: 3882986 | BE201: 3979998 | BF201: 4076708 | BG201: 4173398 | BH201: 4270092 | BI201: 4367088 | BJ201: 4454805 | BK201: 4569087 | BL201: 4685306 | BM201: 4803269
A202: Pacific island small states | B202: PSS | C202: Population, total | D202: SP.POP.TOTL | E202: 865064 | F202: 893394 | G202: 923320 | H202: 954098 | I202: 984824 | J202: 1014633 | K202: 1043365 | L202: 1071166 | M202: 1098151 | N202: 1124577 | O202: 1150712 | P202: 1176559 | Q202: 1202128 | R202: 1227653 | S202: 1253371 | T202: 1279519 | U202: 1306023 | V202: 1332876 | W202: 1360542 | X202: 1389594 | Y202: 1420314 | Z202: 1453209 | AA202: 1487849 | AB202: 1522650 | AC202: 1555395 | AD202: 1584644 | AE202: 1609572 | AF202: 1630869 | AG202: 1650438 | AH202: 1670962 | AI202: 1694327 | AJ202: 1721236 | AK202: 1750932 | AL202: 1782085 | AM202: 1812838 | AN202: 1841674 | AO202: 1868390 | AP202: 1893438 | AQ202: 1917140 | AR202: 1939956 | AS202: 1962451 | AT202: 1984469 | AU202: 2006091 | AV202: 2027859 | AW202: 2050583 | AX202: 2074776 | AY202: 2100892 | AZ202: 2128647 | BA202: 2157454 | BB202: 2186314 | BC202: 2214509 | BD202: 2241808 | BE202: 2268553 | BF202: 2295450 | BG202: 2323558 | BH202: 2353578 | BI202: 2385744 | BJ202: 2419767 | BK202: 2455336 | BL202: 2491878 | BM202: 2528958
A203: Post-demographic dividend | B203: PST | C203: Population, total | D203: SP.POP.TOTL | E203: 755229793 | F203: 764423461 | G203: 773856028 | H203: 783141819 | I203: 792263980 | J203: 801098720 | K203: 809363152 | L203: 817179925 | M203: 824733296 | N203: 832280859 | O203: 839822017 | P203: 849163924 | Q203: 857079422 | R203: 864609745 | S203: 871928836 | T203: 878890622 | U203: 885145869 | V203: 891251760 | W203: 897391855 | X203: 903788370 | Y203: 909890607 | Z203: 915971623 | AA203: 921511883 | AB203: 926614804 | AC203: 931410415 | AD203: 936241263 | AE203: 941376248 | AF203: 946671291 | AG203: 952173528 | AH203: 958081653 | AI203: 964173901 | AJ203: 970997793 | AK203: 977878861 | AL203: 984374928 | AM203: 990074277 | AN203: 995310615 | AO203: 1000603716 | AP203: 1005700198 | AQ203: 1010590857 | AR203: 1015421531 | AS203: 1020504874 | AT203: 1025401797 | AU203: 1030561691 | AV203: 1035711715 | AW203: 1041075191 | AX203: 1046366703 | AY203: 1052054839 | AZ203: 1057981930 | BA203: 1064394135 | BB203: 1069878419 | BC203: 1074870583 | BD203: 1077841980 | BE203: 1082374116 | BF203: 1087130325 | BG203: 1092088238 | BH203: 1096977604 | BI203: 1101866343 | BJ203: 1105983497 | BK203: 1109795203 | BL203: 1112707633 | BM203: 1115116448
A204: French Polynesia | B204: PYF | C204: Population, total | D204: SP.POP.TOTL | E204: 78080 | F204: 80705 | G204: 83652 | H204: 86847 | I204: 90132 | J204: 93442 | K204: 96719 | L204: 99990 | M204: 103329 | N204: 106814 | O204: 110490 | P204: 114385 | Q204: 118438 | R204: 122641 | S204: 126919 | T204: 131229 | U204: 135559 | V204: 139893 | W204: 144273 | X204: 148734 | Y204: 153298 | Z204: 157954 | AA204: 162679 | AB204: 167456 | AC204: 172249 | AD204: 177024 | AE204: 181807 | AF204: 186588 | AG204: 191260 | AH204: 195728 | AI204: 199906 | AJ204: 203716 | AK204: 207238 | AL204: 210644 | AM204: 214196 | AN204: 218064 | AO204: 222323 | AP204: 226854 | AQ204: 231562 | AR204: 236217 | AS204: 240681 | AT204: 244929 | AU204: 248976 | AV204: 252707 | AW204: 255995 | AX204: 258780 | AY204: 261007 | AZ204: 262717 | BA204: 264064 | BB204: 265256 | BC204: 266449 | BD204: 267702 | BE204: 268995 | BF204: 270332 | BG204: 271713 | BH204: 273119 | BI204: 274576 | BJ204: 276108 | BK204: 277673 | BL204: 279285 | BM204: 280904
A205: Qatar | B205: QAT | C205: Population, total | D205: SP.POP.TOTL | E205: 47383 | F205: 51427 | G205: 56266 | H205: 61721 | I205: 67562 | J205: 73631 | K205: 79850 | L205: 86298 | M205: 93206 | N205: 100880 | O205: 109521 | P205: 119413 | Q205: 130505 | R205: 142181 | S205: 153624 | T205: 164314 | U205: 173716 | V205: 182319 | W205: 191947 | X205: 205172 | Y205: 223622 | Z205: 247984 | AA205: 277229 | AB205: 309299 | AC205: 341272 | AD205: 370886 | AE205: 397739 | AF205: 422154 | AG205: 443611 | AH205: 461688 | AI205: 476275 | AJ205: 487354 | AK205: 495403 | AL205: 501479 | AM205: 507044 | AN205: 513447 | AO205: 522531 | AP205: 535320 | AQ205: 551566 | AR205: 570486 | AS205: 592467 | AT205: 615013 | AU205: 640872 | AV205: 681791 | AW205: 753332 | AX205: 865410 | AY205: 1022704 | AZ205: 1218441 | BA205: 1436670 | BB205: 1654944 | BC205: 1856329 | BD205: 2035862 | BE205: 2196078 | BF205: 2336579 | BG205: 2459202 | BH205: 2565708 | BI205: 2654379 | BJ205: 2724727 | BK205: 2781682 | BL205: 2832071 | BM205: 2881060
A206: Romania | B206: ROU | C206: Population, total | D206: SP.POP.TOTL | E206: 18406905 | F206: 18555250 | G206: 18676550 | H206: 18797850 | I206: 18919126 | J206: 19031576 | K206: 19215450 | L206: 19534242 | M206: 19799831 | N206: 20009141 | O206: 20250398 | P206: 20461567 | Q206: 20657957 | R206: 20835681 | S206: 21029429 | T206: 21293583 | U206: 21551634 | V206: 21756096 | W206: 21951464 | X206: 22090488 | Y206: 22207282 | Z206: 22353070 | AA206: 22475741 | AB206: 22560478 | AC206: 22640547 | AD206: 22732999 | AE206: 22836841 | AF206: 22949430 | AG206: 23057662 | AH206: 23161458 | AI206: 23201835 | AJ206: 23001155 | AK206: 22794284 | AL206: 22763280 | AM206: 22730211 | AN206: 22684270 | AO206: 22619004 | AP206: 22553978 | AQ206: 22507344 | AR206: 22472040 | AS206: 22442971 | AT206: 22131970 | AU206: 21730496 | AV206: 21574326 | AW206: 21451748 | AX206: 21319685 | AY206: 21193760 | AZ206: 20882982 | BA206: 20537875 | BB206: 20367487 | BC206: 20246871 | BD206: 20147528 | BE206: 20058035 | BF206: 19983693 | BG206: 19908979 | BH206: 19815616 | BI206: 19702267 | BJ206: 19588715 | BK206: 19473970 | BL206: 19371648 | BM206: 19286123
A207: Russian Federation | B207: RUS | C207: Population, total | D207: SP.POP.TOTL | E207: 119897000 | F207: 121236000 | G207: 122591000 | H207: 123960000 | I207: 125345000 | J207: 126745000 | K207: 127468000 | L207: 128196000 | M207: 128928000 | N207: 129664000 | O207: 130404000 | P207: 131155000 | Q207: 131909000 | R207: 132669000 | S207: 133432000 | T207: 134200000 | U207: 135147000 | V207: 136100000 | W207: 137060000 | X207: 138027000 | Y207: 139010000 | Z207: 139941000 | AA207: 140823000 | AB207: 141668000 | AC207: 142745000 | AD207: 143858000 | AE207: 144894000 | AF207: 145908000 | AG207: 146857000 | AH207: 147721000 | AI207: 147969407 | AJ207: 148394216 | AK207: 148538197 | AL207: 148458777 | AM207: 148407912 | AN207: 148375787 | AO207: 148160129 | AP207: 147915361 | AQ207: 147670784 | AR207: 147214776 | AS207: 146596869 | AT207: 145976482 | AU207: 145306497 | AV207: 144648618 | AW207: 144067316 | AX207: 143518814 | AY207: 143049637 | AZ207: 142805114 | BA207: 142742366 | BB207: 142785349 | BC207: 142849468 | BD207: 142960908 | BE207: 143201721 | BF207: 143506995 | BG207: 143819667 | BH207: 144096870 | BI207: 144342397 | BJ207: 144496739 | BK207: 144477859 | BL207: 144406261 | BM207: 144104080
A208: Rwanda | B208: RWA | C208: Population, total | D208: SP.POP.TOTL | E208: 2935575 | F208: 2998334 | G208: 3052937 | H208: 3105417 | I208: 3164258 | J208: 3235536 | K208: 3321674 | L208: 3420897 | M208: 3529839 | N208: 3643237 | O208: 3757351 | P208: 3871428 | Q208: 3987223 | R208: 4106411 | S208: 4231579 | T208: 4364709 | U208: 4506109 | V208: 4655386 | W208: 4812872 | X208: 4978812 | Y208: 5153314 | Z208: 5329250 | AA208: 5504847 | AB208: 5690989 | AC208: 5902847 | AD208: 6146884 | AE208: 6443748 | AF208: 6779981 | AG208: 7088194 | AH208: 7276983 | AI208: 7288883 | AJ208: 7083928 | AK208: 6702239 | AL208: 6263758 | AM208: 5936253 | AN208: 5836490 | AO208: 6013112 | AP208: 6419898 | AQ208: 6962800 | AR208: 7501238 | AS208: 7933688 | AT208: 8231150 | AU208: 8427061 | AV208: 8557160 | AW208: 8680516 | AX208: 8840220 | AY208: 9043342 | AZ208: 9273759 | BA208: 9524532 | BB208: 9782770 | BC208: 10039338 | BD208: 10293333 | BE208: 10549668 | BF208: 10811538 | BG208: 11083629 | BH208: 11369066 | BI208: 11668829 | BJ208: 11980960 | BK208: 12301969 | BL208: 12626938 | BM208: 12952209
A209: South Asia | B209: SAS | C209: Population, total | D209: SP.POP.TOTL | E209: 572839530 | F209: 584939711 | G209: 597494450 | H209: 610498308 | I209: 623943328 | J209: 637823175 | K209: 652144171 | L209: 666908586 | M209: 682102192 | N209: 697706091 | O209: 713711358 | P209: 730107660 | Q209: 746911710 | R209: 764174968 | S209: 781966557 | T209: 800335570 | U209: 819292532 | V209: 838819900 | W209: 858901743 | X209: 879510842 | Y209: 900620583 | Z209: 922226632 | AA209: 944315173 | AB209: 966836458 | AC209: 989728262 | AD209: 1012942302 | AE209: 1036437878 | AF209: 1060208544 | AG209: 1084281159 | AH209: 1108702366 | AI209: 1133495194 | AJ209: 1158655616 | AK209: 1184133340 | AL209: 1209847774 | AM209: 1235693864 | AN209: 1261587780 | AO209: 1287476203 | AP209: 1313346375 | AQ209: 1339202700 | AR209: 1365067953 | AS209: 1390946065 | AT209: 1416822995 | AU209: 1442644044 | AV209: 1468324423 | AW209: 1493757846 | AX209: 1518861546 | AY209: 1543610686 | AZ209: 1568003175 | BA209: 1592010815 | BB209: 1615610187 | BC209: 1638792927 | BD209: 1661532158 | BE209: 1683740452 | BF209: 1705761545 | BG209: 1727632022 | BH209: 1749417067 | BI209: 1771187426 | BJ209: 1792883164 | BK209: 1814455018 | BL209: 1835776769 | BM209: 1856882402
A210: Saudi Arabia | B210: SAU | C210: Population, total | D210: SP.POP.TOTL | E210: 4086534 | F210: 4218852 | G210: 4362788 | H210: 4516540 | I210: 4677304 | J210: 4843632 | K210: 5015353 | L210: 5195124 | M210: 5387822 | N210: 5599909 | O210: 5836388 | P210: 6100631 | Q210: 6392973 | R210: 6711922 | S210: 7054532 | T210: 7419486 | U210: 7802928 | V210: 8207695 | W210: 8646845 | X210: 9137928 | Y210: 9691471 | Z210: 10311771 | AA210: 10988851 | AB210: 11701132 | AC210: 12418836 | AD210: 13118998 | AE210: 13794167 | AF210: 14445663 | AG210: 15070082 | AH210: 15666289 | AI210: 16233786 | AJ210: 16772695 | AK210: 17282686 | AL210: 17763297 | AM210: 18214475 | AN210: 18638790 | AO210: 19033843 | AP210: 19407138 | AQ210: 19783301 | AR210: 20194531 | AS210: 20663840 | AT210: 21202646 | AU210: 21805322 | AV210: 22456645 | AW210: 23132686 | AX210: 23816175 | AY210: 24498313 | AZ210: 25184589 | BA210: 25888535 | BB210: 26630303 | BC210: 27421468 | BD210: 28267591 | BE210: 29154906 | BF210: 30052058 | BG210: 30916603 | BH210: 31717676 | BI210: 32443443 | BJ210: 33101183 | BK210: 33702757 | BL210: 34268529 | BM210: 34813867
A211: Sudan | B211: SDN | C211: Population, total | D211: SP.POP.TOTL | E211: 7544498 | F211: 7769475 | G211: 8004122 | H211: 8248818 | I211: 8503989 | J211: 8770094 | K211: 9047803 | L211: 9337662 | M211: 9639846 | N211: 9954411 | O211: 10281695 | P211: 10621471 | Q211: 10974626 | R211: 11343923 | S211: 11732957 | T211: 12144128 | U211: 12578398 | V211: 13034631 | W211: 13510429 | X211: 14002302 | Y211: 14507466 | Z211: 15027254 | AA211: 15562129 | AB211: 16107613 | AC211: 16657956 | AD211: 17210182 | AE211: 17757494 | AF211: 18303430 | AG211: 18867559 | AH211: 19476653 | AI211: 20147592 | AJ211: 20891442 | AK211: 21696240 | AL211: 22527837 | AM211: 23338465 | AN211: 24094741 | AO211: 24782384 | AP211: 25413912 | AQ211: 26015518 | AR211: 26626512 | AS211: 27275019 | AT211: 27971077 | AU211: 28704786 | AV211: 29460517 | AW211: 30214189 | AX211: 30949514 | AY211: 31661824 | AZ211: 32360619 | BA211: 33060844 | BB211: 33783779 | BC211: 34545014 | BD211: 35349676 | BE211: 36193781 | BF211: 37072555 | BG211: 37977657 | BH211: 38902948 | BI211: 39847433 | BJ211: 40813398 | BK211: 41801532 | BL211: 42813237 | BM211: 43849269
A212: Senegal | B212: SEN | C212: Population, total | D212: SP.POP.TOTL | E212: 3206757 | F212: 3295280 | G212: 3386803 | H212: 3481654 | I212: 3580241 | J212: 3682879 | K212: 3789381 | L212: 3899648 | M212: 4014107 | N212: 4133324 | O212: 4257508 | P212: 4387532 | Q212: 4522886 | R212: 4660726 | S212: 4797188 | T212: 4929846 | U212: 5057375 | V212: 5181505 | W212: 5306685 | X212: 5439069 | Y212: 5583157 | Z212: 5740441 | AA212: 5909734 | AB212: 6089567 | AC212: 6277420 | AD212: 6471329 | AE212: 6670665 | AF212: 6875746 | AG212: 7086624 | AH212: 7303511 | AI212: 7526306 | AJ212: 7755503 | AK212: 7990090 | AL212: 8226749 | AM212: 8461066 | AN212: 8690155 | AO212: 8912872 | AP212: 9130876 | AQ212: 9347777 | AR212: 9568717 | AS212: 9797731 | AT212: 10036102 | AU212: 10283694 | AV212: 10541470 | AW212: 10810086 | AX212: 11090123 | AY212: 11382272 | AZ212: 11687078 | BA212: 12004700 | BB212: 12335092 | BC212: 12678143 | BD212: 13033814 | BE212: 13401990 | BF212: 13782429 | BG212: 14174740 | BH212: 14578450 | BI212: 14993514 | BJ212: 15419354 | BK212: 15854324 | BL212: 16296362 | BM212: 16743930
A213: Singapore | B213: SGP | C213: Population, total | D213: SP.POP.TOTL | E213: 1646400 | F213: 1702400 | G213: 1750200 | H213: 1795000 | I213: 1841600 | J213: 1886900 | K213: 1934400 | L213: 1977600 | M213: 2012000 | N213: 2042500 | O213: 2074507 | P213: 2112900 | Q213: 2152400 | R213: 2193000 | S213: 2229800 | T213: 2262600 | U213: 2293300 | V213: 2325300 | W213: 2353600 | X213: 2383500 | Y213: 2413945 | Z213: 2532835 | AA213: 2646466 | AB213: 2681061 | AC213: 2732221 | AD213: 2735957 | AE213: 2733373 | AF213: 2774789 | AG213: 2846108 | AH213: 2930901 | AI213: 3047132 | AJ213: 3135083 | AK213: 3230698 | AL213: 3313471 | AM213: 3419048 | AN213: 3524506 | AO213: 3670704 | AP213: 3796038 | AQ213: 3927213 | AR213: 3958723 | AS213: 4027887 | AT213: 4138012 | AU213: 4175950 | AV213: 4114826 | AW213: 4166664 | AX213: 4265762 | AY213: 4401365 | AZ213: 4588599 | BA213: 4839396 | BB213: 4987573 | BC213: 5076732 | BD213: 5183688 | BE213: 5312437 | BF213: 5399162 | BG213: 5469724 | BH213: 5535002 | BI213: 5607283 | BJ213: 5612253 | BK213: 5638676 | BL213: 5703569 | BM213: 5685807
... A270: Zimbabwe | B270: ZWE | C270: Population, total | D270: SP.POP.TOTL | E270: 3776679 | F270: 3905038 | G270: 4039209 | H270: 4178726 | I270: 4322854 | J270: 4471178 | K270: 4623340 | L270: 4779825 | M270: 4941901 | N270: 5111326 | O270: 5289312 | P270: 5476978 | Q270: 5673914 | R270: 5877725 | S270: 6085078 | T270: 6293875 | U270: 6502566 | V270: 6712825 | W270: 6929663 | X270: 7160021 | Y270: 7408630 | Z270: 7675582 | AA270: 7958239 | AB270: 8254746 | AC270: 8562259 | AD270: 8877489 | AE270: 9200150 | AF270: 9527202 | AG270: 9849129 | AH270: 10153852 | AI270: 10432409 | AJ270: 10681008 | AK270: 10900511 | AL270: 11092775 | AM270: 11261752 | AN270: 11410721 | AO270: 11541215 | AP270: 11653254 | AQ270: 11747079 | AR270: 11822722 | AS270: 11881482 | AT270: 11923906 | AU270: 11954293 | AV270: 11982219 | AW270: 12019911 | AX270: 12076697 | AY270: 12155496 | AZ270: 12255920 | BA270: 12379553 | BB270: 12526964 | BC270: 12697728 | BD270: 12894323 | BE270: 13115149 | BF270: 13350378 | BG270: 13586710 | BH270: 13814642 | BI270: 14030338 | BJ270: 14236599 | BK270: 14438812 | BL270: 14645473 | BM270: 14862927

Sheet GDP per capita 7 sept 2021
A1: Data Source | B1: World Development Indicators
A2: Last Updated Date | B2: 44407
A4: Country Name | B4: Country Code | C4: Indicator Name | D4: Indicator Code | E4: 1960 | F4: 1961 | G4: 1962 | H4: 1963 | I4: 1964 | J4: 1965 | K4: 1966 | L4: 1967 | M4: 1968 | N4: 1969 | O4: 1970 | P4: 1971 | Q4: 1972 | R4: 1973 | S4: 1974 | T4: 1975 | U4: 1976 | V4: 1977 | W4: 1978 | X4: 1979 | Y4: 1980 | Z4: 1981 | AA4: 1982 | AB4: 1983 | AC4: 1984 | AD4: 1985 | AE4: 1986 | AF4: 1987 | AG4: 1988 | AH4: 1989 | AI4: 1990 | AJ4: 1991 | AK4: 1992 | AL4: 1993 | AM4: 1994 | AN4: 1995 | AO4: 1996 | AP4: 1997 | AQ4: 1998 | AR4: 1999 | AS4: 2000 | AT4: 2001 | AU4: 2002 | AV4: 2003 | AW4: 2004 | AX4: 2005 | AY4: 2006 | AZ4: 2007 | BA4: 2008 | BB4: 2009 | BC4: 2010 | BD4: 2011 | BE4: 2012 | BF4: 2013 | BG4: 2014 | BH4: 2015 | BI4: 2016 | BJ4: 2017 | BK4: 2018 | BL4: 2019 | BM4: 2020
A5: Aruba | B5: ABW | C5: GDP per capita (current US$) | D5: NY.GDP.PCAP.CD | AE5: 6472.3987 | AF5: 7885.1589 | AG5: 9765.9092 | AH5: 11392.269 | AI5: 12306.718 | AJ5: 13495.794 | AK5: 14045.475 | AL5: 14938.682 | AM5: 16239.988 | AN5: 16439.356 | AO5: 16583.876 | AP5: 17927.959 | AQ5: 19077.687 | AR5: 19355.334 | AS5: 20617.75 | AT5: 20670.367 | AU5: 20436.887 | AV5: 20833.976 | AW5: 22568.375 | AX5: 23300.738 | AY5: 24046.226 | AZ5: 25834.112 | BA5: 27083.635 | BB5: 24631.182 | BC5: 23513.528 | BD5: 24985.014 | BE5: 24712.493 | BF5: 26441.62 | BG5: 26893.012 | BH5: 28396.908 | BI5: 28452.171 | BJ5: 29350.805 | BK5: 30253.279
A6: Africa Eastern and Southern | B6: AFE | C6: GDP per capita (current US$) | D6: NY.GDP.PCAP.CD | E6: 147.45037 | F6: 146.8537 | G6: 156.01793 | H6: 182.04409 | I6: 162.16958 | J6: 180.0173 | K6: 190.63622 | L6: 192.12627 | M6: 203.7834 | N6: 227.65871 | O6: 236.53378 | P6: 253.72845 | Q6: 267.83732 | R6: 339.38725 | S6: 409.66854 | T6: 424.33738 | U6: 411.06239 | V6: 455.7539 | W6: 495.54662 | X6: 563.38452 | Y6: 687.80039 | Z6: 684.45394 | AA6: 641.08015 | AB6: 643.09782 | AC6: 570.82052 | AD6: 495.12113 | AE6: 541.83335 | AF6: 643.09569 | AG6: 656.62646 | AH6: 656.46575 | AI6: 696.22389 | AJ6: 703.65468 | AK6: 682.58685 | AL6: 665.24293 | AM6: 659.5899 | AN6: 722.16972 | AO6: 701.7342 | AP6: 718.85428 | AQ6: 660.47197 | AR6: 635.14337 | AS6: 672.20547 | AT6: 591.08844 | AU6: 589.20682 | AV6: 757.44976 | AW6: 916.60337 | AX6: 1037.7271 | AY6: 1142.9559 | AZ6: 1278.9713 | BA6: 1356.5299 | BB6: 1326.2515 | BC6: 1550.1212 | BD6: 1682.2873 | BE6: 1667.9926 | BF6: 1648.8675 | BG6: 1654.3149 | BH6: 1503.8593 | BI6: 1401.2811 | BJ6: 1536.2068 | BK6: 1530.1619 | BL6: 1481.4253 | BM6: 1326.6637
A7: Afghanistan | B7: AFG | C7: GDP per capita (current US$) | D7: NY.GDP.PCAP.CD | E7: 59.773234 | F7: 59.8609 | G7: 58.458009 | H7: 78.706429 | I7: 82.095307 | J7: 101.10833 | K7: 137.5943 | L7: 160.89843 | M7: 129.10831 | N7: 129.32976 | O7: 156.51877 | P7: 159.56751 | Q7: 135.31723 | R7: 143.14465 | S7: 173.65362 | T7: 186.51084 | U7: 197.44551 | V7: 224.225 | W7: 247.35409 | X7: 275.73812 | Y7: 272.65551 | Z7: 264.1112 | AU7: 179.42658 | AV7: 190.68381 | AW7: 211.38207 | AX7: 242.03131 | AY7: 263.7336 | AZ7: 359.69316 | BA7: 364.66068 | BB7: 438.07614 | BC7: 543.30297 | BD7: 591.1628 | BE7: 641.87144 | BF7: 637.16546 | BG7: 613.85651 | BH7: 578.46635 | BI7: 509.2201 | BJ7: 519.88891 | BK7: 493.75658 | BL7: 507.10339 | BM7: 508.80841
A8: Africa Western and Central | B8: AFW | C8: GDP per capita (current US$) | D8: NY.GDP.PCAP.CD | E8: 107.96378 | F8: 113.1147 | G8: 118.86584 | H8: 123.47897 | I8: 131.89294 | J8: 138.56682 | K8: 144.36839 | L8: 128.62005 | M8: 129.679 | N8: 143.75764 | O8: 195.49068 | P8: 169.16853 | Q8: 200.22691 | R8: 241.78208 | S8: 333.28988 | T8: 377.89846 | U8: 444.5043 | V8: 454.92309 | W8: 482.6185 | X8: 584.54479 | Y8: 718.90192 | Z8: 1317.3165 | AA8: 1136.7947 | AB8: 816.13929 | AC8: 656.90478 | AD8: 651.70046 | AE8: 585.07829 | AF8: 584.29005 | AG8: 561.5256 | AH8: 510.56835 | AI8: 594.8996 | AJ8: 558.59904 | AK8: 547.82307 | AL8: 438.26231 | AM8: 376.35492 | AN8: 459.3649 | AO8: 495.77904 | AP8: 486.52302 | AQ8: 484.09074 | AR8: 500.43618 | AS8: 502.03166 | AT8: 516.92793 | AU8: 605.06101 | AV8: 681.88236 | AW8: 826.81654 | AX8: 988.83939 | AY8: 1224.0576 | AZ8: 1400.086 | BA8: 1666.8998 | BB8: 1444.2019 | BC8: 1655.1301 | BD8: 1827.5183 | BE8: 1936.391 | BF8: 2123.3924 | BG8: 2166.7433 | BH8: 1886.2482 | BI8: 1666.4224 | BJ8: 1606.9783 | BK8: 1695.9592 | BL8: 1772.3392 | BM8: 1714.4268
A9: Angola | B9: AGO | C9: GDP per capita (current US$) | D9: NY.GDP.PCAP.CD | Y9: 711.40958 | Z9: 642.7682 | AA9: 620.33312 | AB9: 623.81536 | AC9: 638.09901 | AD9: 758.74506 | AE9: 685.72813 | AF9: 756.76793 | AG9: 792.83302 | AH9: 891.14928 | AI9: 948.33818 | AM9: 251.07835 | AN9: 398.791 | AO9: 522.67962 | AP9: 514.38517 | AQ9: 423.61905 | AR9: 387.78512 | AS9: 556.83863 | AT9: 527.33353 | AU9: 872.49444 | AV9: 982.96101 | AW9: 1255.5645 | AX9: 1902.4221 | AY9: 2599.5659 | AZ9: 3121.9961 | BA9: 4080.941 | BB9: 3122.7816 | BC9: 3587.8836 | BD9: 4615.4682 | BE9: 5100.097 | BF9: 5254.8811 | BG9: 5408.4117 | BH9: 4166.9798 | BI9: 3506.0731 | BJ9: 4095.8101 | BK9: 3289.644 | BL9: 2809.6261 | BM9: 1895.7709
A10: Albania | B10: ALB | C10: GDP per capita (current US$) | D10: NY.GDP.PCAP.CD | AC10: 639.48474 | AD10: 639.86591 | AE10: 693.87347 | AF10: 674.79338 | AG10: 652.77432 | AH10: 697.9956 | AI10: 617.23044 | AJ10: 336.58699 | AK10: 200.85222 | AL10: 367.27923 | AM10: 586.41634 | AN10: 750.60445 | AO10: 1009.9777 | AP10: 717.38057 | AQ10: 813.79026 | AR10: 1033.2417 | AS10: 1126.6833 | AT10: 1281.6594 | AU10: 1425.1248 | AV10: 1846.1188 | AW10: 2373.5798 | AX10: 2673.7873 | AY10: 2972.7433 | AZ10: 3595.0372 | BA10: 4370.5401 | BB10: 4114.1401 | BC10: 4094.3503 | BD10: 4437.1429 | BE10: 4247.63 | BF10: 4413.0609 | BG10: 4578.632 | BH10: 3952.8012 | BI10: 4124.0557 | BJ10: 4531.0208 | BK10: 5284.3802 | BL10: 5355.8478 | BM10: 5215.2768
A11: Andorra | B11: AND | C11: GDP per capita (current US$) | D11: NY.GDP.PCAP.CD | O11: 3238.6903 | P11: 3496.532 | Q11: 4218.2716 | R11: 5342.1686 | S11: 6320.8096 | T11: 7169.101 | U11: 7151.2499 | V11: 7751.8433 | W11: 9127.8123 | X11: 11818.473 | Y11: 12378.785 | Z11: 10372.786 | AA11: 9610.0206 | AB11: 8025.2076 | AC11: 7728.9067 | AD11: 7775.6142 | AE11: 10361.148 | AF11: 12615.126 | AG11: 14304.641 | AH11: 15165.281 | AI11: 18878.852 | AJ11: 19534.264 | AK11: 20549.806 | AL11: 16515.658 | AM11: 16235.068 | AN11: 18458.174 | AO11: 19016.288 | AP11: 18355.628 | AQ11: 18895.111 | AR11: 19262.309 | AS11: 21854.247 | AT11: 22970.512 | AU11: 25067.24 | AV11: 32272.846 | AW11: 37966.187 | AX11: 40064.225 | AY11: 42674.759 | AZ11: 47804.85 | BA11: 48719.659 | BB11: 43504.216 | BC11: 40850.248 | BD11: 43334.811 | BE11: 38686.461 | BF11: 39540.725 | BG11: 41303.929 | BH11: 35770.777 | BI11: 37475.635 | BJ11: 38964.904 | BK11: 41791.97 | BL11: 40897.331
A12: Arab World | B12: ARB | C12: GDP per capita (current US$) | D12: NY.GDP.PCAP.CD | M12: 307.58698 | N12: 328.31931 | O12: 359.54699 | P12: 404.8275 | Q12: 469.97402 | R12: 578.69526 | S12: 1063.5455 | T12: 1143.7612 | U12: 1377.5607 | V12: 1536.2292 | W12: 1632.7983 | X12: 2138.8245 | Y12: 2802.4945 | Z12: 2801.1605 | AA12: 2549.4076 | AB12: 2324.8461 | AC12: 2288.0868 | AD12: 2198.4671 | AE12: 2038.4897 | AF12: 2112.0715 | AG12: 2019.8272 | AH12: 2060.1615 | AI12: 2750.9603 | AJ12: 1857.8212 | AK12: 1952.8882 | AL12: 1925.1132 | AM12: 1930.0025 | AN12: 2044.926 | AO12: 2191.2017 | AP12: 2309.3705 | AQ12: 2182.0079 | AR12: 2377.023 | AS12: 2678.3145 | AT12: 2536.7863 | AU12: 2484.8452 | AV12: 2696.0469 | AW12: 3134.8725 | AX12: 3765.9273 | AY12: 4360.0642 | AZ12: 4963.7 | BA12: 6149.7118 | BB12: 5180.5555 | BC12: 5948.6743 | BD12: 6870.0986 | BE12: 7455.0419 | BF12: 7505.1742 | BG12: 7436.5801 | BH12: 6346.0323 | BI12: 6093.331 | BJ12: 6095.6634 | BK12: 6568.9841 | BL12: 6570.1742 | BM12: 5802.1041
A13: United Arab Emirates | B13: ARE | C13: GDP per capita (current US$) | D13: NY.GDP.PCAP.CD | T13: 26848.088 | U13: 30117.949 | V13: 33823.182 | W13: 28457.078 | X13: 33512.633 | Y13: 42764.541 | Z13: 44987.538 | AA13: 40025.823 | AB13: 34843.16 | AC13: 32309.833 | AD13: 29720.898 | AE13: 23467.879 | AF13: 23726.307 | AG13: 22295.119 | AH13: 24028.262 | AI13: 27729.391 | AJ13: 26612.253 | AK13: 26420.86 | AL13: 25596.739 | AM13: 25848.016 | AN13: 27221.934 | AO13: 28975.08 | AP13: 29512.675 | AQ13: 26899.602 | AR13: 28470.886 | AS13: 33291.366 | AT13: 31280.756 | AU13: 31567.546 | AV13: 33499.103 | AW13: 36333.187 | AX13: 39365.46 | AY13: 41907.421 | AZ13: 41809.462 | BA13: 44498.941 | BB13: 32024.198 | BC13: 33893.264 | BD13: 39194.672 | BE13: 40976.491 | BF13: 42412.64 | BG13: 43751.806 | BH13: 38663.401 | BI13: 38141.867 | BJ13: 40644.791 | BK13: 43839.324 | BL13: 43103.336
A14: Argentina | B14: ARG | C14: GDP per capita (current US$) | D14: NY.GDP.PCAP.CD | G14: 1155.8907 | H14: 850.30458 | I14: 1173.2381 | J14: 1279.1138 | K14: 1272.8032 | L14: 1062.5434 | M14: 1141.0804 | N14: 1329.0585 | O14: 1322.5906 | P14: 1372.3742 | Q14: 1408.8654 | R14: 2097.0228 | S14: 2844.8633 | T14: 2027.3372 | U14: 1948.2247 | V14: 2129.7084 | W14: 2146.365 | X14: 2520.9207 | Y14: 2758.8348 | Z14: 2776.3221 | AA14: 2927.8974 | AB14: 3553.3775 | AC14: 2659.7082 | AD14: 2926.1265 | AE14: 3613.6217 | AF14: 3562.8761 | AG14: 3985.1925 | AH14: 2383.8675 | AI14: 4333.4834 | AJ14: 5735.36 | AK14: 6823.5388 | AL14: 6969.1197 | AM14: 7483.1403 | AN14: 7408.7087 | AO14: 7721.3541 | AP14: 8213.1251 | AQ14: 8289.5076 | AR14: 7774.7362 | AS14: 7708.0991 | AT14: 7208.3731 | AU14: 2593.4046 | AV14: 3349.8063 | AW14: 4277.7216 | AX14: 5109.8522 | AY14: 5919.0123 | AZ14: 7245.4469 | BA14: 9020.8733 | BB14: 8225.1376 | BC14: 10385.964 | BD14: 12848.864 | BE14: 13082.664 | BF14: 13080.255 | BG14: 12334.798 | BH14: 13789.06 | BI14: 12790.242 | BJ14: 14613.042 | BK14: 11633.498 | BL14: 9912.2818 | BM14: 8441.9194
A15: Armenia | B15: ARM | C15: GDP per capita (current US$) | D15: NY.GDP.PCAP.CD | AI15: 637.85592 | AJ15: 590.50588 | AK15: 369.70723 | AL15: 357.20285 | AM15: 400.51559 | AN15: 456.37493 | AO15: 504.05984 | AP15: 523.28441 | AQ15: 609.17165 | AR15: 597.4329 | AS15: 622.74092 | AT15: 694.42346 | AU15: 783.24121 | AV15: 930.12547 | AW15: 1191.921 | AX15: 1643.7569 | AY15: 2158.1481 | AZ15: 3139.2807 | BA15: 4010.8614 | BB15: 2994.3405 | BC15: 3218.3783 | BD15: 3525.8072 | BE15: 3681.8447 | BF15: 3838.1739 | BG15: 3986.2316 | BH15: 3607.2893 | BI15: 3591.8281 | BJ15: 3914.5279 | BK15: 4220.5403 | BL15: 4622.7382 | BM15: 4267.4521
A16: American Samoa | B16: ASM | C16: GDP per capita (current US$) | D16: NY.GDP.PCAP.CD | AU16: 8666.6554 | AV16: 8807.4628 | AW16: 8528.2488 | AX16: 8395.3188 | AY16: 8340.5234 | AZ16: 8874.8779 | BA16: 9740.8245 | BB16: 11910.013 | BC16: 10216.818 | BD16: 10223.298 | BE16: 11496.524 | BF16: 11450.724 | BG16: 11525.156 | BH16: 12059.635 | BI16: 12038.25 | BJ16: 11003.83 | BK16: 11557.671 | BL16: 11534.568
A17: Antigua and Barbuda | B17: ATG | C17: GDP per capita (current US$) | D17: NY.GDP.PCAP.CD | V17: 1246.6902 | W17: 1416.5405 | X17: 1760.8313 | Y17: 2124.6185 | Z17: 2392.687 | AA17: 2660.5581 | AB17: 2948.3173 | AC17: 3372.6021 | AD17: 3899.3918 | AE17: 4703.1794 | AF17: 5463.5954 | AG17: 6454.8355 | AH17: 7076.5363 | AI17: 7347.6464 | AJ17: 7602.3453 | AK17: 7745.7218 | AL17: 8136.1885 | AM17: 8771.1437 | AN17: 8406.3589 | AO17: 9030.575 | AP17: 9491.6608 | AQ17: 9940.8522 | AR17: 10260.599 | AS17: 10872.293 | AT17: 10367.32 | AU17: 10401.051 | AV17: 10797.951 | AW17: 11446.969 | AX17: 12557.548 | AY17: 13995.804 | AZ17: 15622.693 | BA17: 16044.106 | BB17: 14160.562 | BC17: 13048.961 | BD17: 12746.633 | BE17: 13272.735 | BF17: 12910.591 | BG17: 13501.581 | BH17: 14285.33 | BI17: 15198.743 | BJ17: 15383.576 | BK17: 16673.437 | BL17: 17113.35 | BM17: 14449.997
A18: Australia | B18: AUS | C18: GDP per capita (current US$) | D18: NY.GDP.PCAP.CD | E18: 1807.7857 | F18: 1874.7321 | G18: 1851.8419 | H18: 1964.1505 | I18: 2128.0684 | J18: 2277.5584 | K18: 2340.4387 | L18: 2576.2845 | M18: 2720.0826 | N18: 2986.9495 | O18: 3299.8432 | P18: 3489.9523 | Q18: 3943.7876 | R18: 4763.6284 | S18: 6473.1652 | T18: 6994.3082 | U18: 7476.7487 | V18: 7765.0705 | W18: 8241.9973 | X18: 9281.5234 | Y18: 10194.395 | Z18: 11833.743 | AA18: 12766.522 | AB18: 11518.669 | AC18: 12431.946 | AD18: 11437.713 | AE18: 11364.239 | AF18: 11624.621 | AG18: 14254.514 | AH18: 17798.556 | AI18: 18211.5 | AJ18: 18821.795 | AK18: 18570.12 | AL18: 17634.535 | AM18: 18046.136 | AN18: 20319.631 | AO18: 21861.326 | AP18: 23468.597 | AQ18: 21318.964 | AR18: 20533.035 | AS18: 21679.248 | AT18: 19490.861 | AU18: 20082.483 | AV18: 23447.031 | AW18: 30430.676 | AX18: 33999.243 | AY18: 36044.923 | AZ18: 40960.054 | BA18: 49601.657 | BB18: 42772.359 | BC18: 52022.126 | BD18: 62517.834 | BE18: 68012.148 | BF18: 68150.107 | BG18: 62510.791 | BH18: 56755.722 | BI18: 49971.131 | BJ18: 54027.967 | BK18: 57354.964 | BL18: 55057.205 | BM18: 51812.154
A19: Austria | B19: AUT | C19: GDP per capita (current US$) | D19: NY.GDP.PCAP.CD | E19: 935.46043 | F19: 1031.815 | G19: 1087.8342 | H19: 1167.0005 | I19: 1269.4126 | J19: 1374.5321 | K19: 1486.9686 | L19: 1569.6672 | M19: 1677.6735 | N19: 1825.3861 | O19: 2058.7691 | P19: 2380.9785 | Q19: 2924.0489 | R19: 3890.7224 | S19: 4630.7572 | T19: 5285.6207 | U19: 5678.3867 | V19: 6810.6277 | W19: 8205.469 | X19: 9793.7653 | Y19: 10869.546 | Z19: 9385.2491 | AA19: 9410.3473 | AB19: 9537.4074 | AC19: 8991.065 | AD19: 9172.0968 | AE19: 13083.073 | AF19: 16392.77 | AG19: 17578.619 | AH19: 17468.946 | AI19: 21680.99 | AJ19: 22410.912 | AK19: 24880.164 | AL19: 24081.528 | AM19: 25646.701 | AN19: 30325.85 | AO19: 29809.077 | AP19: 26705.479 | AQ19: 27361.875 | AR19: 27174.297 | AS19: 24564.458 | AT19: 24537.514 | AU19: 26401.745 | AV19: 32222.897 | AW19: 36821.521 | AX19: 38403.134 | AY19: 40635.282 | AZ19: 46855.772 | BA19: 51708.766 | BB19: 47963.179 | BC19: 46858.043 | BD19: 51374.958 | BE19: 48567.695 | BF19: 50716.709 | BG19: 51717.496 | BH19: 44178.047 | BI19: 45276.831 | BJ19: 47309.366 | BK19: 51453.147 | BL19: 50121.554 | BM19: 48105.365
A20: Azerbaijan | B20: AZE | C20: GDP per capita (current US$) | D20: NY.GDP.PCAP.CD | AK20: 60.458623 | AL20: 209.47298 | AM20: 157.07675 | AN20: 314.55509 | AO20: 409.16319 | AP20: 505.50035 | AQ20: 561.90681 | AR20: 573.91651 | AS20: 655.11995 | AT20: 703.68384 | AU20: 763.08064 | AV20: 883.73397 | AW20: 1045.0094 | AX20: 1578.4024 | AY20: 2473.0818 | AZ20: 3851.4379 | BA20: 5574.6038 | BB20: 4950.2948 | BC20: 5843.5338 | BD20: 7189.6912 | BE20: 7496.2946 | BF20: 7875.757 | BG20: 7891.3131 | BH20: 5500.3104 | BI20: 3880.7387 | BJ20: 4147.0897 | BK20: 4739.8417 | BL20: 4805.7537 | BM20: 4214.3113
A21: Burundi | B21: BDI | C21: GDP per capita (current US$) | D21: NY.GDP.PCAP.CD | E21: 70.05191 | F21: 71.167188 | G21: 73.435331 | H21: 78.514621 | I21: 86.16155 | J21: 51.381881 | K21: 52.182552 | L21: 54.806443 | M21: 54.900762 | N21: 55.714934 | O21: 69.769384 | P21: 71.62671 | Q21: 69.139615 | R21: 84.418782 | S21: 94.6854 | T21: 113.75316 | U21: 118.91493 | V21: 142.05298 | W21: 154.51627 | X21: 193.14996 | Y21: 221.23194 | Z21: 227.12812 | AA21: 231.34369 | AB21: 240.7817 | AC21: 213.61684 | AD21: 242.0585 | AE21: 245.91533 | AF21: 225.07148 | AG21: 209.41486 | AH21: 209.89441 | AI21: 208.14668 | AJ21: 209.77801 | AK21: 190.48888 | AL21: 161.88753 | AM21: 156.81238 | AN21: 167.09889 | AO21: 143.40232 | AP21: 158.91467 | AQ21: 144.49302 | AR21: 128.93892 | AS21: 136.46397 | AT21: 134.36343 | AU21: 123.11754 | AV21: 113.56725 | AW21: 128.3367 | AX21: 151.68157 | AY21: 167.37646 | AZ21: 172.4956 | BA21: 198.35285 | BB21: 212.13706 | BC21: 234.23553 | BD21: 249.57797 | BE21: 252.35887 | BF21: 256.97565 | BG21: 274.85784 | BH21: 305.54965 | BI21: 282.19303 | BJ21: 292.99801 | BK21: 271.7525 | BL21: 261.24529 | BM21: 274.00952
A22: Belgium | B22: BEL | C22: GDP per capita (current US$) | D22: NY.GDP.PCAP.CD | E22: 1273.6917 | F22: 1350.1977 | G22: 1438.5232 | H22: 1535.0237 | I22: 1701.8463 | J22: 1835.5948 | K22: 1957.6261 | L22: 2086.636 | M22: 2222.3615 | N22: 2458.0818 | O22: 2765.891 | P22: 3082.928 | Q22: 3831.6319 | R22: 4900.9622 | S22: 5733.7981 | T22: 6701.3774 | U22: 7243.0473 | V22: 8426.947 | W22: 10289.768 | X22: 11810.616 | Y22: 12864.003 | Z22: 10622.802 | AA22: 9343.8611 | AB22: 8846.2343 | AC22: 8457.2688 | AD22: 8750.8185 | AE22: 12170.041 | AF22: 15135.852 | AG22: 16391.094 | AH22: 16525.062 | AI22: 20600.375 | AJ22: 21041.661 | AK22: 23372.619 | AL22: 22283.936 | AM22: 24208.555 | AN22: 28413.826 | AO22: 27489.555 | AP22: 24820.938 | AQ22: 25338.443 | AR22: 25244.275 | AS22: 23041.535 | AT22: 22995.158 | AU22: 24887.561 | AV22: 30587.668 | AW22: 35364.375 | AX22: 36795.977 | AY22: 38672.706 | AZ22: 44262.896 | BA22: 48106.893 | BB22: 44583.545 | BC22: 44141.878 | BD22: 47348.525 | BE22: 44673.116 | BF22: 46744.663 | BG22: 47700.54 | BH22: 40991.808 | BI22: 41984.103 | BJ22: 44089.31 | BK22: 47554.746 | BL22: 46414.435 | BM22: 44594.378
A23: Benin | B23: BEN | C23: GDP per capita (current US$) | D23: NY.GDP.PCAP.CD | E23: 93.0227 | F23: 95.572232 | G23: 94.464497 | H23: 99.858918 | I23: 104.33993 | J23: 110.13258 | K23: 112.94084 | L23: 111.95156 | M23: 116.89515 | N23: 116.02526 | O23: 114.55668 | P23: 112.56998 | Q23: 134.81959 | R23: 161.98706 | S23: 174.01409 | T23: 207.30031 | U23: 208.6564 | V23: 218.45398 | W23: 263.58143 | X23: 327.82231 | Y23: 378.04431 | Z23: 337.97837 | AA23: 322.77745 | AB23: 271.12984 | AC23: 252.86979 | AD23: 244.41094 | AE23: 303.34904 | AF23: 344.50315 | AG23: 346.73663 | AH23: 311.67805 | AI23: 393.68677 | AJ23: 385.75384 | AK23: 317.96274 | AL23: 411.92618 | AM23: 279.66675 | AN23: 367.3877 | AO23: 387.43208 | AP23: 361.1 | AQ23: 379.44178 | AR23: 551.82139 | AS23: 512.67392 | AT23: 518.06748 | AU23: 574.92978 | AV23: 711.28492 | AW23: 798.74426 | AX23: 822.7852 | AY23: 856.05488 | AZ23: 966.20358 | BA23: 1125.426 | BB23: 1088.7579 | BC23: 1036.5346 | BD23: 1130.2732 | BE23: 1145.14 | BF23: 1251.2097 | BG23: 1291.4101 | BH23: 1076.7967 | BI23: 1087.2873 | BJ23: 1136.594 | BK23: 1240.831 | BL23: 1219.5155 | BM23: 1291.041
A24: Burkina Faso | B24: BFA | C24: GDP per capita (current US$) | D24: NY.GDP.PCAP.CD | E24: 68.424734 | F24: 71.55818 | G24: 76.520549 | H24: 78.372196 | I24: 80.472718 | J24: 81.725052 | K24: 82.545684 | L24: 84.36307 | M24: 84.732937 | N24: 86.520209 | O24: 81.500015 | P24: 84.287829 | Q24: 99.326747 | R24: 113.78034 | S24: 124.3589 | T24: 152.728 | U24: 155.64906 | V24: 176.78335 | W24: 225.94152 | X24: 262.07601 | Y24: 282.68585 | Z24: 254.23047 | AA24: 245.09449 | AB24: 217.9946 | AC24: 193.84327 | AD24: 200.89435 | AE24: 256.76248 | AF24: 291.13162 | AG24: 313.06159 | AH24: 304.85352 | AI24: 351.97923 | AJ24: 346.4106 | AK24: 361.04688 | AL24: 334.94324 | AM24: 193.07028 | AN24: 235.83215 | AO24: 249.36056 | AP24: 229.49295 | AQ24: 255.71824 | AR24: 300.42172 | AS24: 255.71869 | AT24: 267.0976 | AU24: 294.66539 | AV24: 374.62736 | AW24: 418.37666 | AX24: 457.93343 | AY24: 473.44987 | AZ24: 535.06228 | BA24: 643.40458 | BB24: 624.17516 | BC24: 647.8361 | BD24: 751.17277 | BE24: 758.00043 | BF24: 787.46944 | BG24: 792.84624 | BH24: 653.32727 | BI24: 688.2507 | BJ24: 734.99627 | BK24: 813.09969 | BL24: 786.89544 | BM24: 830.92514
A25: Bangladesh | B25: BGD | C25: GDP per capita (current US$) | D25: NY.GDP.PCAP.CD | E25: 89.035239 | F25: 97.595292 | G25: 100.12213 | H25: 101.90141 | I25: 100.2211 | J25: 106.64664 | K25: 112.66536 | L25: 122.87063 | M25: 122.8476 | N25: 135.14738 | O25: 140.00271 | P25: 133.55142 | Q25: 94.381677 | R25: 119.55972 | S25: 182.02002 | T25: 277.57061 | U25: 141.19716 | V25: 131.37323 | W25: 176.03395 | X25: 200.76968 | Y25: 227.75193 | Z25: 247.64962 | AA25: 220.7188 | AB25: 204.41769 | AC25: 213.99664 | AD25: 245.45391 | AE25: 233.65807 | AF25: 253.97447 | AG25: 270.6996 | AH25: 285.82922 | AI25: 306.2687 | AJ25: 293.16042 | AK25: 293.64499 | AL25: 300.55575 | AM25: 299.53304 | AN25: 329.42408 | AO25: 394.71749 | AP25: 401.49867 | AQ25: 407.42918 | AR25: 409.54318 | AS25: 418.06894 | AT25: 415.0344 | AU25: 413.08028 | AV25: 446.31068 | AW25: 475.29193 | AX25: 499.46194 | AY25: 509.64019 | AZ25: 558.05184 | BA25: 634.98707 | BB25: 702.26442 | BC25: 781.15358 | BD25: 861.76216 | BE25: 883.11713 | BF25: 981.86085 | BG25: 1118.8738 | BH25: 1248.4533 | BI25: 1401.5646 | BJ25: 1563.7678 | BK25: 1698.1321 | BL25: 1855.6915 | BM25: 1968.7922
A26: Bulgaria | B26: BGR | C26: GDP per capita (current US$) | D26: NY.GDP.PCAP.CD | Y26: 2238.803 | Z26: 2234.8148 | AA26: 2169.004 | AB26: 1852.8134 | AC26: 1963.5727 | AD26: 1914.5506 | AE26: 2260.4273 | AF26: 3132.3014 | AG26: 2511.3931 | AH26: 2477.0208 | AI26: 2366.5298 | AJ26: 1267.7344 | AK26: 1211.9809 | AL26: 1278.2472 | AM26: 1148.4944 | AN26: 2258.286 | AO26: 1470.1037 | AP26: 1361.3924 | AQ26: 1820.4051 | AR26: 1659.7183 | AS26: 1621.243 | AT26: 1770.9135 | AU26: 2092.9577 | AV26: 2719.4977 | AW26: 3389.707 | AX26: 3899.9076 | AY26: 4523.0508 | AZ26: 5885.1043 | BA26: 7265.7355 | BB26: 6988.2333 | BC26: 6812.4063 | BD26: 7809.4251 | BE26: 7395.8498 | BF26: 7655.1297 | BG26: 7876.8665 | BH26: 7055.9357 | BI26: 7548.855 | BJ26: 8334.0817 | BK26: 9427.7304 | BL26: 9828.1485 | BM26: 9975.78
A27: Bahrain | B27: BHR | C27: GDP per capita (current US$) | D27: NY.GDP.PCAP.CD | Y27: 8537.7159 | Z27: 9269.2696 | AA27: 9446.0846 | AB27: 9421.3569 | AC27: 9590.5418 | AD27: 8706.7666 | AE27: 7041.6344 | AF27: 7554.9322 | AG27: 7958.7479 | AH27: 8031.0048 | AI27: 8529.0521 | AJ27: 9055.6444 | AK27: 9082.828 | AL27: 9698.1529 | AM27: 10130.376 | AN27: 10376.953 | AO27: 10544.795 | AP27: 10672.238 | AQ27: 10076.27 | AR27: 10401.562 | AS27: 13636.417 | AT27: 12868.177 | AU27: 13049.91 | AV27: 14222.037 | AW27: 15846.506 | AX27: 17959.397 | AY27: 19307.509 | AZ27: 20976.442 | BA27: 23066.451 | BB27: 19355.921 | BC27: 20722.07 | BD27: 22514.203 | BE27: 23654.37 | BF27: 24744.297 | BG27: 24989.438 | BH27: 22634.086 | BI27: 22608.453 | BJ27: 23742.937 | BK27: 23991.041 | BL27: 23443.435
A28: Bahamas, The | B28: BHS | C28: GDP per capita (current US$) | D28: NY.GDP.PCAP.CD | E28: 1550.2677 | F28: 1651.3177 | G28: 1752.84 | H28: 1867.0104 | I28: 1994.4405 | J28: 2144.7391 | K28: 2322.7058 | L28: 2556.6343 | M28: 2804.3339 | N28: 3215.1539 | O28: 3178.8633 | P28: 3297.4111 | Q28: 3322.2199 | R28: 3696.0318 | S28: 3416.4393 | T28: 3156.2508 | U28: 3328.6159 | V28: 3617.4531 | W28: 4131.3864 | X28: 5533.2519 | Y28: 6340.787 | Z28: 6624.9925 | AA28: 7168.1609 | AB28: 7698.083 | AC28: 8877.7059 | AD28: 9893.042 | AE28: 10344.323 | AF28: 11156.557 | AG28: 11387.709 | AH28: 12163.44 | AI28: 12356.231 | AJ28: 11919.834 | AK28: 11686.74 | AL28: 11406.858 | AM28: 11814.435 | AN28: 12238.605 | AO28: 12708.641 | AP28: 22036.101 | AQ28: 23514.178 | AR28: 26130.013 | AS28: 27098.156 | AT28: 27486.237 | AU28: 28867.082 | AV28: 28327.814 | AW28: 28396.014 | AX28: 30279.392 | AY28: 30713.798 | AZ28: 31472.286 | BA28: 30627.328 | BB28: 28552.517 | BC28: 28443.888 | BD28: 28005.912 | BE28: 29485.864 | BF28: 28784.024 | BG28: 29980.708 | BH28: 31295.564 | BI28: 31563.308 | BJ28: 32719.667 | BK28: 33767.941 | BL28: 34863.384 | BM28: 28607.901
A29: Bosnia and Herzegovina | B29: BIH | C29: GDP per capita (current US$) | D29: NY.GDP.PCAP.CD | AM29: 319.01279 | AN29: 487.4769 | AO29: 740.09969 | AP29: 982.80185 | AQ29: 1102.3907 | AR29: 1251.7476 | AS29: 1467.7765 | AT29: 1530.814 | AU29: 1769.1989 | AV29: 2224.7423 | AW29: 2814.9999 | AX29: 2980.6013 | AY29: 3416.5124 | AZ29: 4193.3681 | BA29: 5090.9459 | BB29: 4714.6937 | BC29: 4635.5103 | BD29: 5092.5547 | BE29: 4778.6361 | BF29: 5131.4046 | BG29: 5329.632 | BH29: 4727.2763 | BI29: 4994.689 | BJ29: 5394.58 | BK29: 6072.1846 | BL29: 6120.1126 | BM29: 6031.5569
A30: Belarus | B30: BLR | C30: GDP per capita (current US$) | D30: NY.GDP.PCAP.CD | AI30: 2124.8405 | AM30: 1739.8064 | AN30: 1323.2511 | AO30: 1452.4455 | AP30: 1394.5682 | AQ30: 1515.9767 | AR30: 1212.046 | AS30: 1276.494 | AT30: 1244.3732 | AU30: 1479.3146 | AV30: 1819.7661 | AW30: 2378.6233 | AX30: 3125.8105 | AY30: 3847.4341 | AZ30: 4735.6576 | BA30: 6377.3697 | BB30: 5351.3554 | BC30: 6029.3968 | BD30: 6519.2302 | BE30: 6940.1593 | BF30: 7978.8726 | BG30: 8318.5127 | BH30: 5949.1063 | BI30: 5022.6266 | BJ30: 5761.7471 | BK30: 6330.0752 | BL30: 6839.1038 | BM30: 6411.2278
A31: Belize | B31: BLZ | C31: GDP per capita (current US$) | D31: NY.GDP.PCAP.CD | E31: 304.90386 | F31: 316.41363 | G31: 327.1 | H31: 336.9381 | I31: 351.16113 | J31: 377.59075 | K31: 406.09425 | L31: 420.37593 | M31: 386.9399 | N31: 396.6277 | O31: 435.68334 | P31: 474.43661 | Q31: 519.55534 | R31: 605.93344 | S31: 786.08107 | T31: 885.95794 | U31: 717.06141 | V31: 858.82181 | W31: 980.75193 | X31: 1074.2948 | Y31: 1373.2168 | Z31: 1328.7741 | AA31: 1202.7932 | AB31: 1232.8532 | AC31: 1337.0376 | AD31: 1289.3907 | AE31: 1366.0417 | AF31: 1612.3313 | AG31: 1788.0013 | AH31: 2011.9468 | AI31: 2197.1616 | AJ31: 2326.7242 | AK31: 2668.5314 | AL31: 2834.6883 | AM31: 2882.152 | AN31: 2997.7605 | AO31: 3003.1827 | AP31: 2954.2272 | AQ31: 2993.0337 | AR31: 3066.0952 | AS31: 3364.4918 | AT31: 3404.4205 | AU31: 3526.0816 | AV31: 3650.6065 | AW31: 3802.2631 | AX31: 3885.034 | AY31: 4155.3238 | AZ31: 4252.3954 | BA31: 4404.3082 | BB31: 4186.52 | BC31: 4270.78 | BD31: 4423.4968 | BE31: 4505.6006 | BF31: 4568.6412 | BG31: 4718.4366 | BH31: 4770.2327 | BI31: 4856.9732 | BJ31: 4945.8577 | BK31: 5001.4222 | BL31: 5078.8099 | BM31: 4435.6212
A32: Bermuda | B32: BMU | C32: GDP per capita (current US$) | D32: NY.GDP.PCAP.CD | E32: 1902.4021 | F32: 1961.5382 | G32: 2020.386 | H32: 2020.2652 | I32: 2199.727 | J32: 2282.2165 | K32: 2630.8505 | L32: 2982.7497 | M32: 2830.1887 | N32: 3053.7037 | O32: 3387.2727 | P32: 3866.3004 | Q32: 4343.1734 | R32: 5009.2937 | S32: 5853.9326 | T32: 6509.434 | U32: 7261.2782 | V32: 8370.7865 | W32: 8876.8657 | X32: 9613.3829 | Y32: 11218.218 | Z32: 13425.977 | AA32: 14166.171 | AB32: 15902.02 | AC32: 17469.826 | AD32: 18269.536 | AE32: 20450.665 | AF32: 22411.796 | AG32: 24253.176 | AH32: 25517.922 | AI32: 26841.52 | AJ32: 27700.31 | AK32: 28669.682 | AL32: 30900.694 | AM32: 31476.064 | AN32: 33989.723 | AO32: 44826.789 | AP32: 48478.883 | AQ32: 51371.741 | AR32: 54245.46 | AS32: 56284.169 | AT32: 58883.959 | AU32: 62583.1 | AV32: 66111.725 | AW32: 70359.319 | AX32: 75882.034 | AY32: 95221.859 | AZ32: 104287.39 | BA32: 106935.49 | BB32: 101407.76 | BC32: 101875.28 | BD32: 97774.162 | BE32: 98431.865 | BF32: 99471.639 | BG32: 98467.684 | BH32: 102005.63 | BI32: 106885.88 | BJ32: 111820.58 | BK32: 113023.19 | BL32: 117098.45
A33: Bolivia | B33: BOL | C33: GDP per capita (current US$) | D33: NY.GDP.PCAP.CD | E33: 102.23772 | F33: 109.0613 | G33: 116.92497 | H33: 123.42934 | I33: 136.31236 | J33: 149.64033 | K33: 162.32605 | L33: 179.58304 | M33: 199.62957 | N33: 211.79702 | O33: 226.80697 | P33: 239.1275 | Q33: 268.58402 | R33: 263.89275 | S33: 429.29756 | T33: 480.80366 | U33: 534.27329 | V33: 617.30683 | W33: 703.13543 | X33: 809.41218 | Y33: 811.2853 | Z33: 1030.8331 | AA33: 960.98378 | AB33: 913.97485 | AC33: 1019.0573 | AD33: 870.18565 | AE33: 627.39863 | AF33: 671.07585 | AG33: 698.692 | AH33: 701.66594 | AI33: 709.05998 | AJ33: 762.07771 | AK33: 788.15232 | AL33: 784.19099 | AM33: 801.04614 | AN33: 880.99269 | AO33: 950.85639 | AP33: 998.51595 | AQ33: 1049.4994 | AR33: 1003.3922 | AS33: 997.58175 | AT33: 948.87021 | AU33: 904.2258 | AV33: 907.53742 | AW33: 967.40646 | AX33: 1034.3118 | AY33: 1218.8741 | AZ33: 1372.6284 | BA33: 1715.2084 | BB33: 1754.2095 | BC33: 1955.4602 | BD33: 2346.3378 | BE33: 2609.8806 | BF33: 2908.2004 | BG33: 3081.8788 | BH33: 3035.9717 | BI33: 3076.6564 | BJ33: 3351.1243 | BK33: 3548.5908 | BL33: 3552.0681 | BM33: 3143.0455
A34: Brazil | B34: BRA | C34: GDP per capita (current US$) | D34: NY.GDP.PCAP.CD | E34: 210.10987 | F34: 205.04078 | G34: 260.42565 | H34: 292.25217 | I34: 261.66662 | J34: 261.35435 | K34: 315.79721 | L34: 347.49305 | M34: 374.78678 | N34: 403.8843 | O34: 445.0231 | P34: 504.74947 | Q34: 586.21438 | R34: 775.2733 | S34: 1004.105 | T34: 1153.8309 | U34: 1390.6249 | V34: 1567.0062 | W34: 1744.2571 | X34: 1908.4876 | Y34: 1947.2764 | Z34: 2132.8833 | AA34: 2226.7671 | AB34: 1570.5398 | AC34: 1578.9264 | AD34: 1648.0821 | AE34: 1941.4911 | AF34: 2087.3075 | AG34: 2300.3768 | AH34: 2908.4961 | AI34: 3100.2804 | AJ34: 3975.3902 | AK34: 2596.9198 | AL34: 2791.209 | AM34: 3500.6115 | AN34: 4748.2157 | AO34: 5166.1639 | AP34: 5282.0086 | AQ34: 5087.1521 | AR34: 3478.3728 | AS34: 3749.7533 | AT34: 3156.7988 | AU34: 2829.2831 | AV34: 3070.9105 | AW34: 3637.4624 | AX34: 4790.437 | AY34: 5886.4637 | AZ34: 7348.0307 | BA34: 8831.0231 | BB34: 8597.9155 | BC34: 11286.243 | BD34: 13245.612 | BE34: 12370.024 | BF34: 12300.325 | BG34: 12112.588 | BH34: 8814.0014 | BI34: 8710.0968 | BJ34: 9928.6431 | BK34: 9151.4453 | BL34: 8897.4878 | BM34: 6796.8445
A35: Barbados | B35: BRB | C35: GDP per capita (current US$) | D35: NY.GDP.PCAP.CD | S35: 1274.5484 | T35: 1633.823 | U35: 1760.6601 | V35: 1988.8952 | W35: 2209.767 | X35: 2667.0796 | Y35: 4010.8112 | Z35: 4398.8249 | AA35: 4580.9705 | AB35: 4851.0996 | AC35: 5271.7298 | AD35: 5500.4141 | AE35: 6019.6532 | AF35: 6605.7792 | AG35: 6999.8761 | AH35: 7717.1774 | AI35: 7711.2955 | AJ35: 7714.7427 | AK35: 7444.1782 | AL35: 7819.57 | AM35: 8121.5619 | AN35: 8335.8993 | AO35: 8851.0465 | AP35: 9315.9676 | AQ35: 10459.442 | AR35: 10914.282 | AS35: 11268.42 | AT35: 11209.421 | AU35: 11361.517 | AV35: 11699.37 | AW35: 12512.578 | AX35: 13822.742 | AY35: 15199.568 | AZ35: 16770.661 | BA35: 17092.582 | BB35: 15885.41 | BC35: 16056.371 | BD35: 16458.353 | BE35: 16249.674 | BF35: 16451.279 | BG35: 16489.072 | BH35: 16524.9 | BI35: 16900.048 | BJ35: 17391.669 | BK35: 17745.255 | BL35: 18148.498 | BM35: 15191.164
A36: Brunei Darussalam | B36: BRN | C36: GDP per capita (current US$) | D36: NY.GDP.PCAP.CD | J36: 1113.783 | K36: 1237.5636 | L36: 1236.4197 | M36: 1364.066 | N36: 1304.3407 | O36: 1382.5376 | P36: 1455.8876 | Q36: 1906.9715 | R36: 2916.1303 | S36: 6923.2218 | T36: 7228.0404 | U36: 8461.8896 | V36: 9917.3015 | W36: 10715.177 | X36: 14945.841 | Y36: 25422.039 | Z36: 21828.122 | AA36: 20693.825 | AB36: 18129.244 | AC36: 17337.026 | AD36: 15699.575 | AE36: 10214.028 | AF36: 11594.568 | AG36: 11009.257 | AH36: 11872.725 | AI36: 13607.89 | AJ36: 13905.168 | AK36: 15274.668 | AL36: 14575.575 | AM36: 14120.953 | AN36: 15933.453 | AO36: 16793.391 | AP36: 16660.148 | AQ36: 12694.149 | AR36: 14101.173 | AS36: 18012.502 | AT36: 16472.003 | AU36: 16850.394 | AV36: 18560.504 | AW36: 21902.027 | AX36: 26105.422 | AY36: 30979.963 | AZ36: 32663.392 | BA36: 37934.676 | BB36: 27956.005 | BC36: 35270.642 | BD36: 47055.961 | BE36: 47739.558 | BF36: 44740.859 | BG36: 41725.868 | BH36: 31164.036 | BI36: 27158.406 | BJ36: 28571.608 | BK36: 31628.476 | BL36: 31085.962 | BM36: 27466.34
A37: Bhutan | B37: BTN | C37: GDP per capita (current US$) | D37: NY.GDP.PCAP.CD | Y37: 316.34994 | Z37: 332.8106 | AA37: 329.57335 | AB37: 356.25056 | AC37: 355.4159 | AD37: 351.6799 | AE37: 399.4935 | AF37: 491.12781 | AG37: 534.29619 | AH37: 506.96839 | AI37: 541.93226 | AJ37: 449.50124 | AK37: 449.40043 | AL37: 424.33784 | AM37: 486.90198 | AN37: 543.30162 | AO37: 560.39108 | AP37: 638.48587 | AQ37: 643.98823 | AR37: 690.91274 | AS37: 718.19634 | AT37: 764.43281 | AU37: 845.50067 | AV37: 962.09537 | AW37: 1068.4318 | AX37: 1228.4324 | AY37: 1330.9774 | AZ37: 1757.1905 | BA37: 1828.1547 | BB37: 1819.1973 | BC37: 2258.1864 | BD37: 2563.2612 | BE37: 2538.9495 | BF37: 2472.7248 | BG37: 2652.2257 | BH37: 2752.6302 | BI37: 2930.5749 | BJ37: 3286.5967 | BK37: 3243.4774 | BL37: 3316.167 | BM37: 3122.3761
A38: Botswana | B38: BWA | C38: GDP per capita (current US$) | D38: NY.GDP.PCAP.CD | E38: 60.493958 | F38: 64.17614 | G38: 68.050349 | H38: 71.106439 | I38: 75.955918 | J38: 81.769994 | K38: 89.979553 | L38: 100.40514 | M38: 110.97864 | N38: 126.54555 | O38: 153.32638 | P38: 197.19422 | Q38: 246.54154 | R38: 353.85848 | S38: 428.19843 | T38: 479.09129 | U38: 483.14132 | V38: 564.12901 | W38: 709.18934 | X38: 947.75505 | Y38: 1181.6139 | Z38: 1154.1786 | AA38: 1054.0559 | AB38: 1176.8195 | AC38: 1202.976 | AD38: 1042.2398 | AE38: 1253.5553 | AF38: 1701.6781 | AG38: 2203.6466 | AH38: 2477.9754 | AI38: 2945.832 | AJ38: 2972.729 | AK38: 3040.9894 | AL38: 2973.3804 | AM38: 2970.1184 | AN38: 3219.9142 | AO38: 3221.6891 | AP38: 3258.9824 | AQ38: 3039.9649 | AR38: 3405.8211 | AS38: 3522.3108 | AT38: 3278.0161 | AU38: 3190.6248 | AV38: 4330.9724 | AW38: 5073.5204 | AX38: 5513.3311 | AY38: 5521.9906 | AZ38: 5832.7371 | BA38: 5713.5439 | BB38: 5255.7765 | BC38: 6434.8125 | BD38: 7617.31 | BE38: 7050.5735 | BF38: 7224.9127 | BG38: 7780.6348 | BH38: 6799.8702 | BI38: 7243.934 | BJ38: 7893.4187 | BK38: 8279.8185 | BL38: 7970.797 | BM38: 6710.9904
A39: Central African Republic | B39: CAF | C39: GDP per capita (current US$) | D39: NY.GDP.PCAP.CD | E39: 74.687347 | F39: 80.688064 | G39: 80.212712 | H39: 81.917909 | I39: 88.290116 | J39: 91.830375 | K39: 94.398236 | L39: 95.896484 | M39: 109.94591 | N39: 105.7071 | O39: 104.41202 | P39: 109.45336 | Q39: 123.31065 | R39: 143.11585 | S39: 146.22777 | T39: 193.35498 | U39: 225.91317 | V39: 248.68603 | W39: 292.47001 | X39: 327.34122 | Y39: 362.40015 | Z39: 306.83224 | AA39: 320.42983 | AB39: 273.50138 | AC39: 257.35364 | AD39: 340.20139 | AE39: 432.01176 | AF39: 453.74622 | AG39: 469.52917 | AH39: 449.3989 | AI39: 513.30419 | AJ39: 478.50328 | AK39: 477.12232 | AL39: 419.8027 | AM39: 271.5055 | AN39: 346.1082 | AO39: 304.63108 | AP39: 276.4216 | AQ39: 278.3319 | AR39: 280.90842 | AS39: 251.20729 | AT39: 250.35715 | AU39: 260.74546 | AV39: 293.66155 | AW39: 320.73681 | AX39: 331.16309 | AY39: 354.67086 | AZ39: 404.37454 | BA39: 464.5612 | BB39: 474.70563 | BC39: 488.42177 | BD39: 551.74969 | BE39: 565.80116 | BF39: 380.29789 | BG39: 424.44911 | BH39: 377.42292 | BI39: 402.19163 | BJ39: 450.9007 | BK39: 475.95385 | BL39: 467.90802 | BM39: 476.85111
A40: Canada | B40: CAN | C40: GDP per capita (current US$) | D40: NY.GDP.PCAP.CD | E40: 2259.2943 | F40: 2240.433 | G40: 2268.5853 | H40: 2374.4984 | I40: 2555.1111 | J40: 2770.3618 | K40: 3047.1061 | L40: 3217.1593 | M40: 3462.6789 | N40: 3763.9534 | O40: 4121.9328 | P40: 4520.1629 | Q40: 5089.5879 | R40: 5838.6609 | S40: 7033.011 | T40: 7511.2113 | U40: 8809.2647 | V40: 8919.0575 | W40: 9123.6913 | X40: 10043.661 | Y40: 11170.564 | Z40: 12337.466 | AA40: 12481.875 | AB40: 13425.122 | AC40: 13877.917 | AD40: 14114.808 | AE40: 14461.069 | AF40: 16308.967 | AG40: 18936.964 | AH40: 20715.631 | AI40: 21448.362 | AJ40: 21768.343 | AK40: 20879.848 | AL40: 20121.161 | AM40: 19935.381 | AN40: 20613.788 | AO40: 21227.348 | AP40: 21901.563 | AQ40: 21024.585 | AR40: 22315.247 | AS40: 24271.002 | AT40: 23822.06 | AU40: 24255.339 | AV40: 28300.463 | AW40: 32143.681 | AX40: 36382.508 | AY40: 40504.061 | AZ40: 44659.895 | BA40: 46710.506 | BB40: 40876.31 | BC40: 47562.083 | BD40: 52223.696 | BE40: 52669.09 | BF40: 52635.175 | BG40: 50955.998 | BH40: 43596.136 | BI40: 42315.604 | BJ40: 45129.356 | BK40: 46454.743 | BL40: 46326.673 | BM40: 43241.618
A41: Central Europe and the Baltics | B41: CEB | C41: GDP per capita (current US$) | D41: NY.GDP.PCAP.CD | AI41: 2313.5644 | AJ41: 2196.1787 | AK41: 2359.7995 | AL41: 2489.8023 | AM41: 2824.8629 | AN41: 3578.6154 | AO41: 3793.635 | AP41: 3745.6101 | AQ41: 4106.1995 | AR41: 3986.196 | AS41: 3946.8433 | AT41: 4352.3403 | AU41: 4936.0393 | AV41: 5943.4391 | AW41: 7171.1742 | AX41: 8356.2677 | AY41: 9474.9761 | AZ41: 12012.392 | BA41: 14585.415 | BB41: 12304.556 | BC41: 12608.383 | BD41: 13907.672 | BE41: 13014.506 | BF41: 13712.809 | BG41: 14153.748 | BH41: 12513.202 | BI41: 12822.376 | BJ41: 14238.197 | BK41: 16034.715 | BL41: 16294.377 | BM41: 16082.458
A42: Switzerland | B42: CHE | C42: GDP per capita (current US$) | D42: NY.GDP.PCAP.CD | E42: 1787.3603 | F42: 1971.3163 | G42: 2131.3917 | H42: 2294.1828 | I42: 2501.2932 | J42: 2620.4755 | K42: 2784.7335 | L42: 2960.7226 | M42: 3121.889 | N42: 3344.7836 | Y42: 19410.189 | Z42: 17679.869 | AA42: 18015.106 | AB42: 17874.251 | AC42: 17005.534 | AD42: 17166.518 | AE42: 24480.423 | AF42: 30466.109 | AG42: 32717.92 | AH42: 31334.979 | AI42: 39607.819 | AJ42: 39577.749 | AK42: 40747.925 | AL42: 39270.114 | AM42: 43128.014 | AN42: 50155.974 | AO42: 48144.579 | AP42: 41631.439 | AQ42: 42740.128 | AR42: 41786.234 | AS42: 38952.034 | AT42: 39727.847 | AU42: 42578.763 | AV42: 49470.397 | AW42: 54878.471 | AX42: 56546.786 | AY42: 59300.617 | AZ42: 65359.519 | BA42: 74572.232 | BB42: 72083.168 | BC42: 77117.126 | BD42: 91254.035 | BE42: 86547.671 | BF42: 88109.487 | BG42: 89684.708 | BH42: 84776.142 | BI42: 83073.28 | BJ42: 83352.089 | BK42: 86429.501 | BL42: 85300.348 | BM42: 86601.556
A43: Channel Islands | B43: CHI | C43: GDP per capita (current US$) | D43: NY.GDP.PCAP.CD | AQ43: 40584.829 | AR43: 42444.008 | AS43: 43382.827 | AT43: 41804.371 | AU43: 44545.922 | AV43: 48858.832 | AW43: 56751.127 | AX43: 58198.984 | AY43: 63243.374 | AZ43: 74458.795
A44: Chile | B44: CHL | C44: GDP per capita (current US$) | D44: NY.GDP.PCAP.CD | E44: 505.34933 | F44: 555.1344 | G44: 638.94536 | H44: 655.25225 | I44: 678.12811 | J44: 670.39569 | K44: 772.72572 | L44: 753.12796 | M44: 756.912 | N44: 870.31984 | O44: 932.86157 | P44: 1094.6823 | Q44: 1173.2184 | R44: 1640.0297 | S44: 1554.3878 | T44: 719.59916 | U44: 961.4246 | V44: 1278.3282 | W44: 1441.9421 | X44: 1937.2666 | Y44: 2542.7638 | Z44: 2979.6079 | AA44: 2156.5131 | AB44: 1709.4421 | AC44: 1624.632 | AD44: 1444.2801 | AE44: 1517.8613 | AF44: 1760.3064 | AG44: 2026.8379 | AH44: 2288.5549 | AI44: 2494.5268 | AJ44: 2803.5627 | AK44: 3350.2141 | AL44: 3535.1744 | AM44: 4024.2152 | AN44: 5107.2775 | AO44: 5349.8052 | AP44: 5745.3711 | AQ44: 5446.5795 | AR44: 4957.7776 | AS44: 5074.9026 | AT44: 4574.5947 | AU44: 4446.2494 | AV44: 4772.5637 | AW44: 6194.8527 | AX44: 7598.5289 | AY44: 9464.5485 | AZ44: 10502.351 | BA44: 10751.482 | BB44: 10208.908 | BC44: 12808.038 | BD44: 14637.233 | BE44: 15351.541 | BF44: 15842.936 | BG44: 14670.989 | BH44: 13574.169 | BI44: 13753.592 | BJ44: 14998.817 | BK44: 15888.144 | BL44: 14741.714 | BM44: 13231.704
A45: China | B45: CHN | C45: GDP per capita (current US$) | D45: NY.GDP.PCAP.CD | E45: 89.520542 | F45: 75.805838 | G45: 70.909412 | H45: 74.313643 | I45: 85.498555 | J45: 98.486778 | K45: 104.32457 | L45: 96.589532 | M45: 91.472718 | N45: 100.1299 | O45: 113.16299 | P45: 118.65458 | Q45: 131.88356 | R45: 157.09037 | S45: 160.14009 | T45: 178.34182 | U45: 165.40554 | V45: 185.42283 | W45: 156.39639 | X45: 183.98315 | Y45: 194.80472 | Z45: 197.07147 | AA45: 203.33492 | AB45: 225.43193 | AC45: 250.71397 | AD45: 294.45885 | AE45: 281.92812 | AF45: 251.81196 | AG45: 283.5377 | AH45: 310.88191 | AI45: 317.88467 | AJ45: 333.14215 | AK45: 366.46069 | AL45: 377.38984 | AM45: 473.49228 | AN45: 609.65668 | AO45: 709.41376 | AP45: 781.74416 | AQ45: 828.58048 | AR45: 873.28706 | AS45: 959.37248 | AT45: 1053.1082 | AU45: 1148.5083 | AV45: 1288.6433 | AW45: 1508.6681 | AX45: 1753.4178 | AY45: 2099.2294 | AZ45: 2693.9701 | BA45: 3468.3046 | BB45: 3832.2364 | BC45: 4550.4531 | BD45: 5618.1323 | BE45: 6316.9183 | BF45: 7050.6463 | BG45: 7678.5995 | BH45: 8066.9426 | BI45: 8147.9377 | BJ45: 8879.4387 | BK45: 9976.6771 | BL45: 10216.63 | BM45: 10500.396
A46: Cote d'Ivoire | B46: CIV | C46: GDP per capita (current US$) | D46: NY.GDP.PCAP.CD | E46: 155.89963 | F46: 170.24305 | G46: 171.12864 | H46: 194.21253 | I46: 226.22704 | J46: 217.60244 | K46: 233.61491 | L46: 238.31049 | M46: 271.85335 | N46: 277.97213 | O46: 285.27303 | P46: 297.28036 | Q46: 331.67001 | R46: 429.41293 | S46: 501.55268 | T46: 607.235 | U46: 694.38325 | V46: 891.6346 | W46: 1074.862 | X46: 1189.5684 | Y46: 1266.6239 | Z46: 1004.6344 | AA46: 863.33343 | AB46: 747.75618 | AC46: 717.89767 | AD46: 703.51952 | AE46: 888.52858 | AF46: 942.93101 | AG46: 924.32725 | AH46: 848.28954 | AI46: 905.32202 | AJ46: 848.75312 | AK46: 870.4807 | AL46: 832.28306 | AM46: 605.26337 | AN46: 774.67138 | AO46: 827.76212 | AP46: 774.72707 | AQ46: 809.01305 | AR46: 771.96841 | AS46: 652.92787 | AT46: 664.7087 | AU46: 719.91298 | AV46: 871.6665 | AW46: 922.85527 | AX46: 931.20008 | AY46: 949.97583 | AZ46: 1062.5569 | BA46: 1240.6149 | BB46: 1215.1668 | BC46: 1213.113 | BD46: 1208.5832 | BE46: 1243.2735 | BF46: 1415.8717 | BG46: 1561.4644 | BH46: 1972.5457 | BI46: 2013.3814 | BJ46: 2111.0266 | BK46: 2314.051 | BL46: 2276.3324 | BM46: 2325.7237
A47: Cameroon | B47: CMR | C47: GDP per capita (current US$) | D47: NY.GDP.PCAP.CD | E47: 118.64315 | F47: 123.51481 | G47: 128.59464 | H47: 130.17527 | I47: 137.62976 | J47: 141.00252 | K47: 144.01537 | L47: 154.67789 | M47: 168.70215 | N47: 173.12172 | O47: 176.57371 | P47: 184.90348 | Q47: 218.17605 | R47: 269.5923 | S47: 297.68604 | T47: 383.44055 | U47: 378.12362 | V47: 430.3814 | W47: 574.16639 | X47: 707.54429 | Y47: 774.18524 | Z47: 743.76016 | AA47: 721.21631 | AB47: 726.50596 | AC47: 749.33907 | AD47: 848.47328 | AE47: 1140.5972 | AF47: 1216.0645 | AG47: 1104.7938 | AH47: 963.83268 | AI47: 1045.3644 | AJ47: 975.47195 | AK47: 965.78074 | AL47: 1129.0494 | AM47: 626.7512 | AN47: 736.79256 | AO47: 738.2004 | AP47: 700.16227 | AQ47: 735.6282 | AR47: 708.44508 | AS47: 651.61026 | AT47: 651.67058 | AU47: 711.22935 | AV47: 867.90355 | AW47: 1011.7564 | AX47: 1012.2826 | AY47: 1063.0816 | AZ47: 1195.6492 | BA47: 1377.2986 | BB47: 1319.9974 | BC47: 1286.5159 | BD47: 1405.0941 | BE47: 1354.5455 | BF47: 1465.6387 | BG47: 1542.6206 | BH47: 1327.5026 | BI47: 1364.3295 | BJ47: 1425.1064 | BK47: 1534.4922 | BL47: 1507.4498 | BM47: 1499.3728
A48: Congo, Dem. Rep. | B48: COD | C48: GDP per capita (current US$) | D48: NY.GDP.PCAP.CD | E48: 220.31399 | F48: 197.39136 | G48: 235.63352 | H48: 377.42988 | I48: 170.467 | J48: 232.81113 | K48: 253.75921 | L48: 184.13044 | M48: 206.71495 | N48: 258.60648 | O48: 243.74978 | P48: 272.06543 | Q48: 292.29713 | R48: 362.84356 | S48: 430.70216 | T48: 446.97554 | U48: 409.52423 | V48: 509.06677 | W48: 615.97891 | X48: 587.15158 | Y48: 546.1125 | Z48: 463.67117 | AA48: 492.53249 | AB48: 387.50766 | AC48: 269.84272 | AD48: 240.7881 | AE48: 263.8313 | AF48: 243.00479 | AG48: 273.12782 | AH48: 269.59288 | AI48: 270.13054 | AJ48: 268.2925 | AK48: 220.36801 | AL48: 275.82162 | AM48: 145.0956 | AN48: 135.82359 | AO48: 134.99516 | AP48: 138.97905 | AQ48: 138.5891 | AR48: 102.59797 | AS48: 405.21622 | AT48: 153.59104 | AU48: 175.00995 | AV48: 173.79613 | AW48: 194.04 | AX48: 218.38623 | AY48: 255.43304 | AZ48: 286.33047 | BA48: 327.56372 | BB48: 298.61969 | BC48: 334.02158 | BD48: 387.08248 | BE48: 424.60037 | BF48: 457.96375 | BG48: 486.7871 | BH48: 497.31704 | BI48: 471.31882 | BJ48: 467.07423 | BK48: 557.06441 | BL48: 580.71686 | BM48: 556.81319
A49: Congo, Rep. | B49: COG | C49: GDP per capita (current US$) | D49: NY.GDP.PCAP.CD | E49: 129.37034 | F49: 145.40598 | G49: 155.73853 | H49: 157.05587 | I49: 165.00917 | J49: 171.64614 | K49: 185.89226 | L49: 194.66034 | M49: 200.39502 | N49: 205.53403 | O49: 207.2213 | P49: 235.83728 | Q49: 291.97749 | R49: 374.1277 | S49: 392.32108 | T49: 499.20196 | U49: 476.85048 | V49: 469.68793 | W49: 523.91233 | X49: 694.17683 | Y49: 959.4275 | Z49: 1088.9767 | AA49: 1146.3056 | AB49: 1080.8163 | AC49: 1098.4416 | AD49: 1051.8737 | AE49: 875.45167 | AF49: 1058.2294 | AG49: 991.51871 | AH49: 1042.052 | AI49: 1187.5498 | AJ49: 1124.8979 | AK49: 1178.0271 | AL49: 1048.613 | AM49: 672.16319 | AN49: 781.52501 | AO49: 912.01235 | AP49: 810.07664 | AQ49: 660.47148 | AR49: 774.71194 | AS49: 1032.1375 | AT49: 869.1005 | AU49: 916.58804 | AV49: 1028.4152 | AW49: 1326.5967 | AX49: 1834.88 | AY49: 2153.4917 | AZ49: 2262.8544 | BA49: 2892.417 | BB49: 2336.161 | BC49: 3073.5578 | BD49: 3557.5562 | BE49: 3923.0935 | BF49: 3883.7468 | BG49: 3776.4856 | BH49: 2447.5393 | BI49: 2039.4532 | BJ49: 2173.6803 | BK49: 2601.4105 | BL49: 2359.1773 | BM49: 1972.5452
A50: Colombia | B50: COL | C50: GDP per capita (current US$) | D50: NY.GDP.PCAP.CD | E50: 251.04152 | F50: 274.05226 | G50: 289.91795 | H50: 274.31496 | I50: 328.65503 | J50: 307.64686 | K50: 281.56605 | L50: 293.64426 | M50: 292.2575 | N50: 307.99521 | O50: 335.1182 | P50: 355.40752 | Q50: 385.11252 | R50: 448.03382 | S50: 525.52573 | T50: 544.29091 | U50: 623.42897 | V50: 773.74582 | W50: 904.01069 | X50: 1061.8483 | Y50: 1241.6396 | Z50: 1323.3766 | AA50: 1386.673 | AB50: 1348.8046 | AC50: 1304.1772 | AD50: 1165.0424 | AE50: 1142.9394 | AF50: 1165.9824 | AG50: 1232.2262 | AH50: 1218.211 | AI50: 1445.3286 | AJ50: 1456.6944 | AK50: 1697.1129 | AL50: 1893.5422 | AM50: 2284.8388 | AN50: 2539.9129 | AO50: 2620.5388 | AP50: 2827.3795 | AQ50: 2566.0242 | AR50: 2209.9317 | AS50: 2520.4811 | AT50: 2439.6825 | AU50: 2396.6271 | AV50: 2281.4018 | AW50: 2782.6232 | AX50: 3414.4652 | AY50: 3741.0928 | AZ50: 4714.0731 | BA50: 5472.5365 | BB50: 5193.2415 | BC50: 6336.7095 | BD50: 7335.1669 | BE50: 8050.2554 | BF50: 8218.3478 | BG50: 8114.3439 | BH50: 6175.876 | BI50: 5870.778 | BJ50: 6376.7067 | BK50: 6729.5833 | BL50: 6424.9795 | BM50: 5332.7735
A51: Comoros | B51: COM | C51: GDP per capita (current US$) | D51: NY.GDP.PCAP.CD | Y51: 689.39849 | Z51: 618.19729 | AA51: 562.81503 | AB51: 570.15412 | AC51: 534.64911 | AD51: 553.6324 | AE51: 763.32535 | AF51: 896.13317 | AG51: 918.89976 | AH51: 854.4652 | AI51: 1043.7907 | AJ51: 1000.5563 | AK51: 1047.9651 | AL51: 1008.0385 | AM51: 690.46725 | AN51: 838.17168 | AO51: 810.54755 | AP51: 726.05231 | AQ51: 718.12127 | AR51: 723.17826 | AS51: 647.42581 | AT51: 680.90557 | AU51: 747.98886 | AV51: 937.7109 | AW51: 1061.0755 | AX51: 1069.0294 | AY51: 1114.9453 | AZ51: 1240.0925 | BA51: 1393.216 | BB51: 1344.7304 | BC51: 1316.4912 | BD51: 1447.9453 | BE51: 1403.3604 | BF51: 1505.3372 | BG51: 1513.8304 | BH51: 1242.5857 | BI51: 1273.0509 | BJ51: 1323.815 | BK51: 1415.9552 | BL51: 1370.1401 | BM51: 1402.5955
A52: Cabo Verde | B52: CPV | C52: GDP per capita (current US$) | D52: NY.GDP.PCAP.CD | Y52: 501.13749 | Z52: 483.12693 | AA52: 477.93926 | AB52: 461.24 | AC52: 431.23755 | AD52: 441.90663 | AE52: 602.1585 | AF52: 732.56327 | AG52: 811.39834 | AH52: 807.56239 | AI52: 908.08813 | AJ52: 923.74428 | AK52: 1003.9295 | AL52: 1339.7296 | AM52: 1080.1566 | AN52: 1261.1031 | AO52: 1269.1206 | AP52: 1213.6329 | AQ52: 1265.1978 | AR52: 1408.9862 | AS52: 1259.3531 | AT52: 1292.2265 | AU52: 1401.8911 | AV52: 1809.11 | AW52: 2024.2664 | AX52: 2099.1484 | AY52: 2361.3801 | AZ52: 3186.7799 | BA52: 3721.22 | BB52: 3517.4302 | BC52: 3378.3234 | BD52: 3740.3741 | BE52: 3447.4831 | BF52: 3616.0356 | BG52: 3588.6256 | BH52: 3043.0314 | BI52: 3130.9988 | BJ52: 3292.6335 | BK52: 3617.3474 | BL52: 3603.7752 | BM52: 3064.2724
A53: Costa Rica | B53: CRI | C53: GDP per capita (current US$) | D53: NY.GDP.PCAP.CD | E53: 381.36368 | F53: 355.00275 | G53: 334.30925 | H53: 344.35466 | I53: 352.33688 | J53: 372.28058 | K53: 393.48068 | L53: 412.23511 | M53: 442.77961 | N53: 474.7953 | O53: 533.09156 | P53: 568.09645 | Q53: 636.90505 | R53: 767.32713 | S53: 816.03686 | T53: 936.33682 | U53: 1122.8076 | V53: 1393.0005 | W53: 1555.5404 | X53: 1734.618 | Y53: 2021.5488 | Z53: 1068.5024 | AA53: 1032.997 | AB53: 1213.5565 | AC53: 1373.9393 | AD53: 1432.0812 | AE53: 1572.455 | AF53: 1571.2923 | AG53: 1558.5059 | AH53: 1727.871 | AI53: 1831.0002 | AJ53: 2247.3734 | AK53: 2605.8052 | AL53: 2841.6428 | AM53: 3031.8888 | AN53: 3265.6934 | AO53: 3215.1057 | AP53: 3391.9777 | AQ53: 3597.4345 | AR53: 3668.8021 | AS53: 3789.0539 | AT53: 3960.3077 | AU53: 4042.7057 | AV53: 4147.8244 | AW53: 4404.7119 | AX53: 4676.3794 | AY53: 5227.466 | AZ53: 6103.7419 | BA53: 6901.3883 | BB53: 6801.0367 | BC53: 8227.1275 | BD53: 9229.8345 | BE53: 10075.005 | BF53: 10744.091 | BG53: 10847.17 | BH53: 11642.778 | BI53: 12011.223 | BJ53: 12225.574 | BK53: 12468.575 | BL53: 12669.706 | BM53: 12076.815
A54: Caribbean small states | B54: CSS | C54: GDP per capita (current US$) | D54: NY.GDP.PCAP.CD | E54: 448.25642 | F54: 476.90148 | G54: 494.73637 | H54: 516.73952 | I54: 547.95053 | J54: 580.94414 | K54: 621.43473 | L54: 658.3509 | M54: 645.92831 | N54: 695.03898 | O54: 755.14456 | P54: 811.13175 | Q54: 925.52753 | R54: 1000.8624 | S54: 1285.4933 | T54: 1485.1613 | U54: 1511.8749 | V54: 1736.7492 | W54: 1759.825 | X54: 1999.1885 | Y54: 2461.6559 | Z54: 2683.6552 | AA54: 2940.2128 | AB54: 2942.7192 | AC54: 2778.8933 | AD54: 2722.8283 | AE54: 2466.2991 | AF54: 2633.1164 | AG54: 2775.6222 | AH54: 2827.6886 | AI54: 2997.3196 | AJ54: 2951.0596 | AK54: 2875.1897 | AL54: 3084.6608 | AM54: 3214.0518 | AN54: 3514.1007 | AO54: 3803.6233 | AP54: 4421.5071 | AQ54: 4690.204 | AR54: 4938.5239 | AS54: 5253.4421 | AT54: 5374.0832 | AU54: 5600.4426 | AV54: 5945.8779 | AW54: 6459.5654 | AX54: 7255.1441 | AY54: 8201.2905 | AZ54: 9054.8514 | BA54: 10225.38 | BB54: 8578.7167 | BC54: 9253.214 | BD54: 9920.9102 | BE54: 10187.302 | BF54: 10306.888 | BG54: 10377.113 | BH54: 10116.52 | BI54: 9560.1947 | BJ54: 9810.4701 | BK54: 10250.434 | BL54: 10355.408 | BM54: 9192.7678
A55: Cuba | B55: CUB | C55: GDP per capita (current US$) | D55: NY.GDP.PCAP.CD | O55: 653.42695 | P55: 779.72379 | Q55: 901.3671 | R55: 1088.127 | S55: 1223.6913 | T55: 1379.0818 | U55: 1443.3024 | V55: 1472.7296 | W55: 1835.1115 | X55: 2000.2802 | Y55: 2021.7246 | Z55: 2035.6072 | AA55: 2107.9324 | AB55: 2224.6535 | AC55: 2396.3537 | AD55: 2269.8252 | AE55: 2378.9107 | AF55: 2451.133 | AG55: 2640.9184 | AH55: 2572.6917 | AI55: 2703.1683 | AJ55: 2278.2104 | AK55: 2057.1036 | AL55: 2073.0937 | AM55: 2624.757 | AN55: 2794.7388 | AO55: 2286.9291 | AP55: 2308.1466 | AQ55: 2331.4627 | AR55: 2558.9041 | AS55: 2747.1003 | AT55: 2837.7357 | AU55: 2999.2418 | AV55: 3197.1332 | AW55: 3395.7108 | AX55: 3786.6635 | AY55: 4683.5691 | AZ55: 5208.7184 | BA55: 5411.2695 | BB55: 5529.6694 | BC55: 5730.3543 | BD55: 6139.7188 | BE55: 6497.3148 | BF55: 6837.7117 | BG55: 7133.3377 | BH55: 7694.0146 | BI55: 8060.7966 | BJ55: 8541.2137 | BK55: 8824.194 | BL55: 9099.6731
A56: Curacao | B56: CUW | C56: GDP per capita (current US$) | D56: NY.GDP.PCAP.CD | BD56: 20146.386 | BE56: 20587.397 | BF56: 20462.718 | BG56: 20258.01 | BH56: 19951.328 | BI56: 19555.366 | BJ56: 19457.532 | BK56: 19630.893 | BL56: 19701.27
A57: Cayman Islands | B57: CYM | C57: GDP per capita (current US$) | D57: NY.GDP.PCAP.CD | AY57: 82801.543 | AZ57: 85433.031 | BA57: 85188.337 | BB57: 77400.421 | BC57: 73351.757 | BD57: 72329.661 | BE57: 72777.148 | BF57: 73514.669 | BG57: 74990.433 | BH57: 76284.194 | BI57: 78471.629 | BJ57: 81513.163 | BK57: 86059.739 | BL57: 91392.643
A58: Cyprus | B58: CYP | C58: GDP per capita (current US$) | D58: NY.GDP.PCAP.CD | T58: 976.33424 | U58: 1157.4116 | V58: 1476.2715 | W58: 1929.4036 | X58: 2559.2597 | Y58: 4232.0229 | Z58: 4033.2405 | AA58: 4122.7845 | AB58: 4091.0485 | AC58: 4258.7436 | AD58: 4488.287 | AE58: 5642.6315 | AF58: 6690.578 | AG58: 7645.6298 | AH58: 8038.9142 | AI58: 9641.5753 | AJ58: 9696.0996 | AK58: 11310.072 | AL58: 10526.142 | AM58: 11617.693 | AN58: 15261.411 | AO58: 15139.226 | AP58: 14234.244 | AQ58: 15092.826 | AR58: 15287.919 | AS58: 14388.348 | AT58: 14821.447 | AU58: 16093.215 | AV58: 20252.239 | AW58: 23792.621 | AX58: 24959.259 | AY58: 26729.323 | AZ58: 31244.926 | BA58: 35397.364 | BB58: 32109.243 | BC58: 31023.638 | BD58: 32396.386 | BE58: 28912.157 | BF58: 27729.193 | BG58: 27163.333 | BH58: 23408.337 | BI58: 24605.921 | BJ58: 26444.074 | BK58: 29089.471 | BL58: 28288.462 | BM58: 26623.801
A59: Czech Republic | B59: CZE | C59: GDP per capita (current US$) | D59: NY.GDP.PCAP.CD | AI59: 3941.5031 | AJ59: 2896.6091 | AK59: 3372.8654 | AL59: 3956.1783 | AM59: 4630.5512 | AN59: 5824.1213 | AO59: 6532.8371 | AP59: 6034.4884 | AQ59: 6489.7036 | AR59: 6337.4191 | AS59: 6029.0382 | AT59: 6637.0417 | AU59: 8060.8687 | AV59: 9818.5685 | AW59: 11749.853 | AX59: 13430.67 | AY59: 15261.798 | AZ59: 18466.548 | BA59: 22804.578 | BB59: 19861.697 | BC59: 19960.068 | BD59: 21871.266 | BE59: 19870.801 | BF59: 20133.169 | BG59: 19890.92 | BH59: 17829.698 | BI59: 18575.232 | BJ59: 20636.2 | BK59: 23419.736 | BL59: 23490.398 | BM59: 22762.197
A60: Germany | B60: DEU | C60: GDP per capita (current US$) | D60: NY.GDP.PCAP.CD | O60: 2761.1668 | P60: 3192.1336 | Q60: 3809.9814 | R60: 5046.7551 | S60: 5639.0776 | T60: 6236.3589 | U60: 6634.8569 | V60: 7682.9538 | W60: 9482.0428 | X60: 11281.023 | Y60: 12138.308 | Z60: 10209.073 | AA60: 9913.7376 | AB60: 9864.3449 | AC60: 9313.1694 | AD60: 9429.5692 | AE60: 13461.831 | AF60: 16677.511 | AG60: 17931.282 | AH60: 17764.376 | AI60: 22303.961 | AJ60: 23357.758 | AK60: 26438.23 | AL60: 25522.63 | AM60: 27076.607 | AN60: 31658.349 | AO60: 30485.867 | AP60: 26964.049 | AQ60: 27289.059 | AR60: 26725.915 | AS60: 23635.929 | AT60: 23607.883 | AU60: 25077.729 | AV60: 30243.577 | AW60: 34044.054 | AX60: 34507.369 | AY60: 36323.448 | AZ60: 41587.213 | BA60: 45427.152 | BB60: 41485.902 | BC60: 41531.934 | BD60: 46644.776 | BE60: 43858.363 | BF60: 46285.764 | BG60: 47959.993 | BH60: 41086.73 | BI60: 42107.517 | BJ60: 44442.772 | BK60: 47787.161 | BL60: 46467.516 | BM60: 45723.644
A61: Djibouti | B61: DJI | C61: GDP per capita (current US$) | D61: NY.GDP.PCAP.CD | AD61: 801.18214 | AF61: 761.45944 | AG61: 748.20374 | AH61: 725.75412 | AI61: 766.14744 | AJ61: 762.01258 | AK61: 777.26738 | AL61: 753.50922 | AM61: 790.0348 | AN61: 789.55553 | AO61: 767.50628 | AP61: 760.64078 | AQ61: 755.75947 | AR61: 765.85832 | AS61: 768.18357 | AT61: 780.90396 | AU61: 791.38418 | AV61: 818.86879 | AW61: 863.23609 | AX61: 904.73668 | AY61: 967.67958 | AZ61: 1052.7191 | BA61: 1223.8524 | BB61: 1267.3174 | BC61: 1343.2751 | BD61: 1451.5481 | BE61: 1559.2407 | BF61: 2312.7209 | BG61: 2464.2977 | BH61: 2658.9642 | BI61: 2802.182 | BJ61: 2914.3746 | BK61: 3141.8794 | BL61: 3414.9354 | BM61: 3425.5035
A62: Dominica | B62: DMA | C62: GDP per capita (current US$) | D62: NY.GDP.PCAP.CD | V62: 624.60612 | W62: 769.11976 | X62: 733.96156 | Y62: 966.6302 | Z62: 1090.2009 | AA62: 1193.5101 | AB62: 1324.6495 | AC62: 1478.1717 | AD62: 1632.2474 | AE62: 1863.5061 | AF62: 2113.9272 | AG62: 2402.7718 | AH62: 2617.8168 | AI62: 2860.3225 | AJ62: 3122.6532 | AK62: 3317.8247 | AL62: 3466.9989 | AM62: 3721.2724 | AN62: 3860.8005 | AO62: 4120.5812 | AP62: 4292.1137 | AQ62: 4593.8633 | AR62: 4751.0921 | AS62: 4787.8014 | AT62: 4883.003 | AU62: 4770.8519 | AV62: 4897.3084 | AW62: 5216.8724 | AX62: 5160.8891 | AY62: 5518.4232 | AZ62: 5951.8634 | BA62: 6468.9448 | BB62: 6903.1458 | BC62: 6967.365 | BD62: 7065.4604 | BE62: 6849.4559 | BF62: 7016.3801 | BG62: 7317.4861 | BH62: 7597.2889 | BI62: 8080.9686 | BJ62: 7274.5177 | BK62: 7693.7715 | BL62: 8001.9971 | BM62: 6526.7932
A63: Denmark | B63: DNK | C63: GDP per capita (current US$) | D63: NY.GDP.PCAP.CD | K63: 2487.1362 | L63: 2700.7463 | M63: 2776.1354 | N63: 3151.1332 | O63: 3464.4552 | P63: 3845.5061 | Q63: 4654.2989 | R63: 6119.3702 | S63: 6770.75 | T63: 7999.1127 | U63: 8787.5897 | V63: 9783.852 | W63: 11826.019 | X63: 13751.999 | Y63: 13883.887 | Z63: 12081.801 | AA63: 11804.433 | AB63: 11857.892 | AC63: 11562.919 | AD63: 12253.1 | AE63: 17201.089 | AF63: 21340.728 | AG63: 22527.047 | AH63: 21901.055 | AI63: 26891.446 | AJ63: 27011.377 | AK63: 29569.66 | AL63: 27597.975 | AM63: 29995.58 | AN63: 35351.365 | AO63: 35650.714 | AP63: 32835.94 | AQ63: 33368.142 | AR63: 33440.795 | AS63: 30743.548 | AT63: 30751.654 | AU63: 33228.694 | AV63: 40458.777 | AW63: 46511.598 | AX63: 48799.826 | AY63: 52027 | AZ63: 58487.055 | BA63: 64322.064 | BB63: 58163.277 | BC63: 58041.398 | BD63: 61753.647 | BE63: 58507.508 | BF63: 61191.194 | BG63: 62548.985 | BH63: 53254.856 | BI63: 54663.998 | BJ63: 57610.098 | BK63: 61598.537 | BL63: 60213.092 | BM63: 60908.835
A64: Dominican Republic | B64: DOM | C64: GDP per capita (current US$) | D64: NY.GDP.PCAP.CD | E64: 204.11487 | F64: 192.02761 | G64: 234.05163 | H64: 258.59578 | I64: 272.9748 | J64: 229.0235 | K64: 245.98755 | L64: 250.97621 | M64: 254.0518 | N64: 281.3776 | O64: 330.13151 | P64: 360.15285 | Q64: 417.91926 | R64: 480.05307 | S64: 583.48442 | T64: 699.603 | U64: 748.99062 | V64: 848.28542 | W64: 854.64716 | X64: 969.49805 | Y64: 1164.9522 | Z64: 1273.8264 | AA64: 1362.5107 | AB64: 1487.2758 | AC64: 1831.0865 | AD64: 780.38587 | AE64: 928.03225 | AF64: 865.83175 | AG64: 783.0354 | AH64: 955.51737 | AI64: 991.61484 | AJ64: 1351.2985 | AK64: 1566.5296 | AL64: 1733.3995 | AM64: 1905.9435 | AN64: 2127.7481 | AO64: 2293.7544 | AP64: 2476.0604 | AQ64: 2638.3133 | AR64: 2653.2251 | AS64: 2869.1781 | AT64: 2977.4345 | AU64: 3110.3254 | AV64: 2418.3504 | AW64: 2487.3291 | AX64: 3932.7844 | AY64: 4109.0336 | AZ64: 4707.7951 | BA64: 5087.9832 | BB64: 5039.4031 | BC64: 5555.392 | BD64: 5913.4266 | BE64: 6110.3666 | BF64: 6238.1324 | BG64: 6608.8255 | BH64: 6921.5206 | BI64: 7280.8836 | BJ64: 7609.3533 | BK64: 8050.6441 | BL64: 8282.1171 | BM64: 7268.1969
A65: Algeria | B65: DZA | C65: GDP per capita (current US$) | D65: NY.GDP.PCAP.CD | E65: 246.30375 | F65: 214.77198 | G65: 172.24251 | H65: 226.89545 | I65: 238.04371 | J65: 249.88359 | K65: 235.59813 | L65: 253.92377 | M65: 281.92579 | N65: 302.75226 | O65: 336.22469 | P65: 341.38892 | Q65: 442.67762 | R65: 554.29291 | S65: 818.00823 | T65: 936.79008 | U65: 1037.6072 | V65: 1192.7442 | W65: 1456.4194 | X65: 1782.6993 | Y65: 2203.0555 | Z65: 2237.0868 | AA65: 2210.302 | AB65: 2312.6556 | AC65: 2467.3461 | AD65: 2582.879 | AE65: 2756.955 | AF65: 2807.5036 | AG65: 2417.3762 | AH65: 2215.9639 | AI65: 2408.823 | AJ65: 1731.6214 | AK65: 1776.0283 | AL65: 1807.2975 | AM65: 1507.8867 | AN65: 1452.2784 | AO65: 1603.9403 | AP65: 1619.7977 | AQ65: 1596.0039 | AR65: 1588.3489 | AS65: 1765.0267 | AT65: 1740.6071 | AU65: 1781.8277 | AV65: 2103.3817 | AW65: 2610.1854 | AX65: 3113.0957 | AY65: 3478.7104 | AZ65: 3950.5143 | BA65: 4923.6303 | BB65: 3883.2713 | BC65: 4480.7874 | BD65: 5455.679 | BE65: 5592.2201 | BF65: 5499.5873 | BG65: 5493.0567 | BH65: 4177.8869 | BI65: 3946.4524 | BJ65: 4109.7034 | BK65: 4153.9562 | BL65: 3975.509 | BM65: 3310.3865
A66: East Asia & Pacific (excluding high income) | B66: EAP | C66: GDP per capita (current US$) | D66: NY.GDP.PCAP.CD | E66: 89.65278 | F66: 78.734461 | G66: 71.198989 | H66: 75.17282 | I66: 85.063538 | J66: 96.844204 | K66: 103.11977 | L66: 97.34588 | M66: 95.699147 | N66: 104.57293 | O66: 113.42958 | P66: 118.71556 | Q66: 131.35906 | R66: 161.53818 | S66: 178.32003 | T66: 196.62397 | U66: 196.10437 | V66: 223.01567 | W66: 212.53379 | X66: 242.34361 | Y66: 275.4185 | Z66: 289.369 | AA66: 298.57883 | AB66: 308.08209 | AC66: 329.15694 | AD66: 355.00065 | AE66: 348.10692 | AF66: 337.83961 | AG66: 368.22271 | AH66: 391.37726 | AI66: 412.85002 | AJ66: 441.33654 | AK66: 487.70778 | AL66: 528.37944 | AM66: 627.4449 | AN66: 764.77642 | AO66: 867.79212 | AP66: 888.24164 | AQ66: 804.94268 | AR66: 876.17482 | AS66: 954.30566 | AT66: 1007.164 | AU66: 1106.7381 | AV66: 1240.8351 | AW66: 1427.1466 | AX66: 1640.2275 | AY66: 1961.1955 | AZ66: 2463.8599 | BA66: 3091.0904 | BB66: 3330.6327 | BC66: 4006.5616 | BD66: 4855.674 | BE66: 5375.5306 | BF66: 5890.4716 | BG66: 6303.5156 | BH66: 6519.0389 | BI66: 6609.4844 | BJ66: 7172.7019 | BK66: 7968.09 | BL66: 8194.2651 | BM66: 8291.746
A67: Early-demographic dividend | B67: EAR | C67: GDP per capita (current US$) | D67: NY.GDP.PCAP.CD | E67: 158.93916 | F67: 156.0031 | G67: 157.44437 | H67: 163.00688 | I67: 182.67246 | J67: 193.38594 | K67: 186.11905 | L67: 190.86499 | M67: 201.63229 | N67: 219.79689 | O67: 226.96601 | P67: 239.84623 | Q67: 256.18635 | R67: 319.52243 | S67: 436.78518 | T67: 458.48822 | U67: 489.20707 | V67: 533.60726 | W67: 578.69512 | X67: 686.25385 | Y67: 833.30533 | Z67: 906.98815 | AA67: 840.89049 | AB67: 825.3833 | AC67: 799.17235 | AD67: 800.76998 | AE67: 783.75675 | AF67: 764.71479 | AG67: 792.49298 | AH67: 787.68375 | AI67: 902.90448 | AJ67: 932.8609 | AK67: 1002.6741 | AL67: 1079.8551 | AM67: 1106.5567 | AN67: 1108.5167 | AO67: 1183.8436 | AP67: 1241.7781 | AQ67: 1204.3127 | AR67: 1251.3348 | AS67: 1337.3089 | AT67: 1301.1635 | AU67: 1242.9593 | AV67: 1358.8447 | AW67: 1554.2291 | AX67: 1782.6192 | AY67: 2006.4118 | AZ67: 2343.8584 | BA67: 2599.7265 | BB67: 2466.2468 | BC67: 2949.3965 | BD67: 3255.8259 | BE67: 3365.3193 | BF67: 3378.6041 | BG67: 3447.0974 | BH67: 3301.1376 | BI67: 3333.147 | BJ67: 3554.5319 | BK67: 3526.975 | BL67: 3581.1327 | BM67: 3254.9694
A68: East Asia & Pacific | B68: EAS | C68: GDP per capita (current US$) | D68: NY.GDP.PCAP.CD | E68: 147.23553 | F68: 147.38512 | G68: 148.73952 | H68: 162.03277 | I68: 181.89999 | J68: 197.87763 | K68: 215.55661 | L68: 227.93876 | M68: 244.98492 | N68: 275.00925 | O68: 316.37013 | P68: 341.93631 | Q68: 414.48826 | R68: 534.18604 | S68: 602.2304 | T68: 647.16689 | U68: 699.57259 | V68: 821.14803 | W68: 1020.8502 | X68: 1091.7847 | Y68: 1162.6829 | Z68: 1262.6403 | AA68: 1217.3899 | AB68: 1275.3132 | AC68: 1345.927 | AD68: 1399.2735 | AE68: 1800.6073 | AF68: 2080.53 | AG68: 2463.3617 | AH68: 2525.8301 | AI68: 2598.978 | AJ68: 2893.1441 | AK68: 3119.8337 | AL68: 3446.1614 | AM68: 3807.2968 | AN68: 4275.8366 | AO68: 4072.7595 | AP68: 3853.8237 | AQ68: 3417.6782 | AR68: 3779.4423 | AS68: 4050.274 | AT68: 3735.1868 | AU68: 3766.2193 | AV68: 4108.0337 | AW68: 4573.8566 | AX68: 4847.6253 | AY68: 5105.633 | AZ68: 5675.0014 | BA68: 6498.4974 | BB68: 6650.3014 | BC68: 7698.9815 | BD68: 8858.8555 | BE68: 9417.6281 | BF68: 9465.4039 | BG68: 9700.7555 | BH68: 9595.1592 | BI68: 9855.7253 | BJ68: 10467.854 | BK68: 11318.84 | BL68: 11499.635
A69: Europe & Central Asia (excluding high income) | B69: ECA | C69: GDP per capita (current US$) | D69: NY.GDP.PCAP.CD | AG69: 2348.7024 | AH69: 2260.9046 | AI69: 2388.5067 | AJ69: 2305.452 | AK69: 2120.9834 | AL69: 2095.2839 | AM69: 1813.3087 | AN69: 1944.3938 | AO69: 1962.2474 | AP69: 2038.8295 | AQ69: 1910.5981 | AR69: 1605.2167 | AS69: 1786.8326 | AT69: 1777.3804 | AU69: 2036.3406 | AV69: 2567.1296 | AW69: 3398.1886 | AX69: 4301.2955 | AY69: 5269.8138 | AZ69: 6811.4562 | BA69: 8410.154 | BB69: 6585.4078 | BC69: 7815.6793 | BD69: 9601.4253 | BE69: 10121.835 | BF69: 10689.039 | BG69: 9916.7567 | BH69: 7546.233 | BI69: 7177.7722 | BJ69: 8018.7141 | BK69: 8206.5967 | BL69: 8337.8574 | BM69: 7656.5939
A70: Europe & Central Asia | B70: ECS | C70: GDP per capita (current US$) | D70: NY.GDP.PCAP.CD | K70: 1032.7918 | L70: 1102.0854 | M70: 1142.8125 | N70: 1253.3553 | O70: 1375.9751 | P70: 1540.0537 | Q70: 1830.201 | R70: 2306.2424 | S70: 2586.2073 | T70: 2999.1628 | U70: 3095.4002 | V70: 3484.1228 | W70: 4223.9321 | X70: 5132.7109 | Y70: 5774.1051 | Z70: 5105.1928 | AA70: 4890.4184 | AB70: 4717.4516 | AC70: 4507.5723 | AD70: 4637.0966 | AE70: 6291.0139 | AF70: 7726.4382 | AG70: 8548.3445 | AH70: 8611.831 | AI70: 10484.719 | AJ70: 10783.002 | AK70: 11542.144 | AL70: 10567.687 | AM70: 11024.373 | AN70: 12701.702 | AO70: 12942.475 | AP70: 12257.124 | AQ70: 12558.74 | AR70: 12399.906 | AS70: 11657.597 | AT70: 11770.264 | AU70: 12840.209 | AV70: 15594.953 | AW70: 18122.439 | AX70: 19235.982 | AY70: 20764.721 | AZ70: 24174.229 | BA70: 26436.531 | BB70: 23165.18 | BC70: 23640.664 | BD70: 26138.774 | BE70: 25097.803 | BF70: 26102.05 | BG70: 26334.394 | BH70: 22582.953 | BI70: 22404.9 | BJ70: 23617.219 | BK70: 25221.761 | BL70: 24791.449 | BM70: 23780.388
A71: Ecuador | B71: ECU | C71: GDP per capita (current US$) | D71: NY.GDP.PCAP.CD | E71: 455.46239 | F71: 375.2213 | G71: 315.6887 | H71: 368.62958 | I71: 440.56023 | J71: 455.19782 | K71: 449.92021 | L71: 459.2788 | M71: 450.99955 | N71: 527.90035 | O71: 471.6308 | P71: 440.85716 | Q71: 495.53592 | R71: 588.33707 | S71: 970.01272 | T71: 1105.4206 | U71: 1264.9116 | V71: 1493.3336 | W71: 1572.4005 | X71: 1821.0472 | Y71: 2238.2171 | Z71: 2660.6128 | AA71: 2369.9507 | AB71: 1988.7873 | AC71: 1912.4313 | AD71: 1891.5625 | AE71: 1648.0146 | AF71: 1464.4929 | AG71: 1337.8899 | AH71: 1390.2131 | AI71: 1489.5299 | AJ71: 1622.2081 | AK71: 1688.5048 | AL71: 1727.755 | AM71: 2026.1131 | AN71: 2132.9068 | AO71: 2155.5182 | AP71: 2356.3699 | AQ71: 2293.8897 | AR71: 1578.9343 | AS71: 1445.2793 | AT71: 1894.6162 | AU71: 2172.1019 | AV71: 2425.8518 | AW71: 2691.2777 | AX71: 3002.1386 | AY71: 3328.8842 | AZ71: 3567.8372 | BA71: 4249.019 | BB71: 4231.6192 | BC71: 4633.5913 | BD71: 5200.5551 | BE71: 5682.0461 | BF71: 6056.3312 | BG71: 6377.0939 | BH71: 6124.4909 | BI71: 6060.093 | BJ71: 6213.5031 | BK71: 6295.9347 | BL71: 6222.5247 | BM71: 5600.3896
A72: Egypt, Arab Rep. | B72: EGY | C72: GDP per capita (current US$) | D72: NY.GDP.PCAP.CD | J72: 162.60847 | K72: 168.96324 | L72: 174.86261 | M72: 180.41085 | N72: 193.58605 | O72: 233.01371 | P72: 243.80682 | Q72: 257.58865 | R72: 273.69861 | S72: 244.74721 | T72: 301.74943 | U72: 337.77437 | V72: 357.07795 | W72: 358.8478 | X72: 426.34652 | Y72: 500.35505 | Z72: 498.55912 | AA72: 607.28152 | AB72: 662.68729 | AC72: 708.19575 | AD72: 792.82404 | AE72: 815.24869 | AF72: 778.11689 | AG72: 655.06781 | AH72: 725.6298 | AI72: 765.64201 | AJ72: 651.07755 | AK72: 713.45255 | AL72: 777.85774 | AM72: 849.4525 | AN72: 965.11087 | AO72: 1063.333 | AP72: 1208.7199 | AQ72: 1281.3969 | AR72: 1343.552 | AS72: 1450.4762 | AT72: 1378.2034 | AU72: 1191.1032 | AV72: 1102.4682 | AW72: 1062.1581 | AX72: 1186.3933 | AY72: 1397.4367 | AZ72: 1667.318 | BA72: 2044.5278 | BB72: 2331.2688 | BC72: 2645.9688 | BD72: 2791.8108 | BE72: 3229.6856 | BF72: 3262.6576 | BG72: 3379.558 | BH72: 3562.9327 | BI72: 3519.8732 | BJ72: 2444.2904 | BK72: 2537.1252 | BL72: 3019.0923 | BM72: 3547.8708
A73: Euro area | B73: EMU | C73: GDP per capita (current US$) | D73: NY.GDP.PCAP.CD | E73: 923.14699 | F73: 1004.9783 | G73: 1106.2378 | H73: 1229.8566 | I73: 1355.5866 | J73: 1468.4721 | K73: 1588.9729 | L73: 1714.3279 | M73: 1828.2153 | N73: 2027.1196 | O73: 2236.6254 | P73: 2521.0972 | Q73: 3025.129 | R73: 3902.3511 | S73: 4400.4249 | T73: 5076.0009 | U73: 5273.7011 | V73: 5974.7354 | W73: 7286.797 | X73: 8790.7815 | Y73: 9803.2664 | Z73: 8487.263 | AA73: 8194.8326 | AB73: 7978.5756 | AC73: 7640.2418 | AD73: 7834.326 | AE73: 10967.7 | AF73: 13528.069 | AG73: 14828.552 | AH73: 15082.234 | AI73: 18894.457 | AJ73: 19553.728 | AK73: 21473.518 | AL73: 19569.031 | AM73: 20597.112 | AN73: 23697.631 | AO73: 23916.316 | AP73: 21810.585 | AQ73: 22380.942 | AR73: 22213.303 | AS73: 20165.89 | AT73: 20432.603 | AU73: 22109.174 | AV73: 27134.801 | AW73: 30949.129 | AX73: 31936.316 | AY73: 33767.001 | AZ73: 38666.771 | BA73: 42177.64 | BB73: 38422.452 | BC73: 37561.065 | BD73: 40599.578 | BE73: 37589.045 | BF73: 39100.928 | BG73: 39854.422 | BH73: 34367.101 | BI73: 35137.754 | BJ73: 37045.478 | BK73: 39997.555 | BL73: 39042.505 | BM73: 37712.121
A74: Eritrea | B74: ERI | C74: GDP per capita (current US$) | D74: NY.GDP.PCAP.CD | AK74: 211.332 | AL74: 208.99948 | AM74: 239.66809 | AN74: 262.23053 | AO74: 315.75068 | AP74: 312.7244 | AQ74: 337.88659 | AR74: 307.90991 | AS74: 308.13419 | AT74: 316.82395 | AU74: 293.95567 | AV74: 334.58557 | AW74: 407.76908 | AX74: 388.59595 | AY74: 415.03603 | AZ74: 439.8321 | BA74: 450.6324 | BB74: 595.10999 | BC74: 501.35532 | BD74: 642.50826
A75: Spain | B75: ESP | C75: GDP per capita (current US$) | D75: NY.GDP.PCAP.CD | E75: 396.39225 | F75: 450.05329 | G75: 520.20613 | H75: 609.48738 | I75: 675.24164 | J75: 774.76161 | K75: 889.65987 | L75: 968.30678 | M75: 950.54574 | N75: 1077.6787 | O75: 1212.2893 | P75: 1362.1655 | Q75: 1708.8086 | R75: 2247.5534 | S75: 2749.9247 | T75: 3209.8374 | U75: 3279.3127 | V75: 3627.5907 | W75: 4356.4392 | X75: 5770.2146 | Y75: 6208.578 | Z75: 5371.1664 | AA75: 5159.7086 | AB75: 4478.5003 | AC75: 4489.9889 | AD75: 4699.6558 | AE75: 6513.5033 | AF75: 8239.6138 | AG75: 9703.1238 | AH75: 10681.971 | AI75: 13804.877 | AJ75: 14811.903 | AK75: 16112.189 | AL75: 13339.909 | AM75: 13415.287 | AN75: 15471.963 | AO75: 16109.084 | AP75: 14730.797 | AQ75: 15394.351 | AR75: 15715.332 | AS75: 14713.066 | AT75: 15355.703 | AU75: 17025.532 | AV75: 21463.443 | AW75: 24861.283 | AX75: 26419.297 | AY75: 28365.313 | AZ75: 32549.971 | BA75: 35366.26 | BB75: 32042.474 | BC75: 30502.72 | BD75: 31636.446 | BE75: 28324.429 | BF75: 29059.548 | BG75: 29461.55 | BH75: 25732.018 | BI75: 26505.343 | BJ75: 28100.586 | BK75: 30374.521 | BL75: 29564.745 | BM75: 27057.164
A76: Estonia | B76: EST | C76: GDP per capita (current US$) | D76: NY.GDP.PCAP.CD | AN76: 3130.807 | AO76: 3376.7947 | AP76: 3678.1579 | AQ76: 4087.5033 | AR76: 4144.6311 | AS76: 4075.9706 | AT76: 4509.1782 | AU76: 5344.8779 | AV76: 7206.1666 | AW76: 8912.9922 | AX76: 10406.397 | AY76: 12631.568 | AZ76: 16741.939 | BA76: 18227.12 | BB76: 14794.971 | BC76: 14784.385 | BD76: 17624.045 | BE76: 17534.421 | BF76: 19174.1 | BG76: 20367.103 | BH76: 17522.23 | BI76: 18437.253 | BJ76: 20407.927 | BK76: 23159.392 | BL76: 23717.799 | BM76: 23312.276
A77: Ethiopia | B77: ETH | C77: GDP per capita (current US$) | D77: NY.GDP.PCAP.CD | Z77: 203.557 | AA77: 208.34239 | AB77: 224.6274 | AC77: 205.62379 | AD77: 233.2187 | AE77: 234.68218 | AF77: 242.96155 | AG77: 243.73586 | AH77: 248.02275 | AI77: 254.24326 | AJ77: 271.39437 | AK77: 204.05018 | AL77: 165.69323 | AM77: 125.54958 | AN77: 134.34296 | AO77: 145.1669 | AP77: 141.50862 | AQ77: 125.07614 | AR77: 119.68408 | AS77: 124.46079 | AT77: 120.76578 | AU77: 111.92723 | AV77: 119.4904 | AW77: 136.46625 | AX77: 162.43273 | AY77: 194.68743 | AZ77: 244.28605 | BA77: 326.43682 | BB77: 380.569 | BC77: 341.55412 | BD77: 354.47957 | BE77: 467.07787 | BF77: 499.53153 | BG77: 566.9264 | BH77: 640.54192 | BI77: 717.12487 | BJ77: 768.52302 | BK77: 771.52487 | BL77: 855.76089 | BM77: 936.34046
A78: European Union | B78: EUU | C78: GDP per capita (current US$) | D78: NY.GDP.PCAP.CD | K78: 1339.2534 | L78: 1444.4528 | M78: 1536.3206 | N78: 1700.9019 | O78: 1879.1701 | P78: 2113.4532 | Q78: 2533.2134 | R78: 3257.9506 | S78: 3666.7074 | T78: 4245.2344 | U78: 4420.1062 | V78: 4982.262 | W78: 6042.4906 | X78: 7272.3885 | Y78: 8098.838 | Z78: 7032.315 | AA78: 6759.5679 | AB78: 6559.0688 | AC78: 6304.9077 | AD78: 6469.2056 | AE78: 9020.4956 | AF78: 11125.199 | AG78: 12173.998 | AH78: 12393.799 | AI78: 15455.694 | AJ78: 15973.128 | AK78: 17511.364 | AL78: 15934.182 | AM78: 16836.753 | AN78: 19466.249 | AO78: 19752.205 | AP78: 18088.821 | AQ78: 18615.6 | AR78: 18477.317 | AS78: 16909.916 | AT78: 17185.047 | AU78: 18682.119 | AV78: 22922.694 | AW78: 26263.882 | AX78: 27333.203 | AY78: 29070.01 | AZ78: 33551.409 | BA78: 36913.835 | BB78: 33361.832 | BC78: 32934.039 | BD78: 35709.531 | BE78: 33150.832 | BF78: 34560.523 | BG78: 35239.175 | BH78: 30466.81 | BI78: 31164.595 | BJ78: 33008.504 | BK78: 35703.69 | BL78: 34960.016 | BM78: 33927.719
A79: Fragile and conflict affected situations | B79: FCS | C79: GDP per capita (current US$) | D79: NY.GDP.PCAP.CD | E79: 140.91132 | F79: 143.0079 | G79: 154.49336 | H79: 173.48639 | I79: 149.14259 | J79: 159.97072 | K79: 166.41349 | L79: 157.46171 | M79: 162.255 | N79: 177.76686 | O79: 211.16073 | P79: 209.56237 | Q79: 234.20109 | R79: 279.80312 | S79: 404.97149 | T79: 443.90592 | U79: 508.59572 | V79: 544.03676 | W79: 584.58312 | X79: 715.59908 | Y79: 867.60891 | Z79: 1181.7385 | AA79: 1106.4575 | AB79: 917.2607 | AC79: 804.70781 | AD79: 808.60286 | AE79: 746.26379 | AF79: 732.43923 | AG79: 752.9596 | AH79: 676.94715 | AI79: 1023.2723 | AJ79: 578.07542 | AK79: 555.89572 | AL79: 502.70158 | AM79: 465.68783 | AN79: 550.01356 | AO79: 551.10288 | AP79: 616.98329 | AQ79: 608.24063 | AR79: 667.81398 | AS79: 767.28279 | AT79: 724.68969 | AU79: 682.3933 | AV79: 684.60739 | AW79: 844.25248 | AX79: 1035.6641 | AY79: 1264.9637 | AZ79: 1524.6308 | BA79: 1918.4639 | BB79: 1777.5338 | BC79: 2067.7123 | BD79: 2047.2547 | BE79: 2298.5025 | BF79: 2362.4012 | BG79: 2504.4445 | BH79: 2167.4078 | BI79: 1928.9786 | BJ79: 1929.8772 | BK79: 2021.7258 | BL79: 2107.4238 | BM79: 1864.5794
A80: Finland | B80: FIN | C80: GDP per capita (current US$) | D80: NY.GDP.PCAP.CD | E80: 1179.353 | F80: 1327.4272 | G80: 1411.7024 | H80: 1522.3192 | I80: 1707.5039 | J80: 1882.0869 | K80: 2010.2135 | L80: 2034.189 | M80: 1907.0773 | N80: 2178.0353 | O80: 2465.6448 | P80: 2716.1901 | Q80: 3177.6457 | R80: 4173.173 | S80: 5297.6078 | T80: 6255.5446 | U80: 6739.6907 | V80: 7069.1057 | W80: 7628.8157 | X80: 9332.2453 | Y80: 11223.938 | Z80: 10926.818 | AA80: 10938.122 | AB80: 10497.48 | AC80: 10833.866 | AD80: 11398.106 | AE80: 14951.047 | AF80: 18571.06 | AG80: 22047.793 | AH80: 23973.239 | AI80: 28364.645 | AJ80: 25484.739 | AK80: 22319.059 | AL80: 17608.812 | AM80: 20301.333 | AN80: 26271.6 | AO80: 25783.45 | AP80: 24691.873 | AQ80: 26009.269 | AR80: 26177.348 | AS80: 24285.467 | AT80: 24946.189 | AU80: 26869.675 | AV80: 32855.133 | AW80: 37702.845 | AX80: 39040.289 | AY80: 41188.094 | AZ80: 48414.845 | BA80: 53554.039 | BB80: 47293.993 | BC80: 46459.973 | BD80: 51081.998 | BE80: 47710.79 | BF80: 49878.043 | BG80: 50260.3 | BH80: 42784.698 | BI80: 43784.284 | BJ80: 46297.496 | BK80: 50013.294 | BL80: 48711.564 | BM80: 49041.342
A81: Fiji | B81: FJI | C81: GDP per capita (current US$) | D81: NY.GDP.PCAP.CD | E81: 285.47429 | F81: 287.26706 | G81: 291.47333 | H81: 296.70832 | I81: 310.81228 | J81: 317.02033 | K81: 316.12981 | L81: 333.26821 | M81: 334.61258 | N81: 357.42438 | O81: 422.38754 | P81: 466.02535 | Q81: 583.31877 | R81: 768.68851 | S81: 987.92375 | T81: 1186.6761 | U81: 1182.0941 | V81: 1202.6314 | W81: 1360.7854 | X81: 1640.5569 | Y81: 1892.8768 | Z81: 1898.0109 | AA81: 1786.8572 | AB81: 1638.3839 | AC81: 1681.7051 | AD81: 1603.2194 | AE81: 1795.3705 | AF81: 1631.9581 | AG81: 1535.3992 | AH81: 1632.1878 | AI81: 1835.1231 | AJ81: 1881.7618 | AK81: 2058.3796 | AL81: 2167.0955 | AM81: 2384.7265 | AN81: 2540.9809 | AO81: 2713.8278 | AP81: 2636.6722 | AQ81: 2066.0689 | AR81: 2401.6864 | AS81: 2069.3175 | AT81: 2030.2464 | AU81: 2248.7142 | AV81: 2818.9139 | AW81: 3311.1599 | AX81: 3627.6329 | AY81: 3715.9327 | AZ81: 4040.1521 | BA81: 4167.6949 | BB81: 3362.8205 | BC81: 3652.5359 | BD81: 4371.4474 | BE81: 4591.577 | BF81: 4840.7273 | BG81: 5605.6091 | BH81: 5390.7142 | BI81: 5651.2727 | BJ81: 6101.0239 | BK81: 6317.4378 | BL81: 6175.8748 | BM81: 4881.5261
A82: France | B82: FRA | C82: GDP per capita (current US$) | D82: NY.GDP.PCAP.CD | E82: 1334.6895 | F82: 1428.046 | G82: 1578.2845 | H82: 1744.6401 | I82: 1909.5416 | J82: 2038.1631 | K82: 2186.4746 | L82: 2343.1045 | M82: 2536.0851 | N82: 2752.0951 | O82: 2857.2517 | P82: 3169.0363 | Q82: 3854.5558 | R82: 4969.763 | S82: 5328.2415 | T82: 6690.5783 | U82: 6866.8169 | V82: 7532.527 | W82: 9264.7753 | X82: 11179.633 | Y82: 12713.365 | Z82: 11104.981 | AA82: 10496.929 | AB82: 9993.4212 | AC82: 9419.6961 | AD82: 9763.3274 | AE82: 13540.246 | AF82: 16302.447 | AG82: 17679.997 | AH82: 17694.309 | AI82: 21793.836 | AJ82: 21675.065 | AK82: 23813.712 | AL82: 22380.108 | AM82: 23496.52 | AN82: 26890.218 | AO82: 26871.831 | AP82: 24228.946 | AQ82: 24974.274 | AR82: 24673.203 | AS82: 22364.029 | AT82: 22433.555 | AU82: 24177.336 | AV82: 29568.389 | AW82: 33741.262 | AX82: 34760.185 | AY82: 36443.626 | AZ82: 41508.433 | BA82: 45334.118 | BB82: 41575.422 | BC82: 40638.335 | BD82: 43790.726 | BE82: 40874.7 | BF82: 42592.935 | BG82: 43011.263 | BH82: 36638.185 | BI82: 37037.374 | BJ82: 38685.258 | BK82: 41526.415 | BL82: 40380.099 | BM82: 38625.067
A83: Faroe Islands | B83: FRO | C83: GDP per capita (current US$) | D83: NY.GDP.PCAP.CD | AQ83: 24035.29 | AR83: 24129.413 | AS83: 22651.862 | AT83: 24418.703 | AU83: 26731.659 | AV83: 31493.319 | AW83: 35467.175 | AX83: 36198.544 | AY83: 41521.675 | AZ83: 47885.699 | BA83: 50863.954 | BB83: 47441.916 | BC83: 48541.401 | BD83: 52092.603 | BE83: 49459.717 | BF83: 54843.319 | BG83: 59433.835 | BH83: 52400.297 | BI83: 56854.103 | BJ83: 59993.091 | BK83: 62918.146 | BL83: 64225.265
A84: Micronesia, Fed. Sts. | B84: FSM | C84: GDP per capita (current US$) | D84: NY.GDP.PCAP.CD | AB84: 1320.8483 | AE84: 1276.5062 | AF84: 1296.8828 | AG84: 1355.6706 | AH84: 1437.3498 | AI84: 1528.4931 | AJ84: 1682.5439 | AK84: 1756.6528 | AL84: 1909.51 | AM84: 1909.8368 | AN84: 2060.4947 | AO84: 2017.6593 | AP84: 1904.8639 | AQ84: 2022.7446 | AR84: 2042.7071 | AS84: 2171.8896 | AT84: 2248.4921 | AU84: 2265.9441 | AV84: 2295.8682 | AW84: 2253.1137 | AX84: 2358.1467 | AY84: 2406.1144 | AZ84: 2458.6584 | BA84: 2541.2616 | BB84: 2721.9761 | BC84: 2885.3055 | BD84: 3009.2568 | BE84: 3131.3867 | BF84: 2994.7924 | BG84: 2971.5126 | BH84: 2906.617 | BI84: 3014.7004 | BJ84: 3289.6421 | BK84: 3568.291 | BL84: 3585.4232
A85: Gabon | B85: GAB | C85: GDP per capita (current US$) | D85: NY.GDP.PCAP.CD | E85: 282.41718 | F85: 331.4358 | G85: 357.52376 | H85: 298.47045 | I85: 410.90408 | J85: 424.62044 | K85: 452.66283 | L85: 490.10328 | M85: 520.48042 | N85: 550.72796 | O85: 549.45382 | P85: 635.50115 | Q85: 703.78427 | R85: 1160.3218 | S85: 2432.8362 | T85: 3331.9943 | U85: 4550.0742 | V85: 4154.2195 | W85: 3452.6156 | X85: 4275.2574 | Y85: 5892.0993 | Z85: 5186.3771 | AA85: 4736.0339 | AB85: 4325.2979 | AC85: 4423.5205 | AD85: 4038.0685 | AE85: 4004.0353 | AF85: 3755.4708 | AG85: 4267.8051 | AH85: 4532.1511 | AI85: 6268.918 | AJ85: 5536.9984 | AK85: 5578.0386 | AL85: 4252.0653 | AM85: 3963.8793 | AN85: 4570.5713 | AO85: 5116.1966 | AP85: 4667.1931 | AQ85: 3831.7807 | AR85: 3888.8795 | AS85: 4135.9924 | AT85: 3993.0313 | AU85: 4141.4344 | AV85: 4933.4622 | AW85: 5739.6132 | AX85: 6891.3619 | AY85: 7221.3699 | AZ85: 8458.3092 | BA85: 10254.172 | BB85: 7721.019 | BC85: 8849.3226 | BD85: 10809.685 | BE85: 9813.5057 | BF85: 9683.5816 | BG85: 9663.4241 | BH85: 7384.7007 | BI85: 6984.4197 | BJ85: 7230.4349 | BK85: 7956.6278 | BL85: 7767.017 | BM85: 7005.8791
A86: United Kingdom | B86: GBR | C86: GDP per capita (current US$) | D86: NY.GDP.PCAP.CD | E86: 1397.5948 | F86: 1472.3857 | G86: 1525.7759 | H86: 1613.4569 | I86: 1748.2881 | J86: 1873.5678 | K86: 1986.7472 | L86: 2058.7819 | M86: 1951.7586 | N86: 2100.6679 | O86: 2347.5443 | P86: 2649.8015 | Q86: 3030.4325 | R86: 3426.2762 | S86: 3665.8628 | T86: 4299.7456 | U86: 4138.1678 | V86: 4681.4399 | W86: 5976.9382 | X86: 7804.7621 | Y86: 10032.062 | Z86: 9599.3062 | AA86: 9146.0774 | AB86: 8691.5188 | AC86: 8179.1944 | AD86: 8652.2165 | AE86: 10611.112 | AF86: 13118.587 | AG86: 15987.168 | AH86: 16239.282 | AI86: 19095.467 | AJ86: 19900.727 | AK86: 20487.171 | AL86: 18389.02 | AM86: 19709.238 | AN86: 23123.695 | AO86: 24333.234 | AP86: 26719.543 | AQ86: 28238.995 | AR86: 28665.707 | AS86: 28156.267 | AT86: 27717.626 | AU86: 29982.619 | AV86: 34383.948 | AW86: 40208.856 | AX86: 41932.877 | AY86: 44472.574 | AZ86: 50444.93 | BA86: 47267.012 | BB86: 38736.902 | BC86: 39536.773 | BD86: 42047.614 | BE86: 42449.108 | BF86: 43401.311 | BG86: 47452.199 | BH86: 45039.236 | BI86: 41048.35 | BJ86: 40304.723 | BK86: 42992.804 | BL86: 42354.415 | BM86: 40284.638
A87: Georgia | B87: GEO | C87: GDP per capita (current US$) | D87: NY.GDP.PCAP.CD | AI87: 1614.6482 | AL87: 547.33489 | AM87: 519.85758 | AN87: 578.34461 | AO87: 689.05944 | AP87: 807.03229 | AQ87: 851.52596 | AR87: 673.54344 | AS87: 749.90853 | AT87: 801.99041 | AU87: 853.51645 | AV87: 1010.008 | AW87: 1305.0475 | AX87: 1642.7609 | AY87: 1996.0571 | AZ87: 2635.3539 | BA87: 3324.7359 | BB87: 2822.6674 | BC87: 3233.2959 | BD87: 4021.7433 | BE87: 4421.8182 | BF87: 4623.7457 | BG87: 4739.1883 | BH87: 4014.1859 | BI87: 4062.1699 | BJ87: 4357.0009 | BK87: 4722.7878 | BL87: 4697.9837 | BM87: 4278.8608
A88: Ghana | B88: GHA | C88: GDP per capita (current US$) | D88: NY.GDP.PCAP.CD | E88: 183.44959 | F88: 190.21888 | G88: 195.4924 | H88: 211.06457 | I88: 230.08878 | J88: 265.32369 | K88: 267.74822 | L88: 214.83215 | M88: 200.30709 | N88: 230.28723 | O88: 253.56662 | P88: 269.36824 | Q88: 228.85973 | R88: 259.70184 | S88: 296.89002 | T88: 281.40613 | U88: 271.12558 | V88: 306.80997 | W88: 345.83442 | X88: 372.06012 | Y88: 402.06071 | Z88: 372.07744 | AA88: 345.64133 | AB88: 337.16335 | AC88: 355.6667 | AD88: 352.35271 | AE88: 435.06819 | AF88: 374.47034 | AG88: 372.68398 | AH88: 365.88968 | AI88: 398.63708 | AJ88: 433.77326 | AK88: 409.74639 | AL88: 370.41945 | AM88: 328.74453 | AN88: 379.98798 | AO88: 397.13575 | AP88: 384.79633 | AQ88: 407.52324 | AR88: 410.33401 | AS88: 258.47104 | AT88: 269.01498 | AU88: 304.56464 | AV88: 367.82136 | AW88: 417.50807 | AX88: 492.54406 | AY88: 913.39385 | AZ88: 1081.1663 | BA88: 1217.0644 | BB88: 1077.6621 | BC88: 1299.3452 | BD88: 1549.4627 | BE88: 1587.5609 | BF88: 2361.0903 | BG88: 1899.6683 | BH88: 1705.5751 | BI88: 1913.4735 | BJ88: 2020.6818 | BK88: 2194.2325 | BL88: 2210.3559 | BM88: 2328.5346
A89: Gibraltar | B89: GIB | C89: GDP per capita (current US$) | D89: NY.GDP.PCAP.CD
A90: Guinea | B90: GIN | C90: GDP per capita (current US$) | D90: NY.GDP.PCAP.CD | AE90: 354.42137 | AF90: 351.90905 | AG90: 398.54615 | AH90: 394.33114 | AI90: 419.80987 | AJ90: 461.37531 | AK90: 489.0716 | AL90: 475.42632 | AM90: 477.76246 | AN90: 508.10152 | AO90: 518.36566 | AP90: 493.82216 | AQ90: 456.49148 | AR90: 429.71969 | AS90: 363.48228 | AT90: 336.15402 | AU90: 343.60263 | AV90: 393.73969 | AW90: 407.30098 | AX90: 322.41554 | AY90: 453.40371 | AZ90: 659.99293 | BA90: 715.09653 | BB90: 674.08548 | BC90: 672.42493 | BD90: 651.13611 | BE90: 717.05054 | BF90: 769.00317 | BG90: 787.23856 | BH90: 769.25548 | BI90: 732.29151 | BJ90: 855.57527 | BK90: 955.11128 | BL90: 1058.1434 | BM90: 1194.0379
A91: Gambia, The | B91: GMB | C91: GDP per capita (current US$) | D91: NY.GDP.PCAP.CD | K91: 106.41322 | L91: 109.45372 | M91: 93.84769 | N91: 100.10177 | O91: 112.61065 | P91: 116.5612 | Q91: 120.1435 | R91: 148.17466 | S91: 183.08176 | T91: 213.30689 | U91: 201.12488 | V91: 239.43311 | W91: 288.05578 | X91: 335.80489 | Y91: 378.31299 | Z91: 332.68061 | AA91: 318.60786 | AB91: 304.83744 | AC91: 244.37334 | AD91: 298.66041 | AE91: 234.65629 | AF91: 265.49165 | AG91: 305.31362 | AH91: 310.29934 | AI91: 331.81774 | AJ91: 695.41099 | AK91: 695.15537 | AL91: 711.72618 | AM91: 682.21416 | AN91: 696.44958 | AO91: 728.66907 | AP91: 669.4011 | AQ91: 678.67618 | AR91: 637.93906 | AS91: 594.14939 | AT91: 505.42164 | AU91: 411.77189 | AV91: 335.90622 | AW91: 642.75622 | AX91: 665.72022 | AY91: 662.36288 | AZ91: 780.38105 | BA91: 924.50987 | BB91: 833.28136 | BC91: 860.63643 | BD91: 762.76312 | BE91: 742.77763 | BF91: 700.51604 | BG91: 607.4299 | BH91: 660.72357 | BI91: 690.78049 | BJ91: 679.75507 | BK91: 732.72073 | BL91: 777.81525 | BM91: 787.00645
A92: Guinea-Bissau | B92: GNB | C92: GDP per capita (current US$) | D92: NY.GDP.PCAP.CD | O92: 111.68884 | P92: 109.3326 | Q92: 119.72821 | R92: 119.77603 | S92: 130.36756 | T92: 142.28182 | U92: 145.87786 | V92: 148.97815 | W92: 158.8667 | X92: 153.00619 | Y92: 141.55935 | Z92: 194.92465 | AA92: 204.2488 | AB92: 197.03105 | AC92: 162.67215 | AD92: 164.94194 | AE92: 145.90548 | AF92: 190.45238 | AG92: 176.25939 | AH92: 223.47142 | AI92: 250.14944 | AJ92: 257.78918 | AK92: 221.79917 | AL92: 227.02325 | AM92: 220.96042 | AN92: 233.24326 | AO92: 243.4383 | AP92: 237.13008 | AQ92: 178.84836 | AR92: 190.67231 | AS92: 308.91032 | AT92: 319.95745 | AU92: 333.05858 | AV92: 372.05619 | AW92: 405.07512 | AX92: 436.47522 | AY92: 430.00394 | AZ92: 493.72199 | BA92: 599.99524 | BB92: 559.41457 | BC92: 558.17467 | BD92: 703.66057 | BE92: 616.37566 | BF92: 634.66204 | BG92: 623.31309 | BH92: 603.39938 | BI92: 661.45784 | BJ92: 738.54994 | BK92: 802.76739 | BL92: 749.45375 | BM92: 727.52017
A93: Equatorial Guinea | B93: GNQ | C93: GDP per capita (current US$) | D93: NY.GDP.PCAP.CD | G93: 34.790581 | H93: 40.751471 | I93: 46.976052 | J93: 234.34409 | K93: 243.76909 | L93: 247.84413 | M93: 225.48657 | N93: 221.13722 | O93: 218.20554 | P93: 217.32147 | Q93: 226.00135 | R93: 292.45983 | S93: 354.30145 | T93: 407.71064 | U93: 418.0081 | V93: 429.41658 | Y93: 202.62745 | Z93: 138.93945 | AA93: 155.61748 | AB93: 144.19631 | AC93: 151.77291 | AD93: 176.41506 | AE93: 207.05265 | AF93: 243.73748 | AG93: 254.53553 | AH93: 217.07239 | AI93: 267.46807 | AJ93: 256.22634 | AK93: 301.17711 | AL93: 294.0705 | AM93: 210.40954 | AN93: 285.55255 | AO93: 450.646 | AP93: 824.55108 | AQ93: 663.72475 | AR93: 1067.644 | AS93: 1725.5576 | AT93: 2313.1659 | AU93: 2744.1915 | AV93: 3618.5445 | AW93: 6152.1312 | AX93: 10963.406 | AY93: 12857.369 | AZ93: 15908.411 | BA93: 22942.61 | BB93: 16668.122 | BC93: 17288.843 | BD93: 21641.694 | BE93: 21711.152 | BF93: 20390.737 | BG93: 19394.081 | BH93: 11283.398 | BI93: 9250.3165 | BJ93: 9667.8578 | BK93: 10005.617 | BL93: 8419.9333 | BM93: 7143.2387
A94: Greece | B94: GRC | C94: GDP per capita (current US$) | D94: NY.GDP.PCAP.CD | E94: 520.32274 | F94: 590.78005 | G94: 617.05776 | H94: 695.22862 | I94: 783.70588 | J94: 899.28124 | K94: 997.43047 | L94: 1068.1146 | M94: 1154.4385 | N94: 1324.059 | O94: 1494.388 | P94: 1652.326 | Q94: 1899.6758 | R94: 2502.8147 | S94: 2828.7486 | T94: 3153.2358 | U94: 3390.545 | V94: 3886.3745 | W94: 4694.6338 | X94: 5705.9494 | Y94: 5893.6619 | Z94: 5380.2676 | AA94: 5579.2346 | AB94: 5019.8788 | AC94: 4852.5657 | AD94: 4813.7112 | AE94: 5656.5053 | AF94: 6564.8844 | AG94: 7598.028 | AH94: 7846.6781 | AI94: 9600.1852 | AJ94: 10188.37 | AK94: 11176.458 | AL94: 10401.983 | AM94: 11091.284 | AN94: 12959.324 | AO94: 13749.115 | AP94: 13427.833 | AQ94: 13472.138 | AR94: 13245.189 | AS94: 12042.954 | AT94: 12538.179 | AU94: 14110.313 | AV94: 18477.578 | AW94: 21955.104 | AX94: 22551.736 | AY94: 24801.158 | AZ94: 28827.326 | BA94: 31997.282 | BB94: 29710.97 | BC94: 26690.607 | BD94: 25450.534 | BE94: 21915.191 | BF94: 21749.152 | BG94: 21601.776 | BH94: 18050.098 | BI94: 17885.393 | BJ94: 18562.229 | BK94: 19765.996 | BL94: 19150.786 | BM94: 17676.192
A95: Grenada | B95: GRD | C95: GDP per capita (current US$) | D95: NY.GDP.PCAP.CD | V95: 792.45497 | W95: 991.22807 | X95: 1153.9605 | Y95: 1245.6247 | Z95: 1276.3704 | AA95: 1346.8581 | AB95: 1372.6677 | AC95: 1477.9157 | AD95: 1678.0732 | AE95: 1872.4686 | AF95: 2162.5302 | AG95: 2408.7145 | AH95: 2757.8884 | AI95: 2886.9982 | AJ95: 3117.8898 | AK95: 3192.2319 | AL95: 3153.8183 | AM95: 3272.5534 | AN95: 3411.967 | AO95: 3632.6787 | AP95: 3861.3978 | AQ95: 4370.6183 | AR95: 4705.7901 | AS95: 5056.9773 | AT95: 5041.0122 | AU95: 5213.7956 | AV95: 5682.7054 | AW95: 5741.6537 | AX95: 6645.9855 | AY95: 6658.2236 | AZ95: 7212.9868 | BA95: 7832.3491 | BB95: 7290.8349 | BC95: 7258.1666 | BD95: 7291.7417 | BE95: 7444.0891 | BF95: 7789.6324 | BG95: 8370.0405 | BH95: 9096.5387 | BI95: 9628.1728 | BJ95: 10152.833 | BK95: 10486.378 | BL95: 10815.911 | BM95: 9680.1758
A96: Greenland | B96: GRL | C96: GDP per capita (current US$) | D96: NY.GDP.PCAP.CD | O96: 1498.2764 | P96: 1876.5032 | Q96: 2196.7117 | R96: 2860.2806 | S96: 3432.706 | T96: 4257.9497 | U96: 4844.6763 | V96: 5713.9549 | W96: 7235.5497 | X96: 8480.6948 | Y96: 9483.1731 | Z96: 8544.0583 | AA96: 7813.6907 | AB96: 7988.171 | AC96: 7198.7022 | AD96: 7760.8284 | AE96: 11271.321 | AF96: 14554.388 | AG96: 16398.011 | AH96: 16813.684 | AI96: 18326.805 | AJ96: 18315.196 | AK96: 18768.93 | AL96: 16797.459 | AM96: 18123.963 | AN96: 21665.702 | AO96: 21422.358 | AP96: 19145.496 | AQ96: 20496.661 | AR96: 20170.438 | AS96: 19004.107 | AT96: 19275.473 | AU96: 20652.878 | AV96: 27459.763 | AW96: 32023.452 | AX96: 32489.782 | AY96: 35458.123 | AZ96: 39780.951 | BA96: 44367.056 | BB96: 44918.565 | BC96: 43988.332 | BD96: 47186.981 | BE96: 45936.766 | BF96: 47535.59 | BG96: 50484.928 | BH96: 44536.401 | BI96: 48181.874 | BJ96: 50321.369 | BK96: 54470.956
A97: Guatemala | B97: GTM | C97: GDP per capita (current US$) | D97: NY.GDP.PCAP.CD | E97: 252.75617 | F97: 253.22729 | G97: 261.17913 | H97: 280.09664 | I97: 279.93046 | J97: 278.82814 | K97: 283.19272 | L97: 287.96805 | M97: 310.66175 | N97: 322.43753 | O97: 349.02498 | P97: 355.09037 | Q97: 367.11888 | R97: 438.54485 | S97: 527.4177 | T97: 594.6518 | U97: 696.22202 | V97: 854.63664 | W97: 925.12574 | X97: 1027.0837 | Y97: 1143.4404 | Z97: 1217.264 | AA97: 1200.2492 | AB97: 1212.7166 | AC97: 1234.7026 | AD97: 1233.0809 | AE97: 892.29291 | AF97: 850.21851 | AG97: 915.39807 | AH97: 955.11346 | AI97: 845.30696 | AJ97: 1011.755 | AK97: 1093.9629 | AL97: 1164.374 | AM97: 1293.4702 | AN97: 1424.6825 | AO97: 1487.6077 | AP97: 1649.0016 | AQ97: 1755.8496 | AR97: 1619.5107 | AS97: 1664.299 | AT97: 1550.3604 | AU97: 1682.9945 | AV97: 1737.8793 | AW97: 1859.0984 | AX97: 2068.5001 | AY97: 2251.088 | AZ97: 2490.7491 | BA97: 2802.462 | BB97: 2651.8171 | BC97: 2852.5473 | BD97: 3228.0457 | BE97: 3355.0369 | BF97: 3522.7737 | BG97: 3779.6423 | BH97: 3994.6369 | BI97: 4173.3017 | BJ97: 4454.0481 | BK97: 4478.4246 | BL97: 4638.6349 | BM97: 4603.3396
A98: Guam | B98: GUM | C98: GDP per capita (current US$) | D98: NY.GDP.PCAP.CD | AU98: 21594.04 | AV98: 22628.279 | AW98: 24472.782 | AX98: 26596.215 | AY98: 26713.058 | AZ98: 27680.55 | BA98: 29288.782 | BB98: 30320.539 | BC98: 31040.084 | BD98: 31210.47 | BE98: 32908.307 | BF98: 33656.454 | BG98: 34843.206 | BH98: 35829.25 | BI98: 36214.007 | BJ98: 36601.92 | BK98: 36502.383 | BL98: 37723.781
A99: Guyana | B99: GUY | C99: GDP per capita (current US$) | D99: NY.GDP.PCAP.CD | E99: 297.67642 | F99: 315.38546 | G99: 321.54524 | H99: 282.30407 | I99: 305.3664 | J99: 327.11573 | K99: 344.16808 | L99: 370.15965 | M99: 334.84225 | N99: 358.32197 | O99: 379.89588 | P99: 395.20292 | Q99: 395.2924 | R99: 420.66562 | S99: 588.13702 | T99: 663.39567 | U99: 602.62485 | V99: 590.06537 | W99: 658.436 | X99: 683.33039 | Y99: 773.18167 | Z99: 729.60509 | AA99: 616.96079 | AB99: 628.19366 | AC99: 564.52787 | AD99: 588.61035 | AE99: 660.1519 | AF99: 468.13833 | AG99: 551.26217 | AH99: 509.37375 | AI99: 533.53836 | AJ99: 468.15831 | AK99: 499.03171 | AL99: 602.14387 | AM99: 712.71285 | AN99: 816.53542 | AO99: 927.18858 | AP99: 988.34132 | AQ99: 951.91248 | AR99: 926.74034 | AS99: 954.40032 | AT99: 955.66538 | AU99: 974.94919 | AV99: 997.21137 | AW99: 1056.4239 | AX99: 1105.5068 | AY99: 3188.6732 | AZ99: 3658.477 | BA99: 4050.7882 | BB99: 4233.7644 | BC99: 4580.6991 | BD99: 4908.567 | BE99: 5378.812 | BF99: 5489.1428 | BG99: 5407.1537 | BH99: 5576.8261 | BI99: 5811.3979 | BJ99: 6124.9537 | BK99: 6145.8187 | BL99: 6609.5104 | BM99: 6955.9392
A100: High income | B100: HIC | C100: GDP per capita (current US$) | D100: NY.GDP.PCAP.CD | E100: 1402.9637 | F100: 1466.3034 | G100: 1562.594 | H100: 1662.1709 | I100: 1792.0562 | J100: 1923.3721 | K100: 2087.1674 | L100: 2216.8649 | M100: 2380.4073 | N100: 2592.9294 | O100: 2805.2333 | P100: 3078.0971 | Q100: 3534.6965 | R100: 4235.6035 | S100: 4730.6689 | T100: 5230.8719 | U100: 5652.6226 | V100: 6349.3541 | W100: 7546.2819 | X100: 8651.173 | Y100: 9583.2042 | Z100: 9649.2061 | AA100: 9485.9568 | AB100: 9724.7398 | AC100: 10076.127 | AD100: 10509.301 | AE100: 12674.962 | AF100: 14591.075 | AG100: 16318.503 | AH100: 16951.008 | AI100: 18905.018 | AJ100: 19836.012 | AK100: 21208.594 | AL100: 21203.524 | AM100: 22567.753 | AN100: 24852.286 | AO100: 24902.239 | AP100: 24328.495 | AQ100: 24269.72 | AR100: 25332.103 | AS100: 25685.895 | AT100: 25277.364 | AU100: 26167.973 | AV100: 29147.401 | AW100: 32222.742 | AX100: 33845.252 | AY100: 35478.277 | AZ100: 38494.4 | BA100: 40574.139 | BB100: 37776.777 | BC100: 39341.132 | BD100: 42258.047 | BE100: 42057.995 | BF100: 42321.549 | BG100: 42995.266 | BH100: 40398.449 | BI100: 41013.341 | BJ100: 42658.207 | BK100: 45114.36 | BL100: 45297.718 | BM100: 43833.932
A101: Hong Kong SAR, China | B101: HKG | C101: GDP per capita (current US$) | D101: NY.GDP.PCAP.CD | E101: 429.44287 | F101: 436.75441 | G101: 487.82113 | H101: 565.72781 | I101: 629.59153 | J101: 676.80551 | K101: 685.92661 | L101: 723.23923 | M101: 714.48297 | N101: 825.52345 | O101: 960.03196 | P101: 1106.4697 | Q101: 1384.7384 | R101: 1893.1812 | S101: 2144.6077 | T101: 2252.1119 | U101: 2850.0146 | V101: 3429.4203 | W101: 3923.9437 | X101: 4569.4537 | Y101: 5700.4126 | Z101: 5991.3203 | AA101: 6133.7841 | AB101: 5595.2351 | AC101: 6208.2262 | AD101: 6542.9315 | AE101: 7435.0307 | AF101: 9071.3326 | AG101: 10609.746 | AH101: 12097.775 | AI101: 13485.545 | AJ101: 15465.859 | AK101: 17976.429 | AL101: 20395.517 | AM101: 22502.58 | AN101: 23497.492 | AO101: 24818.155 | AP101: 27330.033 | AQ101: 25808.971 | AR101: 25091.667 | AS101: 25756.664 | AT101: 25230.216 | AU101: 24665.89 | AV101: 23977.019 | AW101: 24928.1 | AX101: 26649.751 | AY101: 28224.215 | AZ101: 30594.018 | BA101: 31515.663 | BB101: 30697.34 | BC101: 32549.998 | BD101: 35142.488 | BE101: 36730.877 | BF101: 38403.778 | BG101: 40315.286 | BH101: 42431.888 | BI101: 43731.107 | BJ101: 46165.857 | BK101: 48542.682 | BL101: 48354.473 | BM101: 46323.863
...

Sheet AFRO
A3: No | B3: Country | C3: Physicians generalists | D3: Physicians specialists | E3: Nurses | F3: Midwives | G3: Dentists | H3: Pharmacists | I3: Laboratory Scientists | J3: Radiographers | K3: Environment and public health workers | L3: Community Health workers | M3: Physiotherapist | N3: Clinical Officer/Physician Assistant | O3: Last Year Available | P3: Source
A4: 1 | B4: Zimbabawe | D4: 12679.06 | E4: 3577.84 | F4: 3577.84 | H4: 3577.84 | I4: 3577.84 | J4: 3577.84 | O4: 2021 | P4: HLMA
A5: 2 | B5: South Africa | C5: 70131.643 | D5: 93060.643 | E5: 32982.786 | F5: 32982.786 | H5: 55266.429 | J5: 39012.857 | L5: 3000 | M5: 39012.857 | O5: 2020 | P5: HLMA
A6: 3 | B6: Kenya | C6: 38320.08 | D6: 49800 | E6: 12002.4 | F6: 12002.4 | G6: 38320.08 | H6: 32760 | I6: 9840 | K6: 9840 | L6: 240 | N6: 12006 | O6: 2019 | P6: NHWA
A7: 4 | B7: Namiba | C7: 67042.775 | D7: 71841.184 | E7: 50651.836 | F7: 50651.836 | G7: 65003.378 | H7: 45703.888 | J7: 29543.775 | K7: 23780.741 | M7: 19659.896 | O7: 2019 | P7: HLMA
A8: 5 | B8: Lesotho | C8: 28693.57 | D8: 33928.98 | E8: 9854.51 | F8: 9854.51 | G8: 28693.57 | H8: 17959.95 | I8: 12188.43 | J8: 12188.43 | K8: 12188.43 | L8: 2190.85 | M8: 12188.43 | O8: 2020 | P8: HLMA
A9: 6 | B9: Ethiopia | C9: 4350 | D9: 5391 | E9: 3030.4286 | F9: 3881.1429 | G9: 4350 | H9: 3881.1429 | I9: 3030.4286 | J9: 3881.1429 | K9: 3030.4286 | L9: 2654.1429 | N9: 3881.14 | O9: 2019 | P9: HLMA
A10: 7 | B10: Sierra Leone | C10: 9452.5853 | D10: 28720.193 | E10: 4501.6989 | F10: 4501.6989 | G10: 23570.083 | H10: 10373.292 | I10: 4951.3542 | J10: 7406.5712 | K10: 2446.2732 | L10: 18.910956 | M10: 3928.3471 | N10: 6394.1762 | O10: 2019 | P10: HLMA
A11: 8 | B11: Seychelles | C11: 19953.72 | D11: 38849.64 | E11: 10987.2 | F11: 11821.2 | G11: 38849.64 | H11: 16211.28 | I11: 13106.4 | J11: 7501.68 | K11: 9106.8976 | M11: 15213.59 | N11: 11461.673 | O11: 2020 | P11: NHWA
A12: 9 | B12: Rwanda | C12: 11152.244 | D12: 18315.524 | E12: 4623.8824 | F12: 4635.0635 | G12: 4623.8824 | H12: 7682.9689 | I12: 4623.8824 | K12: 4623.8824 | M12: 4623.8824 | N12: 4623.8824 | O12: 2019 | P12: HLMA
A13: 10 | B13: Botswana | C13: 40332.2 | D13: 68600.56 | E13: 29923.9 | F13: 18169.012 | G13: 40332.2 | H13: 33827 | I13: 33827 | J13: 33827 | K13: 18248.4 | L13: 6691.2 | M13: 22628.4 | N13: 10736.234 | O13: 2019 | P13: SADC
A14: 11 | B14: Malawi | C14: 6021.5567 | D14: 14628.897 | E14: 5416.7938 | F14: 5416.7938 | G14: 5416.7938 | H14: 5416.7938 | I14: 5416.7938 | J14: 5416.7938 | K14: 5416.7938 | L14: 2010.2784 | M14: 5416.7938 | N14: 5416.7938 | O14: 2019 | P14: SADC
A15: 12 | B15: Zambia | C15: 25106.732 | D15: 37170.582 | E15: 5825.1178 | F15: 6741.5821 | G15: 24675.147 | H15: 8329.7848 | I15: 5825.1178 | J15: 8329.7848 | K15: 5825.1178 | M15: 8329.7848 | N15: 6275.9016 | O15: 2019 | P15: NHWA
A16: 13 | B16: Eswatini | C16: 26265.357 | D16: 31958.714 | E16: 10845.357 | F16: 10845.357 | G16: 26265.357 | H16: 17704.857 | I16: 9005.4286 | J16: 7477.7857 | K16: 9005.4286 | L16: 300 | M16: 14688.857 | O16: 2019 | P16: SADC
B17: Mean | C17: =AVERAGEIF(C4:C16,">0") -> 28901.872 | D17: =AVERAGEIF(D4:D16,">0") -> 38841.921 | E17: =AVERAGEIF(E4:E16,">0") -> 14171.058 | F17: =AVERAGEIF(F4:F16,">0") -> 13467.786 | G17: =AVERAGEIF(G4:G16,">0") -> 27281.83 | H17: =AVERAGEIF(H4:H16,">0") -> 19899.633 | I17: =AVERAGEIF(I4:I16,">0") -> 9581.1523 | J17: =AVERAGEIF(J4:J16,">0") -> 14378.515 | ... N17: =AVERAGEIF(N4:N16,">0") -> 7599.4752
B18: Median | C18: =MEDIAN(C4:C16) -> 25686.045 | D18: =MEDIAN(D4:D16) -> 33928.98 | E18: =MEDIAN(E4:E16) -> 9854.51 | F18: =MEDIAN(F4:F16) -> 9854.51 | G18: =MEDIAN(G4:G16) -> 26265.357 | H18: =MEDIAN(H4:H16) -> 16211.28 | I18: =MEDIAN(I4:I16) -> 5825.1178 | J18: =MEDIAN(J4:J16) -> 7501.68 | ... N18: =MEDIAN(N4:N16) -> 6335.0389
B19: Min | C19: =_xlfn.MINIFS(C4:C16,C4:C16,">0") -> 4350 | D19: =_xlfn.MINIFS(D4:D16,D4:D16,">0") -> 5391 | E19: =_xlfn.MINIFS(E4:E16,E4:E16,">0") -> 3030.4286 | F19: =_xlfn.MINIFS(F4:F16,F4:F16,">0") -> 3577.84 | G19: =_xlfn.MINIFS(G4:G16,G4:G16,">0") -> 4350 | H19: =_xlfn.MINIFS(H4:H16,H4:H16,">0") -> 3577.84 | I19: =_xlfn.MINIFS(I4:I16,I4:I16,">0") -> 3030.4286 | J19: =_xlfn.MINIFS(J4:J16,J4:J16,">0") -> 3577.84 | ... N19: =_xlfn.MINIFS(N4:N16,N4:N16,">0") -> 3881.14
B20: Max | C20: =MAX(C4:C16) -> 70131.643 | D20: =MAX(D4:D16) -> 93060.643 | E20: =MAX(E4:E16) -> 50651.836 | F20: =MAX(F4:F16) -> 50651.836 | G20: =MAX(G4:G16) -> 65003.378 | H20: =MAX(H4:H16) -> 55266.429 | I20: =MAX(I4:I16) -> 33827 | J20: =MAX(J4:J16) -> 39012.857 | ... N20: =MAX(N4:N16) -> 12006
B21: N | C21: =COUNT(C4:C16) -> 12 | D21: =COUNT(D4:D16) -> 13 | E21: =COUNT(E4:E16) -> 13 | F21: =COUNT(F4:F16) -> 13 | G21: =COUNT(G4:G16) -> 11 | H21: =COUNT(H4:H16) -> 13 | I21: =COUNT(I4:I16) -> 11 | J21: =COUNT(J4:J16) -> 11 | ... N21: =COUNT(N4:N16) -> 8
B22: SD | C22: =STDEV(C4:C16) -> 21940.15 | D22: =STDEV(D4:D16) -> 25855.526 | E22: =STDEV(E4:E16) -> 14562.166 | F22: =STDEV(F4:F16) -> 13749.438 | G22: =STDEV(G4:G16) -> 18411.447 | H22: =STDEV(H4:H16) -> 16844.432 | I22: =STDEV(I4:I16) -> 8740.1135 | J22: =STDEV(J4:J16) -> 13065.772 | ... N22: =STDEV(N4:N16) -> 3269.3851
B23: SEM | C23: =C22/SQRT(C21) -> 6333.5757 | D23: =D22/SQRT(D21) -> 7171.0326 | E23: =E22/SQRT(E21) -> 4038.8181 | F23: =F22/SQRT(F21) -> 3813.408 | G23: =G22/SQRT(G21) -> 5551.2602 | H23: =H22/SQRT(H21) -> 4671.8049 | I23: =I22/SQRT(I21) -> 2635.2434 | J23: =J22/SQRT(J21) -> 3939.4784 | ... N23: =N22/SQRT(N21) -> 1155.9022
B24: 95% LCL | C24: =C17-(1.96*C23) -> 16488.064 | D24: =D17-(1.96*D23) -> 24786.697 | E24: =E17-(1.96*E23) -> 6254.9743 | F24: =F17-(1.96*F23) -> 5993.5066 | G24: =G17-(1.96*G23) -> 16401.36 | H24: =H17-(1.96*H23) -> 10742.895 | I24: =I17-(1.96*I23) -> 4416.0753 | J24: =J17-(1.96*J23) -> 6657.137 | ... N24: =N17-(1.96*N23) -> 5333.9069
B25: 95% UCL | C25: =C17+(1.96*C23) -> 41315.68 | D25: =D17+(1.96*D23) -> 52897.145 | E25: =E17+(1.96*E23) -> 22087.141 | F25: =F17+(1.96*F23) -> 20942.066 | G25: =G17+(1.96*G23) -> 38162.3 | H25: =H17+(1.96*H23) -> 29056.37 | I25: =I17+(1.96*I23) -> 14746.229 | J25: =J17+(1.96*J23) -> 22099.892 | ... N25: =N17+(1.96*N23) -> 9865.0434

Sheet Health buget allocated to HRH
A1: Country name | B1: % of Health Budget Allocated to HRH | C1: latest Year | D1: Source
A2: Lesotho | B2: 0.187 | C2: 2017 | D2: Lesotho HLMA report, 2021
A3: Rwanda | B3: 0.28 | C3: 2015 | D3: Rwanda HLMA report, 2019
A4: Namibia | B4: 0.29 | C4: 2019 | D4: Public expenditure review
A5: Zimbabwe | B5: 0.35 | C5: 2020 | D5: Zimbabwe's HLMA (2021) show 35% and the MOF indicated that tey will hold it constant over the next years. I suggest that we use the 35%
A6: Kenya | B6: 0.41 | C6: 2014 | D6: Kenya Productovity paper, 2019
A7: Uganda | B7: 0.41 | C7: 2018 | D7: Public expenditure review
A8: Eritrea | B8: 0.45 | D8: Lauer et al (2018). Global/regional wage ceilings
A9: Ethiopia | B9: 0.45 | D9: Ethiopia HLMA, 2020
A10: Madagascar | B10: 0.45 | D10: Lauer et al (2018). Global/regional wage ceilings
A11: Mozambique | B11: 0.45 | D11: Lauer et al (2018). Global/regional wage ceilings
A12: South Sudan | B12: 0.45 | D12: Lauer et al (2018). Global/regional wage ceilings
A13: Botswana | B13: 0.461 | C13: 2019 | D13: Unicef health budget brief 2019
A14: Malawi | B14: 0.51 | C14: 2020 | D14: Public expenditure review
A15: Seychelles | B15: 0.54 | C15: 2014 | D15: Public expenditure review
A16: Comoros | B16: 0.57 | D16: Lauer et al (2018). Global/regional wage ceilings
A17: Eswatini | B17: 0.57 | D17: Lauer et al (2018). Global/regional wage ceilings
A18: Mauritius | B18: 0.57 | D18: Lauer et al (2018). Global/regional wage ceilings
A19: United Republic of Tanzania | B19: 0.57 | D19: Lauer et al (2018). Global/regional wage ceilings
A20: South Africa | B20: 0.59425 | C20: 2017 | D20: Public expenditure review
A21: Zambia | B21: 0.62 | C21: 2018 | D21: Public expenditure review
A22: Sub-Regional Average | B22: =AVERAGE(B2:B21) -> 0.4591125
A41: Country name | B41: % of Health Budget Allocated to HRH
A42: Lesotho | B42: 0.187
A43: Rwanda | B43: 0.28
A44: Namibia | B44: 0.29
A45: Zimbabwe | B45: 0.35
A46: Kenya | B46: 0.41
A47: Uganda | B47: 0.41
A48: Eritrea | B48: 0.45
A49: Ethiopia | B49: 0.45
A50: Madagascar | B50: 0.45
A51: Mozambique | B51: 0.45
A52: South Sudan | B52: 0.45
A53: AFRO | B53: 0.4591125
... A62: Zambia | B62: 0.62

Sheet Income relativities in Lesotho
F6: No. | G6: List of cadres | H6: Total Annual Income per worker (LSL) | I6: Total Income per worker (USD) | J6: Wage Index (Income as multiples of GDP per capita) | K6: Wage Relativity (GP as Reference) | L6: Wage Relativity (Lawyer and Engineers in Public Sector as Reference)
F7: 1 | G7: Generalist medical practitioners | H7: 438016 | I7: 28693.57 | J7: 24.78 | K7: 1 | L7: 2.3
F8: 2 | G8: Specialist medical practitioners | H8: 517936 | I8: 33928.98 | J8: 29.3 | K8: 1.18 | L8: 2.73
F9: 3 | G9: Nursing and Midwifery professionals | H9: 150432 | I9: 9854.51 | J9: 8.51 | K9: 0.34 | L9: 0.81
F10: 4 | G10: Nursing associate professionals | H10: 79932 | I10: 5236.19 | J10: 4.52 | K10: 0.18 | L10: 0.43
F11: 5 | G11: Dental specialists | H11: 517936 | I11: 33928.98 | J11: 29.3 | K11: 1.18 | L11: 2.73
F12: 6 | G12: Dentists | H12: 438016 | I12: 28693.57 | J12: 24.78 | K12: 1 | L12: 2.3
F13: 7 | G13: Dental assistants and therapists | H13: 186060 | I13: 12188.43 | J13: 10.53 | K13: 0.42 | L13: 1
F14: 8 | G14: Environmental and occupational health & hygiene workers | H14: 186060 | I14: 12188.43 | J14: 10.53 | K14: 0.42 | L14: 1
F15: 9 | G15: Physiotherapists and physiotherapy assistants | H15: 186060 | I15: 12188.43 | J15: 10.53 | K15: 0.42 | L15: 1
F16: 10 | G16: Optometrists and opticians | H16: 340632 | I16: 22314.14 | J16: 19.27 | K16: 0.78 | L16: 1.83
F17: 11 | G17: Medical imaging and therapeutic equipment operators | H17: 186060 | I17: 12188.43 | J17: 10.53 | K17: 0.42 | L17: 1
F18: 12 | G18: Medical and pathology laboratory technicians | H18: 186060 | I18: 12188.43 | J18: 10.53 | K18: 0.42 | L18: 1
... F30: 25 | G30: Specialised Nursing professional | H30: 186060 | I30: 12188.43 | J30: 10.53 | K30: 0.42 | L30: 1
G31: Average | H31: 242390.92 | I31: 15878.56 | J31: 13.71 | L31: 1.29

Sheet ESA_USD
B2: Descriptive Analysis of salaries of annual income of health workers
A3: No | B3: Country | C3: Physicians generalists | D3: Physicians specialists | E3: Nurses | F3: Midwives | G3: Dentists | H3: Pharmacists | I3: Laboratory Scientists | J3: Radiographers | K3: Environment and public health workers | L3: Community Health workers | M3: Physiotherapist | N3: Clinical Officer/Physician Assistant | O3: Average | P3: Last Year Available | Q3: Data Source | R3: GDP Per capita
A4: 1 | B4: Zimbabwe | D4: 12679.06 | E4: 3577.84 | F4: 3577.84 | H4: 3577.84 | I4: 3577.84 | J4: 3577.84 | O4: =AVERAGEIF(C4:N4,">0") -> 5094.71 | P4: 2021 | Q4: HLMA | R4: =_xlfn.XLOOKUP(B4,'Wage Index_ESA'!C:C,'Wage Index_ESA'!D:D,0,0) -> 1156.1549
A5: 2 | B5: South Africa | C5: 70131.643 | D5: 93060.643 | E5: 32982.786 | F5: 32982.786 | H5: 55266.429 | J5: 39012.857 | L5: 3000 | M5: 39012.857 | O5: =AVERAGEIF(C5:N5,">0") -> 45681.25 | P5: 2020 | Q5: HLMA | R5: =_xlfn.XLOOKUP(B5,'Wage Index_ESA'!C:C,'Wage Index_ESA'!D:D,0,0) -> 6001.4011
A6: 3 | B6: Kenya | C6: 38320.08 | D6: 49800 | E6: 12002.4 | F6: 12002.4 | G6: 38320.08 | H6: 32760 | I6: 9840 | K6: 9840 | L6: 240 | N6: 12006 | O6: =AVERAGEIF(C6:N6,">0") -> 21513.096 | P6: 2019 | Q6: NHWA | R6: =_xlfn.XLOOKUP(B6,'Wage Index_ESA'!C:C,'Wage Index_ESA'!D:D,0,0) -> 1816.5471 | T6: Cadre | U6: Corr
A7: 4 | B7: Namibia | C7: 67042.775 | D7: 71841.184 | E7: 50651.836 | F7: 50651.836 | G7: 65003.378 | H7: 45703.888 | J7: 29543.775 | K7: 23780.741 | M7: 19659.896 | O7: =AVERAGEIF(C7:N7,">0") -> 47097.701 | P7: 2019 | Q7: HLMA | R7: =_xlfn.XLOOKUP(B7,'Wage Index_ESA'!C:C,'Wage Index_ESA'!D:D,0,0) -> 5037.3426 | T7: Sp Doctors | U7: =CORREL($R$4:$R$15,$D$4:$D$15) -> 0.83101453
A8: 5 | B8: Lesotho | C8: 28693.57 | D8: 33928.98 | E8: 9854.51 | F8: 9854.51 | G8: 28693.57 | H8: 17959.95 | I8: 12188.43 | J8: 12188.43 | K8: 12188.43 | L8: 2190.85 | M8: 12188.43 | O8: =AVERAGEIF(C8:N8,">0") -> 16357.242 | P8: 2020 | Q8: HLMA | R8: =_xlfn.XLOOKUP(B8,'Wage Index_ESA'!C:C,'Wage Index_ESA'!D:D,0,0) -> 1113.3721 | T8: Nurses | U8: =CORREL($R$4:$R$15,$E$4:$E$15) -> 0.81580421
A9: 6 | B9: Ethiopia | C9: 4350 | D9: 5391 | E9: 3030.4286 | F9: 3881.1429 | G9: 4350 | H9: 3881.1429 | I9: 3030.4286 | J9: 3881.1429 | K9: 3030.4286 | L9: 2654.1429 | N9: 3881.14 | O9: =AVERAGEIF(C9:N9,">0") -> 3760.0906 | P9: 2019 | Q9: HLMA | R9: =_xlfn.XLOOKUP(B9,'Wage Index_ESA'!C:C,'Wage Index_ESA'!D:D,0,0) -> 855.76089 | T9: Midwives | U9: =CORREL($R$4:$R$15,$F$4:$F$15) -> 0.69621797
A10: 7 | B10: Sierra Leone | C10: 9452.5853 | D10: 28720.193 | E10: 4501.6989 | F10: 4501.6989 | G10: 23570.083 | H10: 10373.292 | I10: 4951.3542 | J10: 7406.5712 | K10: 2446.2732 | L10: 18.910956 | M10: 3928.3471 | N10: 6394.1762 | O10: =AVERAGEIF(C10:N10,">0") -> 8855.4319 | P10: 2019 | Q10: HLMA | R10: =_xlfn.XLOOKUP(B10,'Wage Index_ESA'!C:C,'Wage Index_ESA'!D:D,0,0) -> 527.53417 | T10: Pharmacist | U10: =CORREL($R$4:$R$15,$H$4:$H$15) -> 0.79531598
A11: 8 | B11: Rwanda | C11: 11152.244 | D11: 18315.524 | E11: 4623.8824 | F11: 4635.0635 | G11: 4623.8824 | H11: 7682.9689 | I11: 4623.8824 | K11: 4623.8824 | M11: 4623.8824 | N11: 4623.8824 | O11: =AVERAGEIF(C11:N11,">0") -> 6952.9094 | P11: 2019 | Q11: HLMA | R11: =_xlfn.XLOOKUP(B11,'Wage Index_ESA'!C:C,'Wage Index_ESA'!D:D,0,0) -> 820.14929
A12: 9 | B12: Botswana | C12: 40332.2 | D12: 68600.56 | E12: 29923.9 | F12: 18169.012 | G12: 40332.2 | H12: 33827 | I12: 33827 | J12: 33827 | K12: 18248.4 | L12: 6691.2 | M12: 22628.4 | N12: 10736.234 | O12: =AVERAGEIF(C12:N12,">0") -> 29761.925 | P12: 2019 | Q12: SADC | R12: =_xlfn.XLOOKUP(B12,'Wage Index_ESA'!C:C,'Wage Index_ESA'!D:D,0,0) -> 7970.797
A13: 10 | B13: Malawi | C13: 6021.5567 | D13: 14628.897 | E13: 5416.7938 | F13: 5416.7938 | G13: 5416.7938 | H13: 5416.7938 | I13: 5416.7938 | J13: 5416.7938 | K13: 5416.7938 | L13: 2010.2784 | M13: 5416.7938 | N13: 5416.7938 | O13: =AVERAGEIF(C13:N13,">0") -> 5950.9897 | P13: 2019 | Q13: SADC | R13: =_xlfn.XLOOKUP(B13,'Wage Index_ESA'!C:C,'Wage Index_ESA'!D:D,0,0) -> 583.1102
A14: 11 | B14: Zambia | C14: 25106.732 | D14: 37170.582 | E14: 5825.1178 | F14: 6741.5821 | G14: 24675.147 | H14: 8329.7848 | I14: 5825.1178 | J14: 8329.7848 | K14: 5825.1178 | M14: 8329.7848 | N14: 6275.9016 | O14: =AVERAGEIF(C14:N14,">0") -> 12948.605 | P14: 2019 | Q14: NHWA | R14: =_xlfn.XLOOKUP(B14,'Wage Index_ESA'!C:C,'Wage Index_ESA'!D:D,0,0) -> 1305.0022
A15: 12 | B15: Eswatini | C15: 26265.357 | D15: 31958.714 | E15: 10845.357 | F15: 10845.357 | G15: 26265.357 | H15: 17704.857 | I15: 9005.4286 | J15: 7477.7857 | K15: 9005.4286 | L15: 300 | M15: 14688.857 | O15: =AVERAGEIF(C15:N15,">0") -> 14942.045 | P15: 2019 | Q15: SADC | R15: =_xlfn.XLOOKUP(B15,'Wage Index_ESA'!C:C,'Wage Index_ESA'!D:D,0,0) -> 3894.6696
B16: Mean | C16: =AVERAGEIF(C4:C15,">0") -> 29715.34 | D16: =AVERAGEIF(D4:D15,">0") -> 38841.278 | E16: =AVERAGEIF(E4:E15,">0") -> 14436.379 | F16: =AVERAGEIF(F4:F15,">0") -> 13605.002 | G16: =AVERAGEIF(G4:G15,">0") -> 26125.049 | H16: =AVERAGEIF(H4:H15,">0") -> 20206.995 | I16: =AVERAGEIF(I4:I15,">0") -> 9228.6275 | J16: =AVERAGEIF(J4:J15,">0") -> 15066.198 | ... O16: =AVERAGEIF(O4:O15,">0") -> 18243
B17: Median | C17: =MEDIAN(C4:C15) -> 26265.357 | D17: =MEDIAN(D4:D15) -> 32943.847 | E17: =MEDIAN(E4:E15) -> 7839.8139 | F17: =MEDIAN(F4:F15) -> 8298.0461 | G17: =MEDIAN(G4:G15) -> 25470.252 | H17: =MEDIAN(H4:H15) -> 14039.074 | I17: =MEDIAN(I4:I15) -> 5620.9558 | J17: =MEDIAN(J4:J15) -> 7903.7853 | ... O17: =MEDIAN(O4:O15) -> 13945.325
B18: Min | C18: =_xlfn.MINIFS(C4:C15,C4:C15,">0") -> 4350 | D18: =_xlfn.MINIFS(D4:D15,D4:D15,">0") -> 5391 | E18: =_xlfn.MINIFS(E4:E15,E4:E15,">0") -> 3030.4286 | F18: =_xlfn.MINIFS(F4:F15,F4:F15,">0") -> 3577.84 | G18: =_xlfn.MINIFS(G4:G15,G4:G15,">0") -> 4350 | H18: =_xlfn.MINIFS(H4:H15,H4:H15,">0") -> 3577.84 | I18: =_xlfn.MINIFS(I4:I15,I4:I15,">0") -> 3030.4286 | J18: =_xlfn.MINIFS(J4:J15,J4:J15,">0") -> 3577.84 | ... N18: =_xlfn.MINIFS(N4:N15,N4:N15,">0") -> 3881.14
B19: Max | C19: =MAX(C4:C15) -> 70131.643 | D19: =MAX(D4:D15) -> 93060.643 | E19: =MAX(E4:E15) -> 50651.836 | F19: =MAX(F4:F15) -> 50651.836 | G19: =MAX(G4:G15) -> 65003.378 | H19: =MAX(H4:H15) -> 55266.429 | I19: =MAX(I4:I15) -> 33827 | J19: =MAX(J4:J15) -> 39012.857 | ... N19: =MAX(N4:N15) -> 12006
B20: N | C20: =COUNT(C4:C15) -> 11 | D20: =COUNT(D4:D15) -> 12 | E20: =COUNT(E4:E15) -> 12 | F20: =COUNT(F4:F15) -> 12 | G20: =COUNT(G4:G15) -> 10 | H20: =COUNT(H4:H15) -> 12 | I20: =COUNT(I4:I15) -> 10 | J20: =COUNT(J4:J15) -> 10 | ... O20: =COUNT(O4:O15) -> 12
B21: SD | C21: =STDEV(C4:C15) -> 22820.437 | D21: =STDEV(D4:D15) -> 27005.216 | E21: =STDEV(E4:E15) -> 15176.831 | F21: =STDEV(F4:F15) -> 14351.52 | G21: =STDEV(G4:G15) -> 18981.331 | H21: =STDEV(H4:H15) -> 17555.318 | I21: =STDEV(I4:I15) -> 9130.0829 | J21: =STDEV(J4:J15) -> 13561.072 | ... O21: =STDEV(O4:O15) -> 15137.647
B22: SEM | C22: =C21/SQRT(C20) -> 6880.6206 | D22: =D21/SQRT(D20) -> 7795.7343 | E22: =E21/SQRT(E20) -> 4381.1738 | F22: =F21/SQRT(F20) -> 4142.927 | G22: =G21/SQRT(G20) -> 6002.4238 | H22: =H21/SQRT(H20) -> 5067.7838 | I22: =I21/SQRT(I20) -> 2887.1857 | J22: =J21/SQRT(J20) -> 4288.3874 | ... O22: =O21/SQRT(O20) -> 4369.8622
B23: 95% LCL | C23: =C16-(1.96*C22) -> 16229.324 | D23: =D16-(1.96*D22) -> 23561.639 | E23: =E16-(1.96*E22) -> 5849.2785 | F23: =F16-(1.96*F22) -> 5484.865 | G23: =G16-(1.96*G22) -> 14360.299 | H23: =H16-(1.96*H22) -> 10274.139 | I23: =I16-(1.96*I22) -> 3569.7435 | J23: =J16-(1.96*J22) -> 6660.9589 | ... O23: =O16-(1.96*O22) -> 9678.0698
B24: 95% UCL | C24: =C16+(1.96*C22) -> 43201.357 | D24: =D16+(1.96*D22) -> 54120.917 | E24: =E16+(1.96*E22) -> 23023.48 | F24: =F16+(1.96*F22) -> 21725.139 | G24: =G16+(1.96*G22) -> 37889.8 | H24: =H16+(1.96*H22) -> 30139.852 | I24: =I16+(1.96*I22) -> 14887.512 | J24: =J16+(1.96*J22) -> 23471.437 | ... O24: =O16+(1.96*O22) -> 26807.93
B27: Average Monthly Income (Before Tax) | C27: =C16/12 -> 2476.2784 | D27: =D16/12 -> 3236.7732 | E27: =E16/12 -> 1203.0316 | F27: =F16/12 -> 1133.7501 | G27: =G16/12 -> 2177.0874 | H27: =H16/12 -> 1683.9163 | I27: =I16/12 -> 769.05229 | J27: =J16/12 -> 1255.5165 | ... O27: =O16/12 -> 1520.25
B28: 95% LCL | C28: =C23/12 -> 1352.4436 | D28: =D23/12 -> 1963.4699 | E28: =E23/12 -> 487.43987 | F28: =F23/12 -> 457.07208 | G28: =G23/12 -> 1196.6915 | H28: =H23/12 -> 856.17826 | I28: =I23/12 -> 297.47863 | J28: =J23/12 -> 555.07991 | ... O28: =O23/12 -> 806.50582
B29: 95% UCL | C29: =C24/12 -> 3600.1131 | D29: =D24/12 -> 4510.0764 | E29: =E24/12 -> 1918.6233 | F29: =F24/12 -> 1810.4282 | G29: =G24/12 -> 3157.4833 | H29: =H24/12 -> 2511.6543 | I29: =I24/12 -> 1240.626 | J29: =J24/12 -> 1955.9531 | ... O29: =O24/12 -> 2233.9941

Sheet Data for correlation
A1: Country | B1: Physicians generalists | C1: Physicians specialists | D1: Nurses | E1: Midwives | F1: Dentists | G1: Pharmacists | H1: Laboratory Scientists | I1: Radiographers | J1: Environment and public health workers | K1: Community Health workers | L1: Physiotherapist | M1: Clinical Officer/Physician Assistant | N1: Average | O1: Last Year Available | P1: Data Source | Q1: GDP Per capita
A2: Zimbabwe | C2: 12679.06 | D2: 3577.84 | E2: 3577.84 | G2: 3577.84 | H2: 3577.84 | I2: 3577.84 | N2: 5094.71 | O2: 2021 | P2: HLMA | Q2: 1156.1549
A3: South Africa | B3: 70131.643 | C3: 93060.643 | D3: 32982.786 | E3: 32982.786 | G3: 55266.429 | I3: 39012.857 | K3: 3000 | L3: 39012.857 | N3: 45681.25 | O3: 2020 | P3: HLMA | Q3: 6001.4011
A4: Kenya | B4: 38320.08 | C4: 49800 | D4: 12002.4 | E4: 12002.4 | F4: 38320.08 | G4: 32760 | H4: 9840 | J4: 9840 | K4: 240 | M4: 12006 | N4: 21513.096 | O4: 2019 | P4: NHWA | Q4: 1816.5471
A5: Namibia | B5: 67042.775 | C5: 71841.184 | D5: 50651.836 | E5: 50651.836 | F5: 65003.378 | G5: 45703.888 | I5: 29543.775 | J5: 23780.741 | L5: 19659.896 | N5: 47097.701 | O5: 2019 | P5: HLMA | Q5: 5037.3426
A6: Lesotho | B6: 28693.57 | C6: 33928.98 | D6: 9854.51 | E6: 9854.51 | F6: 28693.57 | G6: 17959.95 | H6: 12188.43 | I6: 12188.43 | J6: 12188.43 | K6: 2190.85 | L6: 12188.43 | N6: 16357.242 | O6: 2020 | P6: HLMA | Q6: 1113.3721
A7: Ethiopia | B7: 4350 | C7: 5391 | D7: 3030.4286 | E7: 3881.1429 | F7: 4350 | G7: 3881.1429 | H7: 3030.4286 | I7: 3881.1429 | J7: 3030.4286 | K7: 2654.1429 | M7: 3881.14 | N7: 3760.0906 | O7: 2019 | P7: HLMA | Q7: 855.76089
A8: Sierra Leone | B8: 9452.5853 | C8: 28720.193 | D8: 4501.6989 | E8: 4501.6989 | F8: 23570.083 | G8: 10373.292 | H8: 4951.3542 | I8: 7406.5712 | J8: 2446.2732 | K8: 18.910956 | L8: 3928.3471 | M8: 6394.1762 | N8: 8855.4319 | O8: 2019 | P8: HLMA | Q8: 527.53417
A9: Rwanda | B9: 11152.244 | C9: 18315.524 | D9: 4623.8824 | E9: 4635.0635 | F9: 4623.8824 | G9: 7682.9689 | H9: 4623.8824 | J9: 4623.8824 | L9: 4623.8824 | M9: 4623.8824 | N9: 6952.9094 | O9: 2019 | P9: HLMA | Q9: 820.14929
A10: Botswana | B10: 40332.2 | C10: 68600.56 | D10: 29923.9 | E10: 18169.012 | F10: 40332.2 | G10: 33827 | H10: 33827 | I10: 33827 | J10: 18248.4 | K10: 6691.2 | L10: 22628.4 | M10: 10736.234 | N10: 29761.925 | O10: 2019 | P10: SADC | Q10: 7970.797
A11: Malawi | B11: 6021.5567 | C11: 14628.897 | D11: 5416.7938 | E11: 5416.7938 | F11: 5416.7938 | G11: 5416.7938 | H11: 5416.7938 | I11: 5416.7938 | J11: 5416.7938 | K11: 2010.2784 | L11: 5416.7938 | M11: 5416.7938 | N11: 5950.9897 | O11: 2019 | P11: SADC | Q11: 583.1102
A12: Zambia | B12: 25106.732 | C12: 37170.582 | D12: 5825.1178 | E12: 6741.5821 | F12: 24675.147 | G12: 8329.7848 | H12: 5825.1178 | I12: 8329.7848 | J12: 5825.1178 | L12: 8329.7848 | M12: 6275.9016 | N12: 12948.605 | O12: 2019 | P12: NHWA | Q12: 1305.0022
A13: Eswatini | B13: 26265.357 | C13: 31958.714 | D13: 10845.357 | E13: 10845.357 | F13: 26265.357 | G13: 17704.857 | H13: 9005.4286 | I13: 7477.7857 | J13: 9005.4286 | K13: 300 | L13: 14688.857 | N13: 14942.045 | O13: 2019 | P13: SADC | Q13: 3894.6696

Sheet ESA_Int$ PPP
B2: Descriptive Analysis of salaries of health workers in Eastern and Southern Africa
A3: No | B3: Country | C3: Physicians generalists | D3: Physicians specialists | E3: Nurses | F3: Midwives | G3: Dentists | H3: Pharmacists | I3: Laboratory Scientists | J3: Radiographers | K3: Environment and public health workers | L3: Community Health workers | M3: Physiotherapist | N3: Clinical Officer/Physician Assistant | O3: Average | P3: Last Year Available | Q3: Data Source
A4: 1 | B4: Zimbabwe | C4: =ESA_USD!C4/(_xlfn.XLOOKUP($B4,'PPP conversion factor'!$A:$A,'PPP conversion factor'!$AH:$AH,,0)) -> 0 | D4: =ESA_USD!D4/(_xlfn.XLOOKUP($B4,'PPP conversion factor'!$A:$A,'PPP conversion factor'!$AH:$AH,,0)) -> 24477.907 | E4: =ESA_USD!E4/(_xlfn.XLOOKUP($B4,'PPP conversion factor'!$A:$A,'PPP conversion factor'!$AH:$AH,,0)) -> 6907.2971 | F4: =ESA_USD!F4/(_xlfn.XLOOKUP($B4,'PPP conversion factor'!$A:$A,'PPP conversion factor'!$AH:$AH,,0)) -> 6907.2971 | G4: =ESA_USD!G4/(_xlfn.XLOOKUP($B4,'PPP conversion factor'!$A:$A,'PPP conversion factor'!$AH:$AH,,0)) -> 0 | H4: =ESA_USD!H4/(_xlfn.XLOOKUP($B4,'PPP conversion factor'!$A:$A,'PPP conversion factor'!$AH:$AH,,0)) -> 6907.2971 | I4: =ESA_USD!I4/(_xlfn.XLOOKUP($B4,'PPP conversion factor'!$A:$A,'PPP conversion factor'!$AH:$AH,,0)) -> 6907.2971 | J4: =ESA_USD!J4/(_xlfn.XLOOKUP($B4,'PPP conversion factor'!$A:$A,'PPP conversion factor'!$AH:$AH,,0)) -> 6907.2971 | ... N4: =ESA_USD!N4/(_xlfn.XLOOKUP($B4,'PPP conversion factor'!$A:$A,'PPP conversion factor'!$AH:$AH,,0)) -> 0 | O4: =AVERAGEIF(C4:N4,">0") -> 9835.732 | P4: 2021 | Q4: HLMA
A5: 2 | B5: South Africa | C5: =ESA_USD!C5/(_xlfn.XLOOKUP($B5,'PPP conversion factor'!$A:$A,'PPP conversion factor'!$AH:$AH,,0)) -> 112170.17 | D5: =ESA_USD!D5/(_xlfn.XLOOKUP($B5,'PPP conversion factor'!$A:$A,'PPP conversion factor'!$AH:$AH,,0)) -> 148843.34 | E5: =ESA_USD!E5/(_xlfn.XLOOKUP($B5,'PPP conversion factor'!$A:$A,'PPP conversion factor'!$AH:$AH,,0)) -> 52753.429 | F5: =ESA_USD!F5/(_xlfn.XLOOKUP($B5,'PPP conversion factor'!$A:$A,'PPP conversion factor'!$AH:$AH,,0)) -> 52753.429 | G5: =ESA_USD!G5/(_xlfn.XLOOKUP($B5,'PPP conversion factor'!$A:$A,'PPP conversion factor'!$AH:$AH,,0)) -> 0 | H5: =ESA_USD!H5/(_xlfn.XLOOKUP($B5,'PPP conversion factor'!$A:$A,'PPP conversion factor'!$AH:$AH,,0)) -> 88394.401 | I5: =ESA_USD!I5/(_xlfn.XLOOKUP($B5,'PPP conversion factor'!$A:$A,'PPP conversion factor'!$AH:$AH,,0)) -> 0 | J5: =ESA_USD!J5/(_xlfn.XLOOKUP($B5,'PPP conversion factor'!$A:$A,'PPP conversion factor'!$AH:$AH,,0)) -> 62398.064 | ... N5: =ESA_USD!N5/(_xlfn.XLOOKUP($B5,'PPP conversion factor'!$A:$A,'PPP conversion factor'!$AH:$AH,,0)) -> 0 | O5: =AVERAGEIF(C5:N5,">0") -> 73063.645 | P5: 2020 | Q5: HLMA
A6: 3 | B6: Kenya | C6: =ESA_USD!C6/(_xlfn.XLOOKUP($B6,'PPP conversion factor'!$A:$A,'PPP conversion factor'!$AH:$AH,,0)) -> 95124.214 | D6: =ESA_USD!D6/(_xlfn.XLOOKUP($B6,'PPP conversion factor'!$A:$A,'PPP conversion factor'!$AH:$AH,,0)) -> 123621.5 | E6: =ESA_USD!E6/(_xlfn.XLOOKUP($B6,'PPP conversion factor'!$A:$A,'PPP conversion factor'!$AH:$AH,,0)) -> 29794.271 | F6: =ESA_USD!F6/(_xlfn.XLOOKUP($B6,'PPP conversion factor'!$A:$A,'PPP conversion factor'!$AH:$AH,,0)) -> 29794.271 | G6: =ESA_USD!G6/(_xlfn.XLOOKUP($B6,'PPP conversion factor'!$A:$A,'PPP conversion factor'!$AH:$AH,,0)) -> 95124.214 | H6: =ESA_USD!H6/(_xlfn.XLOOKUP($B6,'PPP conversion factor'!$A:$A,'PPP conversion factor'!$AH:$AH,,0)) -> 81322.096 | I6: =ESA_USD!I6/(_xlfn.XLOOKUP($B6,'PPP conversion factor'!$A:$A,'PPP conversion factor'!$AH:$AH,,0)) -> 24426.417 | J6: =ESA_USD!J6/(_xlfn.XLOOKUP($B6,'PPP conversion factor'!$A:$A,'PPP conversion factor'!$AH:$AH,,0)) -> 0 | ... N6: =ESA_USD!N6/(_xlfn.XLOOKUP($B6,'PPP conversion factor'!$A:$A,'PPP conversion factor'!$AH:$AH,,0)) -> 29803.208 | O6: =AVERAGEIF(C6:N6,">0") -> 53403.238 | P6: 2019 | Q6: NHWA
A7: 4 | B7: Namibia | C7: =ESA_USD!C7/(_xlfn.XLOOKUP($B7,'PPP conversion factor'!$A:$A,'PPP conversion factor'!$AH:$AH,,0)) -> 105612.21 | D7: =ESA_USD!D7/(_xlfn.XLOOKUP($B7,'PPP conversion factor'!$A:$A,'PPP conversion factor'!$AH:$AH,,0)) -> 113171.12 | E7: =ESA_USD!E7/(_xlfn.XLOOKUP($B7,'PPP conversion factor'!$A:$A,'PPP conversion factor'!$AH:$AH,,0)) -> 79791.63 | F7: =ESA_USD!F7/(_xlfn.XLOOKUP($B7,'PPP conversion factor'!$A:$A,'PPP conversion factor'!$AH:$AH,,0)) -> 79791.63 | G7: =ESA_USD!G7/(_xlfn.XLOOKUP($B7,'PPP conversion factor'!$A:$A,'PPP conversion factor'!$AH:$AH,,0)) -> 102399.56 | H7: =ESA_USD!H7/(_xlfn.XLOOKUP($B7,'PPP conversion factor'!$A:$A,'PPP conversion factor'!$AH:$AH,,0)) -> 71997.148 | I7: =ESA_USD!I7/(_xlfn.XLOOKUP($B7,'PPP conversion factor'!$A:$A,'PPP conversion factor'!$AH:$AH,,0)) -> 0 | J7: =ESA_USD!J7/(_xlfn.XLOOKUP($B7,'PPP conversion factor'!$A:$A,'PPP conversion factor'!$AH:$AH,,0)) -> 46540.189 | ... N7: =ESA_USD!N7/(_xlfn.XLOOKUP($B7,'PPP conversion factor'!$A:$A,'PPP conversion factor'!$AH:$AH,,0)) -> 0 | O7: =AVERAGEIF(C7:N7,">0") -> 74192.816 | P7: 2019 | Q7: HLMA
A8: 5 | B8: Lesotho | C8: =ESA_USD!C8/(_xlfn.XLOOKUP($B8,'PPP conversion factor'!$A:$A,'PPP conversion factor'!$AH:$AH,,0)) -> 54839.551 | D8: =ESA_USD!D8/(_xlfn.XLOOKUP($B8,'PPP conversion factor'!$A:$A,'PPP conversion factor'!$AH:$AH,,0)) -> 64845.54 | E8: =ESA_USD!E8/(_xlfn.XLOOKUP($B8,'PPP conversion factor'!$A:$A,'PPP conversion factor'!$AH:$AH,,0)) -> 18834.077 | F8: =ESA_USD!F8/(_xlfn.XLOOKUP($B8,'PPP conversion factor'!$A:$A,'PPP conversion factor'!$AH:$AH,,0)) -> 18834.077 | G8: =ESA_USD!G8/(_xlfn.XLOOKUP($B8,'PPP conversion factor'!$A:$A,'PPP conversion factor'!$AH:$AH,,0)) -> 54839.551 | H8: =ESA_USD!H8/(_xlfn.XLOOKUP($B8,'PPP conversion factor'!$A:$A,'PPP conversion factor'!$AH:$AH,,0)) -> 34325.307 | I8: =ESA_USD!I8/(_xlfn.XLOOKUP($B8,'PPP conversion factor'!$A:$A,'PPP conversion factor'!$AH:$AH,,0)) -> 23294.697 | J8: =ESA_USD!J8/(_xlfn.XLOOKUP($B8,'PPP conversion factor'!$A:$A,'PPP conversion factor'!$AH:$AH,,0)) -> 23294.697 | ... N8: =ESA_USD!N8/(_xlfn.XLOOKUP($B8,'PPP conversion factor'!$A:$A,'PPP conversion factor'!$AH:$AH,,0)) -> 0 | O8: =AVERAGEIF(C8:N8,">0") -> 31262.189 | P8: 2020 | Q8: HLMA
A9: 6 | B9: Ethiopia | C9: =ESA_USD!C9/(_xlfn.XLOOKUP($B9,'PPP conversion factor'!$A:$A,'PPP conversion factor'!$AH:$AH,,0)) -> 11726.995 | D9: =ESA_USD!D9/(_xlfn.XLOOKUP($B9,'PPP conversion factor'!$A:$A,'PPP conversion factor'!$AH:$AH,,0)) -> 14533.386 | E9: =ESA_USD!E9/(_xlfn.XLOOKUP($B9,'PPP conversion factor'!$A:$A,'PPP conversion factor'!$AH:$AH,,0)) -> 8169.614 | F9: =ESA_USD!F9/(_xlfn.XLOOKUP($B9,'PPP conversion factor'!$A:$A,'PPP conversion factor'!$AH:$AH,,0)) -> 10463.021 | G9: =ESA_USD!G9/(_xlfn.XLOOKUP($B9,'PPP conversion factor'!$A:$A,'PPP conversion factor'!$AH:$AH,,0)) -> 11726.995 | H9: =ESA_USD!H9/(_xlfn.XLOOKUP($B9,'PPP conversion factor'!$A:$A,'PPP conversion factor'!$AH:$AH,,0)) -> 10463.021 | I9: =ESA_USD!I9/(_xlfn.XLOOKUP($B9,'PPP conversion factor'!$A:$A,'PPP conversion factor'!$AH:$AH,,0)) -> 8169.614 | J9: =ESA_USD!J9/(_xlfn.XLOOKUP($B9,'PPP conversion factor'!$A:$A,'PPP conversion factor'!$AH:$AH,,0)) -> 10463.021 | ... N9: =ESA_USD!N9/(_xlfn.XLOOKUP($B9,'PPP conversion factor'!$A:$A,'PPP conversion factor'!$AH:$AH,,0)) -> 10463.014 | O9: =AVERAGEIF(C9:N9,">0") -> 10136.681 | P9: 2019 | Q9: HLMA
A10: 7 | B10: Sierra Leone | C10: =ESA_USD!C10/(_xlfn.XLOOKUP($B10,'PPP conversion factor'!$A:$A,'PPP conversion factor'!$AH:$AH,,0)) -> 33533.188 | D10: =ESA_USD!D10/(_xlfn.XLOOKUP($B10,'PPP conversion factor'!$A:$A,'PPP conversion factor'!$AH:$AH,,0)) -> 101885.31 | E10: =ESA_USD!E10/(_xlfn.XLOOKUP($B10,'PPP conversion factor'!$A:$A,'PPP conversion factor'!$AH:$AH,,0)) -> 15969.844 | F10: =ESA_USD!F10/(_xlfn.XLOOKUP($B10,'PPP conversion factor'!$A:$A,'PPP conversion factor'!$AH:$AH,,0)) -> 15969.844 | G10: =ESA_USD!G10/(_xlfn.XLOOKUP($B10,'PPP conversion factor'!$A:$A,'PPP conversion factor'!$AH:$AH,,0)) -> 83615.222 | H10: =ESA_USD!H10/(_xlfn.XLOOKUP($B10,'PPP conversion factor'!$A:$A,'PPP conversion factor'!$AH:$AH,,0)) -> 36799.408 | I10: =ESA_USD!I10/(_xlfn.XLOOKUP($B10,'PPP conversion factor'!$A:$A,'PPP conversion factor'!$AH:$AH,,0)) -> 17565.003 | J10: =ESA_USD!J10/(_xlfn.XLOOKUP($B10,'PPP conversion factor'!$A:$A,'PPP conversion factor'!$AH:$AH,,0)) -> 26274.922 | ... N10: =ESA_USD!N10/(_xlfn.XLOOKUP($B10,'PPP conversion factor'!$A:$A,'PPP conversion factor'!$AH:$AH,,0)) -> 22683.436 | O10: =AVERAGEIF(C10:N10,">0") -> 31414.777 | P10: 2019 | Q10: HLMA
A11: 8 | B11: Rwanda | C11: =ESA_USD!C11/(_xlfn.XLOOKUP($B11,'PPP conversion factor'!$A:$A,'PPP conversion factor'!$AH:$AH,,0)) -> 32253.632 | D11: =ESA_USD!D11/(_xlfn.XLOOKUP($B11,'PPP conversion factor'!$A:$A,'PPP conversion factor'!$AH:$AH,,0)) -> 52970.7 | E11: =ESA_USD!E11/(_xlfn.XLOOKUP($B11,'PPP conversion factor'!$A:$A,'PPP conversion factor'!$AH:$AH,,0)) -> 13372.825 | F11: =ESA_USD!F11/(_xlfn.XLOOKUP($B11,'PPP conversion factor'!$A:$A,'PPP conversion factor'!$AH:$AH,,0)) -> 13405.162 | G11: =ESA_USD!G11/(_xlfn.XLOOKUP($B11,'PPP conversion factor'!$A:$A,'PPP conversion factor'!$AH:$AH,,0)) -> 13372.825 | H11: =ESA_USD!H11/(_xlfn.XLOOKUP($B11,'PPP conversion factor'!$A:$A,'PPP conversion factor'!$AH:$AH,,0)) -> 22220.071 | I11: =ESA_USD!I11/(_xlfn.XLOOKUP($B11,'PPP conversion factor'!$A:$A,'PPP conversion factor'!$AH:$AH,,0)) -> 13372.825 | J11: =ESA_USD!J11/(_xlfn.XLOOKUP($B11,'PPP conversion factor'!$A:$A,'PPP conversion factor'!$AH:$AH,,0)) -> 0 | ... N11: =ESA_USD!N11/(_xlfn.XLOOKUP($B11,'PPP conversion factor'!$A:$A,'PPP conversion factor'!$AH:$AH,,0)) -> 13372.825 | O11: =AVERAGEIF(C11:N11,">0") -> 20108.651 | P11: 2019 | Q11: HLMA
