Workbook
Name _R²_Impact: Model_2!$AB$3
Name _R²_Impact: Model_3!$AB$3
Name _R²_Impact: Model_1!$AA$3
Name _R²_Outcome: Model_2!$U$3
Name _R²_Outcome: Model_3!$U$3
Name _R²_Outcome: Model_1!$T$3
Name _R²_Output: Model_2!$O$3
Name _R²_Output: Model_3!$O$3
Name _R²_Output: Model_1!$N$3
Name coef1_Dentists: 'Coef.'!$G$4
Name coef1_Medical_and_Pathology_Laboratory_Scientists: 'Coef.'!$I$4
Name coef1_Medical_and_Pathology_Laboratory_Technicians: 'Coef.'!$J$4
Name coef1_Medical_Doctors: 'Coef.'!$D$4
Name coef1_Midwifery_Personnel: 'Coef.'!$F$4
Name coef1_Nursing_Personnel: 'Coef.'!$E$4
Name coef1_Pharmacists: 'Coef.'!$H$4
Name GDP_per_capita_growth__annual: 'Coef.'!$D$10
Name HWF_In_service_training_coef.: Model_2!$K$3
Name HWF_In_service_training_coef.: Model_3!$K$3
Name HWF_In_service_training_coef.: Model_1!$J$3
Name Impact_1_Coef.: Model_2!$AC$3
Name Impact_1_Coef.: Model_3!$AC$3
Name Impact_1_Coef.: Model_1!$AB$3
Name Impact_2_Coef.: Model_2!$AD$3
Name Impact_2_Coef.: Model_3!$AD$3
Name Impact_2_Coef.: Model_1!$AC$3
Name Incentive: Model_2!$L$3
Name Incentive: Model_3!$L$3
Name Incentive: Model_1!$K$3
Name Input_1_coef.: Model_2!$D$3
Name Input_1_coef.: Model_3!$D$3
Name Input_1_coef.: Model_1!$D$3
Name Input_2_coef.: Model_2!$E$3
Name Input_2_coef.: Model_3!$E$3
Name Input_2_coef.: Model_1!$E$3
Name Input_3_coef.: Model_3!$F$3
Name Input_3_coef.: Model_2!$F$3
Name Outcome_1_Coef.: Model_2!$V$3
Name Outcome_1_Coef.: Model_3!$V$3
Name Outcome_1_Coef.: Model_1!$U$3
Name Outcome_2_Coef.: Model_2!$W$3
Name Outcome_2_Coef.: Model_3!$W$3
Name Outcome_2_Coef.: Model_1!$V$3
Name Outcome_3_Coef.: Model_2!$X$3
Name Outcome_3_Coef.: Model_3!$X$3
Name Outcome_3_Coef.: Model_1!$W$3
Name OUTcome1_DALYS_2021_Communicable__maternal__perinatal_and_nutritional_conditions_per_capita_2021: 'Coef.'!$D$8
Name OUTcome1_DALYS_2021_Injuries_per_capita_2021: 'Coef.'!$F$8
Name OUTcome1_DALYS_2021_Noncommunicable_diseases_per_capita__2021: 'Coef.'!$E$8
Name Output_1_Coef.: Model_2!$P$3
Name Output_1_Coef.: Model_3!$P$3
Name Output_1_Coef.: Model_1!$O$3
Name Output_2_Coef.: Model_2!$Q$3
Name Output_2_Coef.: Model_3!$Q$3
Name Output_2_Coef.: Model_1!$P$3
Name Output_3_Coef.: Model_2!$R$3
Name Output_3_Coef.: Model_3!$R$3
Name Output_3_Coef.: Model_1!$Q$3
Name OUTput1_SCI_Infectiousdiseases: 'Coef.'!$D$6
Name OUTput1_SCI_NCD: 'Coef.'!$E$6

Sheet SEM_HWF
A1: Country | B1: ISO | C1: Population_2023 | D1: Invest_1 | E1: Invest_2 | F1: Output_1 | G1: Output_2 | H1: Output_3 | I1: Output_4 | J1: SCI_Average | K1: DALYS_2021_All Causes per capita 2021 | L1: Outcome_1 | M1: Outcome_2 | N1: Outcome_3 | O1: Outcome_4 | P1: Outcome_5 | Q1: Impact_1 | R1: Impact_2 | S1: Impact_3 | T1: GDP_Growth_per_capita | U1: HR_1 | V1: HR_2 | W1: HR_3 | X1: HR_4 | Y1: HR_5 | Z1: HR_6 | AA1: HR_7 | AB1: HR_8 | AC1: DADLYs All | AD1: Outcome_1a | AE1: Outcome_2a | AF1: Outcome_3a | AG1: HR_1d | AH1: HR_2d | AI1: HR_3d | AJ1: HR_4d | AK1: HR_5d | AL1: HR_6d | AM1: HR_7d
A2: Algeria | B2: DZA | C2: 46053477 | D2: 61.01303 | E2: 0.13419182 | F2: 88.72 | G2: 82.21 | H2: 60.71 | I2: 68.12 | J2: 74.94 | K2: 0.25858507 | L2: 0.054826069 | M2: 0.17657851 | N2: 0.02400285 | O2: 0.262 | P2: 0.5866345 | Q2: 15545.11 | R2: 28.18 | S2: 37.36 | T2: 3.3 | U2: 16.39659 | V2: 22.750942 | W2: 2.0148316 | X2: 3.5224268 | Y2: 2.9622085 | Z2: 0.029530886 | AA2: 3.3087621 | AB2: 50.985293 | AC2: =K2*$C2 -> 11908741 | AD2: =L2*$C2 -> 2524931.1 | AE2: =M2*$C2 -> 8132054.4 | AF2: =N2*$C2 -> 1105414.7 | AG2: 75512 | AH2: 104776 | AI2: 9279 | AJ2: 16222 | AK2: 13642 | AL2: 136 | AM2: 15238
A3: Angola | B3: AGO | C3: 36148636 | D3: 18.553569 | E3: 2.4607173 | F3: 21.08 | G3: 36.07 | H3: 53.76 | I3: 44.51 | J3: 38.855 | K3: 0.55586603 | L3: 0.34291113 | M3: 0.16924787 | N3: 0.040767474 | O3: 0.291 | P3: 0.2930257 | Q3: 8866.691 | R3: 9.49 | S3: 45 | T3: 4.4239045 | U3: 2.4047934 | V3: 18.456575 | W3: 0.0091289752 | X3: 0.070265445 | Y3: 0.39669547 | Z3: 0.0035962629 | AA3: 0.004979441 | AB3: 21.346034 | AC3: =K3*$C3 -> 20093799 | AD3: =L3*$C3 -> 12395770 | AE3: =M3*$C3 -> 6118079.5 | AF3: =N3*$C3 -> 1473688.6 | AG3: 8693 | AH3: 66718 | AI3: 33 | AJ3: 254 | AK3: 1434 | AL3: 13 | AM3: 18
A4: Benin | B4: BEN | C4: 13124347 | D4: 10.88486 | E4: 2.8272298 | F4: 16.86 | G4: 47 | H4: 60.77 | I4: 42.82 | J4: 41.8625 | K4: 0.5415334 | L4: 0.32523931 | M4: 0.16627788 | N4: 0.047324915 | O4: 0.254 | P4: 0.3140346 | Q4: 3966.803 | R4: 4.16 | S4: 37.6 | T4: 7.4531157 | U4: 2.3178296 | V4: 4.7164251 | W4: 1.8484729 | X4: 0.050288216 | Y4: 0.32992118 | Z4: 0.5089777 | AA4: 1.2434904 | AB4: 11.015405 | AC4: =K4*$C4 -> 7107272.3 | AD4: =L4*$C4 -> 4268553.5 | AE4: =M4*$C4 -> 2182288.6 | AF4: =N4*$C4 -> 621108.6 | AG4: 3042 | AH4: 6190 | AI4: 2426 | AJ4: 66 | AK4: 433 | AL4: 668 | AM4: 1632
A5: Botswana | B5: BWA | C5: 2483754 | D5: 32.040541 | E5: 6.3942892 | F5: 43.33 | G5: 66.05 | H5: 60.17 | I5: 53.85 | J5: 55.85 | K5: 0.51046947 | L5: 0.29056739 | M5: 0.16281769 | N5: 0.03681854 | O5: 0.336 | P5: 0.3750613 | Q5: 16749.389 | R5: 23.79 | S5: 57.4 | T5: -2.9898688 | U5: 3.78862 | V5: 30.135835 | W5: 0 | X5: 0.35832856 | Y5: 0.5314536 | Z5: 0.60392454 | AA5: 1.2521369 | AB5: 36.670298 | AC5: =K5*$C5 -> 1267880.6 | AD5: =L5*$C5 -> 721697.91 | AE5: =M5*$C5 -> 404399.1 | AF5: =N5*$C5 -> 91448.197 | AG5: 941 | AH5: 7485 | AI5: 0 | AJ5: 89 | AK5: 132 | AL5: 150 | AM5: 311
A6: Burkina Faso | B6: BFA | C6: 22720842 | D6: 10.935549 | E6: 3.0043273 | F6: 14.92 | G6: 50.01 | H6: 54.76 | I6: 60.22 | J6: 44.9775 | K6: 0.53931546 | L6: 0.30772701 | M6: 0.16837414 | N6: 0.059056873 | O6: 0.298 | P6: 0.2846235 | Q6: 2508.528 | R6: 4.3 | S6: 0 | T6: 4.985103 | U6: 1.4625338 | V6: 5.994056 | W6: 3.6217848 | X6: 0.058536563 | Y6: 0.39655221 | Z6: 0.0026407472 | AA6: 0.48589749 | AB6: 12.022002 | AC6: =K6*$C6 -> 12253701 | AD6: =L6*$C6 -> 6991816.7 | AE6: =M6*$C6 -> 3825602.3 | AF6: =N6*$C6 -> 1341821.9 | AG6: 3323 | AH6: 13619 | AI6: 8229 | AJ6: 133 | AK6: 901 | AL6: 6 | AM6: 1104
A7: Burundi | B7: BDI | C7: 12999141 | D7: 9.4270121 | E7: 3.2873539 | F7: 13.85 | G7: 60.47 | H7: 59.39 | I7: 59.42 | J7: 48.2825 | K7: 0.46057153 | L7: 0.25291885 | M7: 0.15453908 | N7: 0.051080321 | O7: 0.221 | P7: 0.2583942 | Q7: 879.67 | R7: 0.9 | S7: 33.33 | T7: 3.4892317 | U7: 0.7985143 | V7: 8.3643988 | W7: 0.37156301 | X7: 0.010769942 | Y7: 0.095390919 | Z7: 0.98006476 | AA7: 0.70081554 | AB7: 11.321517 | AC7: =K7*$C7 -> 5987034.2 | AD7: =L7*$C7 -> 3287727.8 | AE7: =M7*$C7 -> 2008875.3 | AF7: =N7*$C7 -> 664000.29 | AG7: 1038 | AH7: 10873 | AI7: 483 | AJ7: 14 | AK7: 124 | AL7: 1274 | AM7: 911
A8: Cabo Verde | B8: CPV | C8: 573322 | D8: 24.528465 | F8: 66.2 | G8: 90.4 | H8: 56.77 | I8: 75.55 | J8: 72.23 | K8: 0.28416804 | L8: 0.064726853 | M8: 0.18145936 | N8: 0.034756189 | O8: 0.341 | P8: 0.5024222 | Q8: 10052.799 | R8: 11.35 | S8: 52.5 | T8: 7.2718815 | U8: 6.6454802 | V8: 16.378231 | W8: 0.45349734 | X8: 0.13953764 | Y8: 0.17442205 | Z8: 0.069768821 | AA8: 0.13953764 | AB8: 24.000474 | AC8: =K8*$C8 -> 162919.79 | AD8: =L8*$C8 -> 37109.329 | AE8: =M8*$C8 -> 104034.64 | AF8: =N8*$C8 -> 19926.488 | AG8: 381 | AH8: 939 | AI8: 26 | AJ8: 8 | AK8: 10 | AL8: 4 | AM8: 8
A9: Cameroon | B9: CMR | C9: 28608129 | D9: 7.6903691 | E9: 2.9013855 | F9: 28.28 | G9: 56.12 | H9: 49.14 | I9: 47.52 | J9: 45.265 | K9: 0.54981019 | L9: 0.32608299 | M9: 0.1751217 | N9: 0.042805912 | O9: 0.286 | P9: 0.3372569 | Q9: 4880.519 | R9: 6.23 | S9: 49 | T9: 3.6707428 | U9: 1.3150108 | V9: 5.7798257 | W9: 0.58479882 | X9: 0.11080767 | Y9: 0.2104297 | Z9: 0.10241844 | AA9: 0.083542688 | AB9: 8.1868339 | AC9: =K9*$C9 -> 15729041 | AD9: =L9*$C9 -> 9328624.2 | AE9: =M9*$C9 -> 5009904.3 | AF9: =N9*$C9 -> 1224597 | AG9: 3762 | AH9: 16535 | AI9: 1673 | AJ9: 317 | AK9: 602 | AL9: 293 | AM9: 239
A10: Central African Republic | B10: CAF | C10: 5119136 | D10: 10.510261 | E10: 0.072434098 | F10: 16.76 | G10: 38.69 | H10: 43.77 | I10: 38.17 | J10: 34.3475 | K10: 0.83557862 | L10: 0.58633456 | M10: 0.16570339 | N10: 0.07557031 | O10: 0.186 | P10: 0.1516031 | Q10: 1145.161 | R10: 1.57 | S10: 59.27 | T10: 1.5396325 | U10: 0.74817313 | V10: 7.3371756 | W10: 3.7057035 | X10: 0.0058603639 | Y10: 0.02539491 | Z10: 0.21878692 | AA10: 0.56064148 | AB10: 12.601736 | AC10: =K10*$C10 -> 4277440.6 | AD10: =L10*$C10 -> 3001526.3 | AE10: =M10*$C10 -> 848258.18 | AF10: =N10*$C10 -> 386854.7 | AG10: 383 | AH10: 3756 | AI10: 1897 | AJ10: 3 | AK10: 13 | AL10: 112 | AM10: 287
A11: Chad | B11: TCD | C11: 17921183 | D11: 3.9757716 | E11: 4.1133942 | F11: 10.76 | G11: 41.09 | H11: 58.54 | I11: 28.87 | J11: 34.815 | K11: 0.72291648 | L11: 0.50936099 | M11: 0.15067299 | N11: 0.056395953 | O11: 0.239 | P11: 0.2375145 | Q11: 2588.82 | R11: 3.29 | S11: 36.9 | T11: 3.6544511 | U11: 0.91567616 | V11: 1.3263633 | W11: 0.47150905 | X11: 0.0072539854 | Y11: 0.090953817 | Z11: 0.57362285 | AA11: 0.58478282 | AB11: 3.970162 | AC11: =K11*$C11 -> 12955518 | AD11: =L11*$C11 -> 9128351.6 | AE11: =M11*$C11 -> 2700238.2 | AF11: =N11*$C11 -> 1010682.2 | AG11: 1641 | AH11: 2377 | AI11: 845 | AJ11: 13 | AK11: 163 | AL11: 1028 | AM11: 1048
A12: Comoros | B12: COM | C12: 926492 | D12: 20.789889 | E12: 0.9298947 | F12: 37.44 | G12: 51.48 | H12: 56.05 | I12: 49.64 | J12: 48.6525 | K12: 0.3998434 | L12: 0.18043054 | M12: 0.17489083 | N12: 0.039609689 | O12: 0.249 | P12: 0.3180644 | Q12: 3392.316 | R12: 6.02 | S12: 55.92 | T12: 3.3887835 | U12: 3.8208641 | V12: 8.4728201 | W12: 6.3249332 | X12: 0.34538884 | Y12: 0.43173605 | Z12: 1.7377376 | AA12: 0.17269442 | AB12: 21.306174 | AC12: =K12*$C12 -> 370451.72 | AD12: =L12*$C12 -> 167167.45 | AE12: =M12*$C12 -> 162034.96 | AF12: =N12*$C12 -> 36698.06 | AG12: 354 | AH12: 785 | AI12: 586 | AJ12: 32 | AK12: 40 | AL12: 161 | AM12: 16
A13: Congo | B13: COG | C13: 5940746 | D13: 13.271803 | E13: 0.42558796 | F13: 28.57 | G13: 36.21 | H13: 52.47 | I13: 52.06 | J13: 42.3275 | K13: 0.45539965 | L13: 0.27170787 | M13: 0.15151453 | N13: 0.027856401 | O13: 0.263 | P13: 0.3395313 | Q13: 5622.161 | R13: 7.57 | S13: 41.9 | T13: 2.5796664 | U13: 1.7539885 | V13: 9.3809767 | W13: 2.0031154 | X13: 0.016832903 | Y13: 0.053865289 | Z13: 0.53865289 | AA13: 1.3079165 | AB13: 15.055348 | AC13: =K13*$C13 -> 2705413.6 | AD13: =L13*$C13 -> 1614147.4 | AE13: =M13*$C13 -> 900109.35 | AF13: =N13*$C13 -> 165487.8 | AG13: 1042 | AH13: 5573 | AI13: 1190 | AJ13: 10 | AK13: 32 | AL13: 320 | AM13: 777
A14: Côte d'Ivoire | B14: CIV | C14: 28444206 | D14: 10.770365 | E14: 1.395126 | F14: 19.16 | G14: 58.23 | H14: 58.65 | I14: 51.18 | J14: 46.805 | K14: 0.50783164 | L14: 0.2963126 | M14: 0.162066 | N14: 0.045583166 | O14: 0.312 | P14: 0.3432034 | Q14: 6726.072 | R14: 8.59 | S14: 45.6 | T14: 5.95 | U14: 1.8172418 | V14: 5.6475473 | W14: 3.040338 | X14: 0.14941532 | Y14: 0.42820671 | Z14: 0.17472803 | AA14: 0 | AB14: 11.257477 | AC14: =K14*$C14 -> 14444868 | AD14: =L14*$C14 -> 8428376.7 | AE14: =M14*$C14 -> 4609838.8 | AF14: =N14*$C14 -> 1296577 | AG14: 5169 | AH14: 16064 | AI14: 8648 | AJ14: 425 | AK14: 1218 | AL14: 497 | AM14: 0
A15: Democratic Republic of the Congo | B15: COD | C15: 98151951 | D15: 13.539167 | E15: 6.8932479 | F15: 24.44 | G15: 48.21 | H15: 59.59 | I15: 43.22 | J15: 43.865 | K15: 0.61083886 | L15: 0.39012943 | M15: 0.16891108 | N15: 0.047809794 | O15: 0.261 | P15: 0.290413 | Q15: 1592.477 | R15: 2.41 | S15: 41.64 | T15: 6.6759303 | U15: 2.1690858 | V15: 11.748722 | W15: 0.43728117 | X15: 0.045949163 | Y15: 0.09454728 | Z15: 0.29892427 | AA15: 0.29892427 | AB15: 15.093434 | AC15: =K15*$C15 -> 59955026 | AD15: =L15*$C15 -> 38291964 | AE15: =M15*$C15 -> 16578952 | AF15: =N15*$C15 -> 4692624.6 | AG15: 21290 | AH15: 115316 | AI15: 4292 | AJ15: 451 | AK15: 928 | AL15: 2934 | AM15: 2934
A16: Equatorial Guinea | B16: GNQ | C16: 1543389 | D16: 17.115684 | E16: 23.864221 | F16: 41.09 | G16: 43.59 | H16: 50.27 | I16: 48.65 | J16: 45.9 | K16: 0.58306554 | L16: 0.37725803 | M16: 0.17062504 | N16: 0.031497727 | O16: 0.174 | P16: 0.4242096 | Q16: 18565.41 | R16: 18.85 | S16: 50.2 | T16: 0.90724825 | U16: 1.7817932 | V16: 15.893595 | W16: 0.16846045 | X16: 0 | Y16: 0.090709471 | Z16: 0.86821922 | AA16: 1.4772685 | AB16: 20.280046 | AC16: =K16*$C16 -> 899896.94 | AD16: =L16*$C16 -> 582255.9 | AE16: =M16*$C16 -> 263340.81 | AF16: =N16*$C16 -> 48613.246 | AG16: 275 | AH16: 2453 | AI16: 26 | AJ16: 0 | AK16: 14 | AL16: 134 | AM16: 228
A17: Eritrea | B17: ERI | C17: 3727656 | D17: 14.517287 | E17: 2.6869969 | F17: 35.7 | G17: 36.43 | H17: 60.09 | I17: 51.96 | J17: 46.045 | K17: 0.43861377 | L17: 0.18328273 | M17: 0.20161049 | N17: 0.049832601 | O17: 0.214 | P17: 0.2559651 | Q17: 650 | R17: 2.78 | S17: 0 | U17: 0.80211264 | V17: 13.933689 | W17: 0.17973762 | X17: 0.17973762 | Y17: 0.61432707 | Z17: 0.91210133 | AA17: 0.82357385 | AB17: 17.445279 | AC17: =K17*$C17 -> 1635001.2 | AD17: =L17*$C17 -> 683214.95 | AE17: =M17*$C17 -> 751534.57 | AF17: =N17*$C17 -> 185758.79 | AG17: 299 | AH17: 5194 | AI17: 67 | AJ17: 67 | AK17: 229 | AL17: 340 | AM17: 307
A18: Eswatini | B18: SWZ | C18: 1197512 | D18: 43.650798 | E18: 4.3127443 | F18: 32.98 | G18: 65.08 | H18: 62 | I18: 73.19 | J18: 58.3125 | K18: 0.71206086 | L18: 0.38181597 | M18: 0.23565534 | N18: 0.07556241 | O18: 0.293 | P18: 0.3252324 | Q18: 11315.553 | R18: 24.95 | S18: 63.7 | T18: 2.6407046 | U18: 5.7201932 | V18: 43.774092 | W18: 0 | X18: 0.29227265 | Y18: 0.35072717 | Z18: 0 | AA18: 0 | AB18: 50.137285 | AC18: =K18*$C18 -> 852701.43 | AD18: =L18*$C18 -> 457229.21 | AE18: =M18*$C18 -> 282200.1 | AF18: =N18*$C18 -> 90486.892 | AG18: 685 | AH18: 5242 | AI18: 0 | AJ18: 35 | AK18: 42 | AL18: 0 | AM18: 0
A19: Ethiopia | B19: ETH | C19: 123771387 | D19: 17.313519 | E19: 1.864483 | F19: 20.87 | G19: 29.04 | H19: 52.49 | I19: 47.93 | J19: 37.5825 | K19: 0.38864963 | L19: 0.20396758 | M19: 0.13963053 | N19: 0.041155729 | O19: 0.378 | P19: 0.3120527 | Q19: 3591.681 | R19: 4.7 | S19: 30.98 | T19: 7.3166911 | U19: 1.4876621 | V19: 10.605197 | W19: 1.7770666 | X19: 0.28455688 | Y19: 1.5290287 | Z19: 1.9194259 | AA19: 1.7550098 | AB19: 19.357947 | AC19: =K19*$C19 -> 48103704 | AD19: =L19*$C19 -> 25245350 | AE19: =M19*$C19 -> 17282264 | AF19: =N19*$C19 -> 5093901.6 | AG19: 18413 | AH19: 131262 | AI19: 21995 | AJ19: 3522 | AK19: 18925 | AL19: 23757 | AM19: 21722
A20: Gabon | B20: GAB | C20: 2383905 | D20: 30.40605 | E20: 1.3004665 | F20: 48.48 | G20: 34.37 | H20: 53.8 | I20: 64.17 | J20: 50.205 | K20: 0.44235278 | L20: 0.24190195 | M20: 0.1657311 | N20: 0.03146404 | O20: 0.218 | P20: 0.3962385 | Q20: 21218.077 | R20: 34.92 | S20: 69 | T20: 3.3839076 | U20: 5.3106143 | V20: 20.281848 | W20: 3.8801882 | X20: 0.18457111 | Y20: 0.78442723 | Z20: 1.0780631 | AA20: 1.0612839 | AB20: 32.580996 | AC20: =K20*$C20 -> 1054527 | AD20: =L20*$C20 -> 576671.27 | AE20: =M20*$C20 -> 395087.19 | AF20: =N20*$C20 -> 75007.281 | AG20: 1266 | AH20: 4835 | AI20: 925 | AJ20: 44 | AK20: 187 | AL20: 257 | AM20: 253
A21: Gambia | B21: GMB | C21: 2631251 | D21: 7.5746518 | E21: 1.3278116 | F21: 28.12 | G21: 43.85 | H21: 57.74 | I21: 63.72 | J21: 48.3575 | K21: 0.43458985 | L21: 0.23410545 | M21: 0.15868965 | N21: 0.036390079 | O21: 0.287 | P21: 0.3467981 | Q21: 3073.541 | R21: 5.97 | S21: 67.2 | T21: 5.7467177 | U21: 0.91971461 | V21: 5.111637 | W21: 1.6304032 | X21: 0.034204263 | Y21: 0.038004736 | Z21: 0.19382415 | AA21: 0.67268383 | AB21: 8.6004718 | AC21: =K21*$C21 -> 1143515 | AD21: =L21*$C21 -> 615990.19 | AE21: =M21*$C21 -> 417552.31 | AF21: =N21*$C21 -> 95751.431 | AG21: 242 | AH21: 1345 | AI21: 429 | AJ21: 9 | AK21: 10 | AL21: 51 | AM21: 177
A22: Ghana | B22: GHA | C22: 33062741 | D22: 40.416607 | E22: 15.163718 | F22: 25.98 | G22: 41.42 | H22: 70.51 | I22: 68.74 | J22: 51.6625 | K22: 0.40610834 | L22: 0.19130623 | M22: 0.17586458 | N22: 0.035717695 | O22: 0.343 | P22: 0.3605526 | Q22: 7061.935 | R22: 10.84 | S22: 47.5 | T22: 5.6848726 | U22: 2.7151409 | V22: 34.116954 | W22: 7.8807743 | X22: 0.073799084 | Y22: 1.7348834 | Z22: 0.8105801 | AA22: 1.13209 | AB22: 48.464221 | AC22: =K22*$C22 -> 13427055 | AD22: =L22*$C22 -> 6325108.3 | AE22: =M22*$C22 -> 5814565.1 | AF22: =N22*$C22 -> 1180924.9 | AG22: 8977 | AH22: 112800 | AI22: 26056 | AJ22: 244 | AK22: 5736 | AL22: 2680 | AM22: 3743
A23: Guinea | B23: GIN | C23: 14238716 | D23: 7.1826172 | E23: 2.7373714 | F23: 18.03 | G23: 47.87 | H23: 58.4 | I23: 50.42 | J23: 43.68 | K23: 0.62038058 | L23: 0.39821246 | M23: 0.16588447 | N23: 0.053108951 | O23: 0.268 | P23: 0.2568856 | Q23: 3895.767 | R23: 6.82 | S23: 68.5 | T23: 5.6685239 | U23: 2.0690068 | V23: 3.5248965 | W23: 0.62716329 | X23: 0.02739011 | Y23: 0.17908918 | Z23: 0.1271182 | AA23: 0.22263243 | AB23: 6.7772965 | AC23: =K23*$C23 -> 8833422.9 | AD23: =L23*$C23 -> 5670034.2 | AE23: =M23*$C23 -> 2361981.9 | AF23: =N23*$C23 -> 756203.27 | AG23: 2946 | AH23: 5019 | AI23: 893 | AJ23: 39 | AK23: 255 | AL23: 181 | AM23: 317
A24: Guinea-Bissau | B24: GNB | C24: 2111612 | D24: 12.653132 | E24: 0.1256791 | F24: 17.33 | G24: 29.95 | H24: 61.51 | I24: 60.3 | J24: 42.2725 | K24: 0.59333548 | L24: 0.36455418 | M24: 0.17227405 | N24: 0.049926094 | O24: 0.214 | P24: 0.2426292 | Q24: 2729.159 | R24: 3.06 | S24: 55.76 | T24: 4.813486 | U24: 2.5146665 | V24: 8.9126222 | W24: 0.96135085 | X24: 0.099450088 | Y24: 0.009471437 | Z24: 0.0047357185 | AA24: 0.80980786 | AB24: 13.312105 | AC24: =K24*$C24 -> 1252894.3 | AD24: =L24*$C24 -> 769796.98 | AE24: =M24*$C24 -> 363775.96 | AF24: =N24*$C24 -> 105424.54 | AG24: 531 | AH24: 1882 | AI24: 203 | AJ24: 21 | AK24: 2 | AL24: 1 | AM24: 171
A25: Kenya | B25: KEN | C25: 57458890 | D25: 23.42452 | E25: 0.84095736 | F25: 40.62 | G25: 53.15 | H25: 50.91 | I25: 73.63 | J25: 54.5775 | K25: 0.35501401 | L25: 0.18481356 | M25: 0.1352383 | N25: 0.031453024 | O25: 0.388 | P25: 0.3336342 | Q25: 6267.148 | R25: 7.39 | S25: 50 | T25: 4.4964983 | U25: 2.7835553 | V25: 21.841529 | W25: 0.04820838 | X25: 0.23390636 | Y25: 0.20640844 | Z25: 1.7403747 | AA25: 0.14549533 | AB25: 26.999477 | AC25: =K25*$C25 -> 20398711 | AD25: =L25*$C25 -> 10619182 | AE25: =M25*$C25 -> 7770642.9 | AF25: =N25*$C25 -> 1807255.9 | AG25: 15994 | AH25: 125499 | AI25: 277 | AJ25: 1344 | AK25: 1186 | AL25: 10000 | AM25: 836
A26: Lesotho | B26: LSO | C26: 2192400 | D26: 23.526334 | E26: 4.2294499 | F26: 32.27 | G26: 50.71 | H26: 65.78 | I26: 74.68 | J26: 55.86 | K26: 0.8061546 | L26: 0.46635144 | M26: 0.24303601 | N26: 0.084683657 | O26: 0.309 | P26: 0.2633865 | Q26: 2891.054 | R26: 3.19 | S26: 56.01 | T26: 2.7622382 | U26: 2.4493706 | V26: 5.6330962 | W26: 12.675607 | X26: 0.38314176 | Y26: 1.1722313 | Z26: 1.897464 | AA26: 1.2452107 | AB26: 25.456121 | AC26: =K26*$C26 -> 1767413.3 | AD26: =L26*$C26 -> 1022428.9 | AE26: =M26*$C26 -> 532832.14 | AF26: =N26*$C26 -> 185660.45 | AG26: 537 | AH26: 1235 | AI26: 2779 | AJ26: 84 | AK26: 257 | AL26: 416 | AM26: 273
A27: Liberia | B27: LBR | C27: 5432272 | D27: 11.11493 | E27: 0.55403733 | F27: 29.07 | G27: 42.02 | H27: 53.05 | I27: 61.65 | J27: 46.4475 | K27: 0.53500919 | L27: 0.33742173 | M27: 0.15837177 | N27: 0.037012274 | O27: 0.357 | P27: 0.3573526 | Q27: 1670.302 | R27: 1.53 | S27: 43 | T27: 4.7929148 | U27: 1.7561713 | V27: 8.1439221 | W27: 1.820601 | X27: 0.014726803 | Y27: 0.31294457 | Z27: 0.21169779 | AA27: 0 | AB27: 12.260064 | AC27: =K27*$C27 -> 2906315.5 | AD27: =L27*$C27 -> 1832966.6 | AE27: =M27*$C27 -> 860318.51 | AF27: =N27*$C27 -> 201060.74 | AG27: 954 | AH27: 4424 | AI27: 989 | AJ27: 8 | AK27: 170 | AL27: 115 | AM27: 0
A28: Madagascar | B28: MDG | C28: 29942591 | D28: 5.5460292 | E28: 2.0891931 | F28: 18.98 | G28: 29.47 | H28: 45.77 | I28: 58.24 | J28: 38.115 | K28: 0.50996008 | L28: 0.28997474 | M28: 0.17565736 | N28: 0.039462753 | O28: 0.304 | P28: 0.2901793 | Q28: 1731.305 | R28: 1.89 | S28: 56.2 | T28: 4.2 | U28: 1.7466758 | V28: 1.5229143 | W28: 1.3338859 | X28: 0.083827081 | Y28: 0.010019173 | Z28: 0.10219556 | AA28: 0.10219556 | AB28: 4.9017134 | AC28: =K28*$C28 -> 15269526 | AD28: =L28*$C28 -> 8682595 | AE28: =M28*$C28 -> 5259636.4 | AF28: =N28*$C28 -> 1181617.1 | AG28: 5230 | AH28: 4560 | AI28: 3994 | AJ28: 251 | AK28: 30 | AL28: 306 | AM28: 306
A29: Malawi | B29: MWI | C29: 20728157 | D29: 5.0174021 | E29: 0.71150071 | F29: 22.25 | G29: 57.77 | H29: 58.77 | I29: 71.89 | J29: 52.67 | K29: 0.44481134 | L29: 0.24303618 | M29: 0.16367847 | N29: 0.033520622 | O29: 0.285 | P29: 0.2989006 | Q29: 1514.554 | R29: 2.77 | S29: 47 | T29: 1.82685 | U29: 0.53791565 | V29: 4.7370347 | W29: 0.2971803 | X29: 0.048725991 | Y29: 0.059339574 | Z29: 0.0434192 | AA29: 0.10082903 | AB29: 5.8244445 | AC29: =K29*$C29 -> 9220119.3 | AD29: =L29*$C29 -> 5037692 | AE29: =M29*$C29 -> 3392753 | AF29: =N29*$C29 -> 694820.71 | AG29: 1115 | AH29: 9819 | AI29: 616 | AJ29: 101 | AK29: 123 | AL29: 90 | AM29: 209
A30: Mali | B30: MLI | C30: 22105727 | D30: 8.1755817 | F30: 15.25 | G30: 59.37 | H30: 67.76 | I30: 47.33 | J30: 47.4275 | K30: 0.63970272 | L30: 0.42599321 | M30: 0.15654856 | N30: 0.053925055 | O30: 0.29 | P30: 0.2959361 | Q30: 2472.828 | R30: 2.99 | S30: 36.5 | T30: 5.0045459 | U30: 2.0157672 | V30: 2.8811538 | W30: 1.4756357 | X30: 0.013571144 | Y30: 0.77853128 | Z30: 0.6767477 | AA30: 0 | AB30: 7.8414069 | AC30: =K30*$C30 -> 14141094 | AD30: =L30*$C30 -> 9416889.6 | AE30: =M30*$C30 -> 3460619.7 | AF30: =N30*$C30 -> 1192052.5 | AG30: 4456 | AH30: 6369 | AI30: 3262 | AJ30: 30 | AK30: 1721 | AL30: 1496 | AM30: 0
A31: Mauritania | B31: MRT | C31: 5030233 | D31: 17.621923 | E31: 0.48384449 | F31: 22.04 | G31: 47.04 | H31: 60.5 | I31: 41.31 | J31: 42.7225 | K31: 0.35641087 | L31: 0.18769682 | M31: 0.13676512 | N31: 0.026374756 | O31: 0.262 | P31: 0.4214104 | Q31: 7258.253 | R31: 15.14 | S31: 76 | T31: 5.2 | U31: 2.5306979 | V31: 12.927831 | W31: 2.6658805 | X31: 0.29620894 | Y31: 0.19283401 | Z31: 0.64808131 | AA31: 0.017891815 | AB31: 19.279425 | AC31: =K31*$C31 -> 1792829.7 | AD31: =L31*$C31 -> 944158.72 | AE31: =M31*$C31 -> 687960.41 | AF31: =N31*$C31 -> 132671.17 | AG31: 1273 | AH31: 6503 | AI31: 1341 | AJ31: 149 | AK31: 97 | AL31: 326 | AM31: 9
A32: Mauritius | B32: MUS | C32: 1275657 | D32: 66.876465 | E32: 9.9309121 | F32: 77.61 | G32: 52.41 | H32: 61.3 | I32: 74.5 | J32: 66.455 | K32: 0.3804525 | L32: 0.056210978 | M32: 0.30203463 | N32: 0.022206883 | O32: 0.397 | P32: 0.5665122 | Q32: 27341.634 | R32: 32.83 | S32: 41.9 | T32: 4.6939032 | U32: 14.369066 | V32: 36.052011 | W32: 4.4447685 | X32: 3.2453865 | Y32: 0.32140301 | Z32: 2.4928331 | AA32: 2.0695218 | AB32: 62.99499 | AC32: =K32*$C32 -> 485326.89 | AD32: =L32*$C32 -> 71705.927 | AE32: =M32*$C32 -> 385292.6 | AF32: =N32*$C32 -> 28328.365 | AG32: 1833 | AH32: 4599 | AI32: 567 | AJ32: 414 | AK32: 41 | AL32: 318 | AM32: 264
A33: Mozambique | B33: MOZ | C33: 34034812 | D33: 10.86393 | E33: 1.0442801 | F33: 23.4 | G33: 57.76 | H33: 49.78 | I33: 55.67 | J33: 46.6525 | K33: 0.63336597 | L33: 0.40815361 | M33: 0.17392551 | N33: 0.043108831 | O33: 0.304 | P33: 0.2511178 | Q33: 1485.598 | R33: 2.43 | S33: 40 | T33: 1.851775 | U33: 1.6803384 | V33: 5.044247 | W33: 3.915109 | X33: 0.10753695 | Y33: 0.14749604 | Z33: 0.094902831 | AA33: 0.63199997 | AB33: 11.62163 | AC33: =K33*$C33 -> 21556492 | AD33: =L33*$C33 -> 13891431 | AE33: =M33*$C33 -> 5919522.2 | AF33: =N33*$C33 -> 1467201 | AG33: 5719 | AH33: 17168 | AI33: 13325 | AJ33: 366 | AK33: 502 | AL33: 323 | AM33: 2151
A34: Namibia | B34: NAM | C34: 2680497 | D34: 62.136352 | E34: 7.4922891 | F34: 55.5 | G34: 57.25 | H34: 64.71 | I34: 74.87 | J34: 63.0825 | K34: 0.53297666 | L34: 0.29762114 | M34: 0.16825145 | N34: 0.046707971 | O34: 0.303 | P34: 0.3993723 | Q34: 10419.859 | R34: 15.64 | S34: 70.1 | T34: 3.711545 | U34: 5.9578504 | V34: 58.041475 | W34: 0.02611456 | X34: 0.83566592 | Y34: 2.4435767 | Z34: 0.36187319 | AA34: 3.9731438 | AB34: 71.6397 | AC34: =K34*$C34 -> 1428642.3 | AD34: =L34*$C34 -> 797772.57 | AE34: =M34*$C34 -> 450997.51 | AF34: =N34*$C34 -> 125200.58 | AG34: 1597 | AH34: 15558 | AI34: 7 | AJ34: 224 | AK34: 655 | AL34: 97 | AM34: 1065
A35: Niger | B35: NER | C35: 27066230 | D35: 4.0944273 | E35: 0.54349922 | F35: 11.68 | G35: 49.68 | H35: 49.3 | I35: 52.36 | J35: 40.755 | K35: 0.74303883 | L35: 0.52283858 | M35: 0.15281919 | N35: 0.062854541 | O35: 0.287 | P35: 0.2645919 | Q35: 1747.635 | R35: 2.34 | S35: 29.2 | T35: 8.4215979 | U35: 0.3672473 | V35: 3.4278878 | W35: 0.63621716 | X35: 0.010344994 | Y35: 0.020689989 | Z35: 0.15960849 | AA35: 0.23978219 | AB35: 4.8617779 | AC35: =K35*$C35 -> 20111260 | AD35: =L35*$C35 -> 14151269 | AE35: =M35*$C35 -> 4136239.3 | AF35: =N35*$C35 -> 1701235.5 | AG35: 994 | AH35: 9278 | AI35: 1722 | AJ35: 28 | AK35: 56 | AL35: 432 | AM35: 649
A36: Nigeria | B36: NGA | C36: 222182400 | D36: 23.664466 | E36: 1.7813083 | F36: 14.08 | G36: 53.21 | H36: 62.66 | I36: 46.44 | J36: 44.0975 | K36: 0.60520175 | L36: 0.41661934 | M36: 0.14433402 | N36: 0.042283575 | O36: 0.38 | P36: 0.3161699 | Q36: 5789.016 | R36: 5.8 | S36: 46.8 | T36: 3.4264395 | U36: 3.8995888 | V36: 9.9324249 | W36: 6.6065989 | X36: 0.22720071 | Y36: 0.82261241 | Z36: 1.6577821 | AA36: 1.7423522 | AB36: 24.88856 | AC36: =K36*$C36 -> 1.3446518e+08 | AD36: =L36*$C36 -> 92565485 | AE36: =M36*$C36 -> 32068479 | AF36: =N36*$C36 -> 9394666.1 | AG36: 86642 | AH36: 220681 | AI36: 146787 | AJ36: 5048 | AK36: 18277 | AL36: 36833 | AM36: 38712
A37: Rwanda | B37: RWA | C37: 13924498 | D37: 11.403764 | E37: 0.69228833 | F37: 26.82 | G37: 70.06 | H37: 44.01 | I37: 67.2 | J37: 52.0225 | K37: 0.3827553 | L37: 0.16597404 | M37: 0.1730401 | N37: 0.040846173 | O37: 0.331 | P37: 0.3176267 | Q37: 3355.683 | R37: 6 | S37: 28.9 | T37: 8.8906553 | U37: 0.87830814 | V37: 9.6958612 | W37: 1.1433087 | X37: 0.1967755 | Y37: 0.058170858 | Z37: 0 | AA37: 1.3465476 | AB37: 13.318972 | AC37: =K37*$C37 -> 5329675.4 | AD37: =L37*$C37 -> 2311105.1 | AE37: =M37*$C37 -> 2409496.5 | AF37: =N37*$C37 -> 568762.46 | AG37: 1223 | AH37: 13501 | AI37: 1592 | AJ37: 274 | AK37: 81 | AL37: 0 | AM37: 1875
A38: Sao Tome and Principe | B38: STP | C38: 232132 | D38: 30.890154 | F38: 44.77 | G38: 53.47 | H38: 62.61 | I38: 79.7 | J38: 60.1375 | K38: 0.26640418 | L38: 0.085742941 | M38: 0.15520469 | N38: 0.021865647 | O38: 0.266 | P38: 0.4141126 | Q38: 5449.789 | R38: 16.63 | S38: 32.13 | T38: 0.9000006 | U38: 4.5232885 | V38: 18.954733 | W38: 2.1539469 | X38: 0.25847363 | Y38: 1.5939207 | Z38: 6.2895249 | AA38: 0 | AB38: 33.773887 | AC38: =K38*$C38 -> 61840.934 | AD38: =L38*$C38 -> 19903.68 | AE38: =M38*$C38 -> 36027.974 | AF38: =N38*$C38 -> 5075.7163 | AG38: 105 | AH38: 440 | AI38: 50 | AJ38: 6 | AK38: 37 | AL38: 146 | AM38: 0
A39: Senegal | B39: SEN | C39: 18116526 | D39: 5.7327207 | E39: 1.4601029 | F39: 30.05 | G39: 63.69 | H39: 55.65 | I39: 59.11 | J39: 52.125 | K39: 0.36508063 | L39: 0.16490721 | M39: 0.15800663 | N39: 0.036505767 | O39: 0.328 | P39: 0.3396112 | Q39: 4464.78 | R39: 6.73 | S39: 58.7 | T39: 6.8920074 | U39: 1.0890609 | V39: 2.6384749 | W39: 1.5952286 | X39: 0.10874049 | Y39: 0.20147351 | Z39: 0 | AA39: 0.14351537 | AB39: 5.7764938 | AC39: =K39*$C39 -> 6613992.8 | AD39: =L39*$C39 -> 2987545.8 | AE39: =M39*$C39 -> 2862531.2 | AF39: =N39*$C39 -> 661357.68 | AG39: 1973 | AH39: 4780 | AI39: 2890 | AJ39: 197 | AK39: 365 | AL39: 0 | AM39: 260
A40: Seychelles | B40: SYC | C40: 99912 | D40: 230.71805 | E40: 10.684803 | F40: 78.3 | G40: 87.12 | H40: 57.3 | I40: 79.13 | J40: 75.4625 | K40: 0.31209413 | L40: 0.067825983 | M40: 0.22109038 | N40: 0.023145292 | O40: 0.318 | P40: 0.52842651 | Q40: 35085.182 | S40: 46 | T40: 3.4656807 | U40: 82.872928 | V40: 62.555048 | W40: 31.22748 | X40: 4.4038754 | Y40: 5.4047562 | Z40: 1.0008808 | AA40: 2.1018496 | AB40: 189.56682 | AC40: =K40*$C40 -> 31181.949 | AD40: =L40*$C40 -> 6776.6296 | AE40: =M40*$C40 -> 22089.582 | AF40: =N40*$C40 -> 2312.4924 | AG40: 828 | AH40: 625 | AI40: 312 | AJ40: 44 | AK40: 54 | AL40: 10 | AM40: 21
A41: Sierra Leone | B41: SLE | C41: 8472212 | D41: 11.384249 | E41: 5.26334 | F41: 14.19 | G41: 50.54 | H41: 54.72 | I41: 72.06 | J41: 47.8775 | K41: 0.62214616 | L41: 0.39564769 | M41: 0.17921993 | N41: 0.04572357 | O41: 0.327 | P41: 0.3091938 | Q41: 2966.491 | R41: 2.63 | S41: 59 | T41: 4 | U41: 1.3054442 | V41: 8.6825023 | W41: 2.6805278 | X41: 0.017704939 | Y41: 0.10504931 | Z41: 0 | AA41: 0.35173813 | AB41: 13.142967 | AC41: =K41*$C41 -> 5270954.1 | AD41: =L41*$C41 -> 3352011.1 | AE41: =M41*$C41 -> 1518389.2 | AF41: =N41*$C41 -> 387379.77 | AG41: 1106 | AH41: 7356 | AI41: 2271 | AJ41: 15 | AK41: 89 | AL41: 0 | AM41: 298
A42: South Africa | B42: ZAF | C42: 61452696 | D42: 66.053003 | E42: 2.1852693 | F42: 79.53 | G42: 68.77 | H42: 60.66 | I42: 76.38 | J42: 71.335 | K42: 0.59898341 | L42: 0.27289034 | M42: 0.23352654 | N42: 0.066110009 | O42: 0.458 | P42: 0.4456413 | Q42: 13771.97 | R42: 21.64 | S42: 54 | T42: 0.57985369 | U42: 8.0603461 | V42: 64.645008 | W42: 0.25108744 | X42: 0.19039035 | Y42: 2.7385292 | Z42: 0.0021154483 | AA42: 0.18062674 | AB42: 76.068103 | AC42: =K42*$C42 -> 36809146 | AD42: =L42*$C42 -> 16769847 | AE42: =M42*$C42 -> 14350835 | AF42: =N42*$C42 -> 4062638.3 | AG42: 49533 | AH42: 397261 | AI42: 1543 | AJ42: 1170 | AK42: 16829 | AL42: 13 | AM42: 1110
A43: South Sudan | B43: SSD | C43: 11891023 | D43: 6.4682067 | E43: 1.0973402 | F43: 21.91 | G43: 35.58 | H43: 59.48 | I43: 29.42 | J43: 36.5975 | K43: 0.63690566 | L43: 0.41618333 | M43: 0.15884745 | N43: 0.057924879 | O43: 0.213 | P43: 0.291139 | Q43: 660.094 | R43: 3.35 | S43: 46.32 | U43: 0.38348256 | V43: 3.8095965 | W43: 2.596917 | X43: 0.026911057 | Y43: 0.13455529 | Z43: 0.53401629 | AA43: 0.22874399 | AB43: 7.7142227 | AC43: =K43*$C43 -> 7573459.8 | AD43: =L43*$C43 -> 4948845.6 | AE43: =M43*$C43 -> 1888858.6 | AF43: =N43*$C43 -> 688786.07 | AG43: 456 | AH43: 4530 | AI43: 3088 | AJ43: 32 | AK43: 160 | AL43: 635 | AM43: 272
A44: Togo | B44: UGA | C44: 49700758 | D44: 23.242417 | E44: 0.20829094 | F44: 22.84 | G44: 55.37 | H44: 56.9 | I44: 52.14 | J44: 46.8125 | K44: 0.39850537 | L44: 0.21625225 | M44: 0.13944238 | N44: 0.040092692 | O44: 0.278 | P44: 0.3235637 | Q44: 3240.979 | R44: 4.33 | S44: 40.1 | T44: 6.136452 | U44: 1.8213002 | V44: 14.928746 | W44: 6.631086 | X44: 0.1014069 | Y44: 0.34446155 | Z44: 0.75894215 | AA44: 2.6921119 | AB44: 27.278055 | AC44: =K44*$C44 -> 19806019 | AD44: =L44*$C44 -> 10747901 | AE44: =M44*$C44 -> 6930392.2 | AF44: =N44*$C44 -> 1992637.2 | AG44: 9052 | AH44: 74197 | AI44: 32957 | AJ44: 504 | AK44: 1712 | AL44: 3772 | AM44: 13380
A45: Uganda | B45: TZA | C45: 65136238 | D45: 9.0431618 | E45: 5.9479843 | F45: 27.27 | G45: 54.91 | H45: 54.5 | I45: 68.17 | J45: 51.2125 | K45: 0.40710628 | L45: 0.22733353 | M45: 0.14378753 | N45: 0.03339787 | O45: 0.365 | P45: 0.3246088 | Q45: 3638.147 | R45: 3.2 | S45: 41.2 | T45: 5.5263138 | U45: 1.3345874 | V45: 7.0860709 | W45: 0 | X45: 0.1159109 | Y45: 0.34727213 | Z45: 0.23826982 | AA45: 0.72816609 | AB45: 9.8502772 | AC45: =K45*$C45 -> 26517371 | AD45: =L45*$C45 -> 14807651 | AE45: =M45*$C45 -> 9365779 | AF45: =N45*$C45 -> 2175411.6 | AG45: 8693 | AH45: 46156 | AI45: 0 | AJ45: 755 | AK45: 2262 | AL45: 1552 | AM45: 4743
A46: United Republic of Tanzania | B46: TGO | C46: 8886635 | D46: 6.2109686 | E46: 9.350128 | F46: 19.6 | G46: 52.66 | H46: 50.72 | I46: 63.1 | J46: 46.52 | K46: 0.48252291 | L46: 0.25168432 | M46: 0.18194219 | N46: 0.045928544 | O46: 0.313 | P46: 0.3347842 | Q46: 2895.085 | R46: 3.7 | S46: 33.8 | T46: 5.3000053 | U46: 0.82145829 | V46: 2.9595004 | W46: 2.0975319 | X46: 0.024756277 | Y46: 0.28694776 | Z46: 0.14178595 | AA46: 0.46586813 | AB46: 6.7978487 | AC46: =K46*$C46 -> 4288005 | AD46: =L46*$C46 -> 2236626.7 | AE46: =M46*$C46 -> 1616853.8 | AF46: =N46*$C46 -> 408150.21 | AG46: 730 | AH46: 2630 | AI46: 1864 | AJ46: 22 | AK46: 255 | AL46: 126 | AM46: 414
A47: Zambia | B47: ZMB | C47: 20032801 | D47: 29.968206 | E47: 5.9489349 | F47: 37.54 | G47: 60.64 | H47: 57.47 | I47: 74.31 | J47: 57.49 | K47: 0.50513805 | L47: 0.30859836 | M47: 0.15379622 | N47: 0.036071447 | O47: 0.265 | P47: 0.3161706 | Q47: 3747.732 | R47: 5.23 | S47: 52.3 | T47: 4.0431483 | U47: 3.2601532 | V47: 24.946586 | W47: 4.5934665 | X47: 0.14126831 | Y47: 0.71133338 | Z47: 0.20915697 | AA47: 0.76524496 | AB47: 34.62721 | AC47: =K47*$C47 -> 10119330 | AD47: =L47*$C47 -> 6182089.6 | AE47: =M47*$C47 -> 3080969 | AF47: =N47*$C47 -> 722612.11 | AG47: 6531 | AH47: 49975 | AI47: 9202 | AJ47: 283 | AK47: 1425 | AL47: 419 | AM47: 1533
A48: Zimbabwe | B48: ZWE | C48: 15581023 | D48: 29.796679 | E48: 2.426871 | F48: 40.41 | G48: 47.83 | H48: 66.74 | I48: 71.16 | J48: 56.535 | K48: 0.55124774 | L48: 0.29968262 | M48: 0.1852836 | N48: 0.057561611 | O48: 0.324 | P48: 0.285771 | Q48: 4465.361 | R48: 4.5 | S48: 46 | T48: 2.0294841 | U48: 1.4260938 | V48: 29.867744 | W48: 1.8002669 | X48: 0.31576874 | Y48: 1.2207157 | Z48: 0.92997745 | AA48: 0.67710573 | AB48: 36.237672 | AC48: =K48*$C48 -> 8589003.8 | AD48: =L48*$C48 -> 4669361.7 | AE48: =M48*$C48 -> 2886908.1 | AF48: =N48*$C48 -> 896868.78 | AG48: 2222 | AH48: 46537 | AI48: 2805 | AJ48: 492 | AK48: 1902 | AL48: 1449 | AM48: 1055

Sheet Sheet5

Sheet Sheet1
D4: AGO | E4: Unit increase | I4: SCI | J4: Increased SCI | K4: DALYS Coef | L4: DALYS per capita
D5: 36148636 | E5: =D5/10000 -> 3614.8636 | F5: 21.08 | G5: 36.07 | H5: 53.76 | I5: =AVERAGE(F5:H5) -> 36.97 | J5: =I5*1.073 -> 39.66881 | K5: =-0.56 -> -0.56 | L5: 0.55586603 | M5: =L5*K5 -> -0.31128498 | N5: =M5*D5 -> -11252527

Sheet SEM_Vars_HWF
B2: varname | C2: variable definition
B3: Invest_1 | C3: Salary per capita
B4: Invest_2 | C4: Total core cadre training per capita
B5: Output_1 | C5: SCI_Infectious diseases
B6: Output_2 | C6: SCI_NCD
B7: Output_3 | C7: SCI_RMNCH
B8: Outcome_1 | C8: DALYS_2021_Communicable, maternal, perinatal and nutritional conditions per capita 2021
B9: Outcome_2 | C9: DALYS_2021_Noncommunicable diseases per capita (2021)
B10: Outcome_3 | C10: DALYS_2021_Injuries per capita 2021
B11: Outcome_4 | C11: Health_Security_Index_2021
B12: Outcome_5 | C12: HAQ
B13: Impact_1 | C13: GDP per capita growth (annual %) | D13: Gross domestic product is the total income earned through the production of goods and services in an economic territory during an accounting period. It can be measured in three different ways: using either the expenditure approach, the income approach, or the production approach. The core indicator has been divided by the general population to achieve a per capita estimate.This indicator denotes the percentage change over each previous year of the constant price (base year 2015) series in United States dollars.
B14: Impact_2 | C14: GDP growth (annual %) | D14: Gross domestic product is the total income earned through the production of goods and services in an economic territory during an accounting period. It can be measured in three different ways: using either the expenditure approach, the income approach, or the production approach. This indicator denotes the percentage change over each previous year of the constant price (base year 2015) series in United States dollars.
B15: Impact_3 | C15: GDP per capita, PPP (constant 2017 international $) | D15: This indicator provides values for gross domestic product (GDP) expressed in constant international dollars, converted by purchasing power parities (PPPs). PPPs account for the different price levels across countries and thus PPP-based comparisons of economic output are more appropriate for comparing the output of economies and the average material well-being of their inhabitants than exchange-rate based comparisons. Gross domestic product is the total income earned through the production of goods and services in an economic territory during an accounting period. It can be measured in three different ways: using either the expenditure approach, the income approach, or the production approach. The core indicator has been divided by the general population to achieve a per capita estimate. This indicator is expressed in constant prices, meaning the series has been adjusted to account for price changes over time. The reference year for this adjustment is 2021. The PPP conversion factor is a currency conversion factor and a spatial price deflator. PPPs convert different currencies to a common currency and, in the process of conversion, equalize their purchasing power by eliminating the differences in price levels between countries, thereby allowing volume or output comparisons of GDP and its expenditure components.
B16: HR_1 | C16: Density_2023_Medical Doctors
B17: HR_2 | C17: Density_2023_Nursing Personnel
B18: HR_3 | C18: Density_2023_Midwifery Personnel
B19: HR_4 | C19: Density_2023_Dentists
B20: HR_5 | C20: Density_2023_Pharmacists
B21: HR_6 | C21: Density_2023_Medical and Pathology Laboratory Scientists
B22: HR_7 | C22: Density_2023_Medical and Pathology Laboratory Technicians
B23: HR_8 | C23: Density_7_cadres_2023
A27: Construct | B27: Var_code | C27: Var_name
A28: HRH AVAILABILITY | B28: HR_1 | C28: Density_2023_Medical Doctors
B29: HR_2 | C29: Density_2023_Nursing Personnel
B30: HR_3 | C30: Density_2023_Midwifery Personnel
B31: HR_4 | C31: Density_2023_Dentists
B32: HR_5 | C32: Density_2023_Pharmacists
B33: HR_6 | C33: Density_2023_Medical and Pathology Laboratory Scientists
B34: HR_7 | C34: Density_2023_Medical and Pathology Laboratory Technicians
A35: OUTPUT | B35: Output_1 | C35: SCI_Infectious diseases
B36: Output_2 | C36: SCI_NCD
B37: Output_3 | C37: SCI_RMNCH
A38: OUTCOME | B38: Outcome_1 | C38: DALYS_2021_Communicable, maternal, perinatal and nutritional conditions per capita 2021
B39: Outcome_2 | C39: DALYS_2021_Noncommunicable diseases per capita (2021)
B40: Outcome_3 | C40: DALYS_2021_Injuries per capita 2021
A41: IMPACT | B41: Impact_1 | C41: GDP per capita growth (annual %)

Sheet SEM
A1: Country | B1: ISO | C1: Population_2023 | D1: Invest_1 | E1: Invest_2 | F1: Output_1 | G1: Output_2 | H1: Output_3 | I1: Output_4 | J1: SCI_Average | K1: DALYS_2021_All Causes per capita 2021 | L1: Outcome_1 | M1: Outcome_2 | N1: Outcome_3 | O1: Outcome_4 | P1: Outcome_5 | Q1: Impact_1 | R1: Impact_2 | S1: Impact_3 | T1: GDP_Growth_per_capita
A2: Algeria | B2: DZA | C2: 46053477 | D2: 61.01303 | E2: 0.13419182 | F2: 88.72 | G2: 82.21 | H2: 60.71 | I2: 68.12 | J2: 74.94 | K2: 0.25858507 | L2: 0.054826069 | M2: 0.17657851 | N2: 0.02400285 | O2: 0.262 | P2: 0.5866345 | Q2: 15545.11 | R2: 28.18 | S2: 37.36 | T2: 3.3
A3: Angola | B3: AGO | C3: 36148636 | D3: 18.553569 | E3: 2.4607173 | F3: 21.08 | G3: 36.07 | H3: 53.76 | I3: 44.51 | J3: 38.855 | K3: 0.55586603 | L3: 0.34291113 | M3: 0.16924787 | N3: 0.040767474 | O3: 0.291 | P3: 0.2930257 | Q3: 8866.691 | R3: 9.49 | S3: 45 | T3: 4.4239045
A4: Benin | B4: BEN | C4: 13124347 | D4: 10.88486 | E4: 2.8272298 | F4: 16.86 | G4: 47 | H4: 60.77 | I4: 42.82 | J4: 41.8625 | K4: 0.5415334 | L4: 0.32523931 | M4: 0.16627788 | N4: 0.047324915 | O4: 0.254 | P4: 0.3140346 | Q4: 3966.803 | R4: 4.16 | S4: 37.6 | T4: 7.4531157
A5: Botswana | B5: BWA | C5: 2483754 | D5: 32.040541 | E5: 6.3942892 | F5: 43.33 | G5: 66.05 | H5: 60.17 | I5: 53.85 | J5: 55.85 | K5: 0.51046947 | L5: 0.29056739 | M5: 0.16281769 | N5: 0.03681854 | O5: 0.336 | P5: 0.3750613 | Q5: 16749.389 | R5: 23.79 | S5: 57.4 | T5: -2.9898688
A6: Burkina Faso | B6: BFA | C6: 22720842 | D6: 10.935549 | E6: 3.0043273 | F6: 14.92 | G6: 50.01 | H6: 54.76 | I6: 60.22 | J6: 44.9775 | K6: 0.53931546 | L6: 0.30772701 | M6: 0.16837414 | N6: 0.059056873 | O6: 0.298 | P6: 0.2846235 | Q6: 2508.528 | R6: 4.3 | S6: 0 | T6: 4.985103
A7: Burundi | B7: BDI | C7: 12999141 | D7: 9.4270121 | E7: 3.2873539 | F7: 13.85 | G7: 60.47 | H7: 59.39 | I7: 59.42 | J7: 48.2825 | K7: 0.46057153 | L7: 0.25291885 | M7: 0.15453908 | N7: 0.051080321 | O7: 0.221 | P7: 0.2583942 | Q7: 879.67 | R7: 0.9 | S7: 33.33 | T7: 3.4892317
A8: Cabo Verde | B8: CPV | C8: 573322 | D8: 24.528465 | F8: 66.2 | G8: 90.4 | H8: 56.77 | I8: 75.55 | J8: 72.23 | K8: 0.28416804 | L8: 0.064726853 | M8: 0.18145936 | N8: 0.034756189 | O8: 0.341 | P8: 0.5024222 | Q8: 10052.799 | R8: 11.35 | S8: 52.5 | T8: 7.2718815
A9: Cameroon | B9: CMR | C9: 28608129 | D9: 7.6903691 | E9: 2.9013855 | F9: 28.28 | G9: 56.12 | H9: 49.14 | I9: 47.52 | J9: 45.265 | K9: 0.54981019 | L9: 0.32608299 | M9: 0.1751217 | N9: 0.042805912 | O9: 0.286 | P9: 0.3372569 | Q9: 4880.519 | R9: 6.23 | S9: 49 | T9: 3.6707428
A10: Central African Republic | B10: CAF | C10: 5119136 | D10: 10.510261 | E10: 0.072434098 | F10: 16.76 | G10: 38.69 | H10: 43.77 | I10: 38.17 | J10: 34.3475 | K10: 0.83557862 | L10: 0.58633456 | M10: 0.16570339 | N10: 0.07557031 | O10: 0.186 | P10: 0.1516031 | Q10: 1145.161 | R10: 1.57 | S10: 59.27 | T10: 1.5396325
A11: Chad | B11: TCD | C11: 17921183 | D11: 3.9757716 | E11: 4.1133942 | F11: 10.76 | G11: 41.09 | H11: 58.54 | I11: 28.87 | J11: 34.815 | K11: 0.72291648 | L11: 0.50936099 | M11: 0.15067299 | N11: 0.056395953 | O11: 0.239 | P11: 0.2375145 | Q11: 2588.82 | R11: 3.29 | S11: 36.9 | T11: 3.6544511
A12: Comoros | B12: COM | C12: 926492 | D12: 20.789889 | E12: 0.9298947 | F12: 37.44 | G12: 51.48 | H12: 56.05 | I12: 49.64 | J12: 48.6525 | K12: 0.3998434 | L12: 0.18043054 | M12: 0.17489083 | N12: 0.039609689 | O12: 0.249 | P12: 0.3180644 | Q12: 3392.316 | R12: 6.02 | S12: 55.92 | T12: 3.3887835
A13: Congo | B13: COG | C13: 5940746 | D13: 13.271803 | E13: 0.42558796 | F13: 28.57 | G13: 36.21 | H13: 52.47 | I13: 52.06 | J13: 42.3275 | K13: 0.45539965 | L13: 0.27170787 | M13: 0.15151453 | N13: 0.027856401 | O13: 0.263 | P13: 0.3395313 | Q13: 5622.161 | R13: 7.57 | S13: 41.9 | T13: 2.5796664
A14: Côte d'Ivoire | B14: CIV | C14: 28444206 | D14: 10.770365 | E14: 1.395126 | F14: 19.16 | G14: 58.23 | H14: 58.65 | I14: 51.18 | J14: 46.805 | K14: 0.50783164 | L14: 0.2963126 | M14: 0.162066 | N14: 0.045583166 | O14: 0.312 | P14: 0.3432034 | Q14: 6726.072 | R14: 8.59 | S14: 45.6 | T14: 5.95
A15: Democratic Republic of the Congo | B15: COD | C15: 98151951 | D15: 13.539167 | E15: 6.8932479 | F15: 24.44 | G15: 48.21 | H15: 59.59 | I15: 43.22 | J15: 43.865 | K15: 0.61083886 | L15: 0.39012943 | M15: 0.16891108 | N15: 0.047809794 | O15: 0.261 | P15: 0.290413 | Q15: 1592.477 | R15: 2.41 | S15: 41.64 | T15: 6.6759303
A16: Equatorial Guinea | B16: GNQ | C16: 1543389 | D16: 17.115684 | E16: 23.864221 | F16: 41.09 | G16: 43.59 | H16: 50.27 | I16: 48.65 | J16: 45.9 | K16: 0.58306554 | L16: 0.37725803 | M16: 0.17062504 | N16: 0.031497727 | O16: 0.174 | P16: 0.4242096 | Q16: 18565.41 | R16: 18.85 | S16: 50.2 | T16: 0.90724825
A17: Eritrea | B17: ERI | C17: 3727656 | D17: 14.517287 | E17: 2.6869969 | F17: 35.7 | G17: 36.43 | H17: 60.09 | I17: 51.96 | J17: 46.045 | K17: 0.43861377 | L17: 0.18328273 | M17: 0.20161049 | N17: 0.049832601 | O17: 0.214 | P17: 0.2559651 | Q17: 650 | R17: 2.78 | S17: 0
A18: Eswatini | B18: SWZ | C18: 1197512 | D18: 43.650798 | E18: 4.3127443 | F18: 32.98 | G18: 65.08 | H18: 62 | I18: 73.19 | J18: 58.3125 | K18: 0.71206086 | L18: 0.38181597 | M18: 0.23565534 | N18: 0.07556241 | O18: 0.293 | P18: 0.3252324 | Q18: 11315.553 | R18: 24.95 | S18: 63.7 | T18: 2.6407046
A19: Ethiopia | B19: ETH | C19: 123771387 | D19: 17.313519 | E19: 1.864483 | F19: 20.87 | G19: 29.04 | H19: 52.49 | I19: 47.93 | J19: 37.5825 | K19: 0.38864963 | L19: 0.20396758 | M19: 0.13963053 | N19: 0.041155729 | O19: 0.378 | P19: 0.3120527 | Q19: 3591.681 | R19: 4.7 | S19: 30.98 | T19: 7.3166911
A20: Gabon | B20: GAB | C20: 2383905 | D20: 30.40605 | E20: 1.3004665 | F20: 48.48 | G20: 34.37 | H20: 53.8 | I20: 64.17 | J20: 50.205 | K20: 0.44235278 | L20: 0.24190195 | M20: 0.1657311 | N20: 0.03146404 | O20: 0.218 | P20: 0.3962385 | Q20: 21218.077 | R20: 34.92 | S20: 69 | T20: 3.3839076
A21: Gambia | B21: GMB | C21: 2631251 | D21: 7.5746518 | E21: 1.3278116 | F21: 28.12 | G21: 43.85 | H21: 57.74 | I21: 63.72 | J21: 48.3575 | K21: 0.43458985 | L21: 0.23410545 | M21: 0.15868965 | N21: 0.036390079 | O21: 0.287 | P21: 0.3467981 | Q21: 3073.541 | R21: 5.97 | S21: 67.2 | T21: 5.7467177
A22: Ghana | B22: GHA | C22: 33062741 | D22: 40.416607 | E22: 15.163718 | F22: 25.98 | G22: 41.42 | H22: 70.51 | I22: 68.74 | J22: 51.6625 | K22: 0.40610834 | L22: 0.19130623 | M22: 0.17586458 | N22: 0.035717695 | O22: 0.343 | P22: 0.3605526 | Q22: 7061.935 | R22: 10.84 | S22: 47.5 | T22: 5.6848726
A23: Guinea | B23: GIN | C23: 14238716 | D23: 7.1826172 | E23: 2.7373714 | F23: 18.03 | G23: 47.87 | H23: 58.4 | I23: 50.42 | J23: 43.68 | K23: 0.62038058 | L23: 0.39821246 | M23: 0.16588447 | N23: 0.053108951 | O23: 0.268 | P23: 0.2568856 | Q23: 3895.767 | R23: 6.82 | S23: 68.5 | T23: 5.6685239
A24: Guinea-Bissau | B24: GNB | C24: 2111612 | D24: 12.653132 | E24: 0.1256791 | F24: 17.33 | G24: 29.95 | H24: 61.51 | I24: 60.3 | J24: 42.2725 | K24: 0.59333548 | L24: 0.36455418 | M24: 0.17227405 | N24: 0.049926094 | O24: 0.214 | P24: 0.2426292 | Q24: 2729.159 | R24: 3.06 | S24: 55.76 | T24: 4.813486
A25: Kenya | B25: KEN | C25: 57458890 | D25: 23.42452 | E25: 0.84095736 | F25: 40.62 | G25: 53.15 | H25: 50.91 | I25: 73.63 | J25: 54.5775 | K25: 0.35501401 | L25: 0.18481356 | M25: 0.1352383 | N25: 0.031453024 | O25: 0.388 | P25: 0.3336342 | Q25: 6267.148 | R25: 7.39 | S25: 50 | T25: 4.4964983
A26: Lesotho | B26: LSO | C26: 2192400 | D26: 23.526334 | E26: 4.2294499 | F26: 32.27 | G26: 50.71 | H26: 65.78 | I26: 74.68 | J26: 55.86 | K26: 0.8061546 | L26: 0.46635144 | M26: 0.24303601 | N26: 0.084683657 | O26: 0.309 | P26: 0.2633865 | Q26: 2891.054 | R26: 3.19 | S26: 56.01 | T26: 2.7622382
A27: Liberia | B27: LBR | C27: 5432272 | D27: 11.11493 | E27: 0.55403733 | F27: 29.07 | G27: 42.02 | H27: 53.05 | I27: 61.65 | J27: 46.4475 | K27: 0.53500919 | L27: 0.33742173 | M27: 0.15837177 | N27: 0.037012274 | O27: 0.357 | P27: 0.3573526 | Q27: 1670.302 | R27: 1.53 | S27: 43 | T27: 4.7929148
A28: Madagascar | B28: MDG | C28: 29942591 | D28: 5.5460292 | E28: 2.0891931 | F28: 18.98 | G28: 29.47 | H28: 45.77 | I28: 58.24 | J28: 38.115 | K28: 0.50996008 | L28: 0.28997474 | M28: 0.17565736 | N28: 0.039462753 | O28: 0.304 | P28: 0.2901793 | Q28: 1731.305 | R28: 1.89 | S28: 56.2 | T28: 4.2
A29: Malawi | B29: MWI | C29: 20728157 | D29: 5.0174021 | E29: 0.71150071 | F29: 22.25 | G29: 57.77 | H29: 58.77 | I29: 71.89 | J29: 52.67 | K29: 0.44481134 | L29: 0.24303618 | M29: 0.16367847 | N29: 0.033520622 | O29: 0.285 | P29: 0.2989006 | Q29: 1514.554 | R29: 2.77 | S29: 47 | T29: 1.82685
A30: Mali | B30: MLI | C30: 22105727 | D30: 8.1755817 | F30: 15.25 | G30: 59.37 | H30: 67.76 | I30: 47.33 | J30: 47.4275 | K30: 0.63970272 | L30: 0.42599321 | M30: 0.15654856 | N30: 0.053925055 | O30: 0.29 | P30: 0.2959361 | Q30: 2472.828 | R30: 2.99 | S30: 36.5 | T30: 5.0045459
A31: Mauritania | B31: MRT | C31: 5030233 | D31: 17.621923 | E31: 0.48384449 | F31: 22.04 | G31: 47.04 | H31: 60.5 | I31: 41.31 | J31: 42.7225 | K31: 0.35641087 | L31: 0.18769682 | M31: 0.13676512 | N31: 0.026374756 | O31: 0.262 | P31: 0.4214104 | Q31: 7258.253 | R31: 15.14 | S31: 76 | T31: 5.2
A32: Mauritius | B32: MUS | C32: 1275657 | D32: 66.876465 | E32: 9.9309121 | F32: 77.61 | G32: 52.41 | H32: 61.3 | I32: 74.5 | J32: 66.455 | K32: 0.3804525 | L32: 0.056210978 | M32: 0.30203463 | N32: 0.022206883 | O32: 0.397 | P32: 0.5665122 | Q32: 27341.634 | R32: 32.83 | S32: 41.9 | T32: 4.6939032
A33: Mozambique | B33: MOZ | C33: 34034812 | D33: 10.86393 | E33: 1.0442801 | F33: 23.4 | G33: 57.76 | H33: 49.78 | I33: 55.67 | J33: 46.6525 | K33: 0.63336597 | L33: 0.40815361 | M33: 0.17392551 | N33: 0.043108831 | O33: 0.304 | P33: 0.2511178 | Q33: 1485.598 | R33: 2.43 | S33: 40 | T33: 1.851775
A34: Namibia | B34: NAM | C34: 2680497 | D34: 62.136352 | E34: 7.4922891 | F34: 55.5 | G34: 57.25 | H34: 64.71 | I34: 74.87 | J34: 63.0825 | K34: 0.53297666 | L34: 0.29762114 | M34: 0.16825145 | N34: 0.046707971 | O34: 0.303 | P34: 0.3993723 | Q34: 10419.859 | R34: 15.64 | S34: 70.1 | T34: 3.711545
A35: Niger | B35: NER | C35: 27066230 | D35: 4.0944273 | E35: 0.54349922 | F35: 11.68 | G35: 49.68 | H35: 49.3 | I35: 52.36 | J35: 40.755 | K35: 0.74303883 | L35: 0.52283858 | M35: 0.15281919 | N35: 0.062854541 | O35: 0.287 | P35: 0.2645919 | Q35: 1747.635 | R35: 2.34 | S35: 29.2 | T35: 8.4215979
A36: Nigeria | B36: NGA | C36: 222182400 | D36: 23.664466 | E36: 1.7813083 | F36: 14.08 | G36: 53.21 | H36: 62.66 | I36: 46.44 | J36: 44.0975 | K36: 0.60520175 | L36: 0.41661934 | M36: 0.14433402 | N36: 0.042283575 | O36: 0.38 | P36: 0.3161699 | Q36: 5789.016 | R36: 5.8 | S36: 46.8 | T36: 3.4264395
A37: Rwanda | B37: RWA | C37: 13924498 | D37: 11.403764 | E37: 0.69228833 | F37: 26.82 | G37: 70.06 | H37: 44.01 | I37: 67.2 | J37: 52.0225 | K37: 0.3827553 | L37: 0.16597404 | M37: 0.1730401 | N37: 0.040846173 | O37: 0.331 | P37: 0.3176267 | Q37: 3355.683 | R37: 6 | S37: 28.9 | T37: 8.8906553
A38: Sao Tome and Principe | B38: STP | C38: 232132 | D38: 30.890154 | F38: 44.77 | G38: 53.47 | H38: 62.61 | I38: 79.7 | J38: 60.1375 | K38: 0.26640418 | L38: 0.085742941 | M38: 0.15520469 | N38: 0.021865647 | O38: 0.266 | P38: 0.4141126 | Q38: 5449.789 | R38: 16.63 | S38: 32.13 | T38: 0.9000006
A39: Senegal | B39: SEN | C39: 18116526 | D39: 5.7327207 | E39: 1.4601029 | F39: 30.05 | G39: 63.69 | H39: 55.65 | I39: 59.11 | J39: 52.125 | K39: 0.36508063 | L39: 0.16490721 | M39: 0.15800663 | N39: 0.036505767 | O39: 0.328 | P39: 0.3396112 | Q39: 4464.78 | R39: 6.73 | S39: 58.7 | T39: 6.8920074
A40: Seychelles | B40: SYC | C40: 99912 | D40: 230.71805 | E40: 10.684803 | F40: 78.3 | G40: 87.12 | H40: 57.3 | I40: 79.13 | J40: 75.4625 | K40: 0.31209413 | L40: 0.067825983 | M40: 0.22109038 | N40: 0.023145292 | O40: 0.318 | P40: 0.52842651 | Q40: 35085.182 | S40: 46 | T40: 3.4656807
A41: Sierra Leone | B41: SLE | C41: 8472212 | D41: 11.384249 | E41: 5.26334 | F41: 14.19 | G41: 50.54 | H41: 54.72 | I41: 72.06 | J41: 47.8775 | K41: 0.62214616 | L41: 0.39564769 | M41: 0.17921993 | N41: 0.04572357 | O41: 0.327 | P41: 0.3091938 | Q41: 2966.491 | R41: 2.63 | S41: 59 | T41: 4
A42: South Africa | B42: ZAF | C42: 61452696 | D42: 66.053003 | E42: 2.1852693 | F42: 79.53 | G42: 68.77 | H42: 60.66 | I42: 76.38 | J42: 71.335 | K42: 0.59898341 | L42: 0.27289034 | M42: 0.23352654 | N42: 0.066110009 | O42: 0.458 | P42: 0.4456413 | Q42: 13771.97 | R42: 21.64 | S42: 54 | T42: 0.57985369
A43: South Sudan | B43: SSD | C43: 11891023 | D43: 6.4682067 | E43: 1.0973402 | F43: 21.91 | G43: 35.58 | H43: 59.48 | I43: 29.42 | J43: 36.5975 | K43: 0.63690566 | L43: 0.41618333 | M43: 0.15884745 | N43: 0.057924879 | O43: 0.213 | P43: 0.291139 | Q43: 660.094 | R43: 3.35 | S43: 46.32
A44: Togo | B44: UGA | C44: 49700758 | D44: 23.242417 | E44: 0.20829094 | F44: 22.84 | G44: 55.37 | H44: 56.9 | I44: 52.14 | J44: 46.8125 | K44: 0.39850537 | L44: 0.21625225 | M44: 0.13944238 | N44: 0.040092692 | O44: 0.278 | P44: 0.3235637 | Q44: 3240.979 | R44: 4.33 | S44: 40.1 | T44: 6.136452
A45: Uganda | B45: TZA | C45: 65136238 | D45: 9.0431618 | E45: 5.9479843 | F45: 27.27 | G45: 54.91 | H45: 54.5 | I45: 68.17 | J45: 51.2125 | K45: 0.40710628 | L45: 0.22733353 | M45: 0.14378753 | N45: 0.03339787 | O45: 0.365 | P45: 0.3246088 | Q45: 3638.147 | R45: 3.2 | S45: 41.2 | T45: 5.5263138
A46: United Republic of Tanzania | B46: TGO | C46: 8886635 | D46: 6.2109686 | E46: 9.350128 | F46: 19.6 | G46: 52.66 | H46: 50.72 | I46: 63.1 | J46: 46.52 | K46: 0.48252291 | L46: 0.25168432 | M46: 0.18194219 | N46: 0.045928544 | O46: 0.313 | P46: 0.3347842 | Q46: 2895.085 | R46: 3.7 | S46: 33.8 | T46: 5.3000053
A47: Zambia | B47: ZMB | C47: 20032801 | D47: 29.968206 | E47: 5.9489349 | F47: 37.54 | G47: 60.64 | H47: 57.47 | I47: 74.31 | J47: 57.49 | K47: 0.50513805 | L47: 0.30859836 | M47: 0.15379622 | N47: 0.036071447 | O47: 0.265 | P47: 0.3161706 | Q47: 3747.732 | R47: 5.23 | S47: 52.3 | T47: 4.0431483
A48: Zimbabwe | B48: ZWE | C48: 15581023 | D48: 29.796679 | E48: 2.426871 | F48: 40.41 | G48: 47.83 | H48: 66.74 | I48: 71.16 | J48: 56.535 | K48: 0.55124774 | L48: 0.29968262 | M48: 0.1852836 | N48: 0.057561611 | O48: 0.324 | P48: 0.285771 | Q48: 4465.361 | R48: 4.5 | S48: 46 | T48: 2.0294841

Sheet Model_1
J1: HWF Performance | Z1: Borrowed from Model 1
D2: Input 1 coef. | E2: Input 2 coef. | F2: Input 3 coef. | H2: Percentage of people trained | I2: Percentage of people incentivised | J2: HWF In-service training coef. | K2: Incentive | M2: Total Output coef. | N2: R²_Output | O2: Output 1 Coef. | P2: Output 2 Coef. | Q2: Output 3 Coef. | S2: Total Outcome coef. | T2: R²_Outcome | U2: Outcome 1 Coef. | V2: Outcome 2 Coef. | W2: Outcome 3 Coef. | Y2: Direct effect from HWF availability to Outcome | Z2: Total Impact coef. | AA2: R²_Impact | AB2: Impact 1 Coef. | AC2: Impact 2 Coef.
D3: 0.95 | E3: 0.595 | H3: 0.1 | I3: 0.1 | J3: 0.115 | K3: 0.012 | M3: 0.525 | N3: 0.276 | O3: 0.805 | P3: 0.41 | Q3: 0.874 | S3: -0.416 | T3: 0.444 | U3: 0.869 | V3: -0.604 | W3: 0.574 | Y3: -0.346 | Z3: -0.649 | AA3: 0.421 | AB3: 0.948 | AC3: 0.926
D4: Investments | H4: HWF Availability | O4: SCI_Infectious diseases | P4: SCI_NCD | Q4: SCI_RMNCH | U4: DALYS_2021_Communicable, maternal, perinatal and nutritional conditions per capita 2021 | V4: DALYS_2021_Noncommunicable diseases per capita (2021) | W4: DALYS_2021_Injuries per capita 2021 | AB4: GDP_PPP_2024 | AC4: Productivity
B5: Country | C5: ISO | D5: Education | E5: Employment | F5: Retention | H5: HWF Availability Estimation | I5: Real value | M5: Total Output | S5: Total Outcome from output | Y5: Direct Outcome from HWF availability | Z5: Total Impact | AD5: Initial investment per HWF | AE5: Intial investment per population | AF5: Population | AG5: GDP_PP | AH5: ROI on GDP
B6: Algeria | C6: DZA | D6: =_xlfn.XLOOKUP($C6,SEM!$B:$B,SEM!$D:$D)*Model_1!$D$3 -> 57.962378 | E6: =_xlfn.XLOOKUP($C6,SEM!$B:$B,SEM!$E:$E)*Model_1!$E$3 -> 0.079844134 | H6: =Input_1_coef.*_xlfn.XLOOKUP($C6,COMBINED!$B:$B,COMBINED!$AB:$AB)+Input_2_coef.*_xlfn.XLOOKUP($C6,COMBINED!$B:$B,COMBINED!$AC:$AC) -> 58.042222 | I6: =_xlfn.XLOOKUP($C6,COMBINED!$B:$B,COMBINED!$N:$N) -> 50.985293 | M6: =Total_Output_coef.*$H6*_R²_Output+(HWF_In_service_training_coef.*Percentage_of_people_trained*$H6)+($H6*Incentive*Percentage_of_people_incentivised) -> 9.1474542 | O6: =Output_1_Coef.*$M6*_R²_Output -> 2.0323814 | P6: =Output_2_Coef.*$M6*_R²_Output -> 1.0351259 | Q6: =Output_3_Coef.*$M6*_R²_Output -> 2.2065855 | S6: =Total_Outcome_coef.*M6*_R²_Outcome -> -1.6895714 | U6: =Outcome_1_Coef.*$S6*_R²_Outcome -> -0.65189747 | V6: =Outcome_2_Coef.*$S6*_R²_Outcome -> 0.4531025 | W6: =Outcome_3_Coef.*$S6*_R²_Outcome -> -0.4305974 | Y6: =H6*$Y$3*_R²_Outcome -> -8.9166784 | Z6: =Y6+S6 -> -10.60625 | AB6: =_R²_Impact*$Z6*Impact_1_Coef.*Total_Impact_coef. -> 2.7472424 | AC6: =_R²_Impact*$Z6*Impact_2_Coef.*Total_Impact_coef. -> 2.6834878 | AD6: =_xlfn.XLOOKUP($C6,SEM!$B:$B,SEM!$D:$D)+_xlfn.XLOOKUP($C6,SEM!$B:$B,SEM!$E:$E) -> 61.147221 | AE6: =_xlfn.XLOOKUP($C6,SEM!$B:$B,COMBINED!$AE:$AE)*AD6 -> 14357673 | AF6: =_xlfn.XLOOKUP($C6,SEM!$B:$B,SEM!C:C) -> 46053477 | AG6: =AF6*AB6 -> 1.2652006e+08 | AH6: =AG6/AE6 -> 8.8120172 | AI6: =AE6/AF6 -> 0.3117609 | AJ6: =AB6/AI6 -> 8.8120172
B7: Angola | C7: AGO | D7: =_xlfn.XLOOKUP($C7,SEM!$B:$B,SEM!$D:$D)*Model_1!$D$3 -> 17.625891 | E7: =_xlfn.XLOOKUP($C7,SEM!$B:$B,SEM!$E:$E)*Model_1!$E$3 -> 1.4641268 | H7: =Input_1_coef.*_xlfn.XLOOKUP($C7,COMBINED!$B:$B,COMBINED!$AB:$AB)+Input_2_coef.*_xlfn.XLOOKUP($C7,COMBINED!$B:$B,COMBINED!$AC:$AC) -> 19.090018 | I7: =_xlfn.XLOOKUP($C7,COMBINED!$B:$B,COMBINED!$N:$N) -> 21.346034 | M7: =Total_Output_coef.*$H7*_R²_Output+(HWF_In_service_training_coef.*Percentage_of_people_trained*$H7)+($H7*Incentive*Percentage_of_people_incentivised) -> 3.0085868 | O7: =Output_1_Coef.*$M7*_R²_Output -> 0.66844782 | P7: =Output_2_Coef.*$M7*_R²_Output -> 0.34045168 | Q7: =Output_3_Coef.*$M7*_R²_Output -> 0.72574334 | S7: =Total_Outcome_coef.*M7*_R²_Outcome -> -0.55569802 | U7: =Outcome_1_Coef.*$S7*_R²_Outcome -> -0.2144083 | V7: =Outcome_2_Coef.*$S7*_R²_Outcome -> 0.14902487 | W7: =Outcome_3_Coef.*$S7*_R²_Outcome -> -0.14162297 | Y7: =H7*$Y$3*_R²_Outcome -> -2.9326849 | Z7: =Y7+S7 -> -3.4883829 | AB7: =_R²_Impact*$Z7*Impact_1_Coef.*Total_Impact_coef. -> 0.90356475 | AC7: =_R²_Impact*$Z7*Impact_2_Coef.*Total_Impact_coef. -> 0.88259595 | AD7: =_xlfn.XLOOKUP($C7,SEM!$B:$B,SEM!$D:$D)+_xlfn.XLOOKUP($C7,SEM!$B:$B,SEM!$E:$E) -> 21.014287 | AE7: =_xlfn.XLOOKUP($C7,SEM!$B:$B,COMBINED!$AE:$AE)*AD7 -> 1621525.4 | AF7: =_xlfn.XLOOKUP($C7,SEM!$B:$B,SEM!C:C) -> 36148636 | AG7: =AF7*AB7 -> 32662633 | AH7: =AG7/AE7 -> 20.143152 | AI7: =AE7/AF7 -> 0.044857167 | AJ7: =AB7/AI7 -> 20.143152
B8: Benin | C8: BEN | D8: =_xlfn.XLOOKUP($C8,SEM!$B:$B,SEM!$D:$D)*Model_1!$D$3 -> 10.340617 | E8: =_xlfn.XLOOKUP($C8,SEM!$B:$B,SEM!$E:$E)*Model_1!$E$3 -> 1.6822017 | H8: =Input_1_coef.*_xlfn.XLOOKUP($C8,COMBINED!$B:$B,COMBINED!$AB:$AB)+Input_2_coef.*_xlfn.XLOOKUP($C8,COMBINED!$B:$B,COMBINED!$AC:$AC) -> 12.022819 | I8: =_xlfn.XLOOKUP($C8,COMBINED!$B:$B,COMBINED!$N:$N) -> 11.015405 | M8: =Total_Output_coef.*$H8*_R²_Output+(HWF_In_service_training_coef.*Percentage_of_people_trained*$H8)+($H8*Incentive*Percentage_of_people_incentivised) -> 1.8947963 | O8: =Output_1_Coef.*$M8*_R²_Output -> 0.42098584 | P8: =Output_2_Coef.*$M8*_R²_Output -> 0.21441515 | Q8: =Output_3_Coef.*$M8*_R²_Output -> 0.45707034 | S8: =Total_Outcome_coef.*M8*_R²_Outcome -> -0.34997645 | U8: =Outcome_1_Coef.*$S8*_R²_Outcome -> -0.13503351 | V8: =Outcome_2_Coef.*$S8*_R²_Outcome -> 0.093855285 | W8: =Outcome_3_Coef.*$S8*_R²_Outcome -> -0.089193598 | Y8: =H8*$Y$3*_R²_Outcome -> -1.8469935 | Z8: =Y8+S8 -> -2.19697 | AB8: =_R²_Impact*$Z8*Impact_1_Coef.*Total_Impact_coef. -> 0.56906157 | AC8: =_R²_Impact*$Z8*Impact_2_Coef.*Total_Impact_coef. -> 0.5558555 | AD8: =_xlfn.XLOOKUP($C8,SEM!$B:$B,SEM!$D:$D)+_xlfn.XLOOKUP($C8,SEM!$B:$B,SEM!$E:$E) -> 13.71209 | AE8: =_xlfn.XLOOKUP($C8,SEM!$B:$B,COMBINED!$AE:$AE)*AD8 -> 198235.69 | AF8: =_xlfn.XLOOKUP($C8,SEM!$B:$B,SEM!C:C) -> 13124347 | AG8: =AF8*AB8 -> 7468561.5 | AH8: =AG8/AE8 -> 37.675161
B9: Botswana | C9: BWA | D9: =_xlfn.XLOOKUP($C9,SEM!$B:$B,SEM!$D:$D)*Model_1!$D$3 -> 30.438514 | E9: =_xlfn.XLOOKUP($C9,SEM!$B:$B,SEM!$E:$E)*Model_1!$E$3 -> 3.8046021 | H9: =Input_1_coef.*_xlfn.XLOOKUP($C9,COMBINED!$B:$B,COMBINED!$AB:$AB)+Input_2_coef.*_xlfn.XLOOKUP($C9,COMBINED!$B:$B,COMBINED!$AC:$AC) -> 34.243116 | I9: =_xlfn.XLOOKUP($C9,COMBINED!$B:$B,COMBINED!$N:$N) -> 36.670298 | M9: =Total_Output_coef.*$H9*_R²_Output+(HWF_In_service_training_coef.*Percentage_of_people_trained*$H9)+($H9*Incentive*Percentage_of_people_incentivised) -> 5.396715 | O9: =Output_1_Coef.*$M9*_R²_Output -> 1.1990421 | P9: =Output_2_Coef.*$M9*_R²_Output -> 0.61069227 | Q9: =Output_3_Coef.*$M9*_R²_Output -> 1.3018172 | S9: =Total_Outcome_coef.*M9*_R²_Outcome -> -0.99679486 | U9: =Outcome_1_Coef.*$S9*_R²_Outcome -> -0.38459934 | V9: =Outcome_2_Coef.*$S9*_R²_Outcome -> 0.26731646 | W9: =Outcome_3_Coef.*$S9*_R²_Outcome -> -0.25403915 | Y9: =H9*$Y$3*_R²_Outcome -> -5.2605644 | Z9: =Y9+S9 -> -6.2573593 | AB9: =_R²_Impact*$Z9*Impact_1_Coef.*Total_Impact_coef. -> 1.620788 | AC9: =_R²_Impact*$Z9*Impact_2_Coef.*Total_Impact_coef. -> 1.5831748 | AD9: =_xlfn.XLOOKUP($C9,SEM!$B:$B,SEM!$D:$D)+_xlfn.XLOOKUP($C9,SEM!$B:$B,SEM!$E:$E) -> 38.43483 | AE9: =_xlfn.XLOOKUP($C9,SEM!$B:$B,COMBINED!$AE:$AE)*AD9 -> 350064.43 | AF9: =_xlfn.XLOOKUP($C9,SEM!$B:$B,SEM!C:C) -> 2483754 | AG9: =AF9*AB9 -> 4025638.8 | AH9: =AG9/AE9 -> 11.499708
B10: Burkina Faso | C10: BFA | D10: =_xlfn.XLOOKUP($C10,SEM!$B:$B,SEM!$D:$D)*Model_1!$D$3 -> 10.388772 | E10: =_xlfn.XLOOKUP($C10,SEM!$B:$B,SEM!$E:$E)*Model_1!$E$3 -> 1.7875747 | H10: =Input_1_coef.*_xlfn.XLOOKUP($C10,COMBINED!$B:$B,COMBINED!$AB:$AB)+Input_2_coef.*_xlfn.XLOOKUP($C10,COMBINED!$B:$B,COMBINED!$AC:$AC) -> 12.176347 | I10: =_xlfn.XLOOKUP($C10,COMBINED!$B:$B,COMBINED!$N:$N) -> 12.022002 | M10: =Total_Output_coef.*$H10*_R²_Output+(HWF_In_service_training_coef.*Percentage_of_people_trained*$H10)+($H10*Incentive*Percentage_of_people_incentivised) -> 1.9189922 | O10: =Output_1_Coef.*$M10*_R²_Output -> 0.42636169 | P10: =Output_2_Coef.*$M10*_R²_Output -> 0.21715316 | Q10: =Output_3_Coef.*$M10*_R²_Output -> 0.46290698 | S10: =Total_Outcome_coef.*M10*_R²_Outcome -> -0.35444554 | U10: =Outcome_1_Coef.*$S10*_R²_Outcome -> -0.13675785 | V10: =Outcome_2_Coef.*$S10*_R²_Outcome -> 0.095053787 | W10: =Outcome_3_Coef.*$S10*_R²_Outcome -> -0.090332572 | Y10: =H10*$Y$3*_R²_Outcome -> -1.8705791 | Z10: =Y10+S10 -> -2.2250246 | AB10: =_R²_Impact*$Z10*Impact_1_Coef.*Total_Impact_coef. -> 0.5763283 | AC10: =_R²_Impact*$Z10*Impact_2_Coef.*Total_Impact_coef. -> 0.56295359 | AD10: =_xlfn.XLOOKUP($C10,SEM!$B:$B,SEM!$D:$D)+_xlfn.XLOOKUP($C10,SEM!$B:$B,SEM!$E:$E) -> 13.939877 | AE10: =_xlfn.XLOOKUP($C10,SEM!$B:$B,COMBINED!$AE:$AE)*AD10 -> 380767.73 | AF10: =_xlfn.XLOOKUP($C10,SEM!$B:$B,SEM!C:C) -> 22720842 | AG10: =AF10*AB10 -> 13094664 | AH10: =AG10/AE10 -> 34.390163
B11: Burundi | C11: BDI | D11: =_xlfn.XLOOKUP($C11,SEM!$B:$B,SEM!$D:$D)*Model_1!$D$3 -> 8.9556615 | E11: =_xlfn.XLOOKUP($C11,SEM!$B:$B,SEM!$E:$E)*Model_1!$E$3 -> 1.9559756 | H11: =Input_1_coef.*_xlfn.XLOOKUP($C11,COMBINED!$B:$B,COMBINED!$AB:$AB)+Input_2_coef.*_xlfn.XLOOKUP($C11,COMBINED!$B:$B,COMBINED!$AC:$AC) -> 10.911637 | I11: =_xlfn.XLOOKUP($C11,COMBINED!$B:$B,COMBINED!$N:$N) -> 11.321517 | M11: =Total_Output_coef.*$H11*_R²_Output+(HWF_In_service_training_coef.*Percentage_of_people_trained*$H11)+($H11*Incentive*Percentage_of_people_incentivised) -> 1.719674 | O11: =Output_1_Coef.*$M11*_R²_Output -> 0.38207717 | P11: =Output_2_Coef.*$M11*_R²_Output -> 0.19459831 | Q11: =Output_3_Coef.*$M11*_R²_Output -> 0.41482664 | S11: =Total_Outcome_coef.*M11*_R²_Outcome -> -0.31763067 | U11: =Outcome_1_Coef.*$S11*_R²_Outcome -> -0.12255335 | V11: =Outcome_2_Coef.*$S11*_R²_Outcome -> 0.085180921 | W11: =Outcome_3_Coef.*$S11*_R²_Outcome -> -0.080950081 | Y11: =H11*$Y$3*_R²_Outcome -> -1.6762893 | Z11: =Y11+S11 -> -1.99392 | AB11: =_R²_Impact*$Z11*Impact_1_Coef.*Total_Impact_coef. -> 0.51646733 | AC11: =_R²_Impact*$Z11*Impact_2_Coef.*Total_Impact_coef. -> 0.5044818 | AD11: =_xlfn.XLOOKUP($C11,SEM!$B:$B,SEM!$D:$D)+_xlfn.XLOOKUP($C11,SEM!$B:$B,SEM!$E:$E) -> 12.714366 | AE11: =_xlfn.XLOOKUP($C11,SEM!$B:$B,COMBINED!$AE:$AE)*AD11 -> 187117.32 | AF11: =_xlfn.XLOOKUP($C11,SEM!$B:$B,SEM!C:C) -> 12999141 | AG11: =AF11*AB11 -> 6713631.7 | AH11: =AG11/AE11 -> 35.879263
B12: Cabo Verde | C12: CPV | D12: =_xlfn.XLOOKUP($C12,SEM!$B:$B,SEM!$D:$D)*Model_1!$D$3 -> 23.302042 | E12: =_xlfn.XLOOKUP($C12,SEM!$B:$B,SEM!$E:$E)*Model_1!$E$3 -> 0 | H12: =Input_1_coef.*_xlfn.XLOOKUP($C12,COMBINED!$B:$B,COMBINED!$AB:$AB)+Input_2_coef.*_xlfn.XLOOKUP($C12,COMBINED!$B:$B,COMBINED!$AC:$AC) -> 23.302042 | I12: =_xlfn.XLOOKUP($C12,COMBINED!$B:$B,COMBINED!$N:$N) -> 24.000474 | M12: =Total_Output_coef.*$H12*_R²_Output+(HWF_In_service_training_coef.*Percentage_of_people_trained*$H12)+($H12*Incentive*Percentage_of_people_incentivised) -> 3.6724018 | O12: =Output_1_Coef.*$M12*_R²_Output -> 0.81593424 | P12: =Output_2_Coef.*$M12*_R²_Output -> 0.41556899 | Q12: =Output_3_Coef.*$M12*_R²_Output -> 0.88587146 | S12: =Total_Outcome_coef.*M12*_R²_Outcome -> -0.67830731 | U12: =Outcome_1_Coef.*$S12*_R²_Outcome -> -0.26171538 | V12: =Outcome_2_Coef.*$S12*_R²_Outcome -> 0.18190574 | W12: =Outcome_3_Coef.*$S12*_R²_Outcome -> -0.17287069 | Y12: =H12*$Y$3*_R²_Outcome -> -3.5797529 | Z12: =Y12+S12 -> -4.2580602 | AB12: =_R²_Impact*$Z12*Impact_1_Coef.*Total_Impact_coef. -> 1.1029274 | AC12: =_R²_Impact*$Z12*Impact_2_Coef.*Total_Impact_coef. -> 1.077332 | AD12: =_xlfn.XLOOKUP($C12,SEM!$B:$B,SEM!$D:$D)+_xlfn.XLOOKUP($C12,SEM!$B:$B,SEM!$E:$E) -> 24.528465 | AE12: =_xlfn.XLOOKUP($C12,SEM!$B:$B,COMBINED!$AE:$AE)*AD12 -> 33751.168 | AF12: =_xlfn.XLOOKUP($C12,SEM!$B:$B,SEM!C:C) -> 573322 | AG12: =AF12*AB12 -> 632332.54 | AH12: =AG12/AE12 -> 18.735131
B13: Cameroon | C13: CMR | D13: =_xlfn.XLOOKUP($C13,SEM!$B:$B,SEM!$D:$D)*Model_1!$D$3 -> 7.3058506 | E13: =_xlfn.XLOOKUP($C13,SEM!$B:$B,SEM!$E:$E)*Model_1!$E$3 -> 1.7263244 | H13: =Input_1_coef.*_xlfn.XLOOKUP($C13,COMBINED!$B:$B,COMBINED!$AB:$AB)+Input_2_coef.*_xlfn.XLOOKUP($C13,COMBINED!$B:$B,COMBINED!$AC:$AC) -> 9.032175 | I13: =_xlfn.XLOOKUP($C13,COMBINED!$B:$B,COMBINED!$N:$N) -> 8.1868339 | M13: =Total_Output_coef.*$H13*_R²_Output+(HWF_In_service_training_coef.*Percentage_of_people_trained*$H13)+($H13*Incentive*Percentage_of_people_incentivised) -> 1.4234708 | O13: =Output_1_Coef.*$M13*_R²_Output -> 0.31626674 | P13: =Output_2_Coef.*$M13*_R²_Output -> 0.16107995 | Q13: =Output_3_Coef.*$M13*_R²_Output -> 0.34337531 | S13: =Total_Outcome_coef.*M13*_R²_Outcome -> -0.26292075 | U13: =Outcome_1_Coef.*$S13*_R²_Outcome -> -0.10144429 | V13: =Outcome_2_Coef.*$S13*_R²_Outcome -> 0.070509034 | W13: =Outcome_3_Coef.*$S13*_R²_Outcome -> -0.06700693 | Y13: =H13*$Y$3*_R²_Outcome -> -1.3875588 | Z13: =Y13+S13 -> -1.6504796 | AB13: =_R²_Impact*$Z13*Impact_1_Coef.*Total_Impact_coef. -> 0.42750903 | AC13: =_R²_Impact*$Z13*Impact_2_Coef.*Total_Impact_coef. -> 0.41758793 | AD13: =_xlfn.XLOOKUP($C13,SEM!$B:$B,SEM!$D:$D)+_xlfn.XLOOKUP($C13,SEM!$B:$B,SEM!$E:$E) -> 10.591755 | AE13: =_xlfn.XLOOKUP($C13,SEM!$B:$B,COMBINED!$AE:$AE)*AD13 -> 248069.48 | AF13: =_xlfn.XLOOKUP($C13,SEM!$B:$B,SEM!C:C) -> 28608129 | AG13: =AF13*AB13 -> 12230233 | AH13: =AG13/AE13 -> 49.301644
B14: Central African Republic | C14: CAF | D14: =_xlfn.XLOOKUP($C14,SEM!$B:$B,SEM!$D:$D)*Model_1!$D$3 -> 9.9847476 | E14: =_xlfn.XLOOKUP($C14,SEM!$B:$B,SEM!$E:$E)*Model_1!$E$3 -> 0.043098288 | H14: =Input_1_coef.*_xlfn.XLOOKUP($C14,COMBINED!$B:$B,COMBINED!$AB:$AB)+Input_2_coef.*_xlfn.XLOOKUP($C14,COMBINED!$B:$B,COMBINED!$AC:$AC) -> 10.027846 | I14: =_xlfn.XLOOKUP($C14,COMBINED!$B:$B,COMBINED!$N:$N) -> 12.601736 | M14: =Total_Output_coef.*$H14*_R²_Output+(HWF_In_service_training_coef.*Percentage_of_people_trained*$H14)+($H14*Incentive*Percentage_of_people_incentivised) -> 1.5803885 | O14: =Output_1_Coef.*$M14*_R²_Output -> 0.35113072 | P14: =Output_2_Coef.*$M14*_R²_Output -> 0.17883676 | Q14: =Output_3_Coef.*$M14*_R²_Output -> 0.38122764 | S14: =Total_Outcome_coef.*M14*_R²_Outcome -> -0.29190408 | U14: =Outcome_1_Coef.*$S14*_R²_Outcome -> -0.1126271 | V14: =Outcome_2_Coef.*$S14*_R²_Outcome -> 0.078281669 | W14: =Outcome_3_Coef.*$S14*_R²_Outcome -> -0.074393506 | Y14: =H14*$Y$3*_R²_Outcome -> -1.5405178 | Z14: =Y14+S14 -> -1.8324219 | AB14: =_R²_Impact*$Z14*Impact_1_Coef.*Total_Impact_coef. -> 0.47463592 | AC14: =_R²_Impact*$Z14*Impact_2_Coef.*Total_Impact_coef. -> 0.46362116 | AD14: =_xlfn.XLOOKUP($C14,SEM!$B:$B,SEM!$D:$D)+_xlfn.XLOOKUP($C14,SEM!$B:$B,SEM!$E:$E) -> 10.582695 | AE14: =_xlfn.XLOOKUP($C14,SEM!$B:$B,COMBINED!$AE:$AE)*AD14 -> 68268.964 | AF14: =_xlfn.XLOOKUP($C14,SEM!$B:$B,SEM!C:C) -> 5119136 | AG14: =AF14*AB14 -> 2429725.8 | AH14: =AG14/AE14 -> 35.590489
B15: Chad | C15: TCD | D15: =_xlfn.XLOOKUP($C15,SEM!$B:$B,SEM!$D:$D)*Model_1!$D$3 -> 3.776983 | E15: =_xlfn.XLOOKUP($C15,SEM!$B:$B,SEM!$E:$E)*Model_1!$E$3 -> 2.4474695 | H15: =Input_1_coef.*_xlfn.XLOOKUP($C15,COMBINED!$B:$B,COMBINED!$AB:$AB)+Input_2_coef.*_xlfn.XLOOKUP($C15,COMBINED!$B:$B,COMBINED!$AC:$AC) -> 6.2244525 | I15: =_xlfn.XLOOKUP($C15,COMBINED!$B:$B,COMBINED!$N:$N) -> 3.970162 | M15: =Total_Output_coef.*$H15*_R²_Output+(HWF_In_service_training_coef.*Percentage_of_people_trained*$H15)+($H15*Incentive*Percentage_of_people_incentivised) -> 0.98097372 | O15: =Output_1_Coef.*$M15*_R²_Output -> 0.21795274 | P15: =Output_2_Coef.*$M15*_R²_Output -> 0.11100699 | Q15: =Output_3_Coef.*$M15*_R²_Output -> 0.2366344 | S15: =Total_Outcome_coef.*M15*_R²_Outcome -> -0.18118977 | U15: =Outcome_1_Coef.*$S15*_R²_Outcome -> -0.069909536 | V15: =Outcome_2_Coef.*$S15*_R²_Outcome -> 0.048590748 | W15: =Outcome_3_Coef.*$S15*_R²_Outcome -> -0.0461773 | Y15: =H15*$Y$3*_R²_Outcome -> -0.95622529 | Z15: =Y15+S15 -> -1.1374151 | AB15: =_R²_Impact*$Z15*Impact_1_Coef.*Total_Impact_coef. -> 0.29461449 | AC15: =_R²_Impact*$Z15*Impact_2_Coef.*Total_Impact_coef. -> 0.28777745 | AD15: =_xlfn.XLOOKUP($C15,SEM!$B:$B,SEM!$D:$D)+_xlfn.XLOOKUP($C15,SEM!$B:$B,SEM!$E:$E) -> 8.0891657 | AE15: =_xlfn.XLOOKUP($C15,SEM!$B:$B,COMBINED!$AE:$AE)*AD15 -> 57554.414 | AF15: =_xlfn.XLOOKUP($C15,SEM!$B:$B,SEM!C:C) -> 17921183 | AG15: =AF15*AB15 -> 5279840.2 | AH15: =AG15/AE15 -> 91.736495
B16: Comoros | C16: COM | D16: =_xlfn.XLOOKUP($C16,SEM!$B:$B,SEM!$D:$D)*Model_1!$D$3 -> 19.750394 | E16: =_xlfn.XLOOKUP($C16,SEM!$B:$B,SEM!$E:$E)*Model_1!$E$3 -> 0.55328735 | H16: =Input_1_coef.*_xlfn.XLOOKUP($C16,COMBINED!$B:$B,COMBINED!$AB:$AB)+Input_2_coef.*_xlfn.XLOOKUP($C16,COMBINED!$B:$B,COMBINED!$AC:$AC) -> 20.303682 | I16: =_xlfn.XLOOKUP($C16,COMBINED!$B:$B,COMBINED!$N:$N) -> 21.306174 | M16: =Total_Output_coef.*$H16*_R²_Output+(HWF_In_service_training_coef.*Percentage_of_people_trained*$H16)+($H16*Incentive*Percentage_of_people_incentivised) -> 3.1998602 | O16: =Output_1_Coef.*$M16*_R²_Output -> 0.71094495 | P16: =Output_2_Coef.*$M16*_R²_Output -> 0.36209618 | Q16: =Output_3_Coef.*$M16*_R²_Output -> 0.77188308 | S16: =Total_Outcome_coef.*M16*_R²_Outcome -> -0.59102698 | U16: =Outcome_1_Coef.*$S16*_R²_Outcome -> -0.22803949 | V16: =Outcome_2_Coef.*$S16*_R²_Outcome -> 0.15849925 | W16: =Outcome_3_Coef.*$S16*_R²_Outcome -> -0.15062677 | Y16: =H16*$Y$3*_R²_Outcome -> -3.1191328 | Z16: =Y16+S16 -> -3.7101598 | AB16: =_R²_Impact*$Z16*Impact_1_Coef.*Total_Impact_coef. -> 0.96100964 | AC16: =_R²_Impact*$Z16*Impact_2_Coef.*Total_Impact_coef. -> 0.93870772 | AD16: =_xlfn.XLOOKUP($C16,SEM!$B:$B,SEM!$D:$D)+_xlfn.XLOOKUP($C16,SEM!$B:$B,SEM!$E:$E) -> 21.719783 | AE16: =_xlfn.XLOOKUP($C16,SEM!$B:$B,COMBINED!$AE:$AE)*AD16 -> 42874.853 | AF16: =_xlfn.XLOOKUP($C16,SEM!$B:$B,SEM!C:C) -> 926492 | AG16: =AF16*AB16 -> 890367.74 | AH16: =AG16/AE16 -> 20.766666
B17: Congo | C17: COG | D17: =_xlfn.XLOOKUP($C17,SEM!$B:$B,SEM!$D:$D)*Model_1!$D$3 -> 12.608213 | E17: =_xlfn.XLOOKUP($C17,SEM!$B:$B,SEM!$E:$E)*Model_1!$E$3 -> 0.25322484 | H17: =Input_1_coef.*_xlfn.XLOOKUP($C17,COMBINED!$B:$B,COMBINED!$AB:$AB)+Input_2_coef.*_xlfn.XLOOKUP($C17,COMBINED!$B:$B,COMBINED!$AC:$AC) -> 12.861438 | I17: =_xlfn.XLOOKUP($C17,COMBINED!$B:$B,COMBINED!$N:$N) -> 15.055348 | M17: =Total_Output_coef.*$H17*_R²_Output+(HWF_In_service_training_coef.*Percentage_of_people_trained*$H17)+($H17*Incentive*Percentage_of_people_incentivised) -> 2.0269626 | O17: =Output_1_Coef.*$M17*_R²_Output -> 0.45035054 | P17: =Output_2_Coef.*$M17*_R²_Output -> 0.22937108 | Q17: =Output_3_Coef.*$M17*_R²_Output -> 0.48895202 | S17: =Total_Outcome_coef.*M17*_R²_Outcome -> -0.37438809 | U17: =Outcome_1_Coef.*$S17*_R²_Outcome -> -0.1444524 | V17: =Outcome_2_Coef.*$S17*_R²_Outcome -> 0.1004019 | W17: =Outcome_3_Coef.*$S17*_R²_Outcome -> -0.095415052 | Y17: =H17*$Y$3*_R²_Outcome -> -1.9758255 | Z17: =Y17+S17 -> -2.3502136 | AB17: =_R²_Impact*$Z17*Impact_1_Coef.*Total_Impact_coef. -> 0.60875489 | AC17: =_R²_Impact*$Z17*Impact_2_Coef.*Total_Impact_coef. -> 0.59462766 | AD17: =_xlfn.XLOOKUP($C17,SEM!$B:$B,SEM!$D:$D)+_xlfn.XLOOKUP($C17,SEM!$B:$B,SEM!$E:$E) -> 13.697391 | AE17: =_xlfn.XLOOKUP($C17,SEM!$B:$B,COMBINED!$AE:$AE)*AD17 -> 122509.46 | AF17: =_xlfn.XLOOKUP($C17,SEM!$B:$B,SEM!C:C) -> 5940746 | AG17: =AF17*AB17 -> 3616458.2 | AH17: =AG17/AE17 -> 29.519827
B18: Côte d'Ivoire | C18: CIV | D18: =_xlfn.XLOOKUP($C18,SEM!$B:$B,SEM!$D:$D)*Model_1!$D$3 -> 10.231847 | E18: =_xlfn.XLOOKUP($C18,SEM!$B:$B,SEM!$E:$E)*Model_1!$E$3 -> 0.83009995 | H18: =Input_1_coef.*_xlfn.XLOOKUP($C18,COMBINED!$B:$B,COMBINED!$AB:$AB)+Input_2_coef.*_xlfn.XLOOKUP($C18,COMBINED!$B:$B,COMBINED!$AC:$AC) -> 11.061947 | I18: =_xlfn.XLOOKUP($C18,COMBINED!$B:$B,COMBINED!$N:$N) -> 11.257477 | M18: =Total_Output_coef.*$H18*_R²_Output+(HWF_In_service_training_coef.*Percentage_of_people_trained*$H18)+($H18*Incentive*Percentage_of_people_incentivised) -> 1.7433628 | O18: =Output_1_Coef.*$M18*_R²_Output -> 0.38734036 | P18: =Output_2_Coef.*$M18*_R²_Output -> 0.19727894 | Q18: =Output_3_Coef.*$M18*_R²_Output -> 0.42054096 | S18: =Total_Outcome_coef.*M18*_R²_Outcome -> -0.32200609 | U18: =Outcome_1_Coef.*$S18*_R²_Outcome -> -0.12424154 | V18: =Outcome_2_Coef.*$S18*_R²_Outcome -> 0.086354305 | W18: =Outcome_3_Coef.*$S18*_R²_Outcome -> -0.082065184 | Y18: =H18*$Y$3*_R²_Outcome -> -1.6993805 | Z18: =Y18+S18 -> -2.0213866 | AB18: =_R²_Impact*$Z18*Impact_1_Coef.*Total_Impact_coef. -> 0.52358177 | AC18: =_R²_Impact*$Z18*Impact_2_Coef.*Total_Impact_coef. -> 0.51143114 | AD18: =_xlfn.XLOOKUP($C18,SEM!$B:$B,SEM!$D:$D)+_xlfn.XLOOKUP($C18,SEM!$B:$B,SEM!$E:$E) -> 12.165491 | AE18: =_xlfn.XLOOKUP($C18,SEM!$B:$B,COMBINED!$AE:$AE)*AD18 -> 389551.19 | AF18: =_xlfn.XLOOKUP($C18,SEM!$B:$B,SEM!C:C) -> 28444206 | AG18: =AF18*AB18 -> 14892868 | AH18: =AG18/AE18 -> 38.230836
B19: Democratic Republic of the Congo | C19: COD | D19: =_xlfn.XLOOKUP($C19,SEM!$B:$B,SEM!$D:$D)*Model_1!$D$3 -> 12.862209 | E19: =_xlfn.XLOOKUP($C19,SEM!$B:$B,SEM!$E:$E)*Model_1!$E$3 -> 4.1014825 | H19: =Input_1_coef.*_xlfn.XLOOKUP($C19,COMBINED!$B:$B,COMBINED!$AB:$AB)+Input_2_coef.*_xlfn.XLOOKUP($C19,COMBINED!$B:$B,COMBINED!$AC:$AC) -> 16.963691 | I19: =_xlfn.XLOOKUP($C19,COMBINED!$B:$B,COMBINED!$N:$N) -> 15.093434 | M19: =Total_Output_coef.*$H19*_R²_Output+(HWF_In_service_training_coef.*Percentage_of_people_trained*$H19)+($H19*Incentive*Percentage_of_people_incentivised) -> 2.6734777 | O19: =Output_1_Coef.*$M19*_R²_Output -> 0.59399328 | P19: =Output_2_Coef.*$M19*_R²_Output -> 0.30253074 | Q19: =Output_3_Coef.*$M19*_R²_Output -> 0.64490699 | S19: =Total_Outcome_coef.*M19*_R²_Outcome -> -0.49380203 | U19: =Outcome_1_Coef.*$S19*_R²_Outcome -> -0.1905266 | V19: =Outcome_2_Coef.*$S19*_R²_Outcome -> 0.13242585 | W19: =Outcome_3_Coef.*$S19*_R²_Outcome -> -0.12584841 | Y19: =H19*$Y$3*_R²_Outcome -> -2.6060301 | Z19: =Y19+S19 -> -3.0998321 | AB19: =_R²_Impact*$Z19*Impact_1_Coef.*Total_Impact_coef. -> 0.80292189 | AC19: =_R²_Impact*$Z19*Impact_2_Coef.*Total_Impact_coef. -> 0.78428869 | AD19: =_xlfn.XLOOKUP($C19,SEM!$B:$B,SEM!$D:$D)+_xlfn.XLOOKUP($C19,SEM!$B:$B,SEM!$E:$E) -> 20.432415 | AE19: =_xlfn.XLOOKUP($C19,SEM!$B:$B,COMBINED!$AE:$AE)*AD19 -> 3026960.1 | AF19: =_xlfn.XLOOKUP($C19,SEM!$B:$B,SEM!C:C) -> 98151951 | AG19: =AF19*AB19 -> 78808350 | AH19: =AG19/AE19 -> 26.035477
... B52: Zimbabwe | C52: ZWE | D52: =_xlfn.XLOOKUP($C52,SEM!$B:$B,SEM!$D:$D)*Model_1!$D$3 -> 28.306845 | E52: =_xlfn.XLOOKUP($C52,SEM!$B:$B,SEM!$E:$E)*Model_1!$E$3 -> 1.4439883 | H52: =Input_1_coef.*_xlfn.XLOOKUP($C52,COMBINED!$B:$B,COMBINED!$AB:$AB)+Input_2_coef.*_xlfn.XLOOKUP($C52,COMBINED!$B:$B,COMBINED!$AC:$AC) -> 29.750833 | I52: =_xlfn.XLOOKUP($C52,COMBINED!$B:$B,COMBINED!$N:$N) -> 36.237672 | M52: =Total_Output_coef.*$H52*_R²_Output+(HWF_In_service_training_coef.*Percentage_of_people_trained*$H52)+($H52*Incentive*Percentage_of_people_incentivised) -> 4.6887313 | O52: =Output_1_Coef.*$M52*_R²_Output -> 1.0417423 | P52: =Output_2_Coef.*$M52*_R²_Output -> 0.53057683 | Q52: =Output_3_Coef.*$M52*_R²_Output -> 1.1310345 | S52: =Total_Outcome_coef.*M52*_R²_Outcome -> -0.86602743 | U52: =Outcome_1_Coef.*$S52*_R²_Outcome -> -0.33414456 | V52: =Outcome_2_Coef.*$S52*_R²_Outcome -> 0.23224777 | W52: =Outcome_3_Coef.*$S52*_R²_Outcome -> -0.22071229 | Y52: =H52*$Y$3*_R²_Outcome -> -4.570442 | Z52: =Y52+S52 -> -5.4364694 | AB52: =_R²_Impact*$Z52*Impact_1_Coef.*Total_Impact_coef. -> 1.4081602 | AC52: =_R²_Impact*$Z52*Impact_2_Coef.*Total_Impact_coef. -> 1.3754814 | AD52: =_xlfn.XLOOKUP($C52,SEM!$B:$B,SEM!$D:$D)+_xlfn.XLOOKUP($C52,SEM!$B:$B,SEM!$E:$E) -> 32.22355 | AE52: =_xlfn.XLOOKUP($C52,SEM!$B:$B,COMBINED!$AE:$AE)*AD52 -> 1819406.1 | AF52: =_xlfn.XLOOKUP($C52,SEM!$B:$B,SEM!C:C) -> 15581023 | AG52: =AF52*AB52 -> 21940577 | AH52: =AG52/AE52 -> 12.059198
AF53: =AVERAGE(AF6:AF52) -> 25692337 | AH53: =AVERAGE(AH6:AH52) -> 31.911477

Sheet Model_2
K1: HWF Performance | AA1: Borrowed from Model 1
D2: Input 1 coef. | E2: Input 2 coef. | F2: Input 3 coef. | G2: Percentage of HWF benefiting from the salary increase | I2: Percentage of people trained | J2: Percentage of people incentivised | K2: HWF In-service training coef. | L2: Incentive | N2: Total Output coef. | O2: R²_Output | P2: Output 1 Coef. | Q2: Output 2 Coef. | R2: Output 3 Coef. | T2: Total Outcome coef. | U2: R²_Outcome | V2: Outcome 1 Coef. | W2: Outcome 2 Coef. | X2: Outcome 3 Coef. | Z2: Direct effect from HWF availability to Outcome | AA2: Total Impact coef. | AB2: R²_Impact | AC2: Impact 1 Coef. | AD2: Impact 2 Coef.
D3: 0.95 | E3: 0.595 | F3: 0.2 | G3: 1 | I3: 0.1 | J3: 0.1 | K3: 0.115 | L3: 0.012 | N3: 0.525 | O3: 0.276 | P3: 0.805 | Q3: 0.41 | R3: 0.874 | T3: -0.416 | U3: 0.444 | V3: 0.869 | W3: -0.604 | X3: 0.574 | Z3: -0.346 | AA3: -0.658 | AB3: 0.432 | AC3: 1
D4: Investments | I4: HWF Availability | P4: SCI_Infectious diseases | Q4: SCI_NCD | R4: SCI_RMNCH | V4: DALYS_2021_Communicable, maternal, perinatal and nutritional conditions per capita 2021 | W4: DALYS_2021_Noncommunicable diseases per capita (2021) | X4: DALYS_2021_Injuries per capita 2021 | AC4: GDP per capita growth (annual %)
B5: Country | C5: ISO | D5: Education | E5: Employement | F5: Retention | I5: HWF Availability Estimation | J5: Real value | N5: Total Output | T5: Total Outcome from output | Z5: Direct Outcome from HWF availability | AA5: Total Impact
B6: Algeria | C6: DZA | D6: =_xlfn.XLOOKUP($C6,SEM!$B:$B,SEM!$D:$D)*Input_1_coef. -> 57.962378 | E6: =_xlfn.XLOOKUP($C6,SEM!$B:$B,SEM!$E:$E)*Input_2_coef. -> 0.079844134 | F6: =$E6*Input_3_coef.*Percentage_of_HWF_benefiting_from_the_salary_increase -> 0.015968827 | H6: =+IF(Input_3_coef.>=0.54,D6+E6+F6,D6+E6) -> 58.042222 | I6: =IF(Input_3_coef.>=0.54,(Input_1_coef.*_xlfn.XLOOKUP($C6,COMBINED!$B:$B,COMBINED!$AB:$AB)+Input_2_coef.*_xlfn.XLOOKUP($C6,COMBINED!$B:$B,COMBINED!$AC:$AC))+F6,(Input_1_coef.*_xlfn.XLOOKUP($C6,COMBINED!$B:$B,COMBINED!$AB:$AB)+Input_2_coef.*_xlfn.XLOOKUP($C6,COMBINED!$B:$B,COMBINED!$AC:$AC))) -> 58.042222 | J6: =_xlfn.XLOOKUP($C6,COMBINED!$B:$B,COMBINED!$N:$N) -> 50.985293 | N6: =Total_Output_coef.*$I6*_R²_Output+(HWF_In_service_training_coef.*Percentage_of_people_trained*$I6)+($I6*Incentive*Percentage_of_people_incentivised) -> 9.1474542 | P6: =Output_1_Coef.*$N6*_R²_Output -> 2.0323814 | Q6: =Output_2_Coef.*$N6*_R²_Output -> 1.0351259 | R6: =Output_3_Coef.*$N6*_R²_Output -> 2.2065855 | T6: =Total_Outcome_coef.*N6*_R²_Outcome -> -1.6895714 | V6: =Outcome_1_Coef.*$T6*_R²_Outcome -> -0.65189747 | W6: =Outcome_2_Coef.*$T6*_R²_Outcome -> 0.4531025 | X6: =Outcome_3_Coef.*$T6*_R²_Outcome -> -0.4305974 | Z6: =I6*$Z$3*_R²_Outcome -> -8.9166784 | AA6: =Z6+T6 -> -10.60625 | AC6: =_R²_Impact*$AA6*Impact_1_Coef.*Total_Impact_coef. -> 3.0148901 | AD6: =_R²_Impact*$AA6*Impact_2_Coef.*Total_Impact_coef. -> 0
B7: Angola | C7: AGO | D7: =_xlfn.XLOOKUP($C7,SEM!$B:$B,SEM!$D:$D)*Input_1_coef. -> 17.625891 | E7: =_xlfn.XLOOKUP($C7,SEM!$B:$B,SEM!$E:$E)*Input_2_coef. -> 1.4641268 | F7: =$E7*Input_3_coef.*Percentage_of_HWF_benefiting_from_the_salary_increase -> 0.29282536 | H7: =+IF(Input_3_coef.>=0.54,D7+E7+F7,D7+E7) -> 19.090018 | I7: =IF(Input_3_coef.>=0.54,(Input_1_coef.*_xlfn.XLOOKUP($C7,COMBINED!$B:$B,COMBINED!$AB:$AB)+Input_2_coef.*_xlfn.XLOOKUP($C7,COMBINED!$B:$B,COMBINED!$AC:$AC))+F7,(Input_1_coef.*_xlfn.XLOOKUP($C7,COMBINED!$B:$B,COMBINED!$AB:$AB)+Input_2_coef.*_xlfn.XLOOKUP($C7,COMBINED!$B:$B,COMBINED!$AC:$AC))) -> 19.090018 | J7: =_xlfn.XLOOKUP($C7,COMBINED!$B:$B,COMBINED!$N:$N) -> 21.346034 | N7: =Total_Output_coef.*$I7*_R²_Output+(HWF_In_service_training_coef.*Percentage_of_people_trained*$I7)+($I7*Incentive*Percentage_of_people_incentivised) -> 3.0085868 | P7: =Output_1_Coef.*$N7*_R²_Output -> 0.66844782 | Q7: =Output_2_Coef.*$N7*_R²_Output -> 0.34045168 | R7: =Output_3_Coef.*$N7*_R²_Output -> 0.72574334 | T7: =Total_Outcome_coef.*N7*_R²_Outcome -> -0.55569802 | V7: =Outcome_1_Coef.*$T7*_R²_Outcome -> -0.2144083 | W7: =Outcome_2_Coef.*$T7*_R²_Outcome -> 0.14902487 | X7: =Outcome_3_Coef.*$T7*_R²_Outcome -> -0.14162297 | Z7: =I7*$Z$3*_R²_Outcome -> -2.9326849 | AA7: =Z7+T7 -> -3.4883829 | AC7: =_R²_Impact*$AA7*Impact_1_Coef.*Total_Impact_coef. -> 0.99159377 | AD7: =_R²_Impact*$AA7*Impact_2_Coef.*Total_Impact_coef. -> 0
B8: Benin | C8: BEN | D8: =_xlfn.XLOOKUP($C8,SEM!$B:$B,SEM!$D:$D)*Input_1_coef. -> 10.340617 | E8: =_xlfn.XLOOKUP($C8,SEM!$B:$B,SEM!$E:$E)*Input_2_coef. -> 1.6822017 | F8: =$E8*Input_3_coef.*Percentage_of_HWF_benefiting_from_the_salary_increase -> 0.33644035 | H8: =+IF(Input_3_coef.>=0.54,D8+E8+F8,D8+E8) -> 12.022819 | I8: =IF(Input_3_coef.>=0.54,(Input_1_coef.*_xlfn.XLOOKUP($C8,COMBINED!$B:$B,COMBINED!$AB:$AB)+Input_2_coef.*_xlfn.XLOOKUP($C8,COMBINED!$B:$B,COMBINED!$AC:$AC))+F8,(Input_1_coef.*_xlfn.XLOOKUP($C8,COMBINED!$B:$B,COMBINED!$AB:$AB)+Input_2_coef.*_xlfn.XLOOKUP($C8,COMBINED!$B:$B,COMBINED!$AC:$AC))) -> 12.022819 | J8: =_xlfn.XLOOKUP($C8,COMBINED!$B:$B,COMBINED!$N:$N) -> 11.015405 | N8: =Total_Output_coef.*$I8*_R²_Output+(HWF_In_service_training_coef.*Percentage_of_people_trained*$I8)+($I8*Incentive*Percentage_of_people_incentivised) -> 1.8947963 | P8: =Output_1_Coef.*$N8*_R²_Output -> 0.42098584 | Q8: =Output_2_Coef.*$N8*_R²_Output -> 0.21441515 | R8: =Output_3_Coef.*$N8*_R²_Output -> 0.45707034 | T8: =Total_Outcome_coef.*N8*_R²_Outcome -> -0.34997645 | V8: =Outcome_1_Coef.*$T8*_R²_Outcome -> -0.13503351 | W8: =Outcome_2_Coef.*$T8*_R²_Outcome -> 0.093855285 | X8: =Outcome_3_Coef.*$T8*_R²_Outcome -> -0.089193598 | Z8: =I8*$Z$3*_R²_Outcome -> -1.8469935 | AA8: =Z8+T8 -> -2.19697 | AC8: =_R²_Impact*$AA8*Impact_1_Coef.*Total_Impact_coef. -> 0.6245019 | AD8: =_R²_Impact*$AA8*Impact_2_Coef.*Total_Impact_coef. -> 0
B9: Botswana | C9: BWA | D9: =_xlfn.XLOOKUP($C9,SEM!$B:$B,SEM!$D:$D)*Input_1_coef. -> 30.438514 | E9: =_xlfn.XLOOKUP($C9,SEM!$B:$B,SEM!$E:$E)*Input_2_coef. -> 3.8046021 | F9: =$E9*Input_3_coef.*Percentage_of_HWF_benefiting_from_the_salary_increase -> 0.76092042 | H9: =+IF(Input_3_coef.>=0.54,D9+E9+F9,D9+E9) -> 34.243116 | I9: =IF(Input_3_coef.>=0.54,(Input_1_coef.*_xlfn.XLOOKUP($C9,COMBINED!$B:$B,COMBINED!$AB:$AB)+Input_2_coef.*_xlfn.XLOOKUP($C9,COMBINED!$B:$B,COMBINED!$AC:$AC))+F9,(Input_1_coef.*_xlfn.XLOOKUP($C9,COMBINED!$B:$B,COMBINED!$AB:$AB)+Input_2_coef.*_xlfn.XLOOKUP($C9,COMBINED!$B:$B,COMBINED!$AC:$AC))) -> 34.243116 | J9: =_xlfn.XLOOKUP($C9,COMBINED!$B:$B,COMBINED!$N:$N) -> 36.670298 | N9: =Total_Output_coef.*$I9*_R²_Output+(HWF_In_service_training_coef.*Percentage_of_people_trained*$I9)+($I9*Incentive*Percentage_of_people_incentivised) -> 5.396715 | P9: =Output_1_Coef.*$N9*_R²_Output -> 1.1990421 | Q9: =Output_2_Coef.*$N9*_R²_Output -> 0.61069227 | R9: =Output_3_Coef.*$N9*_R²_Output -> 1.3018172 | T9: =Total_Outcome_coef.*N9*_R²_Outcome -> -0.99679486 | V9: =Outcome_1_Coef.*$T9*_R²_Outcome -> -0.38459934 | W9: =Outcome_2_Coef.*$T9*_R²_Outcome -> 0.26731646 | X9: =Outcome_3_Coef.*$T9*_R²_Outcome -> -0.25403915 | Z9: =I9*$Z$3*_R²_Outcome -> -5.2605644 | AA9: =Z9+T9 -> -6.2573593 | AC9: =_R²_Impact*$AA9*Impact_1_Coef.*Total_Impact_coef. -> 1.7786919 | AD9: =_R²_Impact*$AA9*Impact_2_Coef.*Total_Impact_coef. -> 0
B10: Burkina Faso | C10: BFA | D10: =_xlfn.XLOOKUP($C10,SEM!$B:$B,SEM!$D:$D)*Input_1_coef. -> 10.388772 | E10: =_xlfn.XLOOKUP($C10,SEM!$B:$B,SEM!$E:$E)*Input_2_coef. -> 1.7875747 | F10: =$E10*Input_3_coef.*Percentage_of_HWF_benefiting_from_the_salary_increase -> 0.35751494 | H10: =+IF(Input_3_coef.>=0.54,D10+E10+F10,D10+E10) -> 12.176347 | I10: =IF(Input_3_coef.>=0.54,(Input_1_coef.*_xlfn.XLOOKUP($C10,COMBINED!$B:$B,COMBINED!$AB:$AB)+Input_2_coef.*_xlfn.XLOOKUP($C10,COMBINED!$B:$B,COMBINED!$AC:$AC))+F10,(Input_1_coef.*_xlfn.XLOOKUP($C10,COMBINED!$B:$B,COMBINED!$AB:$AB)+Input_2_coef.*_xlfn.XLOOKUP($C10,COMBINED!$B:$B,COMBINED!$AC:$AC))) -> 12.176347 | J10: =_xlfn.XLOOKUP($C10,COMBINED!$B:$B,COMBINED!$N:$N) -> 12.022002 | N10: =Total_Output_coef.*$I10*_R²_Output+(HWF_In_service_training_coef.*Percentage_of_people_trained*$I10)+($I10*Incentive*Percentage_of_people_incentivised) -> 1.9189922 | P10: =Output_1_Coef.*$N10*_R²_Output -> 0.42636169 | Q10: =Output_2_Coef.*$N10*_R²_Output -> 0.21715316 | R10: =Output_3_Coef.*$N10*_R²_Output -> 0.46290698 | T10: =Total_Outcome_coef.*N10*_R²_Outcome -> -0.35444554 | V10: =Outcome_1_Coef.*$T10*_R²_Outcome -> -0.13675785 | W10: =Outcome_2_Coef.*$T10*_R²_Outcome -> 0.095053787 | X10: =Outcome_3_Coef.*$T10*_R²_Outcome -> -0.090332572 | Z10: =I10*$Z$3*_R²_Outcome -> -1.8705791 | AA10: =Z10+T10 -> -2.2250246 | AC10: =_R²_Impact*$AA10*Impact_1_Coef.*Total_Impact_coef. -> 0.63247659 | AD10: =_R²_Impact*$AA10*Impact_2_Coef.*Total_Impact_coef. -> 0
B11: Burundi | C11: BDI | D11: =_xlfn.XLOOKUP($C11,SEM!$B:$B,SEM!$D:$D)*Input_1_coef. -> 8.9556615 | E11: =_xlfn.XLOOKUP($C11,SEM!$B:$B,SEM!$E:$E)*Input_2_coef. -> 1.9559756 | F11: =$E11*Input_3_coef.*Percentage_of_HWF_benefiting_from_the_salary_increase -> 0.39119511 | H11: =+IF(Input_3_coef.>=0.54,D11+E11+F11,D11+E11) -> 10.911637 | I11: =IF(Input_3_coef.>=0.54,(Input_1_coef.*_xlfn.XLOOKUP($C11,COMBINED!$B:$B,COMBINED!$AB:$AB)+Input_2_coef.*_xlfn.XLOOKUP($C11,COMBINED!$B:$B,COMBINED!$AC:$AC))+F11,(Input_1_coef.*_xlfn.XLOOKUP($C11,COMBINED!$B:$B,COMBINED!$AB:$AB)+Input_2_coef.*_xlfn.XLOOKUP($C11,COMBINED!$B:$B,COMBINED!$AC:$AC))) -> 10.911637 | J11: =_xlfn.XLOOKUP($C11,COMBINED!$B:$B,COMBINED!$N:$N) -> 11.321517 | N11: =Total_Output_coef.*$I11*_R²_Output+(HWF_In_service_training_coef.*Percentage_of_people_trained*$I11)+($I11*Incentive*Percentage_of_people_incentivised) -> 1.719674 | P11: =Output_1_Coef.*$N11*_R²_Output -> 0.38207717 | Q11: =Output_2_Coef.*$N11*_R²_Output -> 0.19459831 | R11: =Output_3_Coef.*$N11*_R²_Output -> 0.41482664 | T11: =Total_Outcome_coef.*N11*_R²_Outcome -> -0.31763067 | V11: =Outcome_1_Coef.*$T11*_R²_Outcome -> -0.12255335 | W11: =Outcome_2_Coef.*$T11*_R²_Outcome -> 0.085180921 | X11: =Outcome_3_Coef.*$T11*_R²_Outcome -> -0.080950081 | Z11: =I11*$Z$3*_R²_Outcome -> -1.6762893 | AA11: =Z11+T11 -> -1.99392 | AC11: =_R²_Impact*$AA11*Impact_1_Coef.*Total_Impact_coef. -> 0.56678372 | AD11: =_R²_Impact*$AA11*Impact_2_Coef.*Total_Impact_coef. -> 0
B12: Cabo Verde | C12: CPV | D12: =_xlfn.XLOOKUP($C12,SEM!$B:$B,SEM!$D:$D)*Input_1_coef. -> 23.302042 | E12: =_xlfn.XLOOKUP($C12,SEM!$B:$B,SEM!$E:$E)*Input_2_coef. -> 0 | F12: =$E12*Input_3_coef.*Percentage_of_HWF_benefiting_from_the_salary_increase -> 0 | H12: =+IF(Input_3_coef.>=0.54,D12+E12+F12,D12+E12) -> 23.302042 | I12: =IF(Input_3_coef.>=0.54,(Input_1_coef.*_xlfn.XLOOKUP($C12,COMBINED!$B:$B,COMBINED!$AB:$AB)+Input_2_coef.*_xlfn.XLOOKUP($C12,COMBINED!$B:$B,COMBINED!$AC:$AC))+F12,(Input_1_coef.*_xlfn.XLOOKUP($C12,COMBINED!$B:$B,COMBINED!$AB:$AB)+Input_2_coef.*_xlfn.XLOOKUP($C12,COMBINED!$B:$B,COMBINED!$AC:$AC))) -> 23.302042 | J12: =_xlfn.XLOOKUP($C12,COMBINED!$B:$B,COMBINED!$N:$N) -> 24.000474 | N12: =Total_Output_coef.*$I12*_R²_Output+(HWF_In_service_training_coef.*Percentage_of_people_trained*$I12)+($I12*Incentive*Percentage_of_people_incentivised) -> 3.6724018 | P12: =Output_1_Coef.*$N12*_R²_Output -> 0.81593424 | Q12: =Output_2_Coef.*$N12*_R²_Output -> 0.41556899 | R12: =Output_3_Coef.*$N12*_R²_Output -> 0.88587146 | T12: =Total_Outcome_coef.*N12*_R²_Outcome -> -0.67830731 | V12: =Outcome_1_Coef.*$T12*_R²_Outcome -> -0.26171538 | W12: =Outcome_2_Coef.*$T12*_R²_Outcome -> 0.18190574 | X12: =Outcome_3_Coef.*$T12*_R²_Outcome -> -0.17287069 | Z12: =I12*$Z$3*_R²_Outcome -> -3.5797529 | AA12: =Z12+T12 -> -4.2580602 | AC12: =_R²_Impact*$AA12*Impact_1_Coef.*Total_Impact_coef. -> 1.2103792 | AD12: =_R²_Impact*$AA12*Impact_2_Coef.*Total_Impact_coef. -> 0
B13: Cameroon | C13: CMR | D13: =_xlfn.XLOOKUP($C13,SEM!$B:$B,SEM!$D:$D)*Input_1_coef. -> 7.3058506 | E13: =_xlfn.XLOOKUP($C13,SEM!$B:$B,SEM!$E:$E)*Input_2_coef. -> 1.7263244 | F13: =$E13*Input_3_coef.*Percentage_of_HWF_benefiting_from_the_salary_increase -> 0.34526487 | H13: =+IF(Input_3_coef.>=0.54,D13+E13+F13,D13+E13) -> 9.032175 | I13: =IF(Input_3_coef.>=0.54,(Input_1_coef.*_xlfn.XLOOKUP($C13,COMBINED!$B:$B,COMBINED!$AB:$AB)+Input_2_coef.*_xlfn.XLOOKUP($C13,COMBINED!$B:$B,COMBINED!$AC:$AC))+F13,(Input_1_coef.*_xlfn.XLOOKUP($C13,COMBINED!$B:$B,COMBINED!$AB:$AB)+Input_2_coef.*_xlfn.XLOOKUP($C13,COMBINED!$B:$B,COMBINED!$AC:$AC))) -> 9.032175 | J13: =_xlfn.XLOOKUP($C13,COMBINED!$B:$B,COMBINED!$N:$N) -> 8.1868339 | N13: =Total_Output_coef.*$I13*_R²_Output+(HWF_In_service_training_coef.*Percentage_of_people_trained*$I13)+($I13*Incentive*Percentage_of_people_incentivised) -> 1.4234708 | P13: =Output_1_Coef.*$N13*_R²_Output -> 0.31626674 | Q13: =Output_2_Coef.*$N13*_R²_Output -> 0.16107995 | R13: =Output_3_Coef.*$N13*_R²_Output -> 0.34337531 | T13: =Total_Outcome_coef.*N13*_R²_Outcome -> -0.26292075 | V13: =Outcome_1_Coef.*$T13*_R²_Outcome -> -0.10144429 | W13: =Outcome_2_Coef.*$T13*_R²_Outcome -> 0.070509034 | X13: =Outcome_3_Coef.*$T13*_R²_Outcome -> -0.06700693 | Z13: =I13*$Z$3*_R²_Outcome -> -1.3875588 | AA13: =Z13+T13 -> -1.6504796 | AC13: =_R²_Impact*$AA13*Impact_1_Coef.*Total_Impact_coef. -> 0.46915873 | AD13: =_R²_Impact*$AA13*Impact_2_Coef.*Total_Impact_coef. -> 0
B14: Central African Republic | C14: CAF | D14: =_xlfn.XLOOKUP($C14,SEM!$B:$B,SEM!$D:$D)*Input_1_coef. -> 9.9847476 | E14: =_xlfn.XLOOKUP($C14,SEM!$B:$B,SEM!$E:$E)*Input_2_coef. -> 0.043098288 | F14: =$E14*Input_3_coef.*Percentage_of_HWF_benefiting_from_the_salary_increase -> 0.0086196577 | H14: =+IF(Input_3_coef.>=0.54,D14+E14+F14,D14+E14) -> 10.027846 | I14: =IF(Input_3_coef.>=0.54,(Input_1_coef.*_xlfn.XLOOKUP($C14,COMBINED!$B:$B,COMBINED!$AB:$AB)+Input_2_coef.*_xlfn.XLOOKUP($C14,COMBINED!$B:$B,COMBINED!$AC:$AC))+F14,(Input_1_coef.*_xlfn.XLOOKUP($C14,COMBINED!$B:$B,COMBINED!$AB:$AB)+Input_2_coef.*_xlfn.XLOOKUP($C14,COMBINED!$B:$B,COMBINED!$AC:$AC))) -> 10.027846 | J14: =_xlfn.XLOOKUP($C14,COMBINED!$B:$B,COMBINED!$N:$N) -> 12.601736 | N14: =Total_Output_coef.*$I14*_R²_Output+(HWF_In_service_training_coef.*Percentage_of_people_trained*$I14)+($I14*Incentive*Percentage_of_people_incentivised) -> 1.5803885 | P14: =Output_1_Coef.*$N14*_R²_Output -> 0.35113072 | Q14: =Output_2_Coef.*$N14*_R²_Output -> 0.17883676 | R14: =Output_3_Coef.*$N14*_R²_Output -> 0.38122764 | T14: =Total_Outcome_coef.*N14*_R²_Outcome -> -0.29190408 | V14: =Outcome_1_Coef.*$T14*_R²_Outcome -> -0.1126271 | W14: =Outcome_2_Coef.*$T14*_R²_Outcome -> 0.078281669 | X14: =Outcome_3_Coef.*$T14*_R²_Outcome -> -0.074393506 | Z14: =I14*$Z$3*_R²_Outcome -> -1.5405178 | AA14: =Z14+T14 -> -1.8324219 | AC14: =_R²_Impact*$AA14*Impact_1_Coef.*Total_Impact_coef. -> 0.52087691 | AD14: =_R²_Impact*$AA14*Impact_2_Coef.*Total_Impact_coef. -> 0
B15: Chad | C15: TCD | D15: =_xlfn.XLOOKUP($C15,SEM!$B:$B,SEM!$D:$D)*Input_1_coef. -> 3.776983 | E15: =_xlfn.XLOOKUP($C15,SEM!$B:$B,SEM!$E:$E)*Input_2_coef. -> 2.4474695 | F15: =$E15*Input_3_coef.*Percentage_of_HWF_benefiting_from_the_salary_increase -> 0.48949391 | H15: =+IF(Input_3_coef.>=0.54,D15+E15+F15,D15+E15) -> 6.2244525 | I15: =IF(Input_3_coef.>=0.54,(Input_1_coef.*_xlfn.XLOOKUP($C15,COMBINED!$B:$B,COMBINED!$AB:$AB)+Input_2_coef.*_xlfn.XLOOKUP($C15,COMBINED!$B:$B,COMBINED!$AC:$AC))+F15,(Input_1_coef.*_xlfn.XLOOKUP($C15,COMBINED!$B:$B,COMBINED!$AB:$AB)+Input_2_coef.*_xlfn.XLOOKUP($C15,COMBINED!$B:$B,COMBINED!$AC:$AC))) -> 6.2244525 | J15: =_xlfn.XLOOKUP($C15,COMBINED!$B:$B,COMBINED!$N:$N) -> 3.970162 | N15: =Total_Output_coef.*$I15*_R²_Output+(HWF_In_service_training_coef.*Percentage_of_people_trained*$I15)+($I15*Incentive*Percentage_of_people_incentivised) -> 0.98097372 | P15: =Output_1_Coef.*$N15*_R²_Output -> 0.21795274 | Q15: =Output_2_Coef.*$N15*_R²_Output -> 0.11100699 | R15: =Output_3_Coef.*$N15*_R²_Output -> 0.2366344 | T15: =Total_Outcome_coef.*N15*_R²_Outcome -> -0.18118977 | V15: =Outcome_1_Coef.*$T15*_R²_Outcome -> -0.069909536 | W15: =Outcome_2_Coef.*$T15*_R²_Outcome -> 0.048590748 | X15: =Outcome_3_Coef.*$T15*_R²_Outcome -> -0.0461773 | Z15: =I15*$Z$3*_R²_Outcome -> -0.95622529 | AA15: =Z15+T15 -> -1.1374151 | AC15: =_R²_Impact*$AA15*Impact_1_Coef.*Total_Impact_coef. -> 0.32331706 | AD15: =_R²_Impact*$AA15*Impact_2_Coef.*Total_Impact_coef. -> 0
B16: Comoros | C16: COM | D16: =_xlfn.XLOOKUP($C16,SEM!$B:$B,SEM!$D:$D)*Input_1_coef. -> 19.750394 | E16: =_xlfn.XLOOKUP($C16,SEM!$B:$B,SEM!$E:$E)*Input_2_coef. -> 0.55328735 | F16: =$E16*Input_3_coef.*Percentage_of_HWF_benefiting_from_the_salary_increase -> 0.11065747 | H16: =+IF(Input_3_coef.>=0.54,D16+E16+F16,D16+E16) -> 20.303682 | I16: =IF(Input_3_coef.>=0.54,(Input_1_coef.*_xlfn.XLOOKUP($C16,COMBINED!$B:$B,COMBINED!$AB:$AB)+Input_2_coef.*_xlfn.XLOOKUP($C16,COMBINED!$B:$B,COMBINED!$AC:$AC))+F16,(Input_1_coef.*_xlfn.XLOOKUP($C16,COMBINED!$B:$B,COMBINED!$AB:$AB)+Input_2_coef.*_xlfn.XLOOKUP($C16,COMBINED!$B:$B,COMBINED!$AC:$AC))) -> 20.303682 | J16: =_xlfn.XLOOKUP($C16,COMBINED!$B:$B,COMBINED!$N:$N) -> 21.306174 | N16: =Total_Output_coef.*$I16*_R²_Output+(HWF_In_service_training_coef.*Percentage_of_people_trained*$I16)+($I16*Incentive*Percentage_of_people_incentivised) -> 3.1998602 | P16: =Output_1_Coef.*$N16*_R²_Output -> 0.71094495 | Q16: =Output_2_Coef.*$N16*_R²_Output -> 0.36209618 | R16: =Output_3_Coef.*$N16*_R²_Output -> 0.77188308 | T16: =Total_Outcome_coef.*N16*_R²_Outcome -> -0.59102698 | V16: =Outcome_1_Coef.*$T16*_R²_Outcome -> -0.22803949 | W16: =Outcome_2_Coef.*$T16*_R²_Outcome -> 0.15849925 | X16: =Outcome_3_Coef.*$T16*_R²_Outcome -> -0.15062677 | Z16: =I16*$Z$3*_R²_Outcome -> -3.1191328 | AA16: =Z16+T16 -> -3.7101598 | AC16: =_R²_Impact*$AA16*Impact_1_Coef.*Total_Impact_coef. -> 1.0546352 | AD16: =_R²_Impact*$AA16*Impact_2_Coef.*Total_Impact_coef. -> 0
B17: Congo | C17: COG | D17: =_xlfn.XLOOKUP($C17,SEM!$B:$B,SEM!$D:$D)*Input_1_coef. -> 12.608213 | E17: =_xlfn.XLOOKUP($C17,SEM!$B:$B,SEM!$E:$E)*Input_2_coef. -> 0.25322484 | F17: =$E17*Input_3_coef.*Percentage_of_HWF_benefiting_from_the_salary_increase -> 0.050644968 | H17: =+IF(Input_3_coef.>=0.54,D17+E17+F17,D17+E17) -> 12.861438 | I17: =IF(Input_3_coef.>=0.54,(Input_1_coef.*_xlfn.XLOOKUP($C17,COMBINED!$B:$B,COMBINED!$AB:$AB)+Input_2_coef.*_xlfn.XLOOKUP($C17,COMBINED!$B:$B,COMBINED!$AC:$AC))+F17,(Input_1_coef.*_xlfn.XLOOKUP($C17,COMBINED!$B:$B,COMBINED!$AB:$AB)+Input_2_coef.*_xlfn.XLOOKUP($C17,COMBINED!$B:$B,COMBINED!$AC:$AC))) -> 12.861438 | J17: =_xlfn.XLOOKUP($C17,COMBINED!$B:$B,COMBINED!$N:$N) -> 15.055348 | N17: =Total_Output_coef.*$I17*_R²_Output+(HWF_In_service_training_coef.*Percentage_of_people_trained*$I17)+($I17*Incentive*Percentage_of_people_incentivised) -> 2.0269626 | P17: =Output_1_Coef.*$N17*_R²_Output -> 0.45035054 | Q17: =Output_2_Coef.*$N17*_R²_Output -> 0.22937108 | R17: =Output_3_Coef.*$N17*_R²_Output -> 0.48895202 | T17: =Total_Outcome_coef.*N17*_R²_Outcome -> -0.37438809 | V17: =Outcome_1_Coef.*$T17*_R²_Outcome -> -0.1444524 | W17: =Outcome_2_Coef.*$T17*_R²_Outcome -> 0.1004019 | X17: =Outcome_3_Coef.*$T17*_R²_Outcome -> -0.095415052 | Z17: =I17*$Z$3*_R²_Outcome -> -1.9758255 | AA17: =Z17+T17 -> -2.3502136 | AC17: =_R²_Impact*$AA17*Impact_1_Coef.*Total_Impact_coef. -> 0.66806231 | AD17: =_R²_Impact*$AA17*Impact_2_Coef.*Total_Impact_coef. -> 0
... B52: Zimbabwe | C52: ZWE | D52: =_xlfn.XLOOKUP($C52,SEM!$B:$B,SEM!$D:$D)*Input_1_coef. -> 28.306845 | E52: =_xlfn.XLOOKUP($C52,SEM!$B:$B,SEM!$E:$E)*Input_2_coef. -> 1.4439883 | F52: =$E52*Input_3_coef.*Percentage_of_HWF_benefiting_from_the_salary_increase -> 0.28879765 | H52: =+IF(Input_3_coef.>=0.54,D52+E52+F52,D52+E52) -> 29.750833 | I52: =IF(Input_3_coef.>=0.54,(Input_1_coef.*_xlfn.XLOOKUP($C52,COMBINED!$B:$B,COMBINED!$AB:$AB)+Input_2_coef.*_xlfn.XLOOKUP($C52,COMBINED!$B:$B,COMBINED!$AC:$AC))+F52,(Input_1_coef.*_xlfn.XLOOKUP($C52,COMBINED!$B:$B,COMBINED!$AB:$AB)+Input_2_coef.*_xlfn.XLOOKUP($C52,COMBINED!$B:$B,COMBINED!$AC:$AC))) -> 29.750833 | J52: =_xlfn.XLOOKUP($C52,COMBINED!$B:$B,COMBINED!$N:$N) -> 36.237672 | N52: =Total_Output_coef.*$I52*_R²_Output+(HWF_In_service_training_coef.*Percentage_of_people_trained*$I52)+($I52*Incentive*Percentage_of_people_incentivised) -> 4.6887313 | P52: =Output_1_Coef.*$N52*_R²_Output -> 1.0417423 | Q52: =Output_2_Coef.*$N52*_R²_Output -> 0.53057683 | R52: =Output_3_Coef.*$N52*_R²_Output -> 1.1310345 | T52: =Total_Outcome_coef.*N52*_R²_Outcome -> -0.86602743 | V52: =Outcome_1_Coef.*$T52*_R²_Outcome -> -0.33414456 | W52: =Outcome_2_Coef.*$T52*_R²_Outcome -> 0.23224777 | X52: =Outcome_3_Coef.*$T52*_R²_Outcome -> -0.22071229 | Z52: =I52*$Z$3*_R²_Outcome -> -4.570442 | AA52: =Z52+T52 -> -5.4364694 | AC52: =_R²_Impact*$AA52*Impact_1_Coef.*Total_Impact_coef. -> 1.545349 | AD52: =_R²_Impact*$AA52*Impact_2_Coef.*Total_Impact_coef. -> 0
B53: Average | D53: =AVERAGE(D6:D52) -> 23.481876 | E53: =AVERAGE(E6:E52) -> 2.065907 | F53: =AVERAGE(F6:F52) -> 0.41318141 | H53: =AVERAGE(H6:H52) -> 25.547783 | I53: =AVERAGE(I6:I52) -> 25.547783 | J53: =AVERAGE(J6:J52) -> 25.627865 | N53: =AVERAGE(N6:N52) -> 4.0263307 | P53: =AVERAGE(P6:P52) -> 0.89457015 | Q53: =AVERAGE(Q6:Q52) -> 0.45561958 | R53: =AVERAGE(R6:R52) -> 0.97124759 | T53: =AVERAGE(T6:T52) -> -0.74367938 | V53: =AVERAGE(V6:V52) -> -0.28693828 | W53: =AVERAGE(W6:W52) -> 0.19943696 | X53: =AVERAGE(X6:X52) -> -0.18953115 | Z53: =AVERAGE(Z6:Z52) -> -3.9247527 | AA53: =AVERAGE(AA6:AA52) -> -4.6684321 | AC53: =AVERAGE(AC6:AC52) -> 1.3270298 | AD53: =AVERAGE(AD6:AD52) -> 0

Sheet Model_3
K1: HWF Performance | AA1: Borrowed from Model 1
D2: Input 1 coef. | E2: Input 2 coef. | F2: Input 3 coef. | G2: Percentage of HWF benefiting from the salary increase | I2: Percentage of people trained | J2: Percentage of people incentivised | K2: HWF In-service training coef. | L2: Incentive | N2: Total Output coef. | O2: R²_Output | P2: Output 1 Coef. | Q2: Output 2 Coef. | R2: Output 3 Coef. | T2: Total Outcome coef. | U2: R²_Outcome | V2: Outcome 1 Coef. | W2: Outcome 2 Coef. | X2: Outcome 3 Coef. | Z2: Direct effect from HWF availability to Outcome | AA2: Total Impact coef. | AB2: R²_Impact | AC2: Impact 1 Coef. | AD2: Impact 2 Coef.
D3: 0.95 | E3: 0.595 | F3: 0.1 | G3: 0.5 | I3: 0.1 | J3: 0.1 | K3: 0.115 | L3: 0.2 | N3: 0.525 | O3: 0.276 | P3: 0.805 | Q3: 0.41 | R3: 0.874 | T3: -0.416 | U3: 0.444 | V3: 0.869 | W3: -0.604 | X3: 0.574 | Z3: -0.346 | AA3: -0.658 | AB3: 0.432 | AC3: 1
D4: Investments | I4: HWF Availability | P4: SCI_Infectious diseases | Q4: SCI_NCD | R4: SCI_RMNCH | V4: DALYS_2021_Communicable, maternal, perinatal and nutritional conditions per capita 2021 | W4: DALYS_2021_Noncommunicable diseases per capita (2021) | X4: DALYS_2021_Injuries per capita 2021 | AC4: GDP per capita growth (annual %)
B5: Country | C5: ISO | D5: Education | E5: Employment | F5: Retention | I5: HWF Availability Estimation | J5: Real value | N5: Total Output | T5: Total Outcome from output | Z5: Direct Outcome from HWF availability | AA5: Total Impact
B6: Algeria | C6: DZA | D6: =_xlfn.XLOOKUP($C6,SEM!$B:$B,SEM!$D:$D)*Input_1_coef. -> 57.962378 | E6: =_xlfn.XLOOKUP($C6,SEM!$B:$B,SEM!$E:$E)*Input_2_coef. -> 0.079844134 | F6: =$E6*Input_3_coef.*Percentage_of_HWF_benefiting_from_the_salary_increase -> 0.0039922067 | H6: =+IF(Input_3_coef.>=54%,D6+E6+F6,D6+E6) -> 58.042222 | I6: =IF(Input_3_coef.>=0.54,(Input_1_coef.*_xlfn.XLOOKUP($C6,COMBINED!$B:$B,COMBINED!$AB:$AB)+Input_2_coef.*_xlfn.XLOOKUP($C6,COMBINED!$B:$B,COMBINED!$AC:$AC))+F6,(Input_1_coef.*_xlfn.XLOOKUP($C6,COMBINED!$B:$B,COMBINED!$AB:$AB)+Input_2_coef.*_xlfn.XLOOKUP($C6,COMBINED!$B:$B,COMBINED!$AC:$AC))) -> 58.042222 | J6: =_xlfn.XLOOKUP($C6,COMBINED!$B:$B,COMBINED!$N:$N) -> 50.985293 | N6: =Total_Output_coef.*$I6+(HWF_In_service_training_coef.*Percentage_of_people_trained*$I6)+($I6*Incentive*Percentage_of_people_incentivised) -> 32.300497 | P6: =Output_1_Coef.*$N6 -> 26.0019 | Q6: =Output_2_Coef.*$N6 -> 13.243204 | R6: =Output_3_Coef.*$N6 -> 28.230634 | T6: =Total_Outcome_coef.*N6 -> -13.437007 | V6: =Outcome_1_Coef.*$T6 -> -11.676759 | W6: =Outcome_2_Coef.*$T6 -> 8.115952 | X6: =Outcome_3_Coef.*$T6 -> -7.7128418 | Z6: =I6*$Z$3 -> -20.082609 | AA6: =Z6+T6 -> -33.519616 | AC6: =$AA6*Impact_1_Coef.*Total_Impact_coef. -> 22.055907 | AD6: =_R²_Impact*$AA6*Impact_2_Coef.*Total_Impact_coef. -> 0
B7: Angola | C7: AGO | D7: =_xlfn.XLOOKUP($C7,SEM!$B:$B,SEM!$D:$D)*Input_1_coef. -> 17.625891 | E7: =_xlfn.XLOOKUP($C7,SEM!$B:$B,SEM!$E:$E)*Input_2_coef. -> 1.4641268 | F7: =$E7*Input_3_coef.*Percentage_of_HWF_benefiting_from_the_salary_increase -> 0.073206341 | H7: =+IF(Input_3_coef.>=54%,D7+E7+F7,D7+E7) -> 19.090018 | I7: =IF(Input_3_coef.>=0.54,(Input_1_coef.*_xlfn.XLOOKUP($C7,COMBINED!$B:$B,COMBINED!$AB:$AB)+Input_2_coef.*_xlfn.XLOOKUP($C7,COMBINED!$B:$B,COMBINED!$AC:$AC))+F7,(Input_1_coef.*_xlfn.XLOOKUP($C7,COMBINED!$B:$B,COMBINED!$AB:$AB)+Input_2_coef.*_xlfn.XLOOKUP($C7,COMBINED!$B:$B,COMBINED!$AC:$AC))) -> 19.090018 | J7: =_xlfn.XLOOKUP($C7,COMBINED!$B:$B,COMBINED!$N:$N) -> 21.346034 | N7: =Total_Output_coef.*$I7+(HWF_In_service_training_coef.*Percentage_of_people_trained*$I7)+($I7*Incentive*Percentage_of_people_incentivised) -> 10.623595 | P7: =Output_1_Coef.*$N7 -> 8.5519939 | Q7: =Output_2_Coef.*$N7 -> 4.3556739 | R7: =Output_3_Coef.*$N7 -> 9.285022 | T7: =Total_Outcome_coef.*N7 -> -4.4194155 | V7: =Outcome_1_Coef.*$T7 -> -3.8404721 | W7: =Outcome_2_Coef.*$T7 -> 2.669327 | X7: =Outcome_3_Coef.*$T7 -> -2.5367445 | Z7: =I7*$Z$3 -> -6.6051462 | AA7: =Z7+T7 -> -11.024562 | AC7: =$AA7*Impact_1_Coef.*Total_Impact_coef. -> 7.2541616 | AD7: =_R²_Impact*$AA7*Impact_2_Coef.*Total_Impact_coef. -> 0
B8: Benin | C8: BEN | D8: =_xlfn.XLOOKUP($C8,SEM!$B:$B,SEM!$D:$D)*Input_1_coef. -> 10.340617 | E8: =_xlfn.XLOOKUP($C8,SEM!$B:$B,SEM!$E:$E)*Input_2_coef. -> 1.6822017 | F8: =$E8*Input_3_coef.*Percentage_of_HWF_benefiting_from_the_salary_increase -> 0.084110087 | H8: =+IF(Input_3_coef.>=54%,D8+E8+F8,D8+E8) -> 12.022819 | I8: =IF(Input_3_coef.>=0.54,(Input_1_coef.*_xlfn.XLOOKUP($C8,COMBINED!$B:$B,COMBINED!$AB:$AB)+Input_2_coef.*_xlfn.XLOOKUP($C8,COMBINED!$B:$B,COMBINED!$AC:$AC))+F8,(Input_1_coef.*_xlfn.XLOOKUP($C8,COMBINED!$B:$B,COMBINED!$AB:$AB)+Input_2_coef.*_xlfn.XLOOKUP($C8,COMBINED!$B:$B,COMBINED!$AC:$AC))) -> 12.022819 | J8: =_xlfn.XLOOKUP($C8,COMBINED!$B:$B,COMBINED!$N:$N) -> 11.015405 | N8: =Total_Output_coef.*$I8+(HWF_In_service_training_coef.*Percentage_of_people_trained*$I8)+($I8*Incentive*Percentage_of_people_incentivised) -> 6.6906988 | P8: =Output_1_Coef.*$N8 -> 5.3860125 | Q8: =Output_2_Coef.*$N8 -> 2.7431865 | R8: =Output_3_Coef.*$N8 -> 5.8476707 | T8: =Total_Outcome_coef.*N8 -> -2.7833307 | V8: =Outcome_1_Coef.*$T8 -> -2.4187144 | W8: =Outcome_2_Coef.*$T8 -> 1.6811317 | X8: =Outcome_3_Coef.*$T8 -> -1.5976318 | Z8: =I8*$Z$3 -> -4.1598954 | AA8: =Z8+T8 -> -6.943226 | AC8: =$AA8*Impact_1_Coef.*Total_Impact_coef. -> 4.5686427 | AD8: =_R²_Impact*$AA8*Impact_2_Coef.*Total_Impact_coef. -> 0
B9: Botswana | C9: BWA | D9: =_xlfn.XLOOKUP($C9,SEM!$B:$B,SEM!$D:$D)*Input_1_coef. -> 30.438514 | E9: =_xlfn.XLOOKUP($C9,SEM!$B:$B,SEM!$E:$E)*Input_2_coef. -> 3.8046021 | F9: =$E9*Input_3_coef.*Percentage_of_HWF_benefiting_from_the_salary_increase -> 0.19023011 | H9: =+IF(Input_3_coef.>=54%,D9+E9+F9,D9+E9) -> 34.243116 | I9: =IF(Input_3_coef.>=0.54,(Input_1_coef.*_xlfn.XLOOKUP($C9,COMBINED!$B:$B,COMBINED!$AB:$AB)+Input_2_coef.*_xlfn.XLOOKUP($C9,COMBINED!$B:$B,COMBINED!$AC:$AC))+F9,(Input_1_coef.*_xlfn.XLOOKUP($C9,COMBINED!$B:$B,COMBINED!$AB:$AB)+Input_2_coef.*_xlfn.XLOOKUP($C9,COMBINED!$B:$B,COMBINED!$AC:$AC))) -> 34.243116 | J9: =_xlfn.XLOOKUP($C9,COMBINED!$B:$B,COMBINED!$N:$N) -> 36.670298 | N9: =Total_Output_coef.*$I9+(HWF_In_service_training_coef.*Percentage_of_people_trained*$I9)+($I9*Incentive*Percentage_of_people_incentivised) -> 19.056294 | P9: =Output_1_Coef.*$N9 -> 15.340317 | Q9: =Output_2_Coef.*$N9 -> 7.8130805 | R9: =Output_3_Coef.*$N9 -> 16.655201 | T9: =Total_Outcome_coef.*N9 -> -7.9274183 | V9: =Outcome_1_Coef.*$T9 -> -6.8889265 | W9: =Outcome_2_Coef.*$T9 -> 4.7881606 | X9: =Outcome_3_Coef.*$T9 -> -4.5503381 | Z9: =I9*$Z$3 -> -11.848118 | AA9: =Z9+T9 -> -19.775536 | AC9: =$AA9*Impact_1_Coef.*Total_Impact_coef. -> 13.012303 | AD9: =_R²_Impact*$AA9*Impact_2_Coef.*Total_Impact_coef. -> 0
B10: Burkina Faso | C10: BFA | D10: =_xlfn.XLOOKUP($C10,SEM!$B:$B,SEM!$D:$D)*Input_1_coef. -> 10.388772 | E10: =_xlfn.XLOOKUP($C10,SEM!$B:$B,SEM!$E:$E)*Input_2_coef. -> 1.7875747 | F10: =$E10*Input_3_coef.*Percentage_of_HWF_benefiting_from_the_salary_increase -> 0.089378736 | H10: =+IF(Input_3_coef.>=54%,D10+E10+F10,D10+E10) -> 12.176347 | I10: =IF(Input_3_coef.>=0.54,(Input_1_coef.*_xlfn.XLOOKUP($C10,COMBINED!$B:$B,COMBINED!$AB:$AB)+Input_2_coef.*_xlfn.XLOOKUP($C10,COMBINED!$B:$B,COMBINED!$AC:$AC))+F10,(Input_1_coef.*_xlfn.XLOOKUP($C10,COMBINED!$B:$B,COMBINED!$AB:$AB)+Input_2_coef.*_xlfn.XLOOKUP($C10,COMBINED!$B:$B,COMBINED!$AC:$AC))) -> 12.176347 | J10: =_xlfn.XLOOKUP($C10,COMBINED!$B:$B,COMBINED!$N:$N) -> 12.022002 | N10: =Total_Output_coef.*$I10+(HWF_In_service_training_coef.*Percentage_of_people_trained*$I10)+($I10*Incentive*Percentage_of_people_incentivised) -> 6.7761368 | P10: =Output_1_Coef.*$N10 -> 5.4547902 | Q10: =Output_2_Coef.*$N10 -> 2.7782161 | R10: =Output_3_Coef.*$N10 -> 5.9223436 | T10: =Total_Outcome_coef.*N10 -> -2.8188729 | V10: =Outcome_1_Coef.*$T10 -> -2.4496006 | W10: =Outcome_2_Coef.*$T10 -> 1.7025992 | X10: =Outcome_3_Coef.*$T10 -> -1.6180331 | Z10: =I10*$Z$3 -> -4.2130159 | AA10: =Z10+T10 -> -7.0318888 | AC10: =$AA10*Impact_1_Coef.*Total_Impact_coef. -> 4.6269828 | AD10: =_R²_Impact*$AA10*Impact_2_Coef.*Total_Impact_coef. -> 0
B11: Burundi | C11: BDI | D11: =_xlfn.XLOOKUP($C11,SEM!$B:$B,SEM!$D:$D)*Input_1_coef. -> 8.9556615 | E11: =_xlfn.XLOOKUP($C11,SEM!$B:$B,SEM!$E:$E)*Input_2_coef. -> 1.9559756 | F11: =$E11*Input_3_coef.*Percentage_of_HWF_benefiting_from_the_salary_increase -> 0.097798778 | H11: =+IF(Input_3_coef.>=54%,D11+E11+F11,D11+E11) -> 10.911637 | I11: =IF(Input_3_coef.>=0.54,(Input_1_coef.*_xlfn.XLOOKUP($C11,COMBINED!$B:$B,COMBINED!$AB:$AB)+Input_2_coef.*_xlfn.XLOOKUP($C11,COMBINED!$B:$B,COMBINED!$AC:$AC))+F11,(Input_1_coef.*_xlfn.XLOOKUP($C11,COMBINED!$B:$B,COMBINED!$AB:$AB)+Input_2_coef.*_xlfn.XLOOKUP($C11,COMBINED!$B:$B,COMBINED!$AC:$AC))) -> 10.911637 | J11: =_xlfn.XLOOKUP($C11,COMBINED!$B:$B,COMBINED!$N:$N) -> 11.321517 | N11: =Total_Output_coef.*$I11+(HWF_In_service_training_coef.*Percentage_of_people_trained*$I11)+($I11*Incentive*Percentage_of_people_incentivised) -> 6.072326 | P11: =Output_1_Coef.*$N11 -> 4.8882224 | Q11: =Output_2_Coef.*$N11 -> 2.4896537 | R11: =Output_3_Coef.*$N11 -> 5.3072129 | T11: =Total_Outcome_coef.*N11 -> -2.5260876 | V11: =Outcome_1_Coef.*$T11 -> -2.1951701 | W11: =Outcome_2_Coef.*$T11 -> 1.5257569 | X11: =Outcome_3_Coef.*$T11 -> -1.4499743 | Z11: =I11*$Z$3 -> -3.7754264 | AA11: =Z11+T11 -> -6.301514 | AC11: =$AA11*Impact_1_Coef.*Total_Impact_coef. -> 4.1463962 | AD11: =_R²_Impact*$AA11*Impact_2_Coef.*Total_Impact_coef. -> 0
B12: Cabo Verde | C12: CPV | D12: =_xlfn.XLOOKUP($C12,SEM!$B:$B,SEM!$D:$D)*Input_1_coef. -> 23.302042 | E12: =_xlfn.XLOOKUP($C12,SEM!$B:$B,SEM!$E:$E)*Input_2_coef. -> 0 | F12: =$E12*Input_3_coef.*Percentage_of_HWF_benefiting_from_the_salary_increase -> 0 | H12: =+IF(Input_3_coef.>=54%,D12+E12+F12,D12+E12) -> 23.302042 | I12: =IF(Input_3_coef.>=0.54,(Input_1_coef.*_xlfn.XLOOKUP($C12,COMBINED!$B:$B,COMBINED!$AB:$AB)+Input_2_coef.*_xlfn.XLOOKUP($C12,COMBINED!$B:$B,COMBINED!$AC:$AC))+F12,(Input_1_coef.*_xlfn.XLOOKUP($C12,COMBINED!$B:$B,COMBINED!$AB:$AB)+Input_2_coef.*_xlfn.XLOOKUP($C12,COMBINED!$B:$B,COMBINED!$AC:$AC))) -> 23.302042 | J12: =_xlfn.XLOOKUP($C12,COMBINED!$B:$B,COMBINED!$N:$N) -> 24.000474 | N12: =Total_Output_coef.*$I12+(HWF_In_service_training_coef.*Percentage_of_people_trained*$I12)+($I12*Incentive*Percentage_of_people_incentivised) -> 12.967586 | P12: =Output_1_Coef.*$N12 -> 10.438907 | Q12: =Output_2_Coef.*$N12 -> 5.3167104 | R12: =Output_3_Coef.*$N12 -> 11.33367 | T12: =Total_Outcome_coef.*N12 -> -5.3945159 | V12: =Outcome_1_Coef.*$T12 -> -4.6878343 | W12: =Outcome_2_Coef.*$T12 -> 3.2582876 | X12: =Outcome_3_Coef.*$T12 -> -3.0964521 | Z12: =I12*$Z$3 -> -8.0625065 | AA12: =Z12+T12 -> -13.457022 | AC12: =$AA12*Impact_1_Coef.*Total_Impact_coef. -> 8.8547208 | AD12: =_R²_Impact*$AA12*Impact_2_Coef.*Total_Impact_coef. -> 0
B13: Cameroon | C13: CMR | D13: =_xlfn.XLOOKUP($C13,SEM!$B:$B,SEM!$D:$D)*Input_1_coef. -> 7.3058506 | E13: =_xlfn.XLOOKUP($C13,SEM!$B:$B,SEM!$E:$E)*Input_2_coef. -> 1.7263244 | F13: =$E13*Input_3_coef.*Percentage_of_HWF_benefiting_from_the_salary_increase -> 0.086316218 | H13: =+IF(Input_3_coef.>=54%,D13+E13+F13,D13+E13) -> 9.032175 | I13: =IF(Input_3_coef.>=0.54,(Input_1_coef.*_xlfn.XLOOKUP($C13,COMBINED!$B:$B,COMBINED!$AB:$AB)+Input_2_coef.*_xlfn.XLOOKUP($C13,COMBINED!$B:$B,COMBINED!$AC:$AC))+F13,(Input_1_coef.*_xlfn.XLOOKUP($C13,COMBINED!$B:$B,COMBINED!$AB:$AB)+Input_2_coef.*_xlfn.XLOOKUP($C13,COMBINED!$B:$B,COMBINED!$AC:$AC))) -> 9.032175 | J13: =_xlfn.XLOOKUP($C13,COMBINED!$B:$B,COMBINED!$N:$N) -> 8.1868339 | N13: =Total_Output_coef.*$I13+(HWF_In_service_training_coef.*Percentage_of_people_trained*$I13)+($I13*Incentive*Percentage_of_people_incentivised) -> 5.0264054 | P13: =Output_1_Coef.*$N13 -> 4.0462563 | Q13: =Output_2_Coef.*$N13 -> 2.0608262 | R13: =Output_3_Coef.*$N13 -> 4.3930783 | T13: =Total_Outcome_coef.*N13 -> -2.0909846 | V13: =Outcome_1_Coef.*$T13 -> -1.8170656 | W13: =Outcome_2_Coef.*$T13 -> 1.2629547 | X13: =Outcome_3_Coef.*$T13 -> -1.2002252 | Z13: =I13*$Z$3 -> -3.1251325 | AA13: =Z13+T13 -> -5.2161172 | AC13: =$AA13*Impact_1_Coef.*Total_Impact_coef. -> 3.4322051 | AD13: =_R²_Impact*$AA13*Impact_2_Coef.*Total_Impact_coef. -> 0
B14: Central African Republic | C14: CAF | D14: =_xlfn.XLOOKUP($C14,SEM!$B:$B,SEM!$D:$D)*Input_1_coef. -> 9.9847476 | E14: =_xlfn.XLOOKUP($C14,SEM!$B:$B,SEM!$E:$E)*Input_2_coef. -> 0.043098288 | F14: =$E14*Input_3_coef.*Percentage_of_HWF_benefiting_from_the_salary_increase -> 0.0021549144 | H14: =+IF(Input_3_coef.>=54%,D14+E14+F14,D14+E14) -> 10.027846 | I14: =IF(Input_3_coef.>=0.54,(Input_1_coef.*_xlfn.XLOOKUP($C14,COMBINED!$B:$B,COMBINED!$AB:$AB)+Input_2_coef.*_xlfn.XLOOKUP($C14,COMBINED!$B:$B,COMBINED!$AC:$AC))+F14,(Input_1_coef.*_xlfn.XLOOKUP($C14,COMBINED!$B:$B,COMBINED!$AB:$AB)+Input_2_coef.*_xlfn.XLOOKUP($C14,COMBINED!$B:$B,COMBINED!$AC:$AC))) -> 10.027846 | J14: =_xlfn.XLOOKUP($C14,COMBINED!$B:$B,COMBINED!$N:$N) -> 12.601736 | N14: =Total_Output_coef.*$I14+(HWF_In_service_training_coef.*Percentage_of_people_trained*$I14)+($I14*Incentive*Percentage_of_people_incentivised) -> 5.5804963 | P14: =Output_1_Coef.*$N14 -> 4.4922995 | Q14: =Output_2_Coef.*$N14 -> 2.2880035 | R14: =Output_3_Coef.*$N14 -> 4.8773537 | T14: =Total_Outcome_coef.*N14 -> -2.3214864 | V14: =Outcome_1_Coef.*$T14 -> -2.0173717 | W14: =Outcome_2_Coef.*$T14 -> 1.4021778 | X14: =Outcome_3_Coef.*$T14 -> -1.3325332 | Z14: =I14*$Z$3 -> -3.4696347 | AA14: =Z14+T14 -> -5.7911211 | AC14: =$AA14*Impact_1_Coef.*Total_Impact_coef. -> 3.8105577 | AD14: =_R²_Impact*$AA14*Impact_2_Coef.*Total_Impact_coef. -> 0
B15: Chad | C15: TCD | D15: =_xlfn.XLOOKUP($C15,SEM!$B:$B,SEM!$D:$D)*Input_1_coef. -> 3.776983 | E15: =_xlfn.XLOOKUP($C15,SEM!$B:$B,SEM!$E:$E)*Input_2_coef. -> 2.4474695 | F15: =$E15*Input_3_coef.*Percentage_of_HWF_benefiting_from_the_salary_increase -> 0.12237348 | H15: =+IF(Input_3_coef.>=54%,D15+E15+F15,D15+E15) -> 6.2244525 | I15: =IF(Input_3_coef.>=0.54,(Input_1_coef.*_xlfn.XLOOKUP($C15,COMBINED!$B:$B,COMBINED!$AB:$AB)+Input_2_coef.*_xlfn.XLOOKUP($C15,COMBINED!$B:$B,COMBINED!$AC:$AC))+F15,(Input_1_coef.*_xlfn.XLOOKUP($C15,COMBINED!$B:$B,COMBINED!$AB:$AB)+Input_2_coef.*_xlfn.XLOOKUP($C15,COMBINED!$B:$B,COMBINED!$AC:$AC))) -> 6.2244525 | J15: =_xlfn.XLOOKUP($C15,COMBINED!$B:$B,COMBINED!$N:$N) -> 3.970162 | N15: =Total_Output_coef.*$I15+(HWF_In_service_training_coef.*Percentage_of_people_trained*$I15)+($I15*Incentive*Percentage_of_people_incentivised) -> 3.4639078 | P15: =Output_1_Coef.*$N15 -> 2.7884458 | Q15: =Output_2_Coef.*$N15 -> 1.4202022 | R15: =Output_3_Coef.*$N15 -> 3.0274554 | T15: =Total_Outcome_coef.*N15 -> -1.4409857 | V15: =Outcome_1_Coef.*$T15 -> -1.2522165 | W15: =Outcome_2_Coef.*$T15 -> 0.87035534 | X15: =Outcome_3_Coef.*$T15 -> -0.82712577 | Z15: =I15*$Z$3 -> -2.1536606 | AA15: =Z15+T15 -> -3.5946462 | AC15: =$AA15*Impact_1_Coef.*Total_Impact_coef. -> 2.3652772 | AD15: =_R²_Impact*$AA15*Impact_2_Coef.*Total_Impact_coef. -> 0
B16: Comoros | C16: COM | D16: =_xlfn.XLOOKUP($C16,SEM!$B:$B,SEM!$D:$D)*Input_1_coef. -> 19.750394 | E16: =_xlfn.XLOOKUP($C16,SEM!$B:$B,SEM!$E:$E)*Input_2_coef. -> 0.55328735 | F16: =$E16*Input_3_coef.*Percentage_of_HWF_benefiting_from_the_salary_increase -> 0.027664367 | H16: =+IF(Input_3_coef.>=54%,D16+E16+F16,D16+E16) -> 20.303682 | I16: =IF(Input_3_coef.>=0.54,(Input_1_coef.*_xlfn.XLOOKUP($C16,COMBINED!$B:$B,COMBINED!$AB:$AB)+Input_2_coef.*_xlfn.XLOOKUP($C16,COMBINED!$B:$B,COMBINED!$AC:$AC))+F16,(Input_1_coef.*_xlfn.XLOOKUP($C16,COMBINED!$B:$B,COMBINED!$AB:$AB)+Input_2_coef.*_xlfn.XLOOKUP($C16,COMBINED!$B:$B,COMBINED!$AC:$AC))) -> 20.303682 | J16: =_xlfn.XLOOKUP($C16,COMBINED!$B:$B,COMBINED!$N:$N) -> 21.306174 | N16: =Total_Output_coef.*$I16+(HWF_In_service_training_coef.*Percentage_of_people_trained*$I16)+($I16*Incentive*Percentage_of_people_incentivised) -> 11.298999 | P16: =Output_1_Coef.*$N16 -> 9.0956941 | Q16: =Output_2_Coef.*$N16 -> 4.6325895 | R16: =Output_3_Coef.*$N16 -> 9.875325 | T16: =Total_Outcome_coef.*N16 -> -4.7003835 | V16: =Outcome_1_Coef.*$T16 -> -4.0846333 | W16: =Outcome_2_Coef.*$T16 -> 2.8390316 | X16: =Outcome_3_Coef.*$T16 -> -2.6980201 | Z16: =I16*$Z$3 -> -7.0250739 | AA16: =Z16+T16 -> -11.725457 | AC16: =$AA16*Impact_1_Coef.*Total_Impact_coef. -> 7.7153509 | AD16: =_R²_Impact*$AA16*Impact_2_Coef.*Total_Impact_coef. -> 0
B17: Congo | C17: COG | D17: =_xlfn.XLOOKUP($C17,SEM!$B:$B,SEM!$D:$D)*Input_1_coef. -> 12.608213 | E17: =_xlfn.XLOOKUP($C17,SEM!$B:$B,SEM!$E:$E)*Input_2_coef. -> 0.25322484 | F17: =$E17*Input_3_coef.*Percentage_of_HWF_benefiting_from_the_salary_increase -> 0.012661242 | H17: =+IF(Input_3_coef.>=54%,D17+E17+F17,D17+E17) -> 12.861438 | I17: =IF(Input_3_coef.>=0.54,(Input_1_coef.*_xlfn.XLOOKUP($C17,COMBINED!$B:$B,COMBINED!$AB:$AB)+Input_2_coef.*_xlfn.XLOOKUP($C17,COMBINED!$B:$B,COMBINED!$AC:$AC))+F17,(Input_1_coef.*_xlfn.XLOOKUP($C17,COMBINED!$B:$B,COMBINED!$AB:$AB)+Input_2_coef.*_xlfn.XLOOKUP($C17,COMBINED!$B:$B,COMBINED!$AC:$AC))) -> 12.861438 | J17: =_xlfn.XLOOKUP($C17,COMBINED!$B:$B,COMBINED!$N:$N) -> 15.055348 | N17: =Total_Output_coef.*$I17+(HWF_In_service_training_coef.*Percentage_of_people_trained*$I17)+($I17*Incentive*Percentage_of_people_incentivised) -> 7.15739 | P17: =Output_1_Coef.*$N17 -> 5.761699 | Q17: =Output_2_Coef.*$N17 -> 2.9345299 | R17: =Output_3_Coef.*$N17 -> 6.2555589 | T17: =Total_Outcome_coef.*N17 -> -2.9774742 | V17: =Outcome_1_Coef.*$T17 -> -2.5874251 | W17: =Outcome_2_Coef.*$T17 -> 1.7983944 | X17: =Outcome_3_Coef.*$T17 -> -1.7090702 | Z17: =I17*$Z$3 -> -4.4500574 | AA17: =Z17+T17 -> -7.4275316 | AC17: =$AA17*Impact_1_Coef.*Total_Impact_coef. -> 4.8873158 | AD17: =_R²_Impact*$AA17*Impact_2_Coef.*Total_Impact_coef. -> 0
... B52: Zimbabwe | C52: ZWE | D52: =_xlfn.XLOOKUP($C52,SEM!$B:$B,SEM!$D:$D)*Input_1_coef. -> 28.306845 | E52: =_xlfn.XLOOKUP($C52,SEM!$B:$B,SEM!$E:$E)*Input_2_coef. -> 1.4439883 | F52: =$E52*Input_3_coef.*Percentage_of_HWF_benefiting_from_the_salary_increase -> 0.072199413 | H52: =+IF(Input_3_coef.>=54%,D52+E52+F52,D52+E52) -> 29.750833 | I52: =IF(Input_3_coef.>=0.54,(Input_1_coef.*_xlfn.XLOOKUP($C52,COMBINED!$B:$B,COMBINED!$AB:$AB)+Input_2_coef.*_xlfn.XLOOKUP($C52,COMBINED!$B:$B,COMBINED!$AC:$AC))+F52,(Input_1_coef.*_xlfn.XLOOKUP($C52,COMBINED!$B:$B,COMBINED!$AB:$AB)+Input_2_coef.*_xlfn.XLOOKUP($C52,COMBINED!$B:$B,COMBINED!$AC:$AC))) -> 29.750833 | J52: =_xlfn.XLOOKUP($C52,COMBINED!$B:$B,COMBINED!$N:$N) -> 36.237672 | N52: =Total_Output_coef.*$I52+(HWF_In_service_training_coef.*Percentage_of_people_trained*$I52)+($I52*Incentive*Percentage_of_people_incentivised) -> 16.556339 | P52: =Output_1_Coef.*$N52 -> 13.327853 | Q52: =Output_2_Coef.*$N52 -> 6.7880988 | R52: =Output_3_Coef.*$N52 -> 14.47024 | T52: =Total_Outcome_coef.*N52 -> -6.8874369 | V52: =Outcome_1_Coef.*$T52 -> -5.9851826 | W52: =Outcome_2_Coef.*$T52 -> 4.1600119 | X52: =Outcome_3_Coef.*$T52 -> -3.9533888 | Z52: =I52*$Z$3 -> -10.293788 | AA52: =Z52+T52 -> -17.181225 | AC52: =$AA52*Impact_1_Coef.*Total_Impact_coef. -> 11.305246 | AD52: =_R²_Impact*$AA52*Impact_2_Coef.*Total_Impact_coef. -> 0
B53: Average | D53: =AVERAGE(D6:D52) -> 23.481876 | E53: =AVERAGE(E6:E52) -> 2.065907 | F53: =AVERAGE(F6:F52) -> 0.10329535 | H53: =+IF(Input_3_coef.>=54%,D53+E53+F53,D53+E53) -> 25.547783 | I53: =AVERAGE(I6:I52) -> 25.547783 | J53: =AVERAGE(J6:J52) -> 25.627865 | N53: =AVERAGE(N6:N52) -> 14.217342 | P53: =AVERAGE(P6:P52) -> 11.44496 | Q53: =AVERAGE(Q6:Q52) -> 5.82911 | R53: =AVERAGE(R6:R52) -> 12.425956 | T53: =AVERAGE(T6:T52) -> -5.9144141 | V53: =AVERAGE(V6:V52) -> -5.1396258 | W53: =AVERAGE(W6:W52) -> 3.5723061 | X53: =AVERAGE(X6:X52) -> -3.3948737 | Z53: =AVERAGE(Z6:Z52) -> -8.8395331 | AA53: =AVERAGE(AA6:AA52) -> -14.753947 | AC53: =AVERAGE(AC6:AC52) -> 9.7080972 | AD53: =AVERAGE(AD6:AD52) -> 0

Sheet Coef.
C2: 1st level Model
D3: coef1_Medical Doctors | E3: coef1_Nursing Personnel | F3: coef1_Midwifery Personnel | G3: coef1_Dentists | H3: coef1_Pharmacists | I3: coef1_Medical and Pathology Laboratory Scientists | J3: coef1_Medical and Pathology Laboratory Technicians
C4: HWFav1 | D4: =0.898 -> 0.898 | E4: 0.761 | F4: 0.764 | G4: 0.882 | H4: 0.912 | I4: 0.232 | J4: 0.6
D5: OUTput1_SCI_Infectiousdiseases | E5: OUTput1_SCI_NCD | F5: OUTput1_SCI_RMNCH
C6: OUTput1 | D6: 0.931 | E6: 0.793 | F6: 0.358
D7: OUTcome1_DALYS_2021_Communicable, maternal, perinatal and nutritional conditions per capita 2021 | E7: OUTcome1_DALYS_2021_Noncommunicable diseases per capita (2021) | F7: OUTcome1_DALYS_2021_Injuries per capita 2021
C8: OUTcome1 | D8: 0.889 | E8: -0.543 | F8: 0.643
D9: GDP per capita growth (annual %)
C10: Impact1 | D10: 1
C12: 2nd Level
D13: HWFav1
C14: OUTput2 | D14: 0.728
D15: HWFav1 | E15: OUTput2
C16: OUTcome2 | D16: -0.184 | E16: -0.559
D17: HWFav1 | E17: OUTput2 | F17: OUTcome2
C18: Impact2 | D18: 0.55 | E18: 0.118 | F18: -0.251

Sheet SEM_Vars
B2: varname | C2: variable definition
B3: Invest_1 | C3: Salary per capita
B4: Invest_2 | C4: Total core cadre training per capita
B5: Output_1 | C5: SCI_Infectious diseases
B6: Output_2 | C6: SCI_NCD
B7: Output_3 | C7: SCI_RMNCH
B8: Outcome_1 | C8: DALYS_2021_Communicable, maternal, perinatal and nutritional conditions per capita 2021
B9: Outcome_2 | C9: DALYS_2021_Noncommunicable diseases per capita (2021)
B10: Outcome_3 | C10: DALYS_2021_Injuries per capita 2021
B11: Outcome_4 | C11: Health_Security_Index_2021
B12: Outcome_5 | C12: HAQ
B13: Impact_1 | C13: GDP per capita growth (annual %) | D13: Gross domestic product is the total income earned through the production of goods and services in an economic territory during an accounting period. It can be measured in three different ways: using either the expenditure approach, the income approach, or the production approach. The core indicator has been divided by the general population to achieve a per capita estimate.This indicator denotes the percentage change over each previous year of the constant price (base year 2015) series in United States dollars.
B14: Impact_2 | C14: GDP growth (annual %) | D14: Gross domestic product is the total income earned through the production of goods and services in an economic territory during an accounting period. It can be measured in three different ways: using either the expenditure approach, the income approach, or the production approach. This indicator denotes the percentage change over each previous year of the constant price (base year 2015) series in United States dollars.
B15: Impact_3 | C15: GDP per capita, PPP (constant 2017 international $) | D15: This indicator provides values for gross domestic product (GDP) expressed in constant international dollars, converted by purchasing power parities (PPPs). PPPs account for the different price levels across countries and thus PPP-based comparisons of economic output are more appropriate for comparing the output of economies and the average material well-being of their inhabitants than exchange-rate based comparisons. Gross domestic product is the total income earned through the production of goods and services in an economic territory during an accounting period. It can be measured in three different ways: using either the expenditure approach, the income approach, or the production approach. The core indicator has been divided by the general population to achieve a per capita estimate. This indicator is expressed in constant prices, meaning the series has been adjusted to account for price changes over time. The reference year for this adjustment is 2021. The PPP conversion factor is a currency conversion factor and a spatial price deflator. PPPs convert different currencies to a common currency and, in the process of conversion, equalize their purchasing power by eliminating the differences in price levels between countries, thereby allowing volume or output comparisons of GDP and its expenditure components.

Sheet COMBINED
A1: Country | B1: ISO | C1: Population_2023 | D1: HAQ | E1: Productivity | F1: GINI INDEX | G1: Density_2023_Medical Doctors | H1: Density_2023_Nursing Personnel | I1: Density_2023_Midwifery Personnel | J1: Density_2023_Dentists | K1: Density_2023_Pharmacists | L1: Density_2023_Medical and Pathology Laboratory Scientists | M1: Density_2023_Medical and Pathology Laboratory Technicians | N1: Density_7_cadres_2023 | O1: GDP_PPP_2023 | P1: GDP_PPP_2024 | Q1: HALE_2021 | R1: SCI_Capacity and Access | S1: SCI_Infectious diseases | T1: SCI_NCD | U1: SCI_RMNCH | V1: SCI_Average | W1: DALYS_2021_All Causes per capita 2021 | X1: DALYS_2021_Communicable, maternal, perinatal and nutritional conditions per capita 2021 | Y1: DALYS_2021_Noncommunicable diseases per capita (2021) | Z1: DALYS_2021_Injuries per capita 2021 | AA1: Health_Security_Index_2021 | AB1: Salary_per_capita | AC1: Total core cadre training per capita | AD1: GDP_Growth_per_capita | AE1: Stock_7_cadres_2023
A2: Algeria | B2: DZA | C2: 46053477 | D2: 58.66345 | E2: 28.18 | F2: 37.36 | G2: 16.39659 | H2: 22.750942 | I2: 2.0148316 | J2: 3.5224268 | K2: 2.9622085 | L2: 0.029530886 | M2: 3.3087621 | N2: 50.985293 | O2: 15227.463 | P2: 15545.11 | Q2: 65.548195 | R2: 88.72 | S2: 82.21 | T2: 60.71 | U2: 68.12 | V2: 74.94 | W2: 0.25858507 | X2: 0.054826069 | Y2: 0.17657851 | Z2: 0.02400285 | AA2: 26.2 | AB2: 61.01303 | AC2: 0.13419182 | AD2: 3.3 | AE2: 234805
A3: Angola | B3: AGO | C3: 36148636 | D3: 29.30257 | E3: 9.49 | F3: 45 | G3: 2.4047934 | H3: 18.456575 | I3: 0.0091289752 | J3: 0.070265445 | K3: 0.39669547 | L3: 0.0035962629 | M3: 0.004979441 | N3: 21.346034 | O3: 8781.558 | P3: 8866.691 | Q3: 53.761871 | R3: 21.08 | S3: 36.07 | T3: 53.76 | U3: 44.51 | V3: 38.855 | W3: 0.55586603 | X3: 0.34291113 | Y3: 0.16924787 | Z3: 0.040767474 | AA3: 29.1 | AB3: 18.553569 | AC3: 2.4607173 | AD3: 4.4239045 | AE3: 77163
A4: Benin | B4: BEN | C4: 13124347 | D4: 31.40346 | E4: 4.16 | F4: 37.6 | G4: 2.3178296 | H4: 4.7164251 | I4: 1.8484729 | J4: 0.050288216 | K4: 0.32992118 | L4: 0.5089777 | M4: 1.2434904 | N4: 11.015405 | O4: 3829.285 | P4: 3966.803 | Q4: 55.715813 | R4: 16.86 | S4: 47 | T4: 60.77 | U4: 42.82 | V4: 41.8625 | W4: 0.5415334 | X4: 0.32523931 | Y4: 0.16627788 | Z4: 0.047324915 | AA4: 25.4 | AB4: 10.88486 | AC4: 2.8272298 | AD4: 7.4531157 | AE4: 14457
A5: Botswana | B5: BWA | C5: 2483754 | D5: 37.50613 | E5: 23.79 | F5: 57.4 | G5: 3.78862 | H5: 30.135835 | I5: 0 | J5: 0.35832856 | K5: 0.5314536 | L5: 0.60392454 | M5: 1.2521369 | N5: 36.670298 | O5: 17551.773 | P5: 16749.389 | Q5: 53.103672 | R5: 43.33 | S5: 66.05 | T5: 60.17 | U5: 53.85 | V5: 55.85 | W5: 0.51046947 | X5: 0.29056739 | Y5: 0.16281769 | Z5: 0.03681854 | AA5: 33.6 | AB5: 32.040541 | AC5: 6.3942892 | AD5: -2.9898688 | AE5: 9108
A6: Burkina Faso | B6: BFA | C6: 22720842 | D6: 28.46235 | E6: 4.3 | F6: 0 | G6: 1.4625338 | H6: 5.994056 | I6: 3.6217848 | J6: 0.058536563 | K6: 0.39655221 | L6: 0.0026407472 | M6: 0.48589749 | N6: 12.022002 | O6: 2462.852 | P6: 2508.528 | Q6: 54.562424 | R6: 14.92 | S6: 50.01 | T6: 54.76 | U6: 60.22 | V6: 44.9775 | W6: 0.53931546 | X6: 0.30772701 | Y6: 0.16837414 | Z6: 0.059056873 | AA6: 29.8 | AB6: 10.935549 | AC6: 3.0043273 | AD6: 4.985103 | AE6: 27315
A7: Burundi | B7: BDI | C7: 12999141 | D7: 25.83942 | E7: 0.9 | F7: 33.33 | G7: 0.7985143 | H7: 8.3643988 | I7: 0.37156301 | J7: 0.010769942 | K7: 0.095390919 | L7: 0.98006476 | M7: 0.70081554 | N7: 11.321517 | O7: 875.157 | P7: 879.67 | Q7: 55.844139 | R7: 13.85 | S7: 60.47 | T7: 59.39 | U7: 59.42 | V7: 48.2825 | W7: 0.46057153 | X7: 0.25291885 | Y7: 0.15453908 | Z7: 0.051080321 | AA7: 22.1 | AB7: 9.4270121 | AC7: 3.2873539 | AD7: 3.4892317 | AE7: 14717
A8: Cabo Verde | B8: CPV | C8: 573322 | D8: 50.24222 | E8: 11.35 | F8: 52.5 | G8: 6.6454802 | H8: 16.378231 | I8: 0.45349734 | J8: 0.13953764 | K8: 0.17442205 | L8: 0.069768821 | M8: 0.13953764 | N8: 24.000474 | O8: 9530.21 | P8: 10052.799 | Q8: 63.765907 | R8: 66.2 | S8: 90.4 | T8: 56.77 | U8: 75.55 | V8: 72.23 | W8: 0.28416804 | X8: 0.064726853 | Y8: 0.18145936 | Z8: 0.034756189 | AA8: 34.1 | AB8: 24.528465 | AC8: 0 | AD8: 7.2718815 | AE8: 1376
A9: Cameroon | B9: CMR | C9: 28608129 | D9: 33.72569 | E9: 6.23 | F9: 49 | G9: 1.3150108 | H9: 5.7798257 | I9: 0.58479882 | J9: 0.11080767 | K9: 0.2104297 | L9: 0.10241844 | M9: 0.083542688 | N9: 8.1868339 | O9: 4829.024 | P9: 4880.519 | Q9: 54.007027 | R9: 28.28 | S9: 56.12 | T9: 49.14 | U9: 47.52 | V9: 45.265 | W9: 0.54981019 | X9: 0.32608299 | Y9: 0.1751217 | Z9: 0.042805912 | AA9: 28.6 | AB9: 7.6903691 | AC9: 2.9013855 | AD9: 3.6707428 | AE9: 23421
A10: Central African Republic | B10: CAF | C10: 5119136 | D10: 15.16031 | E10: 1.57 | F10: 59.27 | G10: 0.74817313 | H10: 7.3371756 | I10: 3.7057035 | J10: 0.0058603639 | K10: 0.02539491 | L10: 0.21878692 | M10: 0.56064148 | N10: 12.601736 | O10: 1163.458 | P10: 1145.161 | Q10: 45.432892 | R10: 16.76 | S10: 38.69 | T10: 43.77 | U10: 38.17 | V10: 34.3475 | W10: 0.83557862 | X10: 0.58633456 | Y10: 0.16570339 | Z10: 0.07557031 | AA10: 18.6 | AB10: 10.510261 | AC10: 0.072434098 | AD10: 1.5396325 | AE10: 6451
A11: Chad | B11: TCD | C11: 17921183 | D11: 23.75145 | E11: 3.29 | F11: 36.9 | G11: 0.91567616 | H11: 1.3263633 | I11: 0.47150905 | J11: 0.0072539854 | K11: 0.090953817 | L11: 0.57362285 | M11: 0.58478282 | N11: 3.970162 | O11: 2623.622 | P11: 2588.82 | Q11: 51.51506 | R11: 10.76 | S11: 41.09 | T11: 58.54 | U11: 28.87 | V11: 34.815 | W11: 0.72291648 | X11: 0.50936099 | Y11: 0.15067299 | Z11: 0.056395953 | AA11: 23.9 | AB11: 3.9757716 | AC11: 4.1133942 | AD11: 3.6544511 | AE11: 7115
A12: Comoros | B12: COM | C12: 926492 | D12: 31.80644 | E12: 6.02 | F12: 55.92 | G12: 3.8208641 | H12: 8.4728201 | I12: 6.3249332 | J12: 0.34538884 | K12: 0.43173605 | L12: 1.7377376 | M12: 0.17269442 | N12: 21.306174 | O12: 3356.835 | P12: 3392.316 | Q12: 59.019386 | R12: 37.44 | S12: 51.48 | T12: 56.05 | U12: 49.64 | V12: 48.6525 | W12: 0.3998434 | X12: 0.18043054 | Y12: 0.17489083 | Z12: 0.039609689 | AA12: 24.9 | AB12: 20.789889 | AC12: 0.9298947 | AD12: 3.3887835 | AE12: 1974
A13: Congo | B13: COG | C13: 5940746 | D13: 33.95313 | E13: 7.57 | F13: 41.9 | G13: 1.7539885 | H13: 9.3809767 | I13: 2.0031154 | J13: 0.016832903 | K13: 0.053865289 | L13: 0.53865289 | M13: 1.3079165 | N13: 15.055348 | O13: 5633.357 | P13: 5622.161 | Q13: 54.835735 | R13: 28.57 | S13: 36.21 | T13: 52.47 | U13: 52.06 | V13: 42.3275 | W13: 0.45539965 | X13: 0.27170787 | Y13: 0.15151453 | Z13: 0.027856401 | AA13: 26.3 | AB13: 13.271803 | AC13: 0.42558796 | AD13: 2.5796664 | AE13: 8944
... A16: Equatorial Guinea | B16: GNQ | C16: 1543389 | D16: 42.42096 | E16: 18.85 | F16: 50.2 | G16: 1.7817932 | H16: 15.893595 | I16: 0.16846045 | J16: 0 | K16: 0.090709471 | L16: 0.86821922 | M16: 1.4772685 | N16: 20.280046 | O16: 18770.064 | P16: 18565.41 | Q16: 53.256332 | R16: 41.09 | S16: 43.59 | T16: 50.27 | U16: 48.65 | V16: 45.9 | W16: 0.58306554 | X16: 0.37725803 | Y16: 0.17062504 | Z16: 0.031497727 | AA16: 17.4 | AB16: 17.115684 | AC16: 23.864221 | AD16: 0.90724825 | AE16: 3130
A17: Eritrea | B17: ERI | C17: 3727656 | D17: 25.59651 | E17: 2.78 | F17: 0 | G17: 0.80211264 | H17: 13.933689 | I17: 0.17973762 | J17: 0.17973762 | K17: 0.61432707 | L17: 0.91210133 | M17: 0.82357385 | N17: 17.445279 | O17: 650 | P17: 650 | Q17: 55.424946 | R17: 35.7 | S17: 36.43 | T17: 60.09 | U17: 51.96 | V17: 46.045 | W17: 0.43861377 | X17: 0.18328273 | Y17: 0.20161049 | Z17: 0.049832601 | AA17: 21.4 | AB17: 14.517287 | AC17: 2.6869969 | AE17: 6503
A18: Eswatini | B18: SWZ | C18: 1197512 | D18: 32.52324 | E18: 24.95 | F18: 63.7 | G18: 5.7201932 | H18: 43.774092 | I18: 0 | J18: 0.29227265 | K18: 0.35072717 | L18: 0 | M18: 0 | N18: 50.137285 | O18: 11033.557 | P18: 11315.553 | Q18: 47.467403 | R18: 32.98 | S18: 65.08 | T18: 62 | U18: 73.19 | V18: 58.3125 | W18: 0.71206086 | X18: 0.38181597 | Y18: 0.23565534 | Z18: 0.07556241 | AA18: 29.3 | AB18: 43.650798 | AC18: 4.3127443 | AD18: 2.6407046 | AE18: 6004
A19: Ethiopia | B19: ETH | C19: 123771387 | D19: 31.20527 | E19: 4.7 | F19: 30.98 | G19: 1.4876621 | H19: 10.605197 | I19: 1.7770666 | J19: 0.28455688 | K19: 1.5290287 | L19: 1.9194259 | M19: 1.7550098 | N19: 19.357947 | O19: 3409.15 | P19: 3591.681 | Q19: 58.827312 | R19: 20.87 | S19: 29.04 | T19: 52.49 | U19: 47.93 | V19: 37.5825 | W19: 0.38864963 | X19: 0.20396758 | Y19: 0.13963053 | Z19: 0.041155729 | AA19: 37.8 | AB19: 17.313519 | AC19: 1.864483 | AD19: 7.3166911 | AE19: 239596
A20: Gabon | B20: GAB | C20: 2383905 | D20: 39.62385 | E20: 34.92 | F20: 69 | G20: 5.3106143 | H20: 20.281848 | I20: 3.8801882 | J20: 0.18457111 | K20: 0.78442723 | L20: 1.0780631 | M20: 1.0612839 | N20: 32.580996 | O20: 21035.029 | P20: 21218.077 | Q20: 56.258869 | R20: 48.48 | S20: 34.37 | T20: 53.8 | U20: 64.17 | V20: 50.205 | W20: 0.44235278 | X20: 0.24190195 | Y20: 0.1657311 | Z20: 0.03146404 | AA20: 21.8 | AB20: 30.40605 | AC20: 1.3004665 | AD20: 3.3839076 | AE20: 7767
A21: Gambia | B21: GMB | C21: 2631251 | D21: 34.67981 | E21: 5.97 | F21: 67.2 | G21: 0.91971461 | H21: 5.111637 | I21: 1.6304032 | J21: 0.034204263 | K21: 0.038004736 | L21: 0.19382415 | M21: 0.67268383 | N21: 8.6004718 | O21: 2991.887 | P21: 3073.541 | Q21: 55.842545 | R21: 28.12 | S21: 43.85 | T21: 57.74 | U21: 63.72 | V21: 48.3575 | W21: 0.43458985 | X21: 0.23410545 | Y21: 0.15868965 | Z21: 0.036390079 | AA21: 28.7 | AB21: 7.5746518 | AC21: 1.3278116 | AD21: 5.7467177 | AE21: 2263
A22: Ghana | B22: GHA | C22: 33062741 | D22: 36.05526 | E22: 10.84 | F22: 47.5 | G22: 2.7151409 | H22: 34.116954 | I22: 7.8807743 | J22: 0.073799084 | K22: 1.7348834 | L22: 0.8105801 | M22: 1.13209 | N22: 48.464221 | O22: 6808.539 | P22: 7061.935 | Q22: 57.882519 | R22: 25.98 | S22: 41.42 | T22: 70.51 | U22: 68.74 | V22: 51.6625 | W22: 0.40610834 | X22: 0.19130623 | Y22: 0.17586458 | Z22: 0.035717695 | AA22: 34.3 | AB22: 40.416607 | AC22: 15.163718 | AD22: 5.6848726 | AE22: 160236
A23: Guinea | B23: GIN | C23: 14238716 | D23: 25.68856 | E23: 6.82 | F23: 68.5 | G23: 2.0690068 | H23: 3.5248965 | I23: 0.62716329 | J23: 0.02739011 | K23: 0.17908918 | L23: 0.1271182 | M23: 0.22263243 | N23: 6.7772965 | O23: 3764.533 | P23: 3895.767 | Q23: 53.426258 | R23: 18.03 | S23: 47.87 | T23: 58.4 | U23: 50.42 | V23: 43.68 | W23: 0.62038058 | X23: 0.39821246 | Y23: 0.16588447 | Z23: 0.053108951 | AA23: 26.8 | AB23: 7.1826172 | AC23: 2.7373714 | AD23: 5.6685239 | AE23: 9650
A24: Guinea-Bissau | B24: GNB | C24: 2111612 | D24: 24.26292 | E24: 3.06 | F24: 55.76 | G24: 2.5146665 | H24: 8.9126222 | I24: 0.96135085 | J24: 0.099450088 | K24: 0.009471437 | L24: 0.0047357185 | M24: 0.80980786 | N24: 13.312105 | O24: 2662.157 | P24: 2729.159 | Q24: 51.450367 | R24: 17.33 | S24: 29.95 | T24: 61.51 | U24: 60.3 | V24: 42.2725 | W24: 0.59333548 | X24: 0.36455418 | Y24: 0.17227405 | Z24: 0.049926094 | AA24: 21.4 | AB24: 12.653132 | AC24: 0.1256791 | AD24: 4.813486 | AE24: 2811
A25: Kenya | B25: KEN | C25: 57458890 | D25: 33.36342 | E25: 7.39 | F25: 50 | G25: 2.7835553 | H25: 21.841529 | I25: 0.04820838 | J25: 0.23390636 | K25: 0.20640844 | L25: 1.7403747 | M25: 0.14549533 | N25: 26.999477 | O25: 6102.005 | P25: 6267.148 | Q25: 58.217083 | R25: 40.62 | S25: 53.15 | T25: 50.91 | U25: 73.63 | V25: 54.5775 | W25: 0.35501401 | X25: 0.18481356 | Y25: 0.1352383 | Z25: 0.031453024 | AA25: 38.8 | AB25: 23.42452 | AC25: 0.84095736 | AD25: 4.4964983 | AE25: 155136
A26: Lesotho | B26: LSO | C26: 2192400 | D26: 26.33865 | E26: 3.19 | F26: 56.01 | G26: 2.4493706 | H26: 5.6330962 | I26: 12.675607 | J26: 0.38314176 | K26: 1.1722313 | L26: 1.897464 | M26: 1.2452107 | N26: 25.456121 | O26: 2851.384 | P26: 2891.054 | Q26: 44.634335 | R26: 32.27 | S26: 50.71 | T26: 65.78 | U26: 74.68 | V26: 55.86 | W26: 0.8061546 | X26: 0.46635144 | Y26: 0.24303601 | Z26: 0.084683657 | AA26: 30.9 | AB26: 23.526334 | AC26: 4.2294499 | AD26: 2.7622382 | AE26: 5581
A27: Liberia | B27: LBR | C27: 5432272 | D27: 35.73526 | E27: 1.53 | F27: 43 | G27: 1.7561713 | H27: 8.1439221 | I27: 1.820601 | J27: 0.014726803 | K27: 0.31294457 | L27: 0.21169779 | M27: 0 | N27: 12.260064 | O27: 1631.358 | P27: 1670.302 | Q27: 53.960999 | R27: 29.07 | S27: 42.02 | T27: 53.05 | U27: 61.65 | V27: 46.4475 | W27: 0.53500919 | X27: 0.33742173 | Y27: 0.15837177 | Z27: 0.037012274 | AA27: 35.7 | AB27: 11.11493 | AC27: 0.55403733 | AD27: 4.7929148 | AE27: 6660
A28: Madagascar | B28: MDG | C28: 29942591 | D28: 29.01793 | E28: 1.89 | F28: 56.2 | G28: 1.7466758 | H28: 1.5229143 | I28: 1.3338859 | J28: 0.083827081 | K28: 0.010019173 | L28: 0.10219556 | M28: 0.10219556 | N28: 4.9017134 | O28: 1707.712 | P28: 1731.305 | Q28: 55.13702 | R28: 18.98 | S28: 29.47 | T28: 45.77 | U28: 58.24 | V28: 38.115 | W28: 0.50996008 | X28: 0.28997474 | Y28: 0.17565736 | Z28: 0.039462753 | AA28: 30.4 | AB28: 5.5460292 | AC28: 2.0891931 | AD28: 4.2 | AE28: 14677
A29: Malawi | B29: MWI | C29: 20728157 | D29: 29.89006 | E29: 2.77 | F29: 47 | G29: 0.53791565 | H29: 4.7370347 | I29: 0.2971803 | J29: 0.048725991 | K29: 0.059339574 | L29: 0.0434192 | M29: 0.10082903 | N29: 5.8244445 | O29: 1530.622 | P29: 1514.554 | Q29: 54.668175 | R29: 22.25 | S29: 57.77 | T29: 58.77 | U29: 71.89 | V29: 52.67 | W29: 0.44481134 | X29: 0.24303618 | Y29: 0.16367847 | Z29: 0.033520622 | AA29: 28.5 | AB29: 5.0174021 | AC29: 0.71150071 | AD29: 1.82685 | AE29: 12073
... A39: Senegal | B39: SEN | C39: 18116526 | D39: 33.96112 | E39: 6.73 | F39: 58.7 | G39: 1.0890609 | H39: 2.6384749 | I39: 1.5952286 | J39: 0.10874049 | K39: 0.20147351 | L39: 0 | M39: 0.14351537 | N39: 5.7764938 | O39: 4300.203 | P39: 4464.78 | Q39: 58.903 | R39: 30.05 | S39: 63.69 | T39: 55.65 | U39: 59.11 | V39: 52.125 | W39: 0.36508063 | X39: 0.16490721 | Y39: 0.15800663 | Z39: 0.036505767 | AA39: 32.8 | AB39: 5.7327207 | AC39: 1.4601029 | AD39: 6.8920074 | AE39: 10465
A40: Seychelles | B40: SYC | C40: 99912 | D40: 52.842651 | F40: 46 | G40: 82.872928 | H40: 62.555048 | I40: 31.22748 | J40: 4.4038754 | K40: 5.4047562 | L40: 1.0008808 | M40: 2.1018496 | N40: 189.56682 | O40: 34366.619 | P40: 35085.182 | Q40: 64.721451 | R40: 78.3 | S40: 87.12 | T40: 57.3 | U40: 79.13 | V40: 75.4625 | W40: 0.31209413 | X40: 0.067825983 | Y40: 0.22109038 | Z40: 0.023145292 | AA40: 31.8 | AB40: 230.71805 | AC40: 10.684803 | AD40: 3.4656807 | AE40: 1894
A41: Sierra Leone | B41: SLE | C41: 8472212 | D41: 30.91938 | E41: 2.63 | F41: 59 | G41: 1.3054442 | H41: 8.6825023 | I41: 2.6805278 | J41: 0.017704939 | K41: 0.10504931 | L41: 0 | M41: 0.35173813 | N41: 13.142967 | O41: 2920.12 | P41: 2966.491 | Q41: 53.127224 | R41: 14.19 | S41: 50.54 | T41: 54.72 | U41: 72.06 | V41: 47.8775 | W41: 0.62214616 | X41: 0.39564769 | Y41: 0.17921993 | Z41: 0.04572357 | AA41: 32.7 | AB41: 11.384249 | AC41: 5.26334 | AD41: 4 | AE41: 11135
A42: South Africa | B42: ZAF | C42: 61452696 | D42: 44.56413 | E42: 21.64 | F42: 54 | G42: 8.0603461 | H42: 64.645008 | I42: 0.25108744 | J42: 0.19039035 | K42: 2.7385292 | L42: 0.0021154483 | M42: 0.18062674 | N42: 76.068103 | O42: 13897.062 | P42: 13771.97 | Q42: 52.757084 | R42: 79.53 | S42: 68.77 | T42: 60.66 | U42: 76.38 | V42: 71.335 | W42: 0.59898341 | X42: 0.27289034 | Y42: 0.23352654 | Z42: 0.066110009 | AA42: 45.8 | AB42: 66.053003 | AC42: 2.1852693 | AD42: 0.57985369 | AE42: 467459
A43: South Sudan | B43: SSD | C43: 11891023 | D43: 29.1139 | E43: 3.35 | F43: 46.32 | G43: 0.38348256 | H43: 3.8095965 | I43: 2.596917 | J43: 0.026911057 | K43: 0.13455529 | L43: 0.53401629 | M43: 0.22874399 | N43: 7.7142227 | O43: 938.257 | P43: 660.094 | Q43: 50.530018 | R43: 21.91 | S43: 35.58 | T43: 59.48 | U43: 29.42 | V43: 36.5975 | W43: 0.63690566 | X43: 0.41618333 | Y43: 0.15884745 | Z43: 0.057924879 | AA43: 21.3 | AB43: 6.4682067 | AC43: 1.0973402 | AE43: 9173
A44: Togo | B44: UGA | C44: 49700758 | D44: 32.35637 | E44: 4.33 | F44: 40.1 | G44: 1.8213002 | H44: 14.928746 | I44: 6.631086 | J44: 0.1014069 | K44: 0.34446155 | L44: 0.75894215 | M44: 2.6921119 | N44: 27.278055 | O44: 3143.583 | P44: 3240.979 | Q44: 55.849014 | R44: 22.84 | S44: 55.37 | T44: 56.9 | U44: 52.14 | V44: 46.8125 | W44: 0.39850537 | X44: 0.21625225 | Y44: 0.13944238 | Z44: 0.040092692 | AA44: 27.8 | AB44: 23.242417 | AC44: 0.20829094 | AD44: 6.136452 | AE44: 135574
A45: Uganda | B45: TZA | C45: 65136238 | D45: 32.46088 | E45: 3.2 | F45: 41.2 | G45: 1.3345874 | H45: 7.0860709 | I45: 0 | J45: 0.1159109 | K45: 0.34727213 | L45: 0.23826982 | M45: 0.72816609 | N45: 9.8502772 | O45: 3553.409 | P45: 3638.147 | Q45: 57.224392 | R45: 27.27 | S45: 54.91 | T45: 54.5 | U45: 68.17 | V45: 51.2125 | W45: 0.40710628 | X45: 0.22733353 | Y45: 0.14378753 | Z45: 0.03339787 | AA45: 36.5 | AB45: 9.0431618 | AC45: 5.9479843 | AD45: 5.5263138 | AE45: 64161
A46: United Republic of Tanzania | B46: TGO | C46: 8886635 | D46: 33.47842 | E46: 3.7 | F46: 33.8 | G46: 0.82145829 | H46: 2.9595004 | I46: 2.0975319 | J46: 0.024756277 | K46: 0.28694776 | L46: 0.14178595 | M46: 0.46586813 | N46: 6.7978487 | O46: 2815.904 | P46: 2895.085 | Q46: 58.072868 | R46: 19.6 | S46: 52.66 | T46: 50.72 | U46: 63.1 | V46: 46.52 | W46: 0.48252291 | X46: 0.25168432 | Y46: 0.18194219 | Z46: 0.045928544 | AA46: 31.3 | AB46: 6.2109686 | AC46: 9.350128 | AD46: 5.3000053 | AE46: 6041
A47: Zambia | B47: ZMB | C47: 20032801 | D47: 31.61706 | E47: 5.23 | F47: 52.3 | G47: 3.2601532 | H47: 24.946586 | I47: 4.5934665 | J47: 0.14126831 | K47: 0.71133338 | L47: 0.20915697 | M47: 0.76524496 | N47: 34.62721 | O47: 3701.027 | P47: 3747.732 | Q47: 52.970093 | R47: 37.54 | S47: 60.64 | T47: 57.47 | U47: 74.31 | V47: 57.49 | W47: 0.50513805 | X47: 0.30859836 | Y47: 0.15379622 | Z47: 0.036071447 | AA47: 26.5 | AB47: 29.968206 | AC47: 5.9489349 | AD47: 4.0431483 | AE47: 69368
A48: Zimbabwe | B48: ZWE | C48: 15581023 | D48: 28.5771 | E48: 4.5 | F48: 46 | G48: 1.4260938 | H48: 29.867744 | I48: 1.8002669 | J48: 0.31576874 | K48: 1.2207157 | L48: 0.92997745 | M48: 0.67710573 | N48: 36.237672 | O48: 4473.673 | P48: 4465.361 | Q48: 51.248913 | R48: 40.41 | S48: 47.83 | T48: 66.74 | U48: 71.16 | V48: 56.535 | W48: 0.55124774 | X48: 0.29968262 | Y48: 0.1852836 | Z48: 0.057561611 | AA48: 32.4 | AB48: 29.796679 | AC48: 2.426871 | AD48: 2.0294841 | AE48: 56462

Sheet Sheet2
B1: Occupations | C1: 2014 | D1: 2015 | E1: 2016 | F1: 2017 | G1: 2018 | H1: 2019 | I1: 2020 | J1: 2021 | K1: 2022 | L1: 2023 | M1: Density 2014 | N1: Density 2015 | O1: Density 2016 | P1: Density 2017 | Q1: Density 2018 | R1: Density 2019 | S1: Density 2020 | T1: Density 2021 | U1: Density 2022 | V1: Density 2023
B2: AGO | C2: 0 | D2: 0 | E2: 0 | F2: 0 | G2: 6400 | H2: 23199 | I2: 23199 | J2: 23199 | K2: 77163 | L2: 77163 | Y2: Row Labels | Z2: Sum of 2023
A3: AGO | B3: Dentists | C3: 0 | D3: 0 | E3: 0 | F3: 0 | G3: 0 | H3: 1652 | I3: 1652 | J3: 1652 | K3: 254 | L3: 254 | M3: 0 | N3: 0 | O3: 0 | P3: 0 | Q3: 0 | R3: 0.51060797 | S3: 0.4941893 | T3: 0.4787882 | U3: 0.071370393 | V3: 0.070265445 | Y3: AGO | Z3: 77163
A4: AGO | B4: Medical and Pathology Laboratory scientists | C4: 0 | D4: 0 | E4: 0 | F4: 0 | G4: 0 | H4: 98 | I4: 98 | J4: 98 | K4: 13 | L4: 13 | M4: 0 | N4: 0 | O4: 0 | P4: 0 | Q4: 0 | R4: 0.030290304 | S4: 0.029316314 | T4: 0.02840269 | U4: 0.0036528154 | V4: 0.0035962629 | Y4: BDI | Z4: 14717
A5: AGO | B5: Medical and Pathology Laboratory Technicians | C5: 0 | D5: 0 | E5: 0 | F5: 0 | G5: 0 | H5: 0 | I5: 0 | J5: 0 | K5: 18 | L5: 18 | M5: 0 | N5: 0 | O5: 0 | P5: 0 | Q5: 0 | R5: 0 | S5: 0 | T5: 0 | U5: 0.0050577444 | V5: 0.004979441 | Y5: BEN | Z5: 14457
A6: AGO | B6: Medical Doctors | C6: 0 | D6: 0 | E6: 0 | F6: 0 | G6: 6400 | H6: 6593 | I6: 6593 | J6: 6593 | K6: 8693 | L6: 8693 | M6: 0 | N6: 0 | O6: 0 | P6: 0 | Q6: 2.0464589 | R6: 2.0377956 | S6: 1.97227 | T6: 1.9108055 | U6: 2.4426096 | V6: 2.4047934 | Y6: BFA | Z6: 27315
A7: AGO | B7: Midwifery personnel | C7: 0 | D7: 0 | E7: 0 | F7: 0 | G7: 0 | H7: 0 | I7: 0 | J7: 0 | K7: 33 | L7: 33 | M7: 0 | N7: 0 | O7: 0 | P7: 0 | Q7: 0 | R7: 0 | S7: 0 | T7: 0 | U7: 0.0092725314 | V7: 0.0091289752 | Y7: BWA | Z7: 9108
A8: AGO | B8: Nursing Personnel | C8: 0 | D8: 0 | E8: 0 | F8: 0 | G8: 0 | H8: 12554 | I8: 12554 | J8: 12554 | K8: 66718 | L8: 66718 | M8: 0 | N8: 0 | O8: 0 | P8: 0 | Q8: 0 | R8: 3.8802497 | S8: 3.7554797 | T8: 3.6384426 | U8: 18.746811 | V8: 18.456575 | Y8: CAF | Z8: 6451
A9: AGO | B9: Pharmacists | C9: 0 | D9: 0 | E9: 0 | F9: 0 | G9: 0 | H9: 2302 | I9: 2302 | J9: 2302 | K9: 1434 | L9: 1434 | M9: 0 | N9: 0 | O9: 0 | P9: 0 | Q9: 0 | R9: 0.71151305 | S9: 0.68863424 | T9: 0.66717339 | U9: 0.40293364 | V9: 0.39669547 | Y9: CIV | Z9: 32021
B10: BDI | C10: 7467 | D10: 7467 | E10: 7511 | F10: 7511 | G10: 11392 | H10: 11606 | I10: 11606 | J10: 14017 | K10: 13216 | L10: 14717 | Y10: CMR | Z10: 23421
A11: BDI | B11: Dentists | C11: 4 | D11: 4 | E11: 4 | F11: 4 | G11: 4 | H11: 14 | I11: 14 | J11: 8 | K11: 14 | L11: 14 | M11: 0.0038113703 | N11: 0.0037288569 | O11: 0.003668605 | P11: 0.0035856453 | Q11: 0.0034802364 | R11: 0.011789635 | S11: 0.011456416 | T11: 0.0063738859 | U11: 0.01086149 | V11: 0.010769942 | Y11: COD | Z11: 148145
A12: BDI | B12: Medical and Pathology Laboratory scientists | C12: 0 | D12: 0 | E12: 0 | F12: 0 | G12: 1073 | H12: 1073 | I12: 1073 | J12: 1140 | K12: 1274 | L12: 1274 | M12: 0 | N12: 0 | O12: 0 | P12: 0 | Q12: 0.93357342 | R12: 0.90359127 | S12: 0.87805243 | T12: 0.90827875 | U12: 0.98839558 | V12: 0.98006476 | Y12: COG | Z12: 8944
A13: BDI | B13: Medical and Pathology Laboratory Technicians | C13: 0 | D13: 0 | E13: 0 | F13: 0 | G13: 0 | H13: 0 | I13: 0 | J13: 0 | K13: 911 | L13: 911 | M13: 0 | N13: 0 | O13: 0 | P13: 0 | Q13: 0 | R13: 0 | S13: 0 | T13: 0 | U13: 0.70677267 | V13: 0.70081554 | Y13: COM | Z13: 1974
A14: BDI | B14: Medical Doctors | C14: 609 | D14: 609 | E14: 609 | F14: 609 | G14: 1084 | H14: 1084 | I14: 1084 | J14: 871 | K14: 1038 | L14: 1038 | M14: 0.58028113 | N14: 0.56771847 | O14: 0.55854511 | P14: 0.5459145 | Q14: 0.94314407 | R14: 0.91285456 | S14: 0.8870539 | T14: 0.69395683 | U14: 0.8053019 | V14: 0.7985143 | Y14: CPV | Z14: 1376
A15: BDI | B15: Midwifery personnel | C15: 35 | D15: 35 | E15: 79 | F15: 79 | G15: 160 | H15: 160 | I15: 160 | J15: 346 | K15: 483 | L15: 483 | M15: 0.03334949 | N15: 0.032627498 | O15: 0.072454949 | P15: 0.070816495 | Q15: 0.13920946 | R15: 0.13473868 | S15: 0.13093046 | T15: 0.27567057 | U15: 0.3747214 | V15: 0.37156301 | Y15: DZA | Z15: 234805
A16: BDI | B16: Nursing Personnel | C16: 6819 | D16: 6819 | E16: 6819 | F16: 6819 | G16: 9071 | H16: 9156 | I16: 9156 | J16: 11586 | K16: 9372 | L16: 10873 | M16: 6.4974336 | N16: 6.3567688 | O16: 6.2540544 | P16: 6.1126289 | Q16: 7.8923062 | R16: 7.710421 | S16: 7.4924958 | T16: 9.2309803 | U16: 7.2709917 | V16: 8.3643988 | Y16: ERI | Z16: 6503
A17: BDI | B17: Pharmacists | C17: 0 | D17: 0 | E17: 0 | F17: 0 | G17: 0 | H17: 119 | I17: 119 | J17: 66 | K17: 124 | L17: 124 | M17: 0 | N17: 0 | O17: 0 | P17: 0 | Q17: 0 | R17: 0.10021189 | S17: 0.097379533 | T17: 0.052584559 | U17: 0.096201768 | V17: 0.095390919 | Y17: ETH | Z17: 239596
B18: BEN | C18: 0 | D18: 0 | E18: 0 | F18: 4322 | G18: 4322 | H18: 9525 | I18: 9938 | J18: 9938 | K18: 13264 | L18: 14457 | Y18: GAB | Z18: 7767
A19: BEN | B19: Dentists | C19: 0 | D19: 0 | E19: 0 | F19: 9 | G19: 9 | H19: 12 | I19: 12 | J19: 12 | K19: 50 | L19: 66 | M19: 0 | N19: 0 | O19: 0 | P19: 0.0077607756 | Q19: 0.0075372573 | R19: 0.0097636831 | S19: 0.0094913258 | T19: 0.0092329745 | U19: 0.03744515 | V19: 0.050288216 | Y19: GHA | Z19: 160236
A20: BEN | B20: Medical and Pathology Laboratory scientists | C20: 0 | D20: 0 | E20: 0 | F20: 0 | G20: 0 | H20: 668 | I20: 668 | J20: 668 | K20: 668 | L20: 668 | M20: 0 | N20: 0 | O20: 0 | P20: 0 | Q20: 0 | R20: 0.54351169 | S20: 0.52835047 | T20: 0.51396891 | U20: 0.50026721 | V20: 0.5089777 | Y20: GIN | Z20: 9650
A21: BEN | B21: Medical and Pathology Laboratory Technicians | C21: 0 | D21: 0 | E21: 0 | F21: 1166 | G21: 1166 | H21: 1166 | I21: 1166 | J21: 1166 | K21: 1602 | L21: 1632 | M21: 0 | N21: 0 | O21: 0 | P21: 1.0054516 | Q21: 0.97649356 | R21: 0.94870454 | S21: 0.92224049 | T21: 0.89713735 | U21: 1.1997426 | V21: 1.2434904 | Y21: GMB | Z21: 2263
A22: BEN | B22: Medical Doctors | C22: 0 | D22: 0 | E22: 0 | F22: 523 | G22: 523 | H22: 908 | I22: 908 | J22: 908 | K22: 2608 | L22: 3042 | M22: 0 | N22: 0 | O22: 0 | P22: 0.4509873 | Q22: 0.4379984 | R22: 0.73878535 | S22: 0.71817699 | T22: 0.6986284 | U22: 1.953139 | V22: 2.3178296 | Y22: GNB | Z22: 2811
A23: BEN | B23: Midwifery personnel | C23: 0 | D23: 0 | E23: 0 | F23: 1034 | G23: 1034 | H23: 1055 | I23: 1208 | J23: 1208 | K23: 2061 | L23: 2426 | M23: 0 | N23: 0 | O23: 0 | P23: 0.89162689 | Q23: 0.86594712 | R23: 0.85839047 | S23: 0.95546013 | T23: 0.92945277 | U23: 1.5434891 | V23: 1.8484729 | Y23: GNQ | Z23: 3130
A24: BEN | B24: Nursing Personnel | C24: 0 | D24: 0 | E24: 0 | F24: 1577 | G24: 1577 | H24: 5410 | I24: 5670 | J24: 5670 | K24: 5893 | L24: 6190 | M24: 0 | N24: 0 | O24: 0 | P24: 1.3598604 | Q24: 1.320695 | R24: 4.4017938 | S24: 4.4846515 | T24: 4.3625804 | U24: 4.4132854 | V24: 4.7164251 | Y24: KEN | Z24: 155136
A25: BEN | B25: Pharmacists | C25: 0 | D25: 0 | E25: 0 | F25: 13 | G25: 13 | H25: 306 | I25: 306 | J25: 306 | K25: 382 | L25: 433 | M25: 0 | N25: 0 | O25: 0 | P25: 0.011210009 | Q25: 0.010887149 | R25: 0.24897392 | S25: 0.24202881 | T25: 0.23544085 | U25: 0.28608095 | V25: 0.32992118 | Y25: LBR | Z25: 6660
B26: BFA | C26: 7432 | D26: 12939 | E26: 13788 | F26: 18201 | G26: 19692 | H26: 19929 | I26: 22805 | J26: 24888 | K26: 30815 | L26: 27315 | Y26: LSO | Z26: 5581
A27: BFA | B27: Dentists | C27: 0 | D27: 0 | E27: 0 | F27: 0 | G27: 80 | H27: 91 | I27: 91 | J27: 103 | K27: 109 | L27: 133 | M27: 0 | N27: 0 | O27: 0 | P27: 0 | Q27: 0.03922968 | R27: 0.043433356 | S27: 0.042281086 | T27: 0.046604895 | U27: 0.048073187 | V27: 0.058536563 | Y27: MDG | Z27: 14677
A28: BFA | B28: Medical and Pathology Laboratory scientists | C28: 0 | D28: 0 | E28: 0 | F28: 0 | G28: 699 | H28: 699 | I28: 699 | J28: 699 | K28: 899 | L28: 6 | M28: 0 | N28: 0 | O28: 0 | P28: 0 | Q28: 0.34276933 | R28: 0.33362545 | S28: 0.3247745 | T28: 0.31627982 | U28: 0.39649353 | V28: 0.0026407472 | Y28: MLI | Z28: 17334
A29: BFA | B29: Medical and Pathology Laboratory Technicians | C29: 0 | D29: 0 | E29: 0 | F29: 0 | G29: 0 | H29: 0 | I29: 800 | J29: 906 | K29: 945 | L29: 1104 | M29: 0 | N29: 0 | O29: 0 | P29: 0 | Q29: 0 | R29: 0 | S29: 0.37170185 | T29: 0.40994208 | U29: 0.4167813 | V29: 0.48589749 | Y29: MOZ | Z29: 39554
A30: BFA | B30: Medical Doctors | C30: 857 | D30: 1189 | E30: 1202 | F30: 1626 | G30: 1684 | H30: 1910 | I30: 2061 | J30: 2221 | K30: 3323 | L30: 3323 | M30: 0.47166068 | N30: 0.63521679 | O30: 0.6235896 | P30: 0.81972759 | Q30: 0.82578477 | R30: 0.91162319 | S30: 0.9575969 | T30: 1.0049463 | U30: 1.4655706 | V30: 1.4625338 | Y30: MRT | Z30: 9698
A31: BFA | B31: Midwifery personnel | C31: 0 | D31: 1744 | E31: 2580 | F31: 6569 | G31: 6569 | H31: 6569 | I31: 7477 | J31: 8052 | K31: 9294 | L31: 8229 | M31: 0 | N31: 0.93172253 | O31: 1.3384868 | P31: 3.3116793 | Q31: 3.2212471 | R31: 3.1353156 | S31: 3.4740185 | T31: 3.6433263 | U31: 4.099011 | V31: 3.6217848 | Y31: MUS | Z31: 8036
A32: BFA | B32: Nursing Personnel | C32: 6358 | D32: 9748 | E32: 9748 | F32: 9748 | G32: 10376 | H32: 10376 | I32: 11364 | J32: 12189 | K32: 15405 | L32: 13619 | M32: 3.4992049 | N32: 5.2078161 | O32: 5.0571975 | P32: 4.9143324 | Q32: 5.0880895 | R32: 4.9523572 | S32: 5.2800248 | T32: 5.5152142 | U32: 6.7941967 | V32: 5.994056 | Y32: MWI | Z32: 12073
A33: BFA | B33: Pharmacists | C33: 217 | D33: 258 | E33: 258 | F33: 258 | G33: 284 | H33: 284 | I33: 313 | J33: 718 | K33: 840 | L33: 901 | M33: 0.11942867 | N33: 0.1378351 | O33: 0.13384868 | P33: 0.13006748 | Q33: 0.13926536 | R33: 0.13555025 | S33: 0.14542835 | T33: 0.32487684 | U33: 0.37047227 | V33: 0.39655221 | Y33: NAM | Z33: 19203
B34: BWA | C34: 0 | D34: 0 | E34: 0 | F34: 9809 | G34: 9809 | H34: 10761 | I34: 10907 | J34: 11110 | K34: 9819 | L34: 9108 | Y34: NER | Z34: 13159
A35: BWA | B35: Dentists | C35: 0 | D35: 0 | E35: 0 | F35: 91 | G35: 91 | H35: 96 | I35: 96 | J35: 89 | K35: 99 | L35: 89 | M35: 0 | N35: 0 | O35: 0 | P35: 0.37887619 | Q35: 0.37121508 | R35: 0.38404578 | S35: 0.37700253 | T35: 0.3438387 | U35: 0.37638349 | V35: 0.35832856 | Y35: NGA | Z35: 552980
A36: BWA | B36: Medical and Pathology Laboratory scientists | C36: 0 | D36: 0 | E36: 0 | F36: 0 | G36: 0 | H36: 160 | I36: 160 | J36: 167 | K36: 191 | L36: 150 | M36: 0 | N36: 0 | O36: 0 | P36: 0 | Q36: 0 | R36: 0.6400763 | S36: 0.62833755 | T36: 0.64518048 | U36: 0.72615401 | V36: 0.60392454 | Y36: RWA | Z36: 18546
A37: BWA | B37: Medical and Pathology Laboratory Technicians | C37: 0 | D37: 0 | E37: 0 | F37: 0 | G37: 0 | H37: 318 | I37: 338 | J37: 338 | K37: 365 | L37: 311 | M37: 0 | N37: 0 | O37: 0 | P37: 0 | Q37: 0 | R37: 1.2721516 | S37: 1.3273631 | T37: 1.3058144 | U37: 1.3876765 | V37: 1.2521369 | Y37: SEN | Z37: 10465
A38: BWA | B38: Medical Doctors | C38: 0 | D38: 0 | E38: 0 | F38: 830 | G38: 830 | H38: 925 | I38: 925 | J38: 1024 | K38: 992 | L38: 941 | M38: 0 | N38: 0 | O38: 0 | P38: 3.455684 | Q38: 3.3858079 | R38: 3.7004411 | S38: 3.6325765 | T38: 3.9560767 | U38: 3.7714387 | V38: 3.78862 | Y38: SLE | Z38: 11135
A39: BWA | B39: Midwifery personnel | C39: 0 | D39: 0 | E39: 0 | F39: 1461 | G39: 1461 | H39: 1461 | I39: 1461 | J39: 1461 | K39: 0 | L39: 0 | M39: 0 | N39: 0 | O39: 0 | P39: 6.0828365 | Q39: 5.9598378 | R39: 5.8446967 | S39: 5.7375073 | T39: 5.6443634 | U39: 0 | V39: 0 | Y39: SSD | Z39: 9173
A40: BWA | B40: Nursing Personnel | C40: 0 | D40: 0 | E40: 0 | F40: 7427 | G40: 7427 | H40: 7645 | I40: 7771 | J40: 7886 | K40: 8028 | L40: 7485 | M40: 0 | N40: 0 | O40: 0 | P40: 30.922126 | Q40: 30.296862 | R40: 30.583646 | S40: 30.517569 | T40: 30.466427 | U40: 30.52128 | V40: 30.135835 | Y40: STP | Z40: 784
A41: BWA | B41: Pharmacists | C41: 0 | D41: 0 | E41: 0 | F41: 0 | G41: 0 | H41: 156 | I41: 156 | J41: 145 | K41: 144 | L41: 132 | M41: 0 | N41: 0 | O41: 0 | P41: 0 | Q41: 0 | R41: 0.62407439 | S41: 0.61262911 | T41: 0.56018665 | U41: 0.5474669 | V41: 0.5314536 | Y41: SWZ | Z41: 6004
B42: CAF | C42: 0 | D42: 0 | E42: 1271 | F42: 1271 | G42: 1271 | H42: 2293 | I42: 2293 | J42: 2293 | K42: 2812 | L42: 6451 | Y42: SYC | Z42: 1894
A43: CAF | B43: Dentists | C43: 0 | D43: 0 | E43: 0 | F43: 0 | G43: 0 | H43: 10 | I43: 10 | J43: 10 | K43: 3 | L43: 3 | M43: 0 | N43: 0 | O43: 0 | P43: 0 | Q43: 0 | R43: 0.019196349 | S43: 0.018716007 | T43: 0.01832457 | U43: 0.005377169 | V43: 0.0058603639 | Y43: TCD | Z43: 7115
A44: CAF | B44: Medical and Pathology Laboratory scientists | C44: 0 | D44: 0 | E44: 0 | F44: 0 | G44: 0 | H44: 112 | I44: 112 | J44: 112 | K44: 112 | L44: 112 | M44: 0 | N44: 0 | O44: 0 | P44: 0 | Q44: 0 | R44: 0.21499911 | S44: 0.20961928 | T44: 0.20523518 | U44: 0.20074764 | V44: 0.21878692 | Y44: TGO | Z44: 6041
A45: CAF | B45: Medical and Pathology Laboratory Technicians | C45: 0 | D45: 0 | E45: 0 | F45: 0 | G45: 0 | H45: 0 | I45: 0 | J45: 0 | K45: 3 | L45: 287 | M45: 0 | N45: 0 | O45: 0 | P45: 0 | Q45: 0 | R45: 0 | S45: 0 | T45: 0 | U45: 0.005377169 | V45: 0.56064148 | Y45: TZA | Z45: 64161
A46: CAF | B46: Medical Doctors | C46: 0 | D46: 0 | E46: 324 | F46: 324 | G46: 324 | H46: 335 | I46: 335 | J46: 335 | K46: 146 | L46: 383 | M46: 0 | N46: 0 | O46: 0.66066131 | P46: 0.64842264 | Q46: 0.63594503 | R46: 0.64307768 | S46: 0.62698624 | T46: 0.61387309 | U46: 0.26168889 | V46: 0.74817313 | Y46: UGA | Z46: 135574
A47: CAF | B47: Midwifery personnel | C47: 0 | D47: 0 | E47: 605 | F47: 605 | G47: 605 | H47: 605 | I47: 605 | J47: 605 | K47: 1897 | L47: 1897 | M47: 0 | N47: 0 | O47: 1.2336423 | P47: 1.2107892 | Q47: 1.1874899 | R47: 1.1613791 | S47: 1.1323184 | T47: 1.1086365 | U47: 3.4001632 | V47: 3.7057035 | Y47: ZAF | Z47: 467459
A48: CAF | B48: Nursing Personnel | C48: 0 | D48: 0 | E48: 322 | F48: 322 | G48: 322 | H48: 1195 | I48: 1195 | J48: 1195 | K48: 648 | L48: 3756 | M48: 0 | N48: 0 | O48: 0.65658315 | P48: 0.64442003 | Q48: 0.63201944 | R48: 2.2939637 | S48: 2.2365628 | T48: 2.1897861 | U48: 1.1614685 | V48: 7.3371756 | Y48: ZMB | Z48: 69368
A49: CAF | B49: Pharmacists | C49: 0 | D49: 0 | E49: 20 | F49: 20 | G49: 20 | H49: 36 | I49: 36 | J49: 36 | K49: 3 | L49: 13 | M49: 0 | N49: 0 | O49: 0.040781562 | P49: 0.040026089 | Q49: 0.039255866 | R49: 0.069106855 | S49: 0.067377625 | T49: 0.065968452 | U49: 0.005377169 | V49: 0.02539491 | Y49: ZWE | Z49: 56462
B50: CIV | C50: 14168 | D50: 28331 | E50: 29572 | F50: 31023 | G50: 32603 | H50: 33046 | I50: 33793 | J50: 29969 | K50: 27921 | L50: 32021 | Y50: Grand Total | Z50: 2750125
A51: CIV | B51: Dentists | C51: 0 | D51: 490 | E51: 490 | F51: 490 | G51: 490 | H51: 506 | I51: 506 | J51: 397 | K51: 418 | L51: 425 | M51: 0 | N51: 0.20765579 | O51: 0.20236543 | P51: 0.19719884 | Q51: 0.19220218 | R51: 0.19351717 | S51: 0.18872295 | T51: 0.14447791 | U51: 0.14843464 | V51: 0.14941532
A52: CIV | B52: Medical and Pathology Laboratory scientists | C52: 0 | D52: 2380 | E52: 2380 | F52: 2380 | G52: 2380 | H52: 2380 | I52: 2380 | J52: 2380 | K52: 497 | L52: 497 | M52: 0 | N52: 1.0086139 | O52: 0.9829178 | P52: 0.95782295 | Q52: 0.93355343 | R52: 0.91021909 | S52: 0.88766919 | T52: 0.86613961 | U52: 0.17648808 | V52: 0.17472803
A53: CIV | B53: Medical and Pathology Laboratory Technicians | C53: 0 | D53: 1600 | E53: 1600 | F53: 1600 | G53: 1600 | H53: 1600 | I53: 1600 | J53: 1600 | K53: 0 | L53: 0 | M53: 0 | N53: 0.67805974 | O53: 0.66078507 | P53: 0.64391459 | Q53: 0.62759895 | R53: 0.61191199 | S53: 0.5967524 | T53: 0.58227873 | U53: 0 | V53: 0
A54: CIV | B54: Medical Doctors | C54: 0 | D54: 5240 | E54: 5240 | F54: 5240 | G54: 5240 | H54: 5602 | I54: 5602 | J54: 4435 | K54: 4930 | L54: 5169 | M54: 0 | N54: 2.2206456 | O54: 2.1640711 | P54: 2.1088203 | Q54: 2.0553865 | R54: 2.1424569 | S54: 2.0893793 | T54: 1.6140039 | U54: 1.7506765 | V54: 1.8172418
A55: CIV | B55: Midwifery personnel | C55: 5300 | D55: 5300 | E55: 5300 | F55: 5300 | G55: 5300 | H55: 5300 | I55: 6047 | J55: 7134 | K55: 7425 | L55: 8648 | M55: 2.3047933 | N55: 2.2460729 | O55: 2.1888506 | P55: 2.1329671 | Q55: 2.0789215 | R55: 2.0269585 | S55: 2.2553511 | T55: 2.5962353 | U55: 2.636668 | V55: 3.040338
A56: CIV | B56: Nursing Personnel | C56: 8868 | D56: 10891 | E56: 12132 | F56: 13583 | G56: 15163 | H56: 15163 | I56: 15163 | J56: 12994 | K56: 13489 | L56: 16064 | M56: 3.8563975 | N56: 4.6154679 | O56: 5.0104028 | P56: 5.4664324 | Q56: 5.9476768 | R56: 5.7990135 | S56: 5.6553479 | T56: 4.7288312 | U56: 4.7900356 | V56: 5.6475473
A57: CIV | B57: Pharmacists | C57: 0 | D57: 2430 | E57: 2430 | F57: 2430 | G57: 2430 | H57: 2495 | I57: 2495 | J57: 1029 | K57: 1162 | L57: 1218 | M57: 0 | N57: 1.0298032 | O57: 1.0035673 | P57: 0.97794528 | Q57: 0.9531659 | R57: 0.95420026 | S57: 0.93056077 | T57: 0.37447801 | U57: 0.4126341 | V57: 0.42820671
B58: CMR | C58: 0 | D58: 0 | E58: 0 | F58: 287 | G58: 287 | H58: 12758 | I58: 12970 | J58: 16095 | K58: 23421 | L58: 23421
A59: CMR | B59: Dentists | C59: 0 | D59: 0 | E59: 0 | F59: 88 | G59: 88 | H59: 88 | I59: 300 | J59: 300 | K59: 317 | L59: 317 | M59: 0 | N59: 0 | O59: 0 | P59: 0.036075656 | Q59: 0.035092271 | R59: 0.034131889 | S59: 0.11324564 | T59: 0.11029968 | U59: 0.11356091 | V59: 0.11080767
A60: CMR | B60: Medical and Pathology Laboratory scientists | C60: 0 | D60: 0 | E60: 0 | F60: 0 | G60: 0 | H60: 241 | I60: 241 | J60: 112 | K60: 293 | L60: 293 | M60: 0 | N60: 0 | O60: 0 | P60: 0 | Q60: 0 | R60: 0.093474832 | S60: 0.090973994 | T60: 0.041178548 | U60: 0.10496323 | V60: 0.10241844
A61: CMR | B61: Medical and Pathology Laboratory Technicians | C61: 0 | D61: 0 | E61: 0 | F61: 0 | G61: 0 | H61: 0 | I61: 0 | J61: 48 | K61: 239 | L61: 239 | M61: 0 | N61: 0 | O61: 0 | P61: 0 | Q61: 0 | R61: 0 | S61: 0 | T61: 0.017647949 | U61: 0.085618475 | V61: 0.083542688
A62: CMR | B62: Medical Doctors | C62: 0 | D62: 0 | E62: 0 | F62: 0 | G62: 0 | H62: 3259 | I62: 3259 | J62: 2562 | K62: 3762 | L62: 3762 | M62: 0 | N62: 0 | O62: 0 | P62: 0 | Q62: 0 | R62: 1.2640435 | S62: 1.2302251 | T62: 0.94195928 | U62: 1.3476849 | V62: 1.3150108
A63: CMR | B63: Midwifery personnel | C63: 0 | D63: 0 | E63: 0 | F63: 0 | G63: 0 | H63: 0 | I63: 0 | J63: 1258 | K63: 1673 | L63: 1673 | M63: 0 | N63: 0 | O63: 0 | P63: 0 | Q63: 0 | R63: 0 | S63: 0 | T63: 0.46252333 | U63: 0.59932932 | V63: 0.58479882
A64: CMR | B64: Nursing Personnel | C64: 0 | D64: 0 | E64: 0 | F64: 0 | G64: 0 | H64: 9156 | I64: 9156 | J64: 11478 | K64: 16535 | L64: 16535 | M64: 0 | N64: 0 | O64: 0 | P64: 0 | Q64: 0 | R64: 3.5512679 | S64: 3.4562568 | T64: 4.2200658 | U64: 5.9234372 | V64: 5.7798257
A65: CMR | B65: Pharmacists | C65: 0 | D65: 0 | E65: 0 | F65: 199 | G65: 199 | H65: 14 | I65: 14 | J65: 337 | K65: 602 | L65: 602 | M65: 0 | N65: 0 | O65: 0 | P65: 0.081580176 | Q65: 0.079356385 | R65: 0.0054300732 | S65: 0.0052847964 | T65: 0.12390331 | U65: 0.21565825 | V65: 0.2104297
B66: COD | C66: 70195 | D66: 70195 | E66: 82652 | F66: 83158 | G66: 83934 | H66: 107200 | I66: 117172 | J66: 117172 | K66: 148145 | L66: 148145
A67: COD | B67: Dentists | C67: 0 | D67: 0 | E67: 0 | F67: 147 | G67: 147 | H67: 404 | I67: 422 | J67: 422 | K67: 451 | L67: 451 | M67: 0 | N67: 0 | O67: 0 | P67: 0.017441183 | Q67: 0.016879603 | R67: 0.044935377 | S67: 0.045448101 | T67: 0.04400687 | U67: 0.045550857 | V67: 0.045949163
A68: COD | B68: Medical and Pathology Laboratory scientists | C68: 2126 | D68: 2126 | E68: 2126 | F68: 2126 | G68: 2126 | H68: 2934 | I68: 2934 | J68: 2934 | K68: 2934 | L68: 2934 | M68: 0.27960591 | N68: 0.27028778 | O68: 0.26108001 | P68: 0.25224459 | Q68: 0.2441227 | R68: 0.32633761 | S68: 0.31598277 | T68: 0.30596246 | U68: 0.29633307 | V68: 0.29892427
A69: COD | B69: Medical and Pathology Laboratory Technicians | C69: 0 | D69: 0 | E69: 0 | F69: 0 | G69: 0 | H69: 0 | I69: 0 | J69: 0 | K69: 2934 | L69: 2934 | M69: 0 | N69: 0 | O69: 0 | P69: 0 | Q69: 0 | R69: 0 | S69: 0 | T69: 0 | U69: 0.29633307 | V69: 0.29892427
A70: COD | B70: Medical Doctors | C70: 6418 | D70: 6418 | E70: 6418 | F70: 6418 | G70: 6418 | H70: 6418 | I70: 15016 | J70: 15016 | K70: 21290 | L70: 21290 | M70: 0.84407843 | N70: 0.81594872 | O70: 0.78815215 | P70: 0.76147968 | Q70: 0.73696118 | R70: 0.71384963 | S70: 1.617177 | T70: 1.5658937 | U70: 2.1502832 | V70: 2.1690858
A71: COD | B71: Midwifery personnel | C71: 1555 | D71: 1555 | E71: 1555 | F71: 1793 | G71: 1793 | H71: 1793 | I71: 3149 | J71: 3149 | K71: 4292 | L71: 4292 | M71: 0.2045095 | N71: 0.19769403 | O71: 0.19095927 | P71: 0.21273498 | Q71: 0.20588523 | R71: 0.19942854 | S71: 0.33913761 | T71: 0.32838302 | U71: 0.43349064 | V71: 0.43728117
A72: COD | B72: Nursing Personnel | C72: 59813 | D72: 59813 | E72: 72270 | F72: 72270 | G72: 73046 | H72: 93964 | I72: 93964 | J72: 93964 | K72: 115316 | L72: 115316 | M72: 7.866448 | N72: 7.6042912 | O72: 8.875001 | P72: 8.5746551 | Q72: 8.3876701 | R72: 10.451257 | S72: 10.119634 | T72: 9.798724 | U72: 11.646879 | V72: 11.748722
A73: COD | B73: Pharmacists | C73: 283 | D73: 283 | E73: 283 | F73: 404 | G73: 404 | H73: 1687 | I73: 1687 | J73: 1687 | K73: 928 | L73: 928 | M73: 0.037219414 | N73: 0.035979041 | O73: 0.034753359 | P73: 0.047933592 | Q73: 0.046390202 | R73: 0.18763857 | S73: 0.18168471 | T73: 0.1759232 | U73: 0.093727706 | V73: 0.09454728
B74: COG | C74: 4740 | D74: 5134 | E74: 5134 | F74: 5403 | G74: 5403 | H74: 7050 | I74: 7050 | J74: 7050 | K74: 8944 | L74: 8944
A75: COG | B75: Dentists | C75: 0 | D75: 0 | E75: 0 | F75: 27 | G75: 27 | H75: 27 | I75: 27 | J75: 27 | K75: 10 | L75: 10 | M75: 0 | N75: 0 | O75: 0 | P75: 0.05082506 | Q75: 0.049622666 | R75: 0.048467589 | S75: 0.047350361 | T75: 0.046266103 | U75: 0.016749229 | V75: 0.016832903
A76: COG | B76: Medical and Pathology Laboratory scientists | C76: 0 | D76: 0 | E76: 0 | F76: 0 | G76: 0 | H76: 320 | I76: 320 | J76: 320 | K76: 320 | L76: 320 | M76: 0 | N76: 0 | O76: 0 | P76: 0 | Q76: 0 | R76: 0.57443069 | S76: 0.56118947 | T76: 0.548339 | U76: 0.53597533 | V76: 0.53865289
A77: COG | B77: Medical and Pathology Laboratory Technicians | C77: 0 | D77: 0 | E77: 0 | F77: 0 | G77: 0 | H77: 0 | I77: 0 | J77: 0 | K77: 777 | L77: 777 | M77: 0 | N77: 0 | O77: 0 | P77: 0 | Q77: 0 | R77: 0 | S77: 0 | T77: 0 | U77: 1.3014151 | V77: 1.3079165
A78: COG | B78: Medical Doctors | C78: 0 | D78: 0 | E78: 0 | F78: 530 | G78: 530 | H78: 544 | I78: 544 | J78: 544 | K78: 1042 | L78: 1042 | M78: 0 | N78: 0 | O78: 0 | P78: 0.99767711 | Q78: 0.97407455 | R78: 0.97653217 | S78: 0.9540221 | T78: 0.93217629 | U78: 1.7452697 | V78: 1.7539885
A79: COG | B79: Midwifery personnel | C79: 1282 | D79: 1282 | E79: 1282 | F79: 921 | G79: 921 | H79: 921 | I79: 921 | J79: 921 | K79: 1190 | L79: 1190 | M79: 2.5925906 | N79: 2.5314026 | O79: 2.4716474 | P79: 1.7336993 | Q79: 1.6926843 | R79: 1.6532833 | S79: 1.6151734 | T79: 1.5781882 | U79: 1.9931583 | V79: 2.0031154
A80: COG | B80: Nursing Personnel | C80: 3458 | D80: 3852 | E80: 3852 | F80: 3852 | G80: 3852 | H80: 5081 | I80: 5081 | J80: 5081 | K80: 5573 | L80: 5573 | M80: 6.9931187 | N80: 7.6060553 | O80: 7.4265099 | P80: 7.2510419 | Q80: 7.0795003 | R80: 9.1208823 | S80: 8.9106365 | T80: 8.7065951 | U80: 9.3343454 | V80: 9.3809767
A81: COG | B81: Pharmacists | C81: 0 | D81: 0 | E81: 0 | F81: 73 | G81: 73 | H81: 157 | I81: 157 | J81: 157 | K81: 32 | L81: 32 | M81: 0 | N81: 0 | O81: 0 | P81: 0.1374159 | Q81: 0.13416498 | R81: 0.28183006 | S81: 0.27533358 | T81: 0.26902882 | U81: 0.053597533 | V81: 0.053865289
B82: COM | C82: 0 | D82: 0 | E82: 0 | F82: 216 | G82: 216 | H82: 1459 | I82: 1459 | J82: 1706 | K82: 1974 | L82: 1974
A83: COM | B83: Dentists | C83: 0 | D83: 0 | E83: 0 | F83: 0 | G83: 0 | H83: 32 | I83: 32 | J83: 32 | K83: 32 | L83: 32 | M83: 0 | N83: 0 | O83: 0 | P83: 0 | Q83: 0 | R83: 0.40455836 | S83: 0.39694058 | T83: 0.38947208 | U83: 0.38242106 | V83: 0.34538884
A84: COM | B84: Medical and Pathology Laboratory scientists | C84: 0 | D84: 0 | E84: 0 | F84: 0 | G84: 0 | H84: 0 | I84: 0 | J84: 0 | K84: 161 | L84: 161 | M84: 0 | N84: 0 | O84: 0 | P84: 0 | Q84: 0 | R84: 0 | S84: 0 | T84: 0 | U84: 1.924056 | V84: 1.7377376
A85: COM | B85: Medical and Pathology Laboratory Technicians | C85: 0 | D85: 0 | E85: 0 | F85: 0 | G85: 0 | H85: 8 | I85: 8 | J85: 16 | K85: 16 | L85: 16 | M85: 0 | N85: 0 | O85: 0 | P85: 0 | Q85: 0 | R85: 0.10113959 | S85: 0.099235145 | T85: 0.19473604 | U85: 0.19121053 | V85: 0.17269442
A86: COM | B86: Medical Doctors | C86: 0 | D86: 0 | E86: 0 | F86: 216 | G86: 216 | H86: 220 | I86: 220 | J86: 354 | K86: 354 | L86: 354 | M86: 0 | N86: 0 | O86: 0 | P86: 2.8358961 | Q86: 2.7823829 | R86: 2.7813387 | S86: 2.7289665 | T86: 4.3085349 | U86: 4.230533 | V86: 3.8208641
A87: COM | B87: Midwifery personnel | C87: 0 | D87: 0 | E87: 0 | F87: 0 | G87: 0 | H87: 484 | I87: 484 | J87: 586 | K87: 586 | L87: 586 | M87: 0 | N87: 0 | O87: 0 | P87: 0 | Q87: 0 | R87: 6.1189452 | S87: 6.0037263 | T87: 7.1322075 | U87: 7.0030857 | V87: 6.3249332
A88: COM | B88: Nursing Personnel | C88: 0 | D88: 0 | E88: 0 | F88: 0 | G88: 0 | H88: 679 | I88: 679 | J88: 683 | K88: 785 | L88: 785 | M88: 0 | N88: 0 | O88: 0 | P88: 0 | Q88: 0 | R88: 8.5842227 | S88: 8.4225829 | T88: 8.3127948 | U88: 9.3812666 | V88: 8.4728201
A89: COM | B89: Pharmacists | C89: 0 | D89: 0 | E89: 0 | F89: 0 | G89: 0 | H89: 36 | I89: 36 | J89: 35 | K89: 40 | L89: 40 | M89: 0 | N89: 0 | O89: 0 | P89: 0 | Q89: 0 | R89: 0.45512816 | S89: 0.44655815 | T89: 0.42598509 | U89: 0.47802632 | V89: 0.43173605
B90: CPV | C90: 308 | D90: 852 | E90: 1100 | F90: 1172 | G90: 1188 | H90: 1453 | I90: 1509 | J90: 1627 | K90: 1343 | L90: 1376
A91: CPV | B91: Dentists | C91: 0 | D91: 0 | E91: 0 | F91: 4 | G91: 4 | H91: 81 | I91: 120 | J91: 120 | K91: 8 | L91: 8 | M91: 0 | N91: 0 | O91: 0 | P91: 0.070802225 | Q91: 0.070027766 | R91: 1.4037398 | S91: 2.0595908 | T91: 2.0410767 | U91: 0.13487336 | V91: 0.13953764
A92: CPV | B92: Medical and Pathology Laboratory scientists | C92: 0 | D92: 0 | E92: 0 | F92: 0 | G92: 0 | H92: 65 | I92: 65 | J92: 65 | K92: 2 | L92: 4 | M92: 0 | N92: 0 | O92: 0 | P92: 0 | Q92: 0 | R92: 1.1264579 | S92: 1.1156117 | T92: 1.1055832 | U92: 0.033718341 | V92: 0.069768821
A93: CPV | B93: Medical and Pathology Laboratory Technicians | C93: 0 | D93: 0 | E93: 0 | F93: 0 | G93: 0 | H93: 0 | I93: 0 | J93: 0 | K93: 0 | L93: 8 | M93: 0 | N93: 0 | O93: 0 | P93: 0 | Q93: 0 | R93: 0 | S93: 0 | T93: 0 | U93: 0 | V93: 0.13953764
A94: CPV | B94: Medical Doctors | C94: 308 | D94: 308 | E94: 410 | F94: 410 | G94: 410 | H94: 365 | I94: 382 | J94: 382 | K94: 373 | L94: 381 | M94: 5.6402406 | N94: 5.5780327 | O94: 7.3424858 | P94: 7.257228 | Q94: 7.177846 | R94: 6.3254943 | S94: 6.5563641 | T94: 6.4974274 | U94: 6.2884705 | V94: 6.6454802
A95: CPV | B95: Midwifery personnel | C95: 0 | D95: 0 | E95: 0 | F95: 0 | G95: 0 | H95: 0 | I95: 0 | J95: 0 | K95: 26 | L95: 26 | M95: 0 | N95: 0 | O95: 0 | P95: 0 | Q95: 0 | R95: 0 | S95: 0 | T95: 0 | U95: 0.43833843 | V95: 0.45349734
A96: CPV | B96: Nursing Personnel | C96: 0 | D96: 544 | E96: 690 | F96: 754 | G96: 770 | H96: 770 | I96: 770 | J96: 888 | K96: 924 | L96: 939 | M96: 0 | N96: 9.8521097 | O96: 12.356866 | P96: 13.346219 | Q96: 13.480345 | R96: 13.344194 | S96: 13.215708 | T96: 15.103967 | U96: 15.577873 | V96: 16.378231
A97: CPV | B97: Pharmacists | C97: 0 | D97: 0 | E97: 0 | F97: 4 | G97: 4 | H97: 172 | I97: 172 | J97: 172 | K97: 10 | L97: 10 | M97: 0 | N97: 0 | O97: 0 | P97: 0.070802225 | Q97: 0.070027766 | R97: 2.9807809 | S97: 2.9520802 | T97: 2.9255432 | U97: 0.1685917 | V97: 0.17442205
B98: DZA | C98: 0 | D98: 0 | E98: 0 | F98: 165267 | G98: 180572 | H98: 223170 | I98: 223292 | J98: 223292 | K98: 234805 | L98: 234805
A99: DZA | B99: Dentists | C99: 0 | D99: 0 | E99: 0 | F99: 0 | G99: 14263 | H99: 15437 | I99: 15437 | J99: 15437 | K99: 16222 | L99: 16222 | M99: 0 | N99: 0 | O99: 0 | P99: 0 | Q99: 3.4018646 | R99: 3.6147681 | S99: 3.5526831 | T99: 3.4942756 | U99: 3.6126581 | V99: 3.5224268
A100: DZA | B100: Medical and Pathology Laboratory scientists | C100: 0 | D100: 0 | E100: 0 | F100: 0 | G100: 0 | H100: 136 | I100: 136 | J100: 136 | K100: 136 | L100: 136 | M100: 0 | N100: 0 | O100: 0 | P100: 0 | Q100: 0 | R100: 0.031846114 | S100: 0.031299145 | T100: 0.030784575 | U100: 0.030287357 | V100: 0.029530886
...

Sheet Variables
B2: Country
B3: ISO
B4: Population_2023
B5: HAQ | C5: Healthcare Access and Quality (HAQ) Index is a metric developed by the Institute for Health Metrics and Evaluation (IHME) to assess health system performance.
B6: Productivity | C6: The Productivity Index developed by the International Labour Organization (ILO) measures the efficiency of labour in generating economic output.
B7: GINI INDEX | C7: The Gini coefficient is a key economic metric for measuring income or wealth inequality within a population
B8: Density_2023_Medical Doctors | C8: per 10000 population
B9: Density_2023_Nursing Personnel | C9: per 10000 population
B10: Density_2023_Midwifery Personnel | C10: per 10000 population
B11: Density_2023_Dentists | C11: per 10000 population
B12: Density_2023_Pharmacists | C12: per 10000 population
B13: Density_2023_Medical and Pathology Laboratory Scientists | C13: per 10000 population
B14: Density_2023_Medical and Pathology Laboratory Technicians | C14: per 10000 population
B15: Density_7_cadres_2023 | C15: per 10000 population
B16: GDP_PPP_2023 | C16: Measures a country’s economic output adjusted for price differences across countries (PPP) and inflation (constant currency).
B17: GDP_PPP_2024
B18: HALE_2021 | C18: HALE estimates the average number of years a person can expect to live in full health (discounting years lived with illness/disability). It combines mortality and morbidity data into a single metric.
B19: SCI_Capacity and Access | C19: The UHC Service Coverage Index (SCI) is a WHO-developed metric to track progress toward Universal Health Coverage (UHC) by measuring health service capacity and access.
B20: SCI_Infectious diseases | C20: measures a country's capacity to prevent, detect, and treat communicable diseases
B21: SCI_NCD | C21: evaluates a health system's capacity to prevent, diagnose, and manage chronic diseases
B22: SCI_RMNCH | C22: measures coverage of essential health services for women and children, including prenatal care, skilled birth attendance, immunization, and postnatal care.
B23: SCI_Average
B24: DALYS_2021_All Causes per capita 2021 | C24: measures the average number of healthy life years lost per person in 2021 due to all diseases and injuries, combining premature death and disability.
B25: DALYS_2021_Communicable, maternal, perinatal and nutritional conditions per capita 2021 | C25: measures the average number of healthy life years lost per person in 2021 due to infectious diseases, pregnancy-related complications, birth conditions, and nutritional deficiencies.
B26: DALYS_2021_Noncommunicable diseases per capita (2021) | C26: measures the average number of healthy life years lost per person in 2021 due to Noncommunicable diseases deficiencies.
B27: DALYS_2021_Injuries per capita 2021 | C27: measures the average number of healthy life years lost per person in 2021 due to Injuries
B28: Health_Security_Index_2021 | C28: global benchmark that assesses how well 195 countries are prepared to prevent, detect, and respond to infectious disease threats, revealing widespread gaps in pandemic readiness

Sheet Tuition and salaries
C3: Tuition fees
D4: Generalist Medical Practitioners | E4: Nursing Professionals | F4: Midwifery personnel | G4: Pharmacists | H4: Dentists | I4: Paramedical Practitioners
C5: Variable | D5: Medical Doctors | E5: Nursing Personnel | F5: Midwifery personnel | G5: Pharmacists | H5: Dentist | I5: Clinical Officer/Physician Assistant
C6: Median | D6: 3510.5 | E6: 1881 | F6: 1434 | G6: 1165 | H6: 5292 | I6: 20000
C7: Average | D7: 5843.1667 | E7: 5020.1 | F7: 4508.6 | G7: 5297.6 | H7: 7995.75 | I7: 20000
C8: Minimum | D8: 851 | E8: 400 | F8: 404 | G8: 637 | H8: 799 | I8: 20000
C9: Maximum | D9: 20600 | E9: 11538.5 | F9: 10000 | G9: 18600 | H9: 20600 | I9: 20000
C10: Number of countries | D10: 6 | E10: 5 | F10: 5 | G10: 5 | H10: 4 | I10: 1
C15: Estimated Salaries of Health Workers
F16: 11856.737
C17: Occupation | D17: Median | E17: Minimum | F17: Maximum | G17: Number of Countries
C18: Audiologists and Speech Therapists | D18: 8475.8805 | E18: 3176.4688 | F18: 11856.737 | G18: Inputed with average | H18: =IF(F18<D18,"Check","") | W18: Average | X18: Median | Y18: Min | Z18: Max
C19: Community Health Workers | D19: 2100.5642 | E19: 18.910956 | F19: 6691.2 | G19: 10 | H19: =IF(F19<D19,"Check","") | W19: 11856.737 | X19: 8475.8805 | Y19: 3176.4688 | Z19: 42931.282
B20: Dentist | C20: Dentists | D20: 24675.147 | E20: 4350 | F20: 65003.378 | G20: 13 | H20: =IF(F20<D20,"Check","")
C21: Dental Assistants and Therapists | D21: 8475.8805 | E21: 3176.4688 | F21: 11856.737 | G21: Inputed with average | H21: =IF(F21<F16,"Check","")
C22: Dieticians and nutritionists | D22: 8475.8805 | E22: 3176.4688 | F22: 11856.737 | G22: Inputed with average | H22: =IF(F22<D22,"Check","")
C23: Environmental and occupational health & hygiene workers | D23: 8373.3581 | E23: 2274.6189 | F23: 23780.741 | G23: 14 | H23: =IF(F23<D23,"Check","")
B24: Medical Doctors | C24: Generalist Medical Practitioners | D24: 16711.451 | E24: 4350 | F24: 70131.643 | G24: 17 | H24: =IF(F24<D24,"Check","")
C25: Medical and dental Prosthetic Technicians | D25: 8475.8805 | E25: 3176.4688 | F25: 11856.737 | G25: Inputed with average | H25: =IF(F25<D25,"Check","")
B26: Other Health Workers | C26: Medical and Pathology Laboratory scientists | D26: 7741.2876 | E26: 3030.4286 | F26: 96426.69 | G26: 15 | H26: =IF(F26<D26,"Check","")
C27: Medical and Pathology Laboratory Technicians | D27: 8475.8805 | E27: 3176.4688 | F27: 11856.737 | G27: Inputed with average | H27: =IF(F27<D27,"Check","")
C28: Medical Imaging and Therapeutic Equipment Technicians | D28: 7741.2876 | E28: 3525.7655 | F28: 43430.123 | G28: 15 | H28: =IF(F28<D28,"Check","")
B29: Midwifery personnel | C29: Midwifery personnel | D29: 8216.3677 | E29: 4119.0419 | F29: 22257.168 | G29: 6.6666667 | H29: =IF(F29<D29,"Check","")
B30: Nursing Personnel | C30: Nursing Personnel | D30: 7534.1459 | E30: 4119.0419 | F30: 64855.987 | G30: 8 | H30: =IF(F30<D30,"Check","")
C31: Nursing Personnel | D31: 7534.1459 | E31: 4119.0419 | F31: 64855.987 | G31: 8 | H31: =IF(F31<D31,"Check","")
C32: Optometrists and Ophthalmic Opticians | D32: 8475.8805 | E32: 3176.4688 | F32: 11856.737 | G32: Inputed with average | H32: =IF(F32<D32,"Check","")
C33: Paramedical Practitioners | D33: 6335.0389 | E33: 3525.7655 | F33: 12006 | G33: 10 | H33: =IF(F33<D33,"Check","")
C34: Pharmaceutical Technicians and Assistants | D34: 8475.8805 | E34: 3176.4688 | F34: 11856.737 | G34: Inputed with average | H34: =IF(F34<D34,"Check","")
B35: Pharmacist | C35: Pharmacists | D35: 11129.029 | E35: 4812.3086 | F35: 51236.733 | G35: 9 | H35: =IF(F35<D35,"Check","")
C36: Physiotherapists and physiotherapy assistants | D36: 12188.43 | E36: 3525.7655 | F36: 39012.857 | G36: 13 | H36: =IF(F36<D36,"Check","")
C37: Psychologists | D37: 8475.8805 | E37: 3176.4688 | F37: 11856.737 | G37: Inputed with average | H37: =IF(F37<D37,"Check","")
C38: Social workers | D38: 8475.8805 | E38: 3176.4688 | F38: 11856.737 | G38: Inputed with average | H38: =IF(F38<D38,"Check","")
C39: Specialist Medical Practitioners | D39: 33928.98 | E39: 5391 | F39: 184378.44 | G39: 15 | H39: =IF(F39<D39,"Check","")
C40: Mean | D40: 11859.994 | E40: 5611.1188 | F40: 35120.689 | H40: =IF(F40<D40,"Check","")
C41: Median | D41: 11856.737 | E41: 4581.1543 | F41: 17131.584 | H41: =IF(F41<D41,"Check","")
C48: Training Cost
C50: Occupation | D50: Median | E50: Average | F50: Minimum | G50: Maximum | H50: Number of countries
A51: Generalist Medical Practitioners | B51: Medical Doctors | C51: Generalist Medical Practitioners | D51: 10572 | E51: 17350.8 | F51: 5106 | G51: 31950 | H51: 6 | I51: 6 | J51: 2891.8
A52: Generalist Medical Practitioners | C52: Specialist Medical Practitioners | D52: 5286 | E52: 8675.4 | F52: 2553 | G52: 15975 | I52: 3
A53: Nursing Professionals | B53: Nursing Personnel | C53: Nursing Personnel | D53: 4972.5 | E53: 10171.5 | F53: 1200 | G53: 29541 | H53: 5 | I53: 3
A54: Midwifery personnel | B54: Midwifery personnel | C54: Midwifery personnel | D54: 2292 | E54: 6271.5 | F54: 808 | G54: 19694 | H54: 5 | I54: 2
A55: Pharmacists | B55: Pharmacist | C55: Pharmacists | D55: 3852 | E55: 7888 | F55: 2548 | G55: 21300 | H55: 5 | I55: 4
A56: Dentists | B56: Dentist | C56: Dentists | D56: 10572 | E56: 17350.8 | F56: 5106 | G56: 31950 | H56: 4 | I56: 6
B57: Other Health Workers | C57: Other | D57: 3632.25 | E57: 8221.5 | F57: 1004 | G57: 24617.5 | I57: 3
B58: Community Health Workers | C58: Community Health Workers | D58: 1000 | E58: 1000 | F58: 500 | G58: 1500 | I58: 0.5
D59: 5272.3438 | E59: 9616.1875 | F59: 2353.125 | G59: 22065.938

Sheet Graduates
A1: Country | B1: ISO3 | C1: Generalist Medical Practitioners | D1: Nursing Personnel | E1: Midwifery personnel | F1: Dentists | G1: Other Dental practitioners | H1: Pharmacists | I1: Other Pharmacy practitioners | J1: Medical and Pathology Laboratory scientists | K1: Paramedical Practitioners | L1: Other Health Workers | M1: Total | N1: Medical Doctors | O1: Nursing Personnel | P1: Midwifery Personnel | Q1: Dentists | R1: Pharmacists | S1: Medical and Pathology Laboratory Scientists | T1: Medical Doctors | U1: Nursing Personnel | V1: Midwifery Personnel | W1: Dentists | X1: Pharmacists | Y1: Medical and Pathology Laboratory Scientists | Z1: Total core cadre training | AA1: Population | AB1: Total core cadre training per capita
A2: Mali | B2: MLI | C2: 0 | D2: 0 | E2: 0 | F2: 0 | G2: 0 | H2: 0 | I2: 0 | J2: 0 | K2: 0 | L2: 0 | M2: 0 | N2: 0 | O2: 0 | P2: 0 | Q2: 0 | R2: 0 | S2: 0 | T2: 0 | U2: 0 | V2: 0 | W2: 0 | X2: 0 | Y2: 0 | Z2: =SUM(T2:Y2) -> 0 | AA2: =VLOOKUP(B2,Salaries_total!$B$3:$C$49,2,FALSE) -> 22105727 | AB2: =Z2/AA2 -> 0
A3: Sao Tome and Principe | B3: STP | C3: 0 | D3: 0 | E3: 0 | F3: 0 | G3: 0 | H3: 0 | I3: 0 | J3: 0 | K3: 0 | L3: 0 | M3: 0 | N3: 0 | O3: 0 | P3: 0 | Q3: 0 | R3: 0 | S3: 0 | T3: 0 | U3: 0 | V3: 0 | W3: 0 | X3: 0 | Y3: 0 | Z3: =SUM(T3:Y3) -> 0 | AA3: =VLOOKUP(B3,Salaries_total!$B$3:$C$49,2,FALSE) -> 232132 | AB3: =Z3/AA3 -> 0
A4: Central African Republic | B4: CAF | C4: 18 | D4: 0 | E4: 0 | F4: 0 | G4: 0 | H4: 0 | I4: 0 | J4: 0 | K4: 0 | L4: 0 | M4: 18 | N4: 18 | O4: 0 | P4: 0 | Q4: 0 | R4: 0 | S4: 0 | T4: 370800 | U4: 0 | V4: 0 | W4: 0 | X4: 0 | Y4: 0 | Z4: =SUM(T4:Y4) -> 370800 | AA4: =VLOOKUP(B4,Salaries_total!$B$3:$C$49,2,FALSE) -> 5119136 | AB4: =Z4/AA4 -> 0.072434098
A5: Comoros | B5: COM | C5: 0 | D5: 40 | E5: 29 | F5: 0 | G5: 0 | H5: 0 | I5: 0 | J5: 0 | K5: 0 | L5: 0 | M5: 69 | N5: 0 | O5: 40 | P5: 29 | Q5: 0 | R5: 0 | S5: 0 | T5: 0 | U5: 461540 | V5: 400000 | W5: 0 | X5: 0 | Y5: 0 | Z5: =SUM(T5:Y5) -> 861540 | AA5: =VLOOKUP(B5,Salaries_total!$B$3:$C$49,2,FALSE) -> 926492 | AB5: =Z5/AA5 -> 0.9298947
A6: Cabo Verde | B6: CPV | C6: 0 | D6: 0 | E6: 0 | F6: 0 | G6: 7 | H6: 0 | I6: 0 | J6: 0 | K6: 0 | L6: 83 | M6: 90 | N6: 0 | O6: 0 | P6: 0 | Q6: 0 | R6: 0 | S6: 0 | T6: 0 | U6: 0 | V6: 0 | W6: 0 | X6: 0 | Y6: 0 | Z6: =SUM(T6:Y6) -> 0 | AA6: =VLOOKUP(B6,Salaries_total!$B$3:$C$49,2,FALSE) -> 573322 | AB6: =Z6/AA6 -> 0
A7: Seychelles | B7: SYC | C7: 10 | D7: 40 | E7: 10 | F7: 0 | G7: 0 | H7: 0 | I7: 20 | J7: 0 | K7: 0 | L7: 80 | M7: 160 | N7: 10 | O7: 40 | P7: 10 | Q7: 0 | R7: 0 | S7: 0 | T7: 206000 | U7: 461540 | V7: 400000 | W7: 0 | X7: 0 | Y7: 0 | Z7: =SUM(T7:Y7) -> 1067540 | AA7: =VLOOKUP(B7,Salaries_total!$B$3:$C$49,2,FALSE) -> 99912 | AB7: =Z7/AA7 -> 10.684803
A8: Gambia | B8: GMB | C8: 23 | D8: 137 | E8: 0 | F8: 0 | G8: 0 | H8: 0 | I8: 0 | J8: 6 | K8: 0 | L8: 0 | M8: 166 | N8: 23 | O8: 137 | P8: 0 | Q8: 0 | R8: 0 | S8: 6 | T8: 473800 | U8: 1580774.5 | V8: 1370000 | W8: 0 | X8: 0 | Y8: 69231 | Z8: =SUM(T8:Y8) -> 3493805.5 | AA8: =VLOOKUP(B8,Salaries_total!$B$3:$C$49,2,FALSE) -> 2631251 | AB8: =Z8/AA8 -> 1.3278116
A9: Gabon | B9: GAB | C9: 46 | D9: 95 | E9: 34 | F9: 0 | G9: 0 | H9: 2 | I9: 0 | J9: 6 | K9: 0 | L9: 0 | M9: 183 | N9: 46 | O9: 95 | P9: 34 | Q9: 0 | R9: 2 | S9: 6 | T9: 947600 | U9: 1096157.5 | V9: 950000 | W9: 0 | X9: 37200 | Y9: 69231 | Z9: =SUM(T9:Y9) -> 3100188.5 | AA9: =VLOOKUP(B9,Salaries_total!$B$3:$C$49,2,FALSE) -> 2383905 | AB9: =Z9/AA9 -> 1.3004665
A10: Liberia | B10: LBR | C10: 29 | D10: 63 | E10: 0 | F10: 0 | G10: 0 | H10: 22 | I10: 0 | J10: 56 | K10: 0 | L10: 50 | M10: 220 | N10: 29 | O10: 63 | P10: 0 | Q10: 0 | R10: 22 | S10: 56 | T10: 597400 | U10: 726925.5 | V10: 630000 | W10: 0 | X10: 409200 | Y10: 646156 | Z10: =SUM(T10:Y10) -> 3009681.5 | AA10: =VLOOKUP(B10,Salaries_total!$B$3:$C$49,2,FALSE) -> 5432272 | AB10: =Z10/AA10 -> 0.55403733
A11: Algeria | B11: DZA | C11: 300 | D11: 0 | E11: 0 | F11: 0 | G11: 0 | H11: 0 | I11: 0 | J11: 0 | K11: 0 | L11: 0 | M11: 300 | N11: 300 | O11: 0 | P11: 0 | Q11: 0 | R11: 0 | S11: 0 | T11: 6180000 | U11: 0 | V11: 0 | W11: 0 | X11: 0 | Y11: 0 | Z11: =SUM(T11:Y11) -> 6180000 | AA11: =VLOOKUP(B11,Salaries_total!$B$3:$C$49,2,FALSE) -> 46053477 | AB11: =Z11/AA11 -> 0.13419182
A12: Eswatini | B12: SWZ | C12: 0 | D12: 160 | E12: 80 | F12: 0 | G12: 0 | H12: 44 | I12: 30 | J12: 78 | K12: 0 | L12: 58 | M12: 450 | N12: 0 | O12: 160 | P12: 80 | Q12: 0 | R12: 44 | S12: 78 | T12: 0 | U12: 1846160 | V12: 1600000 | W12: 0 | X12: 818400 | Y12: 900003 | Z12: =SUM(T12:Y12) -> 5164563 | AA12: =VLOOKUP(B12,Salaries_total!$B$3:$C$49,2,FALSE) -> 1197512 | AB12: =Z12/AA12 -> 4.3127443
A13: Mauritania | B13: MRT | C13: 0 | D13: 113 | E13: 0 | F13: 0 | G13: 0 | H13: 0 | I13: 0 | J13: 0 | K13: 0 | L13: 366 | M13: 479 | N13: 0 | O13: 113 | P13: 0 | Q13: 0 | R13: 0 | S13: 0 | T13: 0 | U13: 1303850.5 | V13: 1130000 | W13: 0 | X13: 0 | Y13: 0 | Z13: =SUM(T13:Y13) -> 2433850.5 | AA13: =VLOOKUP(B13,Salaries_total!$B$3:$C$49,2,FALSE) -> 5030233 | AB13: =Z13/AA13 -> 0.48384449
... A48: Democratic Republic of the Congo | B48: COD | C48: 6020 | D48: 24061 | E48: 3453 | F48: 66 | G48: 0 | H48: 178 | I48: 328 | J48: 2571 | K48: 0 | L48: 3151 | M48: 39828 | N48: 6020 | O48: 24061 | P48: 3453 | Q48: 66 | R48: 178 | S48: 2571 | T48: 124012000 | U48: 2.7762785e+08 | V48: 240610000 | W48: 1359600 | X48: 3310800 | Y48: 29665484 | Z48: =SUM(T48:Y48) -> 676585732 | AA48: =VLOOKUP(B48,Salaries_total!$B$3:$C$49,2,FALSE) -> 98151951 | AB48: =Z48/AA48 -> 6.8932479
U52: Generalist Medical Practitioners | V52: Nursing Professionals | W52: Midwifery personnel | X52: Pharmacists | Y52: Dentists | Z52: Paramedical Practitioners
T53: Variable | U53: Medical Doctors | V53: Nursing Personnel | W53: Midwifery personnel | X53: Pharmacists | Y53: Dentist | Z53: Clinical Officer/Physician Assistant
T54: Median | U54: 3510.5 | V54: 1881 | W54: 1434 | X54: 1165 | Y54: 5292 | Z54: 20000
T55: Average | U55: 5843.1667 | V55: 5020.1 | W55: 4508.6 | X55: 5297.6 | Y55: 7995.75 | Z55: 20000
T56: Minimum | U56: 851 | V56: 400 | W56: 404 | X56: 637 | Y56: 799 | Z56: 20000
T57: Maximum | U57: 20600 | V57: 11538.5 | W57: 10000 | X57: 18600 | Y57: 20600 | Z57: 20000

Sheet Salaries_total
A2: Country | B2: ISO | C2: Population_2023 | D2: Density_2023_Medical Doctors | E2: Density_2023_Nursing Personnel | F2: Density_2023_Midwifery Personnel | G2: Density_2023_Dentists | H2: Density_2023_Pharmacists | I2: Density_2023_Medical and Pathology Laboratory Scientists | J2: Density_2023_Medical and Pathology Laboratory Technicians | K2: Density_7_cadres_2023 | L2: Total_2023_Medical Doctors | M2: Total_2023_Nursing Personnel | N2: Total__2023_Midwifery Personnel | O2: Total_2023_Dentists | P2: Total_2023_Pharmacists | Q2: Total_2023_Medical and Pathology Laboratory Scientists | R2: Total_2023_Medical and Pathology Laboratory Technicians | S2: Density_7_cadres_2023 | T2: Salary_Exp_2023_Medical Doctors | U2: Salary_Exp_2023_Nursing Personnel | V2: Salary_Exp_2023_Midwifery Personnel | W2: Salary_Exp_2023_Dentists | X2: Salary_Exp_2023_Pharmacists | Y2: Salary_Exp_2023_Medical and Pathology Laboratory Scientists | Z2: Salary_Exp_2023_Medical and Pathology Laboratory Technicians | AA2: Salary_Exp_7_cadres_2023 | AB2: salary per population for the 7 core cadres | AC2: Total core cadre training per capita
A3: Algeria | B3: DZA | C3: 46053477 | D3: 16.39659 | E3: 22.750942 | F3: 2.0148316 | G3: 3.5224268 | H3: 2.9622085 | I3: 0.029530886 | J3: 3.3087621 | K3: 50.985293 | L3: =C3*D3/10000 -> 75512 | M3: =C3*E3/10000 -> 104776 | N3: =C3*F3/10000 -> 9279 | O3: =C3*G3/10000 -> 16222 | P3: =C3*H3/10000 -> 13642 | Q3: =C3*I3/10000 -> 136 | R3: =C3*J3/10000 -> 15238 | S3: =C3*K3/10000 -> 234805 | T3: =L3*16711.45 -> 1.261915e+09 | U3: =M3*7534.14 -> 7.8939705e+08 | V3: =N3*8216.36 -> 76239604 | W3: =O3*24675.14 -> 4.0028012e+08 | X3: =P3*11129.02 -> 1.5182209e+08 | Y3: =Q3*7741.28 -> 1052814.1 | Z3: =R3*8475.88 -> 1.2915546e+08 | AA3: =SUM(T3:Z3) -> 2.8098622e+09 | AB3: =AA3/C3 -> 61.01303 | AC3: =VLOOKUP(B3,Graduates!$B$2:$AB$48,27,FALSE) -> 0.13419182
A4: Angola | B4: AGO | C4: 36148636 | D4: 2.4047934 | E4: 18.456575 | F4: 0.0091289752 | G4: 0.070265445 | H4: 0.39669547 | I4: 0.0035962629 | J4: 0.004979441 | K4: 21.346034 | L4: =C4*D4/10000 -> 8693 | M4: =C4*E4/10000 -> 66718 | N4: =C4*F4/10000 -> 33 | O4: =C4*G4/10000 -> 254 | P4: =C4*H4/10000 -> 1434 | Q4: =C4*I4/10000 -> 13 | R4: =C4*J4/10000 -> 18 | S4: =C4*K4/10000 -> 77163 | T4: =L4*16711.45 -> 1.4527263e+08 | U4: =M4*7534.14 -> 5.0266275e+08 | V4: =N4*8216.36 -> 271139.88 | W4: =O4*24675.14 -> 6267485.6 | X4: =P4*11129.02 -> 15959015 | Y4: =Q4*7741.28 -> 100636.64 | Z4: =R4*8475.88 -> 152565.84 | AA4: =SUM(T4:Z4) -> 6.7068623e+08 | AB4: =AA4/C4 -> 18.553569 | AC4: =VLOOKUP(B4,Graduates!$B$2:$AB$48,27,FALSE) -> 2.4607173
A5: Benin | B5: BEN | C5: 13124347 | D5: 2.3178296 | E5: 4.7164251 | F5: 1.8484729 | G5: 0.050288216 | H5: 0.32992118 | I5: 0.5089777 | J5: 1.2434904 | K5: 11.015405 | L5: =C5*D5/10000 -> 3042 | M5: =C5*E5/10000 -> 6190 | N5: =C5*F5/10000 -> 2426 | O5: =C5*G5/10000 -> 66 | P5: =C5*H5/10000 -> 433 | Q5: =C5*I5/10000 -> 668 | R5: =C5*J5/10000 -> 1632 | S5: =C5*K5/10000 -> 14457 | T5: =L5*16711.45 -> 50836231 | U5: =M5*7534.14 -> 46636327 | V5: =N5*8216.36 -> 19932889 | W5: =O5*24675.14 -> 1628559.2 | X5: =P5*11129.02 -> 4818865.7 | Y5: =Q5*7741.28 -> 5171175 | Z5: =R5*8475.88 -> 13832636 | AA5: =SUM(T5:Z5) -> 1.4285668e+08 | AB5: =AA5/C5 -> 10.88486 | AC5: =VLOOKUP(B5,Graduates!$B$2:$AB$48,27,FALSE) -> 2.8272298
A6: Botswana | B6: BWA | C6: 2483754 | D6: 3.78862 | E6: 30.135835 | F6: 0 | G6: 0.35832856 | H6: 0.5314536 | I6: 0.60392454 | J6: 1.2521369 | K6: 36.670298 | L6: =C6*D6/10000 -> 941 | M6: =C6*E6/10000 -> 7485 | N6: =C6*F6/10000 -> 0 | O6: =C6*G6/10000 -> 89 | P6: =C6*H6/10000 -> 132 | Q6: =C6*I6/10000 -> 150 | R6: =C6*J6/10000 -> 311 | S6: =C6*K6/10000 -> 9108 | T6: =L6*16711.45 -> 15725474 | U6: =M6*7534.14 -> 56393038 | V6: =N6*8216.36 -> 0 | W6: =O6*24675.14 -> 2196087.5 | X6: =P6*11129.02 -> 1469030.6 | Y6: =Q6*7741.28 -> 1161192 | Z6: =R6*8475.88 -> 2635998.7 | AA6: =SUM(T6:Z6) -> 79580821 | AB6: =AA6/C6 -> 32.040541 | AC6: =VLOOKUP(B6,Graduates!$B$2:$AB$48,27,FALSE) -> 6.3942892
A7: Burkina Faso | B7: BFA | C7: 22720842 | D7: 1.4625338 | E7: 5.994056 | F7: 3.6217848 | G7: 0.058536563 | H7: 0.39655221 | I7: 0.0026407472 | J7: 0.48589749 | K7: 12.022002 | L7: =C7*D7/10000 -> 3323 | M7: =C7*E7/10000 -> 13619 | N7: =C7*F7/10000 -> 8229 | O7: =C7*G7/10000 -> 133 | P7: =C7*H7/10000 -> 901 | Q7: =C7*I7/10000 -> 6 | R7: =C7*J7/10000 -> 1104 | S7: =C7*K7/10000 -> 27315 | T7: =L7*16711.45 -> 55532148 | U7: =M7*7534.14 -> 1.0260745e+08 | V7: =N7*8216.36 -> 67612426 | W7: =O7*24675.14 -> 3281793.6 | X7: =P7*11129.02 -> 10027247 | Y7: =Q7*7741.28 -> 46447.68 | Z7: =R7*8475.88 -> 9357371.5 | AA7: =SUM(T7:Z7) -> 2.4846489e+08 | AB7: =AA7/C7 -> 10.935549 | AC7: =VLOOKUP(B7,Graduates!$B$2:$AB$48,27,FALSE) -> 3.0043273
A8: Burundi | B8: BDI | C8: 12999141 | D8: 0.7985143 | E8: 8.3643988 | F8: 0.37156301 | G8: 0.010769942 | H8: 0.095390919 | I8: 0.98006476 | J8: 0.70081554 | K8: 11.321517 | L8: =C8*D8/10000 -> 1038 | M8: =C8*E8/10000 -> 10873 | N8: =C8*F8/10000 -> 483 | O8: =C8*G8/10000 -> 14 | P8: =C8*H8/10000 -> 124 | Q8: =C8*I8/10000 -> 1274 | R8: =C8*J8/10000 -> 911 | S8: =C8*K8/10000 -> 14717 | T8: =L8*16711.45 -> 17346485 | U8: =M8*7534.14 -> 81918704 | V8: =N8*8216.36 -> 3968501.9 | W8: =O8*24675.14 -> 345451.96 | X8: =P8*11129.02 -> 1379998.5 | Y8: =Q8*7741.28 -> 9862390.7 | Z8: =R8*8475.88 -> 7721526.7 | AA8: =SUM(T8:Z8) -> 1.2254306e+08 | AB8: =AA8/C8 -> 9.4270121 | AC8: =VLOOKUP(B8,Graduates!$B$2:$AB$48,27,FALSE) -> 3.2873539
A9: Cabo Verde | B9: CPV | C9: 573322 | D9: 6.6454802 | E9: 16.378231 | F9: 0.45349734 | G9: 0.13953764 | H9: 0.17442205 | I9: 0.069768821 | J9: 0.13953764 | K9: 24.000474 | L9: =C9*D9/10000 -> 381 | M9: =C9*E9/10000 -> 939 | N9: =C9*F9/10000 -> 26 | O9: =C9*G9/10000 -> 8 | P9: =C9*H9/10000 -> 10 | Q9: =C9*I9/10000 -> 4 | R9: =C9*J9/10000 -> 8 | S9: =C9*K9/10000 -> 1376 | T9: =L9*16711.45 -> 6367062.5 | U9: =M9*7534.14 -> 7074557.5 | V9: =N9*8216.36 -> 213625.36 | W9: =O9*24675.14 -> 197401.12 | X9: =P9*11129.02 -> 111290.2 | Y9: =Q9*7741.28 -> 30965.12 | Z9: =R9*8475.88 -> 67807.04 | AA9: =SUM(T9:Z9) -> 14062709 | AB9: =AA9/C9 -> 24.528465 | AC9: =VLOOKUP(B9,Graduates!$B$2:$AB$48,27,FALSE) -> 0
A10: Cameroon | B10: CMR | C10: 28608129 | D10: 1.3150108 | E10: 5.7798257 | F10: 0.58479882 | G10: 0.11080767 | H10: 0.2104297 | I10: 0.10241844 | J10: 0.083542688 | K10: 8.1868339 | L10: =C10*D10/10000 -> 3762 | M10: =C10*E10/10000 -> 16535 | N10: =C10*F10/10000 -> 1673 | O10: =C10*G10/10000 -> 317 | P10: =C10*H10/10000 -> 602 | Q10: =C10*I10/10000 -> 293 | R10: =C10*J10/10000 -> 239 | S10: =C10*K10/10000 -> 23421 | T10: =L10*16711.45 -> 62868475 | U10: =M10*7534.14 -> 1.24577e+08 | V10: =N10*8216.36 -> 13745970 | W10: =O10*24675.14 -> 7822019.4 | X10: =P10*11129.02 -> 6699670 | Y10: =Q10*7741.28 -> 2268195 | Z10: =R10*8475.88 -> 2025735.3 | AA10: =SUM(T10:Z10) -> 2.2000707e+08 | AB10: =AA10/C10 -> 7.6903691 | AC10: =VLOOKUP(B10,Graduates!$B$2:$AB$48,27,FALSE) -> 2.9013855
A11: Central African Republic | B11: CAF | C11: 5119136 | D11: 0.74817313 | E11: 7.3371756 | F11: 3.7057035 | G11: 0.0058603639 | H11: 0.02539491 | I11: 0.21878692 | J11: 0.56064148 | K11: 12.601736 | L11: =C11*D11/10000 -> 383 | M11: =C11*E11/10000 -> 3756 | N11: =C11*F11/10000 -> 1897 | O11: =C11*G11/10000 -> 3 | P11: =C11*H11/10000 -> 13 | Q11: =C11*I11/10000 -> 112 | R11: =C11*J11/10000 -> 287 | S11: =C11*K11/10000 -> 6451 | T11: =L11*16711.45 -> 6400485.4 | U11: =M11*7534.14 -> 28298230 | V11: =N11*8216.36 -> 15586435 | W11: =O11*24675.14 -> 74025.42 | X11: =P11*11129.02 -> 144677.26 | Y11: =Q11*7741.28 -> 867023.36 | Z11: =R11*8475.88 -> 2432577.6 | AA11: =SUM(T11:Z11) -> 53803454 | AB11: =AA11/C11 -> 10.510261 | AC11: =VLOOKUP(B11,Graduates!$B$2:$AB$48,27,FALSE) -> 0.072434098
A12: Chad | B12: TCD | C12: 17921183 | D12: 0.91567616 | E12: 1.3263633 | F12: 0.47150905 | G12: 0.0072539854 | H12: 0.090953817 | I12: 0.57362285 | J12: 0.58478282 | K12: 3.970162 | L12: =C12*D12/10000 -> 1641 | M12: =C12*E12/10000 -> 2377 | N12: =C12*F12/10000 -> 845 | O12: =C12*G12/10000 -> 13 | P12: =C12*H12/10000 -> 163 | Q12: =C12*I12/10000 -> 1028 | R12: =C12*J12/10000 -> 1048 | S12: =C12*K12/10000 -> 7115 | T12: =L12*16711.45 -> 27423489 | U12: =M12*7534.14 -> 17908651 | V12: =N12*8216.36 -> 6942824.2 | W12: =O12*24675.14 -> 320776.82 | X12: =P12*11129.02 -> 1814030.3 | Y12: =Q12*7741.28 -> 7958035.8 | Z12: =R12*8475.88 -> 8882722.2 | AA12: =SUM(T12:Z12) -> 71250530 | AB12: =AA12/C12 -> 3.9757716 | AC12: =VLOOKUP(B12,Graduates!$B$2:$AB$48,27,FALSE) -> 4.1133942
A13: Comoros | B13: COM | C13: 926492 | D13: 3.8208641 | E13: 8.4728201 | F13: 6.3249332 | G13: 0.34538884 | H13: 0.43173605 | I13: 1.7377376 | J13: 0.17269442 | K13: 21.306174 | L13: =C13*D13/10000 -> 354 | M13: =C13*E13/10000 -> 785 | N13: =C13*F13/10000 -> 586 | O13: =C13*G13/10000 -> 32 | P13: =C13*H13/10000 -> 40 | Q13: =C13*I13/10000 -> 161 | R13: =C13*J13/10000 -> 16 | S13: =C13*K13/10000 -> 1974 | T13: =L13*16711.45 -> 5915853.3 | U13: =M13*7534.14 -> 5914299.9 | V13: =N13*8216.36 -> 4814787 | W13: =O13*24675.14 -> 789604.48 | X13: =P13*11129.02 -> 445160.8 | Y13: =Q13*7741.28 -> 1246346.1 | Z13: =R13*8475.88 -> 135614.08 | AA13: =SUM(T13:Z13) -> 19261666 | AB13: =AA13/C13 -> 20.789889 | AC13: =VLOOKUP(B13,Graduates!$B$2:$AB$48,27,FALSE) -> 0.9298947
A14: Congo | B14: COG | C14: 5940746 | D14: 1.7539885 | E14: 9.3809767 | F14: 2.0031154 | G14: 0.016832903 | H14: 0.053865289 | I14: 0.53865289 | J14: 1.3079165 | K14: 15.055348 | L14: =C14*D14/10000 -> 1042 | M14: =C14*E14/10000 -> 5573 | N14: =C14*F14/10000 -> 1190 | O14: =C14*G14/10000 -> 10 | P14: =C14*H14/10000 -> 32 | Q14: =C14*I14/10000 -> 320 | R14: =C14*J14/10000 -> 777 | S14: =C14*K14/10000 -> 8944 | T14: =L14*16711.45 -> 17413331 | U14: =M14*7534.14 -> 41987762 | V14: =N14*8216.36 -> 9777468.4 | W14: =O14*24675.14 -> 246751.4 | X14: =P14*11129.02 -> 356128.64 | Y14: =Q14*7741.28 -> 2477209.6 | Z14: =R14*8475.88 -> 6585758.8 | AA14: =SUM(T14:Z14) -> 78844410 | AB14: =AA14/C14 -> 13.271803 | AC14: =VLOOKUP(B14,Graduates!$B$2:$AB$48,27,FALSE) -> 0.42558796
... A49: Zimbabwe | B49: ZWE | C49: 15581023 | D49: 1.4260938 | E49: 29.867744 | F49: 1.8002669 | G49: 0.31576874 | H49: 1.2207157 | I49: 0.92997745 | J49: 0.67710573 | K49: 36.237672 | L49: =C49*D49/10000 -> 2222 | M49: =C49*E49/10000 -> 46537 | N49: =C49*F49/10000 -> 2805 | O49: =C49*G49/10000 -> 492 | P49: =C49*H49/10000 -> 1902 | Q49: =C49*I49/10000 -> 1449 | R49: =C49*J49/10000 -> 1055 | S49: =C49*K49/10000 -> 56462 | T49: =L49*16711.45 -> 37132842 | U49: =M49*7534.14 -> 3.5061627e+08 | V49: =N49*8216.36 -> 23046890 | W49: =O49*24675.14 -> 12140169 | X49: =P49*11129.02 -> 21167396 | Y49: =Q49*7741.28 -> 11217115 | Z49: =R49*8475.88 -> 8942053.4 | AA49: =SUM(T49:Z49) -> 4.6426274e+08 | AB49: =AA49/C49 -> 29.796679 | AC49: =VLOOKUP(B49,Graduates!$B$2:$AB$48,27,FALSE) -> 2.426871
